Workbook

Sheet README
A1: Ucell — модель роста ARPU архивной базы
A3: Как пользоваться
A4: 1. Замените ЖЁЛТЫЕ ячейки на листе Inputs фактом от аналитиков (docs/09_data_request_for_analysts.md).
A5: 2. Лист Initiatives: синие ячейки — параметры инициатив (модальные значения бенчмарков). После пилотов подставьте фактические конверсии/отток.
A6: 3. Лист Monthly — помесячный движок на 24 мес.; лист Portfolio — итоги портфеля, динамика ARPU, график.
A7: 4. Лист AB_Calculator — размер выборок для пилотов; лист MC_Results — вероятности из Монте-Карло (значения из Python).
A8: 5. После изменения допущений в коде: python model/arpu_model.py && python model/build_excel.py
A10: Легенда
A11: Синий текст — ввод · Чёрный — формула · Зелёный — ссылка на другой лист · Жёлтая заливка — ключевая гипотеза, заменить фактом
A13: Единицы и определения
A14: Деньги — сум (UZS) без НДС 12%, если не указано «с НДС». Курс — лист Inputs.
A15: ARPU считается по КОГОРТЕ абонентов, бывших на архивных ТП на дату T0: мигрировавшие на актуальные ТП остаются в когорте.
... A20: adoption — добровольное принятие оффера (миграция, допродажа); reprice — изменение условий ТП для целевой группы (stay/downgrade/churn); relative — относительный прирост выручки всей когорты (платформа).

Sheet Inputs
A1: Базовые допущения
A3: Параметр | C3: Значение | D3: Ед. | E3: Источник / комментарий
A4: Абонентская база Ucell | C4: 11000000 | D4: абон. | E4: Ucell: >10,9 млн на начало 2026 (итоги 2025, kun.uz 25.02.2026)
A5: Доля абонентов на архивных ТП | C5: 0.4 | D5: % | E5: HYPOTHESIS — заменить фактом (запрос D1)
A6: Доля активных среди архивных (доход за 30 дн.) | C6: 0.8 | D6: % | E6: HYPOTHESIS — запрос D1
A7: Активная архивная когорта (N) | C7: =C4*C5*C6 -> 3520000 | D7: абон. | E7: Формула
A8: ARPU архивной когорты (ARPU0, net) | C8: =SUMPRODUCT(C17:C21,D17:D21) -> 18500 | D8: сум/мес | E8: Средневзвешенный по сегментам (ниже)
A9: Месячный отток архивной когорты (c) | C9: 0.015 | D9: % | E9: HYPOTHESIS — запрос D4
A10: НДС | C10: 0.12 | D10: % | E10: НК РУз: 12%
A11: Курс, сум за 1 USD | C11: 12100 | D11: сум | E11: ЦБ РУз, 2026: 11 950–12 205
A12: Рынок мобильной связи РУз, абонентов | C12: 36500000 | D12: абон. | E12: HYPOTHESIS: 35,6 млн на конец 2024 + рост
A13: Выручка когорты в месяц (R0 мес. 0) | C13: =C7*C8 -> 65120000000 | D13: сум/мес | E13: Формула
A15: Сегменты архивной когорты (HYPOTHESIS — проверить кластеризацией, запрос D2)
A16: Код | B16: Сегмент | C16: Доля когорты | D16: ARPU net, сум | E16: Абонентов | F16: Выручка/мес, сум
A17: S1 | B17: Спящие / почти нулевые (2-я SIM, ARPU<5k) | C17: 0.2 | D17: 3000 | E17: =$C$7*C17 -> 704000 | F17: =E17*D17 -> 2112000000
A18: S2 | B18: PAYG / голосовые, много кнопочных 2G/3G | C18: 0.2 | D18: 10000 | E18: =$C$7*C18 -> 704000 | F18: =E18*D18 -> 7040000000
A19: S3 | B19: Недооценённые старые пакеты (платят мало, потребляют много) | C19: 0.3 | D19: 21000 | E19: =$C$7*C19 -> 1056000 | F19: =E19*D19 -> 22176000000
A20: S4 | B20: Старые пакеты mid/high + докупка пакетов | C20: 0.2 | D20: 40000 | E20: =$C$7*C20 -> 704000 | F20: =E20*D20 -> 28160000000
A21: S5 | B21: Социально защищённые (жен. 55+, муж. 60+) | C21: 0.1 | D21: 16000 | E21: =$C$7*C21 -> 352000 | F21: =E21*D21 -> 5632000000
A22: Итого | C22: =SUM(C17:C21) -> 1 | E22: =SUM(E17:E21) -> 3520000 | F22: =SUM(F17:F21) -> 65120000000
A23: Проверка: сумма долей = 100% | C23: =IF(ABS(C22-1)<0.0001,"OK","ОШИБКА: доли ≠ 100%") -> OK

Sheet Initiatives
A1: Инициативы: параметры (синие) → производные (чёрные) → итоги из листа Monthly (зелёные)
A3: Параметр | B3: Ключ | C3: A1 | D3: A2 | E3: A3 | F3: A4 | G3: A5 | H3: A6 | I3: A7 | J3: A8 | K3: B1 | L3: B2 | M3: B3 | N3: B4 | O3: B5
A4: Название | B4: name | C4: «Ucell 30 — Upgrade»: мягкая миграция с подарком | D4: Точечная индексация недооценённых архивных ТП (more-for-more) | E4: PAYG → суточные/недельные микропакеты | F4: Smart add-on: пакет-«бустер» в момент исчерпания (opt-in автопродление) | G4: Контент-надстройка (Yandex Plus / OVVA / Ucell TV) для архивных ТП | H4: Реактивация спящих архивных SIM (win-back оффер) | I4: «Musofir»: пакеты роуминга/OTP для трудовых мигрантов на архивных ТП | J4: ОПЦИЯ: ежегодная индексация архивных пакетов на инфляцию (волна 2) | K4: AI Next-Best-Offer: персональные офферы в реальном времени (RTD/CVM) | L4: «Ucell Oila»: семейный/групповой аккаунт с общим пакетом | M4: Sunset-программа: вывод устаревших семейств ТП с ценовой защитой | N4: Апгрейд 2G/3G → 4G-смартфон в рассрочку (BNPL-партнёр) | O4: Персональные лимиты «Mobil avans» на ML-скоринге
A5: Группа (EASY/HARD) | B5: group | C5: EASY | D5: EASY | E5: EASY | F5: EASY | G5: EASY | H5: EASY | I5: EASY | J5: EASY | K5: HARD | L5: HARD | M5: HARD | N5: HARD | O5: HARD
A6: Тип механики | B6: type | C6: adoption | D6: reprice | E6: adoption | F6: adoption | G6: adoption | H6: adoption | I6: adoption | J6: reprice | K6: relative | L6: adoption | M6: reprice | N6: adoption | O6: adoption
A7: Сложность биллинг/интеграции (1–5) | B7: complexity | C7: 1 | D7: 1 | E7: 2 | F7: 2 | G7: 2 | H7: 1 | I7: 2 | J7: 1 | K7: 4 | L7: 4 | M7: 5 | N7: 4 | O7: 3
A8: Опция вне базового портфеля (1=да) | B8: optional | C8: 0 | D8: 0 | E8: 0 | F8: 0 | G8: 0 | H8: 0 | I8: 0 | J8: 1 | K8: 0 | L8: 0 | M8: 0 | N8: 0 | O8: 0
A9: ARPU целевого сегмента, сум | B9: segment_arpu | C9: 21000 | D9: 21000 | E9: 10000 | F9: 28000 | G9: 28000 | H9: 3000 | I9: 15000 | J9: 28000 | K9: 0 | L9: 28000 | M9: 15000 | N9: 10000 | O9: 14000
A10: Доля целевой группы от когорты | B10: eligible_share | C10: 0.46 | D10: 0.22 | E10: 0.2 | F10: 0.15 | G10: 0.35 | H10: 0.2 | I10: 0.06 | J10: 0.38 | K10: 0 | L10: 0.2 | M10: 0.25 | N10: 0.08 | O10: 0.3
A11: Охват коммуникацией | B11: reach | C11: 0.85 | D11: 0 | E11: 0.8 | F11: 0.9 | G11: 0.8 | H11: 0.7 | I11: 0.8 | J11: 0 | K11: 0 | L11: 0.8 | M11: 0 | N11: 0.7 | O11: 0.9
A12: Конверсия (take-up) | B12: takeup | C12: 0.12 | D12: 0 | E12: 0.15 | F12: 0.12 | G12: 0.025 | H12: 0.06 | I12: 0.18 | J12: 0 | K12: 0 | L12: 0.04 | M12: 0 | N12: 0.05 | O12: 0.18
A13: Каннибализация (сделали бы и так) | B13: cannibal | C13: 0.2 | D13: 0 | E13: 0.2 | F13: 0.45 | G13: 0.2 | H13: 0.2 | I13: 0.25 | J13: 0 | K13: 0 | L13: 0.1 | M13: 0 | N13: 0.35 | O13: 0.5
A14: ΔARPU на адоптера, сум/мес | B14: delta | C14: 6500 | D14: 0 | E14: 2500 | F14: 7500 | G14: 12000 | H14: 7000 | I14: 7000 | J14: 0 | K14: 0 | L14: 22000 | M14: 0 | N14: 10000 | O14: 3000
A15: Доп. отток от изменения/контакта | B15: churn_incr | C15: 0.002 | D15: 0.025 | E15: 0 | F15: 0 | G15: 0 | H15: 0 | I15: 0 | J15: 0.01 | K15: 0 | L15: 0 | M15: 0.04 | N15: 0 | O15: 0
A16: Снижение оттока адоптеров (отн.) | B16: churn_red | C16: 0.1 | D16: 0 | E16: 0.05 | F16: 0.05 | G16: 0.25 | H16: 0 | I16: 0.2 | J16: 0 | K16: 0 | L16: 0.3 | M16: 0 | N16: 0.2 | O16: 0.1
A17: Доля адоптеров, активных через 6 мес. (A6) | B17: adopter_decay_6m | C17: 1 | D17: 1 | E17: 1 | F17: 1 | G17: 1 | H17: 0.65 | I17: 1 | J17: 1 | K17: 1 | L17: 1 | M17: 1 | N17: 1 | O17: 1
A18: Повышение абонплаты, сум с НДС | B18: price_up_gross | C18: 0 | D18: 5000 | E18: 0 | F18: 0 | G18: 0 | H18: 0 | I18: 0 | J18: 2000 | K18: 0 | L18: 0 | M18: 6500 | N18: 0 | O18: 0
... A35: Вероятность запуска как задумано | B35: exec_prob | C35: 0.92 | D35: 0.8 | E35: 0.9 | F35: 0.9 | G35: 0.85 | H35: 0.92 | I35: 0.9 | J35: 0.65 | K35: 0.65 | L35: 0.65 | M35: 0.6 | N35: 0.6 | O35: 0.7
A37: ПРОИЗВОДНЫЕ
A38: Целевая группа, абон. | B38: elig | C38: =Inputs!$C$7*C$10 -> 1619200 | D38: =Inputs!$C$7*D$10 -> 774400 | E38: =Inputs!$C$7*E$10 -> 704000 | F38: =Inputs!$C$7*F$10 -> 528000 | G38: =Inputs!$C$7*G$10 -> 1232000 | H38: =Inputs!$C$7*H$10 -> 704000 | I38: =Inputs!$C$7*I$10 -> 211200 | J38: =Inputs!$C$7*J$10 -> 1337600 | ... O38: =Inputs!$C$7*O$10 -> 1056000
A39: Охвачено коммуникацией, абон. | B39: contacted | C39: =IF(C$6="adoption",C$38*C$11,IF(C$6="reprice",C$38,0)) -> 1376320 | D39: =IF(D$6="adoption",D$38*D$11,IF(D$6="reprice",D$38,0)) -> 774400 | E39: =IF(E$6="adoption",E$38*E$11,IF(E$6="reprice",E$38,0)) -> 563200 | F39: =IF(F$6="adoption",F$38*F$11,IF(F$6="reprice",F$38,0)) -> 475200 | G39: =IF(G$6="adoption",G$38*G$11,IF(G$6="reprice",G$38,0)) -> 985600 | H39: =IF(H$6="adoption",H$38*H$11,IF(H$6="reprice",H$38,0)) -> 492800 | I39: =IF(I$6="adoption",I$38*I$11,IF(I$6="reprice",I$38,0)) -> 168960 | J39: =IF(J$6="adoption",J$38*J$11,IF(J$6="reprice",J$38,0)) -> 1337600 | ... O39: =IF(O$6="adoption",O$38*O$11,IF(O$6="reprice",O$38,0)) -> 950400
A40: Адоптеры при полном наборе (инкр.), абон. | B40: a_final | C40: =IF(C$6="adoption",C$39*C$12*(1-C$13),0) -> 132126.72 | D40: =IF(D$6="adoption",D$39*D$12*(1-D$13),0) -> 0 | E40: =IF(E$6="adoption",E$39*E$12*(1-E$13),0) -> 67584 | F40: =IF(F$6="adoption",F$39*F$12*(1-F$13),0) -> 31363.2 | G40: =IF(G$6="adoption",G$39*G$12*(1-G$13),0) -> 19712 | H40: =IF(H$6="adoption",H$39*H$12*(1-H$13),0) -> 23654.4 | I40: =IF(I$6="adoption",I$39*I$12*(1-I$13),0) -> 22809.6 | J40: =IF(J$6="adoption",J$39*J$12*(1-J$13),0) -> 0 | ... O40: =IF(O$6="adoption",O$39*O$12*(1-O$13),0) -> 85536
A41: reprice: остаются и платят больше, абон. | B41: stay | C41: =IF(C$6="reprice",C$38*(1-C$19-C$15),0) -> 0 | D41: =IF(D$6="reprice",D$38*(1-D$19-D$15),0) -> 693088 | E41: =IF(E$6="reprice",E$38*(1-E$19-E$15),0) -> 0 | F41: =IF(F$6="reprice",F$38*(1-F$19-F$15),0) -> 0 | G41: =IF(G$6="reprice",G$38*(1-G$19-G$15),0) -> 0 | H41: =IF(H$6="reprice",H$38*(1-H$19-H$15),0) -> 0 | I41: =IF(I$6="reprice",I$38*(1-I$19-I$15),0) -> 0 | J41: =IF(J$6="reprice",J$38*(1-J$19-J$15),0) -> 1270720 | ... O41: =IF(O$6="reprice",O$38*(1-O$19-O$15),0) -> 0
A42: reprice: ушли на более дешёвый ТП, абон. | B42: down | C42: =IF(C$6="reprice",C$38*C$19,0) -> 0 | D42: =IF(D$6="reprice",D$38*D$19,0) -> 61952 | E42: =IF(E$6="reprice",E$38*E$19,0) -> 0 | F42: =IF(F$6="reprice",F$38*F$19,0) -> 0 | G42: =IF(G$6="reprice",G$38*G$19,0) -> 0 | H42: =IF(H$6="reprice",H$38*H$19,0) -> 0 | I42: =IF(I$6="reprice",I$38*I$19,0) -> 0 | J42: =IF(J$6="reprice",J$38*J$19,0) -> 53504 | ... O42: =IF(O$6="reprice",O$38*O$19,0) -> 0
A43: Доп. отток всего, абон. | B43: lost_total | C43: =IF(C$6="relative",0,C$39*C$15) -> 2752.64 | D43: =IF(D$6="relative",0,D$39*D$15) -> 19360 | E43: =IF(E$6="relative",0,E$39*E$15) -> 0 | F43: =IF(F$6="relative",0,F$39*F$15) -> 0 | G43: =IF(G$6="relative",0,G$39*G$15) -> 0 | H43: =IF(H$6="relative",0,H$39*H$15) -> 0 | I43: =IF(I$6="relative",0,I$39*I$15) -> 0 | J43: =IF(J$6="relative",0,J$39*J$15) -> 13376 | ... O43: =IF(O$6="relative",0,O$39*O$15) -> 0
A44: Повышение абонплаты net, сум | B44: up_net | C44: =C$18/(1+Inputs!$C$10) -> 0 | D44: =D$18/(1+Inputs!$C$10) -> 4464.2857 | E44: =E$18/(1+Inputs!$C$10) -> 0 | F44: =F$18/(1+Inputs!$C$10) -> 0 | G44: =G$18/(1+Inputs!$C$10) -> 0 | H44: =H$18/(1+Inputs!$C$10) -> 0 | I44: =I$18/(1+Inputs!$C$10) -> 0 | J44: =J$18/(1+Inputs!$C$10) -> 1785.7143 | ... O44: =O$18/(1+Inputs!$C$10) -> 0
A45: Темп «засыпания» адоптеров, в мес. | B45: decay_m | C45: =1-C$17^(1/6) -> 0 | D45: =1-D$17^(1/6) -> 0 | E45: =1-E$17^(1/6) -> 0 | F45: =1-F$17^(1/6) -> 0 | G45: =1-G$17^(1/6) -> 0 | H45: =1-H$17^(1/6) -> 0.069280329 | I45: =1-I$17^(1/6) -> 0 | J45: =1-J$17^(1/6) -> 0 | ... O45: =1-O$17^(1/6) -> 0
A46: Месяцев подготовки (разовые затраты) | B46: build | C46: =MAX(C$33-1,1) -> 1 | D46: =MAX(D$33-1,1) -> 1 | E46: =MAX(E$33-1,1) -> 1 | F46: =MAX(F$33-1,1) -> 1 | G46: =MAX(G$33-1,1) -> 2 | H46: =MAX(H$33-1,1) -> 1 | I46: =MAX(I$33-1,1) -> 2 | J46: =MAX(J$33-1,1) -> 13 | ... O46: =MAX(O$33-1,1) -> 5
A47: Месяцев распределения доп. оттока | B47: K | C47: =IF(C$6="reprice",2,3) -> 3 | D47: =IF(D$6="reprice",2,3) -> 2 | E47: =IF(E$6="reprice",2,3) -> 3 | F47: =IF(F$6="reprice",2,3) -> 3 | G47: =IF(G$6="reprice",2,3) -> 3 | H47: =IF(H$6="reprice",2,3) -> 3 | I47: =IF(I$6="reprice",2,3) -> 3 | J47: =IF(J$6="reprice",2,3) -> 2 | ... O47: =IF(O$6="reprice",2,3) -> 3
A48: Месяц оценки (12-й после запуска, ≤24) | B48: eval_m | C48: =MIN(C$33+11,24) -> 13 | D48: =MIN(D$33+11,24) -> 13 | E48: =MIN(E$33+11,24) -> 13 | F48: =MIN(F$33+11,24) -> 13 | G48: =MIN(G$33+11,24) -> 14 | H48: =MIN(H$33+11,24) -> 13 | I48: =MIN(I$33+11,24) -> 14 | J48: =MIN(J$33+11,24) -> 24 | ... O48: =MIN(O$33+11,24) -> 17
A50: ИТОГИ (из листа Monthly)
A51: Выручка Y1 (мес. 1–12), сум | B51: rev1 | C51: =SUM(Monthly!C14:N14)+SUM(Monthly!C15:N15) -> 7.3179048e+09 | D51: =SUM(Monthly!C28:N28)+SUM(Monthly!C29:N29) -> 2.5719985e+10 | E51: =SUM(Monthly!C42:N42)+SUM(Monthly!C43:N43) -> 1.6057907e+09 | F51: =SUM(Monthly!C56:N56)+SUM(Monthly!C57:N57) -> 2.3391784e+09 | G51: =SUM(Monthly!C70:N70)+SUM(Monthly!C71:N71) -> 1.9896857e+09 | H51: =SUM(Monthly!C84:N84)+SUM(Monthly!C85:N85) -> 1.1529593e+09 | I51: =SUM(Monthly!C98:N98)+SUM(Monthly!C99:N99) -> 1.4043123e+09 | J51: =SUM(Monthly!C112:N112)+SUM(Monthly!C113:N113) -> 0 | K51: =SUM(Monthly!C126:N126)+SUM(Monthly!C127:N127) -> 6.1807245e+09 | L51: =SUM(Monthly!C140:N140)+SUM(Monthly!C141:N141) -> 1.3505551e+09 | M51: =SUM(Monthly!C154:N154)+SUM(Monthly!C155:N155) -> 3.9521429e+09 | N51: =SUM(Monthly!C168:N168)+SUM(Monthly!C169:N169) -> 2.2088416e+08 | O51: =SUM(Monthly!C182:N182)+SUM(Monthly!C183:N183) -> 1.5139852e+09
A52: Выручка Y2 (мес. 13–24), сум | B52: rev2 | C52: =SUM(Monthly!O14:Z14)+SUM(Monthly!O15:Z15) -> 8.4716185e+09 | D52: =SUM(Monthly!O28:Z28)+SUM(Monthly!O29:Z29) -> 2.3397644e+10 | E52: =SUM(Monthly!O42:Z42)+SUM(Monthly!O43:Z43) -> 1.7005611e+09 | F52: =SUM(Monthly!O56:Z56)+SUM(Monthly!O57:Z57) -> 2.3467208e+09 | G52: =SUM(Monthly!O70:Z70)+SUM(Monthly!O71:Z71) -> 2.7143398e+09 | H52: =SUM(Monthly!O84:Z84)+SUM(Monthly!O85:Z85) -> 5.4151312e+08 | I52: =SUM(Monthly!O98:Z98)+SUM(Monthly!O99:Z99) -> 1.756884e+09 | J52: =SUM(Monthly!O112:Z112)+SUM(Monthly!O113:Z113) -> 1.8414311e+10 | K52: =SUM(Monthly!O126:Z126)+SUM(Monthly!O127:Z127) -> 2.210659e+10 | L52: =SUM(Monthly!O140:Z140)+SUM(Monthly!O141:Z141) -> 6.2165895e+09 | M52: =SUM(Monthly!O154:Z154)+SUM(Monthly!O155:Z155) -> 4.0127466e+10 | N52: =SUM(Monthly!O168:Z168)+SUM(Monthly!O169:Z169) -> 7.0858929e+08 | O52: =SUM(Monthly!O182:Z182)+SUM(Monthly!O183:Z183) -> 2.8469061e+09
A53: Run-rate выручки/год на мес. 24, сум | B53: runrate | C53: =(Monthly!Z14+Monthly!Z15)*12 -> 8.0688544e+09 | D53: =(Monthly!Z28+Monthly!Z29)*12 -> 2.150208e+10 | E53: =(Monthly!Z42+Monthly!Z43)*12 -> 1.5951189e+09 | F53: =(Monthly!Z56+Monthly!Z57)*12 -> 2.1989019e+09 | G53: =(Monthly!Z70+Monthly!Z71)*12 -> 2.6558431e+09 | H53: =(Monthly!Z84+Monthly!Z85)*12 -> 3.2110096e+08 | I53: =(Monthly!Z98+Monthly!Z99)*12 -> 1.6952985e+09 | J53: =(Monthly!Z112+Monthly!Z113)*12 -> 1.84129e+10 | K53: =(Monthly!Z126+Monthly!Z127)*12 -> 2.2631817e+10 | L53: =(Monthly!Z140+Monthly!Z141)*12 -> 6.0070844e+09 | M53: =(Monthly!Z154+Monthly!Z155)*12 -> 3.6876533e+10 | N53: =(Monthly!Z168+Monthly!Z169)*12 -> 6.7321956e+08 | O53: =(Monthly!Z182+Monthly!Z183)*12 -> 2.7352683e+09
A54: Run-rate выручки/год, USD | B54: runrate_usd | C54: =C$53/Inputs!$C$11 -> 666847.47 | D54: =D$53/Inputs!$C$11 -> 1777031.4 | E54: =E$53/Inputs!$C$11 -> 131828.01 | F54: =F$53/Inputs!$C$11 -> 181727.43 | G54: =G$53/Inputs!$C$11 -> 219491.17 | H54: =H$53/Inputs!$C$11 -> 26537.269 | I54: =I$53/Inputs!$C$11 -> 140107.31 | J54: =J$53/Inputs!$C$11 -> 1521727.2 | ... O54: =O$53/Inputs!$C$11 -> 226055.23
A55: Затраты за 24 мес., сум | B55: cost24 | C55: =SUM(Monthly!C16:Z16) -> 1560701440 | D55: =SUM(Monthly!C30:Z30) -> 6.2643797e+09 | E55: =SUM(Monthly!C44:Z44) -> 1.0984466e+09 | F55: =SUM(Monthly!C58:Z58) -> 9.0744142e+08 | G55: =SUM(Monthly!C72:Z72) -> 567840000 | H55: =SUM(Monthly!C86:Z86) -> 524883200 | I55: =SUM(Monthly!C100:Z100) -> 395344000 | J55: =SUM(Monthly!C114:Z114) -> 1.6912965e+09 | K55: =SUM(Monthly!C128:Z128) -> 11550000000 | L55: =SUM(Monthly!C142:Z142) -> 6.4981167e+09 | M55: =SUM(Monthly!C156:Z156) -> 1.0025933e+10 | N55: =SUM(Monthly!C170:Z170) -> 3.6525564e+09 | O55: =SUM(Monthly!C184:Z184) -> 3307520000
A56: Вклад (маржа − затраты) за 24 мес., сум | B56: contrib24 | C56: =SUM(Monthly!C17:Z17) -> 1.1860393e+10 | D56: =SUM(Monthly!C31:Z31) -> 4.2853249e+10 | E56: =SUM(Monthly!C45:Z45) -> 1.7119524e+09 | F56: =SUM(Monthly!C59:Z59) -> 3.0755729e+09 | G56: =SUM(Monthly!C73:Z73) -> 8.4336762e+08 | H56: =SUM(Monthly!C87:Z87) -> 9.1541833e+08 | I56: =SUM(Monthly!C101:Z101) -> 1.5013738e+09 | J56: =SUM(Monthly!C115:Z115) -> 1.6723015e+10 | K56: =SUM(Monthly!C129:Z129) -> 1.2494218e+10 | L56: =SUM(Monthly!C143:Z143) -> -66043748 | M56: =SUM(Monthly!C157:Z157) -> 3.4053675e+10 | N56: =SUM(Monthly!C171:Z171) -> -2.862504e+09 | O56: =SUM(Monthly!C185:Z185) -> -2.5489609e+08
A57: ROI за 24 мес. (вклад / затраты) | B57: roi | C57: =IF(C$55>0,C$56/C$55,0) -> 7.5993993 | D57: =IF(D$55>0,D$56/D$55,0) -> 6.8407809 | E57: =IF(E$55>0,E$56/E$55,0) -> 1.5585212 | F57: =IF(F$55>0,F$56/F$55,0) -> 3.3892798 | G57: =IF(G$55>0,G$56/G$55,0) -> 1.4852205 | H57: =IF(H$55>0,H$56/H$55,0) -> 1.744042 | I57: =IF(I$55>0,I$56/I$55,0) -> 3.797639 | J57: =IF(J$55>0,J$56/J$55,0) -> 9.8876894 | ... O57: =IF(O$55>0,O$56/O$55,0) -> -0.077065623
A58: ΔARPU когорты на месяц оценки | B58: upl_eval | C58: =(INDEX(Monthly!$C$5:$Z$5,1,C$48)+INDEX(Monthly!$C$14:$Z$14,1,C$48))/(INDEX(Monthly!$C$4:$Z$4,1,C$48)+INDEX(Monthly!$C$18:$Z$18,1,C$48))/Inputs!$C$8-1 -> 0.014079405 | D58: =(INDEX(Monthly!$C$5:$Z$5,1,D$48)+INDEX(Monthly!$C$28:$Z$28,1,D$48))/(INDEX(Monthly!$C$4:$Z$4,1,D$48)+INDEX(Monthly!$C$32:$Z$32,1,D$48))/Inputs!$C$8-1 -> 0.045519115 | E58: =(INDEX(Monthly!$C$5:$Z$5,1,E$48)+INDEX(Monthly!$C$42:$Z$42,1,E$48))/(INDEX(Monthly!$C$4:$Z$4,1,E$48)+INDEX(Monthly!$C$46:$Z$46,1,E$48))/Inputs!$C$8-1 -> 0.0026650034 | F58: =(INDEX(Monthly!$C$5:$Z$5,1,F$48)+INDEX(Monthly!$C$56:$Z$56,1,F$48))/(INDEX(Monthly!$C$4:$Z$4,1,F$48)+INDEX(Monthly!$C$60:$Z$60,1,F$48))/Inputs!$C$8-1 -> 0.0038192832 | G58: =(INDEX(Monthly!$C$5:$Z$5,1,G$48)+INDEX(Monthly!$C$70:$Z$70,1,G$48))/(INDEX(Monthly!$C$4:$Z$4,1,G$48)+INDEX(Monthly!$C$74:$Z$74,1,G$48))/Inputs!$C$8-1 -> 0.0041433641 | H58: =(INDEX(Monthly!$C$5:$Z$5,1,H$48)+INDEX(Monthly!$C$84:$Z$84,1,H$48))/(INDEX(Monthly!$C$4:$Z$4,1,H$48)+INDEX(Monthly!$C$88:$Z$88,1,H$48))/Inputs!$C$8-1 -> 0.001300974 | I58: =(INDEX(Monthly!$C$5:$Z$5,1,I$48)+INDEX(Monthly!$C$98:$Z$98,1,I$48))/(INDEX(Monthly!$C$4:$Z$4,1,I$48)+INDEX(Monthly!$C$102:$Z$102,1,I$48))/Inputs!$C$8-1 -> 0.0026445083 | J58: =(INDEX(Monthly!$C$5:$Z$5,1,J$48)+INDEX(Monthly!$C$112:$Z$112,1,J$48))/(INDEX(Monthly!$C$4:$Z$4,1,J$48)+INDEX(Monthly!$C$116:$Z$116,1,J$48))/Inputs!$C$8-1 -> 0.038780132 | K58: =(INDEX(Monthly!$C$5:$Z$5,1,K$48)+INDEX(Monthly!$C$126:$Z$126,1,K$48))/(INDEX(Monthly!$C$4:$Z$4,1,K$48)+INDEX(Monthly!$C$130:$Z$130,1,K$48))/Inputs!$C$8-1 -> 0.029765596 | L58: =(INDEX(Monthly!$C$5:$Z$5,1,L$48)+INDEX(Monthly!$C$140:$Z$140,1,L$48))/(INDEX(Monthly!$C$4:$Z$4,1,L$48)+INDEX(Monthly!$C$144:$Z$144,1,L$48))/Inputs!$C$8-1 -> 0.0085341902 | M58: =(INDEX(Monthly!$C$5:$Z$5,1,M$48)+INDEX(Monthly!$C$154:$Z$154,1,M$48))/(INDEX(Monthly!$C$4:$Z$4,1,M$48)+INDEX(Monthly!$C$158:$Z$158,1,M$48))/Inputs!$C$8-1 -> 0.080881056 | N58: =(INDEX(Monthly!$C$5:$Z$5,1,N$48)+INDEX(Monthly!$C$168:$Z$168,1,N$48))/(INDEX(Monthly!$C$4:$Z$4,1,N$48)+INDEX(Monthly!$C$172:$Z$172,1,N$48))/Inputs!$C$8-1 -> 0.0011404358 | O58: =(INDEX(Monthly!$C$5:$Z$5,1,O$48)+INDEX(Monthly!$C$182:$Z$182,1,O$48))/(INDEX(Monthly!$C$4:$Z$4,1,O$48)+INDEX(Monthly!$C$186:$Z$186,1,O$48))/Inputs!$C$8-1 -> 0.0043452665
A59: ΔARPU когорты на мес. 24 | B59: upl24 | C59: =(Monthly!Z$5+Monthly!Z14)/(Monthly!Z$4+Monthly!Z18)/Inputs!$C$8-1 -> 0.014399468 | D59: =(Monthly!Z$5+Monthly!Z28)/(Monthly!Z$4+Monthly!Z32)/Inputs!$C$8-1 -> 0.045519115 | E59: =(Monthly!Z$5+Monthly!Z42)/(Monthly!Z$4+Monthly!Z46)/Inputs!$C$8-1 -> 0.0026093627 | F59: =(Monthly!Z$5+Monthly!Z56)/(Monthly!Z$4+Monthly!Z60)/Inputs!$C$8-1 -> 0.0038910367 | G59: =(Monthly!Z$5+Monthly!Z70)/(Monthly!Z$4+Monthly!Z74)/Inputs!$C$8-1 -> 0.0044219761 | H59: =(Monthly!Z$5+Monthly!Z84)/(Monthly!Z$4+Monthly!Z88)/Inputs!$C$8-1 -> 0.00059057687 | I59: =(Monthly!Z$5+Monthly!Z98)/(Monthly!Z$4+Monthly!Z102)/Inputs!$C$8-1 -> 0.0026853683 | J59: =(Monthly!Z$5+Monthly!Z112)/(Monthly!Z$4+Monthly!Z116)/Inputs!$C$8-1 -> 0.038780132 | K59: =(Monthly!Z$5+Monthly!Z126)/(Monthly!Z$4+Monthly!Z130)/Inputs!$C$8-1 -> 0.029655258 | L59: =(Monthly!Z$5+Monthly!Z140)/(Monthly!Z$4+Monthly!Z144)/Inputs!$C$8-1 -> 0.0087538549 | M59: =(Monthly!Z$5+Monthly!Z154)/(Monthly!Z$4+Monthly!Z158)/Inputs!$C$8-1 -> 0.080881056 | N59: =(Monthly!Z$5+Monthly!Z168)/(Monthly!Z$4+Monthly!Z172)/Inputs!$C$8-1 -> 0.0011436099 | O59: =(Monthly!Z$5+Monthly!Z182)/(Monthly!Z$4+Monthly!Z186)/Inputs!$C$8-1 -> 0.0043201933
A60: Δ абонентов к мес. 24 (вкл. новые линии) | B60: dsubs24 | C60: =Monthly!Z18+Monthly!Z19 -> 1064.6633 | D60: =Monthly!Z32+Monthly!Z33 -> -13989.323 | E60: =Monthly!Z46+Monthly!Z47 -> 792.47852 | F60: =Monthly!Z60+Monthly!Z61 -> 373.84642 | G60: =Monthly!Z74+Monthly!Z75 -> 1128.2649 | H60: =Monthly!Z88+Monthly!Z89 -> 0 | I60: =Monthly!Z102+Monthly!Z103 -> 1056.8201 | J60: =Monthly!Z116+Monthly!Z117 -> -11587.316 | K60: =Monthly!Z130+Monthly!Z131 -> 28471.16 | L60: =Monthly!Z144+Monthly!Z145 -> 8081.6304 | M60: =Monthly!Z158+Monthly!Z159 -> -29585.01 | N60: =Monthly!Z172+Monthly!Z173 -> 231.40439 | O60: =Monthly!Z186+Monthly!Z187 -> 1732.8187
A61: Δ доли рынка к мес. 24, п.п. | B61: dshare | C61: =IF(Inputs!$C$12>0,C$60/Inputs!$C$12*100,0) -> 0.0029168858 | D61: =IF(Inputs!$C$12>0,D$60/Inputs!$C$12*100,0) -> -0.038326913 | E61: =IF(Inputs!$C$12>0,E$60/Inputs!$C$12*100,0) -> 0.002171174 | F61: =IF(Inputs!$C$12>0,F$60/Inputs!$C$12*100,0) -> 0.0010242368 | G61: =IF(Inputs!$C$12>0,G$60/Inputs!$C$12*100,0) -> 0.0030911368 | H61: =IF(Inputs!$C$12>0,H$60/Inputs!$C$12*100,0) -> 0 | I61: =IF(Inputs!$C$12>0,I$60/Inputs!$C$12*100,0) -> 0.0028953975 | J61: =IF(Inputs!$C$12>0,J$60/Inputs!$C$12*100,0) -> -0.031746071 | ... O61: =IF(Inputs!$C$12>0,O$60/Inputs!$C$12*100,0) -> 0.0047474486
A62: Ожидаемый вклад с учётом P(запуска), сум | B62: exp_contrib | C62: =C$56*C$35 -> 1.0911562e+10 | D62: =D$56*D$35 -> 3.4282599e+10 | E62: =E$56*E$35 -> 1.5407572e+09 | F62: =F$56*F$35 -> 2.7680156e+09 | G62: =G$56*G$35 -> 7.1686248e+08 | H62: =H$56*H$35 -> 8.4218487e+08 | I62: =I$56*I$35 -> 1.3512364e+09 | J62: =J$56*J$35 -> 1.086996e+10 | ... O62: =O$56*O$35 -> -1.7842726e+08

Sheet Monthly
A1: Помесячный движок, 24 мес. (формулы; сум без НДС)
A3: Месяц | C3: 1 | D3: 2 | E3: 3 | F3: 4 | G3: 5 | H3: 6 | I3: 7 | J3: 8 | K3: 9 | L3: 10 | M3: 11 | N3: 12 | O3: 13 | P3: 14 | Q3: 15 | R3: 16 | S3: 17 | T3: 18 | U3: 19 | V3: 20 | W3: 21 | X3: 22 | Y3: 23 | Z3: 24
A4: S0: абоненты когорты без инициатив | C4: =Inputs!$C$7*(1-Inputs!$C$9)^C$3 -> 3467200 | D4: =Inputs!$C$7*(1-Inputs!$C$9)^D$3 -> 3415192 | E4: =Inputs!$C$7*(1-Inputs!$C$9)^E$3 -> 3363964.1 | F4: =Inputs!$C$7*(1-Inputs!$C$9)^F$3 -> 3313504.7 | G4: =Inputs!$C$7*(1-Inputs!$C$9)^G$3 -> 3263802.1 | H4: =Inputs!$C$7*(1-Inputs!$C$9)^H$3 -> 3214845.1 | I4: =Inputs!$C$7*(1-Inputs!$C$9)^I$3 -> 3166622.4 | J4: =Inputs!$C$7*(1-Inputs!$C$9)^J$3 -> 3119123 | ... Z4: =Inputs!$C$7*(1-Inputs!$C$9)^Z$3 -> 2449132
A5: R0: выручка когорты без инициатив | C5: =C4*Inputs!$C$8 -> 64143200000 | D5: =D4*Inputs!$C$8 -> 63181052000 | E5: =E4*Inputs!$C$8 -> 62233336220 | F5: =F4*Inputs!$C$8 -> 6.1299836e+10 | G5: =G4*Inputs!$C$8 -> 6.0380339e+10 | H5: =H4*Inputs!$C$8 -> 5.9474634e+10 | I5: =I4*Inputs!$C$8 -> 5.8582514e+10 | J5: =J4*Inputs!$C$8 -> 5.7703776e+10 | ... Z5: =Z4*Inputs!$C$8 -> 4.5308942e+10
A7: A1 — «Ucell 30 — Upgrade»: мягкая миграция с подарком
A8: Доля набора | B8: f | C8: =IF(C$3<Initiatives!$C$33,0,MIN((C$3-Initiatives!$C$33+1)/Initiatives!$C$34,1)) -> 0 | D8: =IF(D$3<Initiatives!$C$33,0,MIN((D$3-Initiatives!$C$33+1)/Initiatives!$C$34,1)) -> 0.25 | E8: =IF(E$3<Initiatives!$C$33,0,MIN((E$3-Initiatives!$C$33+1)/Initiatives!$C$34,1)) -> 0.5 | F8: =IF(F$3<Initiatives!$C$33,0,MIN((F$3-Initiatives!$C$33+1)/Initiatives!$C$34,1)) -> 0.75 | G8: =IF(G$3<Initiatives!$C$33,0,MIN((G$3-Initiatives!$C$33+1)/Initiatives!$C$34,1)) -> 1 | H8: =IF(H$3<Initiatives!$C$33,0,MIN((H$3-Initiatives!$C$33+1)/Initiatives!$C$34,1)) -> 1 | I8: =IF(I$3<Initiatives!$C$33,0,MIN((I$3-Initiatives!$C$33+1)/Initiatives!$C$34,1)) -> 1 | J8: =IF(J$3<Initiatives!$C$33,0,MIN((J$3-Initiatives!$C$33+1)/Initiatives!$C$34,1)) -> 1 | ... Z8: =IF(Z$3<Initiatives!$C$33,0,MIN((Z$3-Initiatives!$C$33+1)/Initiatives!$C$34,1)) -> 1
A9: Адоптеры (цель) | B9: target | C9: =Initiatives!$C$40*C8 -> 0 | D9: =Initiatives!$C$40*D8 -> 33031.68 | E9: =Initiatives!$C$40*E8 -> 66063.36 | F9: =Initiatives!$C$40*F8 -> 99095.04 | G9: =Initiatives!$C$40*G8 -> 132126.72 | H9: =Initiatives!$C$40*H8 -> 132126.72 | I9: =Initiatives!$C$40*I8 -> 132126.72 | J9: =Initiatives!$C$40*J8 -> 132126.72 | ... Z9: =Initiatives!$C$40*Z8 -> 132126.72
A10: Новые адоптеры | B10: new | C10: =MAX(C9-N(B9),0) -> 0 | D10: =MAX(D9-N(C9),0) -> 33031.68 | E10: =MAX(E9-N(D9),0) -> 33031.68 | F10: =MAX(F9-N(E9),0) -> 33031.68 | G10: =MAX(G9-N(F9),0) -> 33031.68 | H10: =MAX(H9-N(G9),0) -> 0 | I10: =MAX(I9-N(H9),0) -> 0 | J10: =MAX(J9-N(I9),0) -> 0 | ... Z10: =MAX(Z9-N(Y9),0) -> 0
A11: Удержанные (эффект оттока) | B11: R | C11: =IF(Initiatives!$C$6="adoption",N(B11)*(1-Inputs!$C$9)+N(B12)*Inputs!$C$9*Initiatives!$C$16,IF(Initiatives!$C$6="relative",N(B11)*(1-Inputs!$C$9)+C$4*Inputs!$C$9*Initiatives!$C$23*C8,0)) -> 0 | D11: =IF(Initiatives!$C$6="adoption",N(C11)*(1-Inputs!$C$9)+N(C12)*Inputs!$C$9*Initiatives!$C$16,IF(Initiatives!$C$6="relative",N(C11)*(1-Inputs!$C$9)+D$4*Inputs!$C$9*Initiatives!$C$23*D8,0)) -> 0 | E11: =IF(Initiatives!$C$6="adoption",N(D11)*(1-Inputs!$C$9)+N(D12)*Inputs!$C$9*Initiatives!$C$16,IF(Initiatives!$C$6="relative",N(D11)*(1-Inputs!$C$9)+E$4*Inputs!$C$9*Initiatives!$C$23*E8,0)) -> 49.54752 | F11: =IF(Initiatives!$C$6="adoption",N(E11)*(1-Inputs!$C$9)+N(E12)*Inputs!$C$9*Initiatives!$C$16,IF(Initiatives!$C$6="relative",N(E11)*(1-Inputs!$C$9)+F$4*Inputs!$C$9*Initiatives!$C$23*F8,0)) -> 147.23046 | G11: =IF(Initiatives!$C$6="adoption",N(F11)*(1-Inputs!$C$9)+N(F12)*Inputs!$C$9*Initiatives!$C$16,IF(Initiatives!$C$6="relative",N(F11)*(1-Inputs!$C$9)+G$4*Inputs!$C$9*Initiatives!$C$23*G8,0)) -> 291.66691 | H11: =IF(Initiatives!$C$6="adoption",N(G11)*(1-Inputs!$C$9)+N(G12)*Inputs!$C$9*Initiatives!$C$16,IF(Initiatives!$C$6="relative",N(G11)*(1-Inputs!$C$9)+H$4*Inputs!$C$9*Initiatives!$C$23*H8,0)) -> 481.50464 | I11: =IF(Initiatives!$C$6="adoption",N(H11)*(1-Inputs!$C$9)+N(H12)*Inputs!$C$9*Initiatives!$C$16,IF(Initiatives!$C$6="relative",N(H11)*(1-Inputs!$C$9)+I$4*Inputs!$C$9*Initiatives!$C$23*I8,0)) -> 665.87293 | J11: =IF(Initiatives!$C$6="adoption",N(I11)*(1-Inputs!$C$9)+N(I12)*Inputs!$C$9*Initiatives!$C$16,IF(Initiatives!$C$6="relative",N(I11)*(1-Inputs!$C$9)+J$4*Inputs!$C$9*Initiatives!$C$23*J8,0)) -> 844.88921 | ... Z11: =IF(Initiatives!$C$6="adoption",N(Y11)*(1-Inputs!$C$9)+N(Y12)*Inputs!$C$9*Initiatives!$C$16,IF(Initiatives!$C$6="relative",N(Y11)*(1-Inputs!$C$9)+Z$4*Inputs!$C$9*Initiatives!$C$23*Z8,0)) -> 3068.8738
A12: Пул адоптеров | B12: pool | C12: =N(B12)*(1-Initiatives!$C$45)*(1-Inputs!$C$9*(1-Initiatives!$C$16))+C10 -> 0 | D12: =N(C12)*(1-Initiatives!$C$45)*(1-Inputs!$C$9*(1-Initiatives!$C$16))+D10 -> 33031.68 | E12: =N(D12)*(1-Initiatives!$C$45)*(1-Inputs!$C$9*(1-Initiatives!$C$16))+E10 -> 65617.432 | F12: =N(E12)*(1-Initiatives!$C$45)*(1-Inputs!$C$9*(1-Initiatives!$C$16))+F10 -> 97763.277 | G12: =N(F12)*(1-Initiatives!$C$45)*(1-Inputs!$C$9*(1-Initiatives!$C$16))+G10 -> 129475.15 | H12: =N(G12)*(1-Initiatives!$C$45)*(1-Inputs!$C$9*(1-Initiatives!$C$16))+H10 -> 127727.24 | I12: =N(H12)*(1-Initiatives!$C$45)*(1-Inputs!$C$9*(1-Initiatives!$C$16))+I10 -> 126002.92 | J12: =N(I12)*(1-Initiatives!$C$45)*(1-Inputs!$C$9*(1-Initiatives!$C$16))+J10 -> 124301.88 | ... Z12: =N(Y12)*(1-Initiatives!$C$45)*(1-Inputs!$C$9*(1-Initiatives!$C$16))+Z10 -> 100007.17
A13: Потерянные из-за инициативы | B13: L | C13: =N(B13)*(1-Inputs!$C$9)+IF(AND(C$3>=Initiatives!$C$33,C$3<Initiatives!$C$33+Initiatives!$C$47),Initiatives!$C$43/Initiatives!$C$47,0) -> 0 | D13: =N(C13)*(1-Inputs!$C$9)+IF(AND(D$3>=Initiatives!$C$33,D$3<Initiatives!$C$33+Initiatives!$C$47),Initiatives!$C$43/Initiatives!$C$47,0) -> 917.54667 | E13: =N(D13)*(1-Inputs!$C$9)+IF(AND(E$3>=Initiatives!$C$33,E$3<Initiatives!$C$33+Initiatives!$C$47),Initiatives!$C$43/Initiatives!$C$47,0) -> 1821.3301 | F13: =N(E13)*(1-Inputs!$C$9)+IF(AND(F$3>=Initiatives!$C$33,F$3<Initiatives!$C$33+Initiatives!$C$47),Initiatives!$C$43/Initiatives!$C$47,0) -> 2711.5568 | G13: =N(F13)*(1-Inputs!$C$9)+IF(AND(G$3>=Initiatives!$C$33,G$3<Initiatives!$C$33+Initiatives!$C$47),Initiatives!$C$43/Initiatives!$C$47,0) -> 2670.8835 | H13: =N(G13)*(1-Inputs!$C$9)+IF(AND(H$3>=Initiatives!$C$33,H$3<Initiatives!$C$33+Initiatives!$C$47),Initiatives!$C$43/Initiatives!$C$47,0) -> 2630.8202 | I13: =N(H13)*(1-Inputs!$C$9)+IF(AND(I$3>=Initiatives!$C$33,I$3<Initiatives!$C$33+Initiatives!$C$47),Initiatives!$C$43/Initiatives!$C$47,0) -> 2591.3579 | J13: =N(I13)*(1-Inputs!$C$9)+IF(AND(J$3>=Initiatives!$C$33,J$3<Initiatives!$C$33+Initiatives!$C$47),Initiatives!$C$43/Initiatives!$C$47,0) -> 2552.4876 | ... Z13: =N(Y13)*(1-Inputs!$C$9)+IF(AND(Z$3>=Initiatives!$C$33,Z$3<Initiatives!$C$33+Initiatives!$C$47),Initiatives!$C$43/Initiatives!$C$47,0) -> 2004.2105
A14: Инкр. выручка когорты | B14: rev | C14: =IF(Initiatives!$C$6="adoption",C12*Initiatives!$C$14+C11*Initiatives!$C$9-C13*Initiatives!$C$9,IF(Initiatives!$C$6="reprice",IF(C$3>=Initiatives!$C$33,(Initiatives!$C$41*Initiatives!$C$44+Initiatives!$C$42*Initiatives!$C$20)*(1-Inputs!$C$9)^(C$3-Initiatives!$C$33),0)-C13*Initiatives!$C$9,C$5*Initiatives!$C$22*C8+C11*Inputs!$C$8)) -> 0 | D14: =IF(Initiatives!$C$6="adoption",D12*Initiatives!$C$14+D11*Initiatives!$C$9-D13*Initiatives!$C$9,IF(Initiatives!$C$6="reprice",IF(D$3>=Initiatives!$C$33,(Initiatives!$C$41*Initiatives!$C$44+Initiatives!$C$42*Initiatives!$C$20)*(1-Inputs!$C$9)^(D$3-Initiatives!$C$33),0)-D13*Initiatives!$C$9,D$5*Initiatives!$C$22*D8+D11*Inputs!$C$8)) -> 195437440 | E14: =IF(Initiatives!$C$6="adoption",E12*Initiatives!$C$14+E11*Initiatives!$C$9-E13*Initiatives!$C$9,IF(Initiatives!$C$6="reprice",IF(E$3>=Initiatives!$C$33,(Initiatives!$C$41*Initiatives!$C$44+Initiatives!$C$42*Initiatives!$C$20)*(1-Inputs!$C$9)^(E$3-Initiatives!$C$33),0)-E13*Initiatives!$C$9,E$5*Initiatives!$C$22*E8+E11*Inputs!$C$8)) -> 3.8930588e+08 | F14: =IF(Initiatives!$C$6="adoption",F12*Initiatives!$C$14+F11*Initiatives!$C$9-F13*Initiatives!$C$9,IF(Initiatives!$C$6="reprice",IF(F$3>=Initiatives!$C$33,(Initiatives!$C$41*Initiatives!$C$44+Initiatives!$C$42*Initiatives!$C$20)*(1-Inputs!$C$9)^(F$3-Initiatives!$C$33),0)-F13*Initiatives!$C$9,F$5*Initiatives!$C$22*F8+F11*Inputs!$C$8)) -> 5.8161045e+08 | G14: =IF(Initiatives!$C$6="adoption",G12*Initiatives!$C$14+G11*Initiatives!$C$9-G13*Initiatives!$C$9,IF(Initiatives!$C$6="reprice",IF(G$3>=Initiatives!$C$33,(Initiatives!$C$41*Initiatives!$C$44+Initiatives!$C$42*Initiatives!$C$20)*(1-Inputs!$C$9)^(G$3-Initiatives!$C$33),0)-G13*Initiatives!$C$9,G$5*Initiatives!$C$22*G8+G11*Inputs!$C$8)) -> 7.9162494e+08 | H14: =IF(Initiatives!$C$6="adoption",H12*Initiatives!$C$14+H11*Initiatives!$C$9-H13*Initiatives!$C$9,IF(Initiatives!$C$6="reprice",IF(H$3>=Initiatives!$C$33,(Initiatives!$C$41*Initiatives!$C$44+Initiatives!$C$42*Initiatives!$C$20)*(1-Inputs!$C$9)^(H$3-Initiatives!$C$33),0)-H13*Initiatives!$C$9,H$5*Initiatives!$C$22*H8+H11*Inputs!$C$8)) -> 7.8509142e+08 | I14: =IF(Initiatives!$C$6="adoption",I12*Initiatives!$C$14+I11*Initiatives!$C$9-I13*Initiatives!$C$9,IF(Initiatives!$C$6="reprice",IF(I$3>=Initiatives!$C$33,(Initiatives!$C$41*Initiatives!$C$44+Initiatives!$C$42*Initiatives!$C$20)*(1-Inputs!$C$9)^(I$3-Initiatives!$C$33),0)-I13*Initiatives!$C$9,I$5*Initiatives!$C$22*I8+I11*Inputs!$C$8)) -> 7.785838e+08 | J14: =IF(Initiatives!$C$6="adoption",J12*Initiatives!$C$14+J11*Initiatives!$C$9-J13*Initiatives!$C$9,IF(Initiatives!$C$6="reprice",IF(J$3>=Initiatives!$C$33,(Initiatives!$C$41*Initiatives!$C$44+Initiatives!$C$42*Initiatives!$C$20)*(1-Inputs!$C$9)^(J$3-Initiatives!$C$33),0)-J13*Initiatives!$C$9,J$5*Initiatives!$C$22*J8+J11*Inputs!$C$8)) -> 7.7210266e+08 | ... Z14: =IF(Initiatives!$C$6="adoption",Z12*Initiatives!$C$14+Z11*Initiatives!$C$9-Z13*Initiatives!$C$9,IF(Initiatives!$C$6="reprice",IF(Z$3>=Initiatives!$C$33,(Initiatives!$C$41*Initiatives!$C$44+Initiatives!$C$42*Initiatives!$C$20)*(1-Inputs!$C$9)^(Z$3-Initiatives!$C$33),0)-Z13*Initiatives!$C$9,Z$5*Initiatives!$C$22*Z8+Z11*Inputs!$C$8)) -> 6.7240453e+08
A15: Выручка новых линий | B15: rev_ext | C15: =C12*Initiatives!$C$24*Initiatives!$C$25 -> 0 | D15: =D12*Initiatives!$C$24*Initiatives!$C$25 -> 0 | E15: =E12*Initiatives!$C$24*Initiatives!$C$25 -> 0 | F15: =F12*Initiatives!$C$24*Initiatives!$C$25 -> 0 | G15: =G12*Initiatives!$C$24*Initiatives!$C$25 -> 0 | H15: =H12*Initiatives!$C$24*Initiatives!$C$25 -> 0 | I15: =I12*Initiatives!$C$24*Initiatives!$C$25 -> 0 | J15: =J12*Initiatives!$C$24*Initiatives!$C$25 -> 0 | ... Z15: =Z12*Initiatives!$C$24*Initiatives!$C$25 -> 0
A16: Затраты | B16: cost | C16: =IF(C$3<=Initiatives!$C$46,Initiatives!$C$29/Initiatives!$C$46,0)+IF(C$3>=Initiatives!$C$33,Initiatives!$C$30,0)+IF(C$3=Initiatives!$C$33,Initiatives!$C$39*Initiatives!$C$26,0)+C10*Initiatives!$C$27+C12*Initiatives!$C$28+IF(AND(Initiatives!$C$6="reprice",C$3>=Initiatives!$C$33),Initiatives!$C$41*Initiatives!$C$21*(1-Inputs!$C$9)^(C$3-Initiatives!$C$33)-Initiatives!$C$31,0) -> 400000000 | D16: =IF(D$3<=Initiatives!$C$46,Initiatives!$C$29/Initiatives!$C$46,0)+IF(D$3>=Initiatives!$C$33,Initiatives!$C$30,0)+IF(D$3=Initiatives!$C$33,Initiatives!$C$39*Initiatives!$C$26,0)+D10*Initiatives!$C$27+D12*Initiatives!$C$28+IF(AND(Initiatives!$C$6="reprice",D$3>=Initiatives!$C$33),Initiatives!$C$41*Initiatives!$C$21*(1-Inputs!$C$9)^(D$3-Initiatives!$C$33)-Initiatives!$C$31,0) -> 302511360 | E16: =IF(E$3<=Initiatives!$C$46,Initiatives!$C$29/Initiatives!$C$46,0)+IF(E$3>=Initiatives!$C$33,Initiatives!$C$30,0)+IF(E$3=Initiatives!$C$33,Initiatives!$C$39*Initiatives!$C$26,0)+E10*Initiatives!$C$27+E12*Initiatives!$C$28+IF(AND(Initiatives!$C$6="reprice",E$3>=Initiatives!$C$33),Initiatives!$C$41*Initiatives!$C$21*(1-Inputs!$C$9)^(E$3-Initiatives!$C$33)-Initiatives!$C$31,0) -> 96063360 | F16: =IF(F$3<=Initiatives!$C$46,Initiatives!$C$29/Initiatives!$C$46,0)+IF(F$3>=Initiatives!$C$33,Initiatives!$C$30,0)+IF(F$3=Initiatives!$C$33,Initiatives!$C$39*Initiatives!$C$26,0)+F10*Initiatives!$C$27+F12*Initiatives!$C$28+IF(AND(Initiatives!$C$6="reprice",F$3>=Initiatives!$C$33),Initiatives!$C$41*Initiatives!$C$21*(1-Inputs!$C$9)^(F$3-Initiatives!$C$33)-Initiatives!$C$31,0) -> 96063360 | G16: =IF(G$3<=Initiatives!$C$46,Initiatives!$C$29/Initiatives!$C$46,0)+IF(G$3>=Initiatives!$C$33,Initiatives!$C$30,0)+IF(G$3=Initiatives!$C$33,Initiatives!$C$39*Initiatives!$C$26,0)+G10*Initiatives!$C$27+G12*Initiatives!$C$28+IF(AND(Initiatives!$C$6="reprice",G$3>=Initiatives!$C$33),Initiatives!$C$41*Initiatives!$C$21*(1-Inputs!$C$9)^(G$3-Initiatives!$C$33)-Initiatives!$C$31,0) -> 96063360 | H16: =IF(H$3<=Initiatives!$C$46,Initiatives!$C$29/Initiatives!$C$46,0)+IF(H$3>=Initiatives!$C$33,Initiatives!$C$30,0)+IF(H$3=Initiatives!$C$33,Initiatives!$C$39*Initiatives!$C$26,0)+H10*Initiatives!$C$27+H12*Initiatives!$C$28+IF(AND(Initiatives!$C$6="reprice",H$3>=Initiatives!$C$33),Initiatives!$C$41*Initiatives!$C$21*(1-Inputs!$C$9)^(H$3-Initiatives!$C$33)-Initiatives!$C$31,0) -> 30000000 | I16: =IF(I$3<=Initiatives!$C$46,Initiatives!$C$29/Initiatives!$C$46,0)+IF(I$3>=Initiatives!$C$33,Initiatives!$C$30,0)+IF(I$3=Initiatives!$C$33,Initiatives!$C$39*Initiatives!$C$26,0)+I10*Initiatives!$C$27+I12*Initiatives!$C$28+IF(AND(Initiatives!$C$6="reprice",I$3>=Initiatives!$C$33),Initiatives!$C$41*Initiatives!$C$21*(1-Inputs!$C$9)^(I$3-Initiatives!$C$33)-Initiatives!$C$31,0) -> 30000000 | J16: =IF(J$3<=Initiatives!$C$46,Initiatives!$C$29/Initiatives!$C$46,0)+IF(J$3>=Initiatives!$C$33,Initiatives!$C$30,0)+IF(J$3=Initiatives!$C$33,Initiatives!$C$39*Initiatives!$C$26,0)+J10*Initiatives!$C$27+J12*Initiatives!$C$28+IF(AND(Initiatives!$C$6="reprice",J$3>=Initiatives!$C$33),Initiatives!$C$41*Initiatives!$C$21*(1-Inputs!$C$9)^(J$3-Initiatives!$C$33)-Initiatives!$C$31,0) -> 30000000 | ... Z16: =IF(Z$3<=Initiatives!$C$46,Initiatives!$C$29/Initiatives!$C$46,0)+IF(Z$3>=Initiatives!$C$33,Initiatives!$C$30,0)+IF(Z$3=Initiatives!$C$33,Initiatives!$C$39*Initiatives!$C$26,0)+Z10*Initiatives!$C$27+Z12*Initiatives!$C$28+IF(AND(Initiatives!$C$6="reprice",Z$3>=Initiatives!$C$33),Initiatives!$C$41*Initiatives!$C$21*(1-Inputs!$C$9)^(Z$3-Initiatives!$C$33)-Initiatives!$C$31,0) -> 30000000
A17: Вклад | B17: contrib | C17: =(C14+C15)*Initiatives!$C$32-C16 -> -400000000 | D17: =(D14+D15)*Initiatives!$C$32-D16 -> -136389536 | E17: =(E14+E15)*Initiatives!$C$32-E16 -> 2.3484663e+08 | F17: =(F14+F15)*Initiatives!$C$32-F16 -> 3.9830552e+08 | G17: =(G14+G15)*Initiatives!$C$32-G16 -> 5.7681784e+08 | H17: =(H14+H15)*Initiatives!$C$32-H16 -> 6.3732771e+08 | I17: =(I14+I15)*Initiatives!$C$32-I16 -> 6.3179623e+08 | J17: =(J14+J15)*Initiatives!$C$32-J16 -> 6.2628726e+08 | ... Z17: =(Z14+Z15)*Initiatives!$C$32-Z16 -> 5.4154385e+08
A18: Δ абонентов когорты | B18: dsubs | C18: =C11-C13 -> 0 | D18: =D11-D13 -> -917.54667 | E18: =E11-E13 -> -1771.7826 | F18: =F11-F13 -> -2564.3264 | G18: =G11-G13 -> -2379.2166 | H18: =H11-H13 -> -2149.3156 | I18: =I11-I13 -> -1925.485 | J18: =J11-J13 -> -1707.5984 | ... Z18: =Z11-Z13 -> 1064.6633
A19: Новые линии | B19: dsubs_ext | C19: =C12*Initiatives!$C$24 -> 0 | D19: =D12*Initiatives!$C$24 -> 0 | E19: =E12*Initiatives!$C$24 -> 0 | F19: =F12*Initiatives!$C$24 -> 0 | G19: =G12*Initiatives!$C$24 -> 0 | H19: =H12*Initiatives!$C$24 -> 0 | I19: =I12*Initiatives!$C$24 -> 0 | J19: =J12*Initiatives!$C$24 -> 0 | ... Z19: =Z12*Initiatives!$C$24 -> 0
A21: A2 — Точечная индексация недооценённых архивных ТП (more-for-more)
A22: Доля набора | B22: f | C22: =IF(C$3<Initiatives!$D$33,0,MIN((C$3-Initiatives!$D$33+1)/Initiatives!$D$34,1)) -> 0 | D22: =IF(D$3<Initiatives!$D$33,0,MIN((D$3-Initiatives!$D$33+1)/Initiatives!$D$34,1)) -> 1 | E22: =IF(E$3<Initiatives!$D$33,0,MIN((E$3-Initiatives!$D$33+1)/Initiatives!$D$34,1)) -> 1 | F22: =IF(F$3<Initiatives!$D$33,0,MIN((F$3-Initiatives!$D$33+1)/Initiatives!$D$34,1)) -> 1 | G22: =IF(G$3<Initiatives!$D$33,0,MIN((G$3-Initiatives!$D$33+1)/Initiatives!$D$34,1)) -> 1 | H22: =IF(H$3<Initiatives!$D$33,0,MIN((H$3-Initiatives!$D$33+1)/Initiatives!$D$34,1)) -> 1 | I22: =IF(I$3<Initiatives!$D$33,0,MIN((I$3-Initiatives!$D$33+1)/Initiatives!$D$34,1)) -> 1 | J22: =IF(J$3<Initiatives!$D$33,0,MIN((J$3-Initiatives!$D$33+1)/Initiatives!$D$34,1)) -> 1 | ... Z22: =IF(Z$3<Initiatives!$D$33,0,MIN((Z$3-Initiatives!$D$33+1)/Initiatives!$D$34,1)) -> 1
A23: Адоптеры (цель) | B23: target | C23: =Initiatives!$D$40*C22 -> 0 | D23: =Initiatives!$D$40*D22 -> 0 | E23: =Initiatives!$D$40*E22 -> 0 | F23: =Initiatives!$D$40*F22 -> 0 | G23: =Initiatives!$D$40*G22 -> 0 | H23: =Initiatives!$D$40*H22 -> 0 | I23: =Initiatives!$D$40*I22 -> 0 | J23: =Initiatives!$D$40*J22 -> 0 | ... Z23: =Initiatives!$D$40*Z22 -> 0
A24: Новые адоптеры | B24: new | C24: =MAX(C23-N(B23),0) -> 0 | D24: =MAX(D23-N(C23),0) -> 0 | E24: =MAX(E23-N(D23),0) -> 0 | F24: =MAX(F23-N(E23),0) -> 0 | G24: =MAX(G23-N(F23),0) -> 0 | H24: =MAX(H23-N(G23),0) -> 0 | I24: =MAX(I23-N(H23),0) -> 0 | J24: =MAX(J23-N(I23),0) -> 0 | ... Z24: =MAX(Z23-N(Y23),0) -> 0
A25: Удержанные (эффект оттока) | B25: R | C25: =IF(Initiatives!$D$6="adoption",N(B25)*(1-Inputs!$C$9)+N(B26)*Inputs!$C$9*Initiatives!$D$16,IF(Initiatives!$D$6="relative",N(B25)*(1-Inputs!$C$9)+C$4*Inputs!$C$9*Initiatives!$D$23*C22,0)) -> 0 | D25: =IF(Initiatives!$D$6="adoption",N(C25)*(1-Inputs!$C$9)+N(C26)*Inputs!$C$9*Initiatives!$D$16,IF(Initiatives!$D$6="relative",N(C25)*(1-Inputs!$C$9)+D$4*Inputs!$C$9*Initiatives!$D$23*D22,0)) -> 0 | E25: =IF(Initiatives!$D$6="adoption",N(D25)*(1-Inputs!$C$9)+N(D26)*Inputs!$C$9*Initiatives!$D$16,IF(Initiatives!$D$6="relative",N(D25)*(1-Inputs!$C$9)+E$4*Inputs!$C$9*Initiatives!$D$23*E22,0)) -> 0 | F25: =IF(Initiatives!$D$6="adoption",N(E25)*(1-Inputs!$C$9)+N(E26)*Inputs!$C$9*Initiatives!$D$16,IF(Initiatives!$D$6="relative",N(E25)*(1-Inputs!$C$9)+F$4*Inputs!$C$9*Initiatives!$D$23*F22,0)) -> 0 | G25: =IF(Initiatives!$D$6="adoption",N(F25)*(1-Inputs!$C$9)+N(F26)*Inputs!$C$9*Initiatives!$D$16,IF(Initiatives!$D$6="relative",N(F25)*(1-Inputs!$C$9)+G$4*Inputs!$C$9*Initiatives!$D$23*G22,0)) -> 0 | H25: =IF(Initiatives!$D$6="adoption",N(G25)*(1-Inputs!$C$9)+N(G26)*Inputs!$C$9*Initiatives!$D$16,IF(Initiatives!$D$6="relative",N(G25)*(1-Inputs!$C$9)+H$4*Inputs!$C$9*Initiatives!$D$23*H22,0)) -> 0 | I25: =IF(Initiatives!$D$6="adoption",N(H25)*(1-Inputs!$C$9)+N(H26)*Inputs!$C$9*Initiatives!$D$16,IF(Initiatives!$D$6="relative",N(H25)*(1-Inputs!$C$9)+I$4*Inputs!$C$9*Initiatives!$D$23*I22,0)) -> 0 | J25: =IF(Initiatives!$D$6="adoption",N(I25)*(1-Inputs!$C$9)+N(I26)*Inputs!$C$9*Initiatives!$D$16,IF(Initiatives!$D$6="relative",N(I25)*(1-Inputs!$C$9)+J$4*Inputs!$C$9*Initiatives!$D$23*J22,0)) -> 0 | ... Z25: =IF(Initiatives!$D$6="adoption",N(Y25)*(1-Inputs!$C$9)+N(Y26)*Inputs!$C$9*Initiatives!$D$16,IF(Initiatives!$D$6="relative",N(Y25)*(1-Inputs!$C$9)+Z$4*Inputs!$C$9*Initiatives!$D$23*Z22,0)) -> 0
A26: Пул адоптеров | B26: pool | C26: =N(B26)*(1-Initiatives!$D$45)*(1-Inputs!$C$9*(1-Initiatives!$D$16))+C24 -> 0 | D26: =N(C26)*(1-Initiatives!$D$45)*(1-Inputs!$C$9*(1-Initiatives!$D$16))+D24 -> 0 | E26: =N(D26)*(1-Initiatives!$D$45)*(1-Inputs!$C$9*(1-Initiatives!$D$16))+E24 -> 0 | F26: =N(E26)*(1-Initiatives!$D$45)*(1-Inputs!$C$9*(1-Initiatives!$D$16))+F24 -> 0 | G26: =N(F26)*(1-Initiatives!$D$45)*(1-Inputs!$C$9*(1-Initiatives!$D$16))+G24 -> 0 | H26: =N(G26)*(1-Initiatives!$D$45)*(1-Inputs!$C$9*(1-Initiatives!$D$16))+H24 -> 0 | I26: =N(H26)*(1-Initiatives!$D$45)*(1-Inputs!$C$9*(1-Initiatives!$D$16))+I24 -> 0 | J26: =N(I26)*(1-Initiatives!$D$45)*(1-Inputs!$C$9*(1-Initiatives!$D$16))+J24 -> 0 | ... Z26: =N(Y26)*(1-Initiatives!$D$45)*(1-Inputs!$C$9*(1-Initiatives!$D$16))+Z24 -> 0
A27: Потерянные из-за инициативы | B27: L | C27: =N(B27)*(1-Inputs!$C$9)+IF(AND(C$3>=Initiatives!$D$33,C$3<Initiatives!$D$33+Initiatives!$D$47),Initiatives!$D$43/Initiatives!$D$47,0) -> 0 | D27: =N(C27)*(1-Inputs!$C$9)+IF(AND(D$3>=Initiatives!$D$33,D$3<Initiatives!$D$33+Initiatives!$D$47),Initiatives!$D$43/Initiatives!$D$47,0) -> 9680 | E27: =N(D27)*(1-Inputs!$C$9)+IF(AND(E$3>=Initiatives!$D$33,E$3<Initiatives!$D$33+Initiatives!$D$47),Initiatives!$D$43/Initiatives!$D$47,0) -> 19214.8 | F27: =N(E27)*(1-Inputs!$C$9)+IF(AND(F$3>=Initiatives!$D$33,F$3<Initiatives!$D$33+Initiatives!$D$47),Initiatives!$D$43/Initiatives!$D$47,0) -> 18926.578 | G27: =N(F27)*(1-Inputs!$C$9)+IF(AND(G$3>=Initiatives!$D$33,G$3<Initiatives!$D$33+Initiatives!$D$47),Initiatives!$D$43/Initiatives!$D$47,0) -> 18642.679 | H27: =N(G27)*(1-Inputs!$C$9)+IF(AND(H$3>=Initiatives!$D$33,H$3<Initiatives!$D$33+Initiatives!$D$47),Initiatives!$D$43/Initiatives!$D$47,0) -> 18363.039 | I27: =N(H27)*(1-Inputs!$C$9)+IF(AND(I$3>=Initiatives!$D$33,I$3<Initiatives!$D$33+Initiatives!$D$47),Initiatives!$D$43/Initiatives!$D$47,0) -> 18087.594 | J27: =N(I27)*(1-Inputs!$C$9)+IF(AND(J$3>=Initiatives!$D$33,J$3<Initiatives!$D$33+Initiatives!$D$47),Initiatives!$D$43/Initiatives!$D$47,0) -> 17816.28 | ... Z27: =N(Y27)*(1-Inputs!$C$9)+IF(AND(Z$3>=Initiatives!$D$33,Z$3<Initiatives!$D$33+Initiatives!$D$47),Initiatives!$D$43/Initiatives!$D$47,0) -> 13989.323
A28: Инкр. выручка когорты | B28: rev | C28: =IF(Initiatives!$D$6="adoption",C26*Initiatives!$D$14+C25*Initiatives!$D$9-C27*Initiatives!$D$9,IF(Initiatives!$D$6="reprice",IF(C$3>=Initiatives!$D$33,(Initiatives!$D$41*Initiatives!$D$44+Initiatives!$D$42*Initiatives!$D$20)*(1-Inputs!$C$9)^(C$3-Initiatives!$D$33),0)-C27*Initiatives!$D$9,C$5*Initiatives!$D$22*C22+C25*Inputs!$C$8)) -> 0 | D28: =IF(Initiatives!$D$6="adoption",D26*Initiatives!$D$14+D25*Initiatives!$D$9-D27*Initiatives!$D$9,IF(Initiatives!$D$6="reprice",IF(D$3>=Initiatives!$D$33,(Initiatives!$D$41*Initiatives!$D$44+Initiatives!$D$42*Initiatives!$D$20)*(1-Inputs!$C$9)^(D$3-Initiatives!$D$33),0)-D27*Initiatives!$D$9,D$5*Initiatives!$D$22*D22+D25*Inputs!$C$8)) -> 2.7050069e+09 | E28: =IF(Initiatives!$D$6="adoption",E26*Initiatives!$D$14+E25*Initiatives!$D$9-E27*Initiatives!$D$9,IF(Initiatives!$D$6="reprice",IF(E$3>=Initiatives!$D$33,(Initiatives!$D$41*Initiatives!$D$44+Initiatives!$D$42*Initiatives!$D$20)*(1-Inputs!$C$9)^(E$3-Initiatives!$D$33),0)-E27*Initiatives!$D$9,E$5*Initiatives!$D$22*E22+E25*Inputs!$C$8)) -> 2.4611518e+09 | F28: =IF(Initiatives!$D$6="adoption",F26*Initiatives!$D$14+F25*Initiatives!$D$9-F27*Initiatives!$D$9,IF(Initiatives!$D$6="reprice",IF(F$3>=Initiatives!$D$33,(Initiatives!$D$41*Initiatives!$D$44+Initiatives!$D$42*Initiatives!$D$20)*(1-Inputs!$C$9)^(F$3-Initiatives!$D$33),0)-F27*Initiatives!$D$9,F$5*Initiatives!$D$22*F22+F25*Inputs!$C$8)) -> 2.4242345e+09 | G28: =IF(Initiatives!$D$6="adoption",G26*Initiatives!$D$14+G25*Initiatives!$D$9-G27*Initiatives!$D$9,IF(Initiatives!$D$6="reprice",IF(G$3>=Initiatives!$D$33,(Initiatives!$D$41*Initiatives!$D$44+Initiatives!$D$42*Initiatives!$D$20)*(1-Inputs!$C$9)^(G$3-Initiatives!$D$33),0)-G27*Initiatives!$D$9,G$5*Initiatives!$D$22*G22+G25*Inputs!$C$8)) -> 2.387871e+09 | H28: =IF(Initiatives!$D$6="adoption",H26*Initiatives!$D$14+H25*Initiatives!$D$9-H27*Initiatives!$D$9,IF(Initiatives!$D$6="reprice",IF(H$3>=Initiatives!$D$33,(Initiatives!$D$41*Initiatives!$D$44+Initiatives!$D$42*Initiatives!$D$20)*(1-Inputs!$C$9)^(H$3-Initiatives!$D$33),0)-H27*Initiatives!$D$9,H$5*Initiatives!$D$22*H22+H25*Inputs!$C$8)) -> 2.3520529e+09 | I28: =IF(Initiatives!$D$6="adoption",I26*Initiatives!$D$14+I25*Initiatives!$D$9-I27*Initiatives!$D$9,IF(Initiatives!$D$6="reprice",IF(I$3>=Initiatives!$D$33,(Initiatives!$D$41*Initiatives!$D$44+Initiatives!$D$42*Initiatives!$D$20)*(1-Inputs!$C$9)^(I$3-Initiatives!$D$33),0)-I27*Initiatives!$D$9,I$5*Initiatives!$D$22*I22+I25*Inputs!$C$8)) -> 2.3167721e+09 | J28: =IF(Initiatives!$D$6="adoption",J26*Initiatives!$D$14+J25*Initiatives!$D$9-J27*Initiatives!$D$9,IF(Initiatives!$D$6="reprice",IF(J$3>=Initiatives!$D$33,(Initiatives!$D$41*Initiatives!$D$44+Initiatives!$D$42*Initiatives!$D$20)*(1-Inputs!$C$9)^(J$3-Initiatives!$D$33),0)-J27*Initiatives!$D$9,J$5*Initiatives!$D$22*J22+J25*Inputs!$C$8)) -> 2.2820205e+09 | ... Z28: =IF(Initiatives!$D$6="adoption",Z26*Initiatives!$D$14+Z25*Initiatives!$D$9-Z27*Initiatives!$D$9,IF(Initiatives!$D$6="reprice",IF(Z$3>=Initiatives!$D$33,(Initiatives!$D$41*Initiatives!$D$44+Initiatives!$D$42*Initiatives!$D$20)*(1-Inputs!$C$9)^(Z$3-Initiatives!$D$33),0)-Z27*Initiatives!$D$9,Z$5*Initiatives!$D$22*Z22+Z25*Inputs!$C$8)) -> 1.79184e+09
A29: Выручка новых линий | B29: rev_ext | C29: =C26*Initiatives!$D$24*Initiatives!$D$25 -> 0 | D29: =D26*Initiatives!$D$24*Initiatives!$D$25 -> 0 | E29: =E26*Initiatives!$D$24*Initiatives!$D$25 -> 0 | F29: =F26*Initiatives!$D$24*Initiatives!$D$25 -> 0 | G29: =G26*Initiatives!$D$24*Initiatives!$D$25 -> 0 | H29: =H26*Initiatives!$D$24*Initiatives!$D$25 -> 0 | I29: =I26*Initiatives!$D$24*Initiatives!$D$25 -> 0 | J29: =J26*Initiatives!$D$24*Initiatives!$D$25 -> 0 | ... Z29: =Z26*Initiatives!$D$24*Initiatives!$D$25 -> 0
A30: Затраты | B30: cost | C30: =IF(C$3<=Initiatives!$D$46,Initiatives!$D$29/Initiatives!$D$46,0)+IF(C$3>=Initiatives!$D$33,Initiatives!$D$30,0)+IF(C$3=Initiatives!$D$33,Initiatives!$D$39*Initiatives!$D$26,0)+C24*Initiatives!$D$27+C26*Initiatives!$D$28+IF(AND(Initiatives!$D$6="reprice",C$3>=Initiatives!$D$33),Initiatives!$D$41*Initiatives!$D$21*(1-Inputs!$C$9)^(C$3-Initiatives!$D$33)-Initiatives!$D$31,0) -> 300000000 | D30: =IF(D$3<=Initiatives!$D$46,Initiatives!$D$29/Initiatives!$D$46,0)+IF(D$3>=Initiatives!$D$33,Initiatives!$D$30,0)+IF(D$3=Initiatives!$D$33,Initiatives!$D$39*Initiatives!$D$26,0)+D24*Initiatives!$D$27+D26*Initiatives!$D$28+IF(AND(Initiatives!$D$6="reprice",D$3>=Initiatives!$D$33),Initiatives!$D$41*Initiatives!$D$21*(1-Inputs!$C$9)^(D$3-Initiatives!$D$33)-Initiatives!$D$31,0) -> 374675200 | E30: =IF(E$3<=Initiatives!$D$46,Initiatives!$D$29/Initiatives!$D$46,0)+IF(E$3>=Initiatives!$D$33,Initiatives!$D$30,0)+IF(E$3=Initiatives!$D$33,Initiatives!$D$39*Initiatives!$D$26,0)+E24*Initiatives!$D$27+E26*Initiatives!$D$28+IF(AND(Initiatives!$D$6="reprice",E$3>=Initiatives!$D$33),Initiatives!$D$41*Initiatives!$D$21*(1-Inputs!$C$9)^(E$3-Initiatives!$D$33)-Initiatives!$D$31,0) -> 293076672 | F30: =IF(F$3<=Initiatives!$D$46,Initiatives!$D$29/Initiatives!$D$46,0)+IF(F$3>=Initiatives!$D$33,Initiatives!$D$30,0)+IF(F$3=Initiatives!$D$33,Initiatives!$D$39*Initiatives!$D$26,0)+F24*Initiatives!$D$27+F26*Initiatives!$D$28+IF(AND(Initiatives!$D$6="reprice",F$3>=Initiatives!$D$33),Initiatives!$D$41*Initiatives!$D$21*(1-Inputs!$C$9)^(F$3-Initiatives!$D$33)-Initiatives!$D$31,0) -> 2.8898052e+08 | G30: =IF(G$3<=Initiatives!$D$46,Initiatives!$D$29/Initiatives!$D$46,0)+IF(G$3>=Initiatives!$D$33,Initiatives!$D$30,0)+IF(G$3=Initiatives!$D$33,Initiatives!$D$39*Initiatives!$D$26,0)+G24*Initiatives!$D$27+G26*Initiatives!$D$28+IF(AND(Initiatives!$D$6="reprice",G$3>=Initiatives!$D$33),Initiatives!$D$41*Initiatives!$D$21*(1-Inputs!$C$9)^(G$3-Initiatives!$D$33)-Initiatives!$D$31,0) -> 2.8494581e+08 | H30: =IF(H$3<=Initiatives!$D$46,Initiatives!$D$29/Initiatives!$D$46,0)+IF(H$3>=Initiatives!$D$33,Initiatives!$D$30,0)+IF(H$3=Initiatives!$D$33,Initiatives!$D$39*Initiatives!$D$26,0)+H24*Initiatives!$D$27+H26*Initiatives!$D$28+IF(AND(Initiatives!$D$6="reprice",H$3>=Initiatives!$D$33),Initiatives!$D$41*Initiatives!$D$21*(1-Inputs!$C$9)^(H$3-Initiatives!$D$33)-Initiatives!$D$31,0) -> 2.8097163e+08 | I30: =IF(I$3<=Initiatives!$D$46,Initiatives!$D$29/Initiatives!$D$46,0)+IF(I$3>=Initiatives!$D$33,Initiatives!$D$30,0)+IF(I$3=Initiatives!$D$33,Initiatives!$D$39*Initiatives!$D$26,0)+I24*Initiatives!$D$27+I26*Initiatives!$D$28+IF(AND(Initiatives!$D$6="reprice",I$3>=Initiatives!$D$33),Initiatives!$D$41*Initiatives!$D$21*(1-Inputs!$C$9)^(I$3-Initiatives!$D$33)-Initiatives!$D$31,0) -> 2.7705705e+08 | J30: =IF(J$3<=Initiatives!$D$46,Initiatives!$D$29/Initiatives!$D$46,0)+IF(J$3>=Initiatives!$D$33,Initiatives!$D$30,0)+IF(J$3=Initiatives!$D$33,Initiatives!$D$39*Initiatives!$D$26,0)+J24*Initiatives!$D$27+J26*Initiatives!$D$28+IF(AND(Initiatives!$D$6="reprice",J$3>=Initiatives!$D$33),Initiatives!$D$41*Initiatives!$D$21*(1-Inputs!$C$9)^(J$3-Initiatives!$D$33)-Initiatives!$D$31,0) -> 2.732012e+08 | ... Z30: =IF(Z$3<=Initiatives!$D$46,Initiatives!$D$29/Initiatives!$D$46,0)+IF(Z$3>=Initiatives!$D$33,Initiatives!$D$30,0)+IF(Z$3=Initiatives!$D$33,Initiatives!$D$39*Initiatives!$D$26,0)+Z24*Initiatives!$D$27+Z26*Initiatives!$D$28+IF(AND(Initiatives!$D$6="reprice",Z$3>=Initiatives!$D$33),Initiatives!$D$41*Initiatives!$D$21*(1-Inputs!$C$9)^(Z$3-Initiatives!$D$33)-Initiatives!$D$31,0) -> 2.188133e+08
A31: Вклад | B31: contrib | C31: =(C28+C29)*Initiatives!$D$32-C30 -> -300000000 | D31: =(D28+D29)*Initiatives!$D$32-D30 -> 2.3303317e+09 | E31: =(E28+E29)*Initiatives!$D$32-E30 -> 2.1680751e+09 | F31: =(F28+F29)*Initiatives!$D$32-F30 -> 2.135254e+09 | G31: =(G28+G29)*Initiatives!$D$32-G30 -> 2.1029251e+09 | H31: =(H28+H29)*Initiatives!$D$32-H30 -> 2.0710813e+09 | I31: =(I28+I29)*Initiatives!$D$32-I30 -> 2.0397151e+09 | J31: =(J28+J29)*Initiatives!$D$32-J30 -> 2.0088193e+09 | ... Z31: =(Z28+Z29)*Initiatives!$D$32-Z30 -> 1.5730267e+09
A32: Δ абонентов когорты | B32: dsubs | C32: =C25-C27 -> 0 | D32: =D25-D27 -> -9680 | E32: =E25-E27 -> -19214.8 | F32: =F25-F27 -> -18926.578 | G32: =G25-G27 -> -18642.679 | H32: =H25-H27 -> -18363.039 | I32: =I25-I27 -> -18087.594 | J32: =J25-J27 -> -17816.28 | ... Z32: =Z25-Z27 -> -13989.323
A33: Новые линии | B33: dsubs_ext | C33: =C26*Initiatives!$D$24 -> 0 | D33: =D26*Initiatives!$D$24 -> 0 | E33: =E26*Initiatives!$D$24 -> 0 | F33: =F26*Initiatives!$D$24 -> 0 | G33: =G26*Initiatives!$D$24 -> 0 | H33: =H26*Initiatives!$D$24 -> 0 | I33: =I26*Initiatives!$D$24 -> 0 | J33: =J26*Initiatives!$D$24 -> 0 | ... Z33: =Z26*Initiatives!$D$24 -> 0
A35: A3 — PAYG → суточные/недельные микропакеты
A36: Доля набора | B36: f | C36: =IF(C$3<Initiatives!$E$33,0,MIN((C$3-Initiatives!$E$33+1)/Initiatives!$E$34,1)) -> 0 | D36: =IF(D$3<Initiatives!$E$33,0,MIN((D$3-Initiatives!$E$33+1)/Initiatives!$E$34,1)) -> 0.33333333 | E36: =IF(E$3<Initiatives!$E$33,0,MIN((E$3-Initiatives!$E$33+1)/Initiatives!$E$34,1)) -> 0.66666667 | F36: =IF(F$3<Initiatives!$E$33,0,MIN((F$3-Initiatives!$E$33+1)/Initiatives!$E$34,1)) -> 1 | G36: =IF(G$3<Initiatives!$E$33,0,MIN((G$3-Initiatives!$E$33+1)/Initiatives!$E$34,1)) -> 1 | H36: =IF(H$3<Initiatives!$E$33,0,MIN((H$3-Initiatives!$E$33+1)/Initiatives!$E$34,1)) -> 1 | I36: =IF(I$3<Initiatives!$E$33,0,MIN((I$3-Initiatives!$E$33+1)/Initiatives!$E$34,1)) -> 1 | J36: =IF(J$3<Initiatives!$E$33,0,MIN((J$3-Initiatives!$E$33+1)/Initiatives!$E$34,1)) -> 1 | ... Z36: =IF(Z$3<Initiatives!$E$33,0,MIN((Z$3-Initiatives!$E$33+1)/Initiatives!$E$34,1)) -> 1
A37: Адоптеры (цель) | B37: target | C37: =Initiatives!$E$40*C36 -> 0 | D37: =Initiatives!$E$40*D36 -> 22528 | E37: =Initiatives!$E$40*E36 -> 45056 | F37: =Initiatives!$E$40*F36 -> 67584 | G37: =Initiatives!$E$40*G36 -> 67584 | H37: =Initiatives!$E$40*H36 -> 67584 | I37: =Initiatives!$E$40*I36 -> 67584 | J37: =Initiatives!$E$40*J36 -> 67584 | ... Z37: =Initiatives!$E$40*Z36 -> 67584
A38: Новые адоптеры | B38: new | C38: =MAX(C37-N(B37),0) -> 0 | D38: =MAX(D37-N(C37),0) -> 22528 | E38: =MAX(E37-N(D37),0) -> 22528 | F38: =MAX(F37-N(E37),0) -> 22528 | G38: =MAX(G37-N(F37),0) -> 0 | H38: =MAX(H37-N(G37),0) -> 0 | I38: =MAX(I37-N(H37),0) -> 0 | J38: =MAX(J37-N(I37),0) -> 0 | ... Z38: =MAX(Z37-N(Y37),0) -> 0
A39: Удержанные (эффект оттока) | B39: R | C39: =IF(Initiatives!$E$6="adoption",N(B39)*(1-Inputs!$C$9)+N(B40)*Inputs!$C$9*Initiatives!$E$16,IF(Initiatives!$E$6="relative",N(B39)*(1-Inputs!$C$9)+C$4*Inputs!$C$9*Initiatives!$E$23*C36,0)) -> 0 | D39: =IF(Initiatives!$E$6="adoption",N(C39)*(1-Inputs!$C$9)+N(C40)*Inputs!$C$9*Initiatives!$E$16,IF(Initiatives!$E$6="relative",N(C39)*(1-Inputs!$C$9)+D$4*Inputs!$C$9*Initiatives!$E$23*D36,0)) -> 0 | E39: =IF(Initiatives!$E$6="adoption",N(D39)*(1-Inputs!$C$9)+N(D40)*Inputs!$C$9*Initiatives!$E$16,IF(Initiatives!$E$6="relative",N(D39)*(1-Inputs!$C$9)+E$4*Inputs!$C$9*Initiatives!$E$23*E36,0)) -> 16.896 | F39: =IF(Initiatives!$E$6="adoption",N(E39)*(1-Inputs!$C$9)+N(E40)*Inputs!$C$9*Initiatives!$E$16,IF(Initiatives!$E$6="relative",N(E39)*(1-Inputs!$C$9)+F$4*Inputs!$C$9*Initiatives!$E$23*F36,0)) -> 50.193792 | G39: =IF(Initiatives!$E$6="adoption",N(F39)*(1-Inputs!$C$9)+N(F40)*Inputs!$C$9*Initiatives!$E$16,IF(Initiatives!$E$6="relative",N(F39)*(1-Inputs!$C$9)+G$4*Inputs!$C$9*Initiatives!$E$23*G36,0)) -> 99.410012 | H39: =IF(Initiatives!$E$6="adoption",N(G39)*(1-Inputs!$C$9)+N(G40)*Inputs!$C$9*Initiatives!$E$16,IF(Initiatives!$E$6="relative",N(G39)*(1-Inputs!$C$9)+H$4*Inputs!$C$9*Initiatives!$E$23*H36,0)) -> 147.17593 | I39: =IF(Initiatives!$E$6="adoption",N(H39)*(1-Inputs!$C$9)+N(H40)*Inputs!$C$9*Initiatives!$E$16,IF(Initiatives!$E$6="relative",N(H39)*(1-Inputs!$C$9)+I$4*Inputs!$C$9*Initiatives!$E$23*I36,0)) -> 193.52344 | J39: =IF(Initiatives!$E$6="adoption",N(I39)*(1-Inputs!$C$9)+N(I40)*Inputs!$C$9*Initiatives!$E$16,IF(Initiatives!$E$6="relative",N(I39)*(1-Inputs!$C$9)+J$4*Inputs!$C$9*Initiatives!$E$23*J36,0)) -> 238.48383 | ... Z39: =IF(Initiatives!$E$6="adoption",N(Y39)*(1-Inputs!$C$9)+N(Y40)*Inputs!$C$9*Initiatives!$E$16,IF(Initiatives!$E$6="relative",N(Y39)*(1-Inputs!$C$9)+Z$4*Inputs!$C$9*Initiatives!$E$23*Z36,0)) -> 792.47852
A40: Пул адоптеров | B40: pool | C40: =N(B40)*(1-Initiatives!$E$45)*(1-Inputs!$C$9*(1-Initiatives!$E$16))+C38 -> 0 | D40: =N(C40)*(1-Initiatives!$E$45)*(1-Inputs!$C$9*(1-Initiatives!$E$16))+D38 -> 22528 | E40: =N(D40)*(1-Initiatives!$E$45)*(1-Inputs!$C$9*(1-Initiatives!$E$16))+E38 -> 44734.976 | F40: =N(E40)*(1-Initiatives!$E$45)*(1-Inputs!$C$9*(1-Initiatives!$E$16))+F38 -> 66625.503 | G40: =N(F40)*(1-Initiatives!$E$45)*(1-Inputs!$C$9*(1-Initiatives!$E$16))+G38 -> 65676.089 | H40: =N(G40)*(1-Initiatives!$E$45)*(1-Inputs!$C$9*(1-Initiatives!$E$16))+H38 -> 64740.205 | I40: =N(H40)*(1-Initiatives!$E$45)*(1-Inputs!$C$9*(1-Initiatives!$E$16))+I38 -> 63817.657 | J40: =N(I40)*(1-Initiatives!$E$45)*(1-Inputs!$C$9*(1-Initiatives!$E$16))+J38 -> 62908.255 | ... Z40: =N(Y40)*(1-Initiatives!$E$45)*(1-Inputs!$C$9*(1-Initiatives!$E$16))+Z38 -> 50000.715
A41: Потерянные из-за инициативы | B41: L | C41: =N(B41)*(1-Inputs!$C$9)+IF(AND(C$3>=Initiatives!$E$33,C$3<Initiatives!$E$33+Initiatives!$E$47),Initiatives!$E$43/Initiatives!$E$47,0) -> 0 | D41: =N(C41)*(1-Inputs!$C$9)+IF(AND(D$3>=Initiatives!$E$33,D$3<Initiatives!$E$33+Initiatives!$E$47),Initiatives!$E$43/Initiatives!$E$47,0) -> 0 | E41: =N(D41)*(1-Inputs!$C$9)+IF(AND(E$3>=Initiatives!$E$33,E$3<Initiatives!$E$33+Initiatives!$E$47),Initiatives!$E$43/Initiatives!$E$47,0) -> 0 | F41: =N(E41)*(1-Inputs!$C$9)+IF(AND(F$3>=Initiatives!$E$33,F$3<Initiatives!$E$33+Initiatives!$E$47),Initiatives!$E$43/Initiatives!$E$47,0) -> 0 | G41: =N(F41)*(1-Inputs!$C$9)+IF(AND(G$3>=Initiatives!$E$33,G$3<Initiatives!$E$33+Initiatives!$E$47),Initiatives!$E$43/Initiatives!$E$47,0) -> 0 | H41: =N(G41)*(1-Inputs!$C$9)+IF(AND(H$3>=Initiatives!$E$33,H$3<Initiatives!$E$33+Initiatives!$E$47),Initiatives!$E$43/Initiatives!$E$47,0) -> 0 | I41: =N(H41)*(1-Inputs!$C$9)+IF(AND(I$3>=Initiatives!$E$33,I$3<Initiatives!$E$33+Initiatives!$E$47),Initiatives!$E$43/Initiatives!$E$47,0) -> 0 | J41: =N(I41)*(1-Inputs!$C$9)+IF(AND(J$3>=Initiatives!$E$33,J$3<Initiatives!$E$33+Initiatives!$E$47),Initiatives!$E$43/Initiatives!$E$47,0) -> 0 | ... Z41: =N(Y41)*(1-Inputs!$C$9)+IF(AND(Z$3>=Initiatives!$E$33,Z$3<Initiatives!$E$33+Initiatives!$E$47),Initiatives!$E$43/Initiatives!$E$47,0) -> 0
A42: Инкр. выручка когорты | B42: rev | C42: =IF(Initiatives!$E$6="adoption",C40*Initiatives!$E$14+C39*Initiatives!$E$9-C41*Initiatives!$E$9,IF(Initiatives!$E$6="reprice",IF(C$3>=Initiatives!$E$33,(Initiatives!$E$41*Initiatives!$E$44+Initiatives!$E$42*Initiatives!$E$20)*(1-Inputs!$C$9)^(C$3-Initiatives!$E$33),0)-C41*Initiatives!$E$9,C$5*Initiatives!$E$22*C36+C39*Inputs!$C$8)) -> 0 | D42: =IF(Initiatives!$E$6="adoption",D40*Initiatives!$E$14+D39*Initiatives!$E$9-D41*Initiatives!$E$9,IF(Initiatives!$E$6="reprice",IF(D$3>=Initiatives!$E$33,(Initiatives!$E$41*Initiatives!$E$44+Initiatives!$E$42*Initiatives!$E$20)*(1-Inputs!$C$9)^(D$3-Initiatives!$E$33),0)-D41*Initiatives!$E$9,D$5*Initiatives!$E$22*D36+D39*Inputs!$C$8)) -> 56320000 | E42: =IF(Initiatives!$E$6="adoption",E40*Initiatives!$E$14+E39*Initiatives!$E$9-E41*Initiatives!$E$9,IF(Initiatives!$E$6="reprice",IF(E$3>=Initiatives!$E$33,(Initiatives!$E$41*Initiatives!$E$44+Initiatives!$E$42*Initiatives!$E$20)*(1-Inputs!$C$9)^(E$3-Initiatives!$E$33),0)-E41*Initiatives!$E$9,E$5*Initiatives!$E$22*E36+E39*Inputs!$C$8)) -> 112006400 | F42: =IF(Initiatives!$E$6="adoption",F40*Initiatives!$E$14+F39*Initiatives!$E$9-F41*Initiatives!$E$9,IF(Initiatives!$E$6="reprice",IF(F$3>=Initiatives!$E$33,(Initiatives!$E$41*Initiatives!$E$44+Initiatives!$E$42*Initiatives!$E$20)*(1-Inputs!$C$9)^(F$3-Initiatives!$E$33),0)-F41*Initiatives!$E$9,F$5*Initiatives!$E$22*F36+F39*Inputs!$C$8)) -> 1.6706569e+08 | G42: =IF(Initiatives!$E$6="adoption",G40*Initiatives!$E$14+G39*Initiatives!$E$9-G41*Initiatives!$E$9,IF(Initiatives!$E$6="reprice",IF(G$3>=Initiatives!$E$33,(Initiatives!$E$41*Initiatives!$E$44+Initiatives!$E$42*Initiatives!$E$20)*(1-Inputs!$C$9)^(G$3-Initiatives!$E$33),0)-G41*Initiatives!$E$9,G$5*Initiatives!$E$22*G36+G39*Inputs!$C$8)) -> 1.6518432e+08 | H42: =IF(Initiatives!$E$6="adoption",H40*Initiatives!$E$14+H39*Initiatives!$E$9-H41*Initiatives!$E$9,IF(Initiatives!$E$6="reprice",IF(H$3>=Initiatives!$E$33,(Initiatives!$E$41*Initiatives!$E$44+Initiatives!$E$42*Initiatives!$E$20)*(1-Inputs!$C$9)^(H$3-Initiatives!$E$33),0)-H41*Initiatives!$E$9,H$5*Initiatives!$E$22*H36+H39*Inputs!$C$8)) -> 1.6332227e+08 | I42: =IF(Initiatives!$E$6="adoption",I40*Initiatives!$E$14+I39*Initiatives!$E$9-I41*Initiatives!$E$9,IF(Initiatives!$E$6="reprice",IF(I$3>=Initiatives!$E$33,(Initiatives!$E$41*Initiatives!$E$44+Initiatives!$E$42*Initiatives!$E$20)*(1-Inputs!$C$9)^(I$3-Initiatives!$E$33),0)-I41*Initiatives!$E$9,I$5*Initiatives!$E$22*I36+I39*Inputs!$C$8)) -> 1.6147938e+08 | J42: =IF(Initiatives!$E$6="adoption",J40*Initiatives!$E$14+J39*Initiatives!$E$9-J41*Initiatives!$E$9,IF(Initiatives!$E$6="reprice",IF(J$3>=Initiatives!$E$33,(Initiatives!$E$41*Initiatives!$E$44+Initiatives!$E$42*Initiatives!$E$20)*(1-Inputs!$C$9)^(J$3-Initiatives!$E$33),0)-J41*Initiatives!$E$9,J$5*Initiatives!$E$22*J36+J39*Inputs!$C$8)) -> 1.5965548e+08 | ... Z42: =IF(Initiatives!$E$6="adoption",Z40*Initiatives!$E$14+Z39*Initiatives!$E$9-Z41*Initiatives!$E$9,IF(Initiatives!$E$6="reprice",IF(Z$3>=Initiatives!$E$33,(Initiatives!$E$41*Initiatives!$E$44+Initiatives!$E$42*Initiatives!$E$20)*(1-Inputs!$C$9)^(Z$3-Initiatives!$E$33),0)-Z41*Initiatives!$E$9,Z$5*Initiatives!$E$22*Z36+Z39*Inputs!$C$8)) -> 1.3292657e+08
A43: Выручка новых линий | B43: rev_ext | C43: =C40*Initiatives!$E$24*Initiatives!$E$25 -> 0 | D43: =D40*Initiatives!$E$24*Initiatives!$E$25 -> 0 | E43: =E40*Initiatives!$E$24*Initiatives!$E$25 -> 0 | F43: =F40*Initiatives!$E$24*Initiatives!$E$25 -> 0 | G43: =G40*Initiatives!$E$24*Initiatives!$E$25 -> 0 | H43: =H40*Initiatives!$E$24*Initiatives!$E$25 -> 0 | I43: =I40*Initiatives!$E$24*Initiatives!$E$25 -> 0 | J43: =J40*Initiatives!$E$24*Initiatives!$E$25 -> 0 | ... Z43: =Z40*Initiatives!$E$24*Initiatives!$E$25 -> 0
A44: Затраты | B44: cost | C44: =IF(C$3<=Initiatives!$E$46,Initiatives!$E$29/Initiatives!$E$46,0)+IF(C$3>=Initiatives!$E$33,Initiatives!$E$30,0)+IF(C$3=Initiatives!$E$33,Initiatives!$E$39*Initiatives!$E$26,0)+C38*Initiatives!$E$27+C40*Initiatives!$E$28+IF(AND(Initiatives!$E$6="reprice",C$3>=Initiatives!$E$33),Initiatives!$E$41*Initiatives!$E$21*(1-Inputs!$C$9)^(C$3-Initiatives!$E$33)-Initiatives!$E$31,0) -> 250000000 | D44: =IF(D$3<=Initiatives!$E$46,Initiatives!$E$29/Initiatives!$E$46,0)+IF(D$3>=Initiatives!$E$33,Initiatives!$E$30,0)+IF(D$3=Initiatives!$E$33,Initiatives!$E$39*Initiatives!$E$26,0)+D38*Initiatives!$E$27+D40*Initiatives!$E$28+IF(AND(Initiatives!$E$6="reprice",D$3>=Initiatives!$E$33),Initiatives!$E$41*Initiatives!$E$21*(1-Inputs!$C$9)^(D$3-Initiatives!$E$33)-Initiatives!$E$31,0) -> 117502400 | E44: =IF(E$3<=Initiatives!$E$46,Initiatives!$E$29/Initiatives!$E$46,0)+IF(E$3>=Initiatives!$E$33,Initiatives!$E$30,0)+IF(E$3=Initiatives!$E$33,Initiatives!$E$39*Initiatives!$E$26,0)+E38*Initiatives!$E$27+E40*Initiatives!$E$28+IF(AND(Initiatives!$E$6="reprice",E$3>=Initiatives!$E$33),Initiatives!$E$41*Initiatives!$E$21*(1-Inputs!$C$9)^(E$3-Initiatives!$E$33)-Initiatives!$E$31,0) -> 39684493 | F44: =IF(F$3<=Initiatives!$E$46,Initiatives!$E$29/Initiatives!$E$46,0)+IF(F$3>=Initiatives!$E$33,Initiatives!$E$30,0)+IF(F$3=Initiatives!$E$33,Initiatives!$E$39*Initiatives!$E$26,0)+F38*Initiatives!$E$27+F40*Initiatives!$E$28+IF(AND(Initiatives!$E$6="reprice",F$3>=Initiatives!$E$33),Initiatives!$E$41*Initiatives!$E$21*(1-Inputs!$C$9)^(F$3-Initiatives!$E$33)-Initiatives!$E$31,0) -> 46251651 | G44: =IF(G$3<=Initiatives!$E$46,Initiatives!$E$29/Initiatives!$E$46,0)+IF(G$3>=Initiatives!$E$33,Initiatives!$E$30,0)+IF(G$3=Initiatives!$E$33,Initiatives!$E$39*Initiatives!$E$26,0)+G38*Initiatives!$E$27+G40*Initiatives!$E$28+IF(AND(Initiatives!$E$6="reprice",G$3>=Initiatives!$E$33),Initiatives!$E$41*Initiatives!$E$21*(1-Inputs!$C$9)^(G$3-Initiatives!$E$33)-Initiatives!$E$31,0) -> 34702827 | H44: =IF(H$3<=Initiatives!$E$46,Initiatives!$E$29/Initiatives!$E$46,0)+IF(H$3>=Initiatives!$E$33,Initiatives!$E$30,0)+IF(H$3=Initiatives!$E$33,Initiatives!$E$39*Initiatives!$E$26,0)+H38*Initiatives!$E$27+H40*Initiatives!$E$28+IF(AND(Initiatives!$E$6="reprice",H$3>=Initiatives!$E$33),Initiatives!$E$41*Initiatives!$E$21*(1-Inputs!$C$9)^(H$3-Initiatives!$E$33)-Initiatives!$E$31,0) -> 34422061 | I44: =IF(I$3<=Initiatives!$E$46,Initiatives!$E$29/Initiatives!$E$46,0)+IF(I$3>=Initiatives!$E$33,Initiatives!$E$30,0)+IF(I$3=Initiatives!$E$33,Initiatives!$E$39*Initiatives!$E$26,0)+I38*Initiatives!$E$27+I40*Initiatives!$E$28+IF(AND(Initiatives!$E$6="reprice",I$3>=Initiatives!$E$33),Initiatives!$E$41*Initiatives!$E$21*(1-Inputs!$C$9)^(I$3-Initiatives!$E$33)-Initiatives!$E$31,0) -> 34145297 | J44: =IF(J$3<=Initiatives!$E$46,Initiatives!$E$29/Initiatives!$E$46,0)+IF(J$3>=Initiatives!$E$33,Initiatives!$E$30,0)+IF(J$3=Initiatives!$E$33,Initiatives!$E$39*Initiatives!$E$26,0)+J38*Initiatives!$E$27+J40*Initiatives!$E$28+IF(AND(Initiatives!$E$6="reprice",J$3>=Initiatives!$E$33),Initiatives!$E$41*Initiatives!$E$21*(1-Inputs!$C$9)^(J$3-Initiatives!$E$33)-Initiatives!$E$31,0) -> 33872477 | ... Z44: =IF(Z$3<=Initiatives!$E$46,Initiatives!$E$29/Initiatives!$E$46,0)+IF(Z$3>=Initiatives!$E$33,Initiatives!$E$30,0)+IF(Z$3=Initiatives!$E$33,Initiatives!$E$39*Initiatives!$E$26,0)+Z38*Initiatives!$E$27+Z40*Initiatives!$E$28+IF(AND(Initiatives!$E$6="reprice",Z$3>=Initiatives!$E$33),Initiatives!$E$41*Initiatives!$E$21*(1-Inputs!$C$9)^(Z$3-Initiatives!$E$33)-Initiatives!$E$31,0) -> 30000214
A45: Вклад | B45: contrib | C45: =(C42+C43)*Initiatives!$E$32-C44 -> -250000000 | D45: =(D42+D43)*Initiatives!$E$32-D44 -> -69630400 | E45: =(E42+E43)*Initiatives!$E$32-E44 -> 55520947 | F45: =(F42+F43)*Initiatives!$E$32-F44 -> 95754189 | G45: =(G42+G43)*Initiatives!$E$32-G44 -> 1.0570385e+08 | H45: =(H42+H43)*Initiatives!$E$32-H44 -> 1.0440187e+08 | I45: =(I42+I43)*Initiatives!$E$32-I44 -> 1.0311217e+08 | J45: =(J42+J43)*Initiatives!$E$32-J44 -> 1.0183468e+08 | ... Z45: =(Z42+Z43)*Initiatives!$E$32-Z44 -> 82987372
A46: Δ абонентов когорты | B46: dsubs | C46: =C39-C41 -> 0 | D46: =D39-D41 -> 0 | E46: =E39-E41 -> 16.896 | F46: =F39-F41 -> 50.193792 | G46: =G39-G41 -> 99.410012 | H46: =H39-H41 -> 147.17593 | I46: =I39-I41 -> 193.52344 | J46: =J39-J41 -> 238.48383 | ... Z46: =Z39-Z41 -> 792.47852
A47: Новые линии | B47: dsubs_ext | C47: =C40*Initiatives!$E$24 -> 0 | D47: =D40*Initiatives!$E$24 -> 0 | E47: =E40*Initiatives!$E$24 -> 0 | F47: =F40*Initiatives!$E$24 -> 0 | G47: =G40*Initiatives!$E$24 -> 0 | H47: =H40*Initiatives!$E$24 -> 0 | I47: =I40*Initiatives!$E$24 -> 0 | J47: =J40*Initiatives!$E$24 -> 0 | ... Z47: =Z40*Initiatives!$E$24 -> 0
A49: A4 — Smart add-on: пакет-«бустер» в момент исчерпания (opt-in автопродление)
A50: Доля набора | B50: f | C50: =IF(C$3<Initiatives!$F$33,0,MIN((C$3-Initiatives!$F$33+1)/Initiatives!$F$34,1)) -> 0 | D50: =IF(D$3<Initiatives!$F$33,0,MIN((D$3-Initiatives!$F$33+1)/Initiatives!$F$34,1)) -> 0.5 | E50: =IF(E$3<Initiatives!$F$33,0,MIN((E$3-Initiatives!$F$33+1)/Initiatives!$F$34,1)) -> 1 | F50: =IF(F$3<Initiatives!$F$33,0,MIN((F$3-Initiatives!$F$33+1)/Initiatives!$F$34,1)) -> 1 | G50: =IF(G$3<Initiatives!$F$33,0,MIN((G$3-Initiatives!$F$33+1)/Initiatives!$F$34,1)) -> 1 | H50: =IF(H$3<Initiatives!$F$33,0,MIN((H$3-Initiatives!$F$33+1)/Initiatives!$F$34,1)) -> 1 | I50: =IF(I$3<Initiatives!$F$33,0,MIN((I$3-Initiatives!$F$33+1)/Initiatives!$F$34,1)) -> 1 | J50: =IF(J$3<Initiatives!$F$33,0,MIN((J$3-Initiatives!$F$33+1)/Initiatives!$F$34,1)) -> 1 | ... Z50: =IF(Z$3<Initiatives!$F$33,0,MIN((Z$3-Initiatives!$F$33+1)/Initiatives!$F$34,1)) -> 1
A51: Адоптеры (цель) | B51: target | C51: =Initiatives!$F$40*C50 -> 0 | D51: =Initiatives!$F$40*D50 -> 15681.6 | E51: =Initiatives!$F$40*E50 -> 31363.2 | F51: =Initiatives!$F$40*F50 -> 31363.2 | G51: =Initiatives!$F$40*G50 -> 31363.2 | H51: =Initiatives!$F$40*H50 -> 31363.2 | I51: =Initiatives!$F$40*I50 -> 31363.2 | J51: =Initiatives!$F$40*J50 -> 31363.2 | ... Z51: =Initiatives!$F$40*Z50 -> 31363.2
A52: Новые адоптеры | B52: new | C52: =MAX(C51-N(B51),0) -> 0 | D52: =MAX(D51-N(C51),0) -> 15681.6 | E52: =MAX(E51-N(D51),0) -> 15681.6 | F52: =MAX(F51-N(E51),0) -> 0 | G52: =MAX(G51-N(F51),0) -> 0 | H52: =MAX(H51-N(G51),0) -> 0 | I52: =MAX(I51-N(H51),0) -> 0 | J52: =MAX(J51-N(I51),0) -> 0 | ... Z52: =MAX(Z51-N(Y51),0) -> 0
A53: Удержанные (эффект оттока) | B53: R | C53: =IF(Initiatives!$F$6="adoption",N(B53)*(1-Inputs!$C$9)+N(B54)*Inputs!$C$9*Initiatives!$F$16,IF(Initiatives!$F$6="relative",N(B53)*(1-Inputs!$C$9)+C$4*Inputs!$C$9*Initiatives!$F$23*C50,0)) -> 0 | D53: =IF(Initiatives!$F$6="adoption",N(C53)*(1-Inputs!$C$9)+N(C54)*Inputs!$C$9*Initiatives!$F$16,IF(Initiatives!$F$6="relative",N(C53)*(1-Inputs!$C$9)+D$4*Inputs!$C$9*Initiatives!$F$23*D50,0)) -> 0 | E53: =IF(Initiatives!$F$6="adoption",N(D53)*(1-Inputs!$C$9)+N(D54)*Inputs!$C$9*Initiatives!$F$16,IF(Initiatives!$F$6="relative",N(D53)*(1-Inputs!$C$9)+E$4*Inputs!$C$9*Initiatives!$F$23*E50,0)) -> 11.7612 | F53: =IF(Initiatives!$F$6="adoption",N(E53)*(1-Inputs!$C$9)+N(E54)*Inputs!$C$9*Initiatives!$F$16,IF(Initiatives!$F$6="relative",N(E53)*(1-Inputs!$C$9)+F$4*Inputs!$C$9*Initiatives!$F$23*F50,0)) -> 34.939585 | G53: =IF(Initiatives!$F$6="adoption",N(F53)*(1-Inputs!$C$9)+N(F54)*Inputs!$C$9*Initiatives!$F$16,IF(Initiatives!$F$6="relative",N(F53)*(1-Inputs!$C$9)+G$4*Inputs!$C$9*Initiatives!$F$23*G50,0)) -> 57.437488 | H53: =IF(Initiatives!$F$6="adoption",N(G53)*(1-Inputs!$C$9)+N(G54)*Inputs!$C$9*Initiatives!$F$16,IF(Initiatives!$F$6="relative",N(G53)*(1-Inputs!$C$9)+H$4*Inputs!$C$9*Initiatives!$F$23*H50,0)) -> 79.269859 | I53: =IF(Initiatives!$F$6="adoption",N(H53)*(1-Inputs!$C$9)+N(H54)*Inputs!$C$9*Initiatives!$F$16,IF(Initiatives!$F$6="relative",N(H53)*(1-Inputs!$C$9)+I$4*Inputs!$C$9*Initiatives!$F$23*I50,0)) -> 100.45136 | J53: =IF(Initiatives!$F$6="adoption",N(I53)*(1-Inputs!$C$9)+N(I54)*Inputs!$C$9*Initiatives!$F$16,IF(Initiatives!$F$6="relative",N(I53)*(1-Inputs!$C$9)+J$4*Inputs!$C$9*Initiatives!$F$23*J50,0)) -> 120.99635 | ... Z53: =IF(Initiatives!$F$6="adoption",N(Y53)*(1-Inputs!$C$9)+N(Y54)*Inputs!$C$9*Initiatives!$F$16,IF(Initiatives!$F$6="relative",N(Y53)*(1-Inputs!$C$9)+Z$4*Inputs!$C$9*Initiatives!$F$23*Z50,0)) -> 373.84642
A54: Пул адоптеров | B54: pool | C54: =N(B54)*(1-Initiatives!$F$45)*(1-Inputs!$C$9*(1-Initiatives!$F$16))+C52 -> 0 | D54: =N(C54)*(1-Initiatives!$F$45)*(1-Inputs!$C$9*(1-Initiatives!$F$16))+D52 -> 15681.6 | E54: =N(D54)*(1-Initiatives!$F$45)*(1-Inputs!$C$9*(1-Initiatives!$F$16))+E52 -> 31139.737 | F54: =N(E54)*(1-Initiatives!$F$45)*(1-Inputs!$C$9*(1-Initiatives!$F$16))+F52 -> 30695.996 | G54: =N(F54)*(1-Initiatives!$F$45)*(1-Inputs!$C$9*(1-Initiatives!$F$16))+G52 -> 30258.578 | H54: =N(G54)*(1-Initiatives!$F$45)*(1-Inputs!$C$9*(1-Initiatives!$F$16))+H52 -> 29827.393 | I54: =N(H54)*(1-Initiatives!$F$45)*(1-Inputs!$C$9*(1-Initiatives!$F$16))+I52 -> 29402.353 | J54: =N(I54)*(1-Initiatives!$F$45)*(1-Inputs!$C$9*(1-Initiatives!$F$16))+J52 -> 28983.369 | ... Z54: =N(Y54)*(1-Initiatives!$F$45)*(1-Inputs!$C$9*(1-Initiatives!$F$16))+Z52 -> 23036.55
A55: Потерянные из-за инициативы | B55: L | C55: =N(B55)*(1-Inputs!$C$9)+IF(AND(C$3>=Initiatives!$F$33,C$3<Initiatives!$F$33+Initiatives!$F$47),Initiatives!$F$43/Initiatives!$F$47,0) -> 0 | D55: =N(C55)*(1-Inputs!$C$9)+IF(AND(D$3>=Initiatives!$F$33,D$3<Initiatives!$F$33+Initiatives!$F$47),Initiatives!$F$43/Initiatives!$F$47,0) -> 0 | E55: =N(D55)*(1-Inputs!$C$9)+IF(AND(E$3>=Initiatives!$F$33,E$3<Initiatives!$F$33+Initiatives!$F$47),Initiatives!$F$43/Initiatives!$F$47,0) -> 0 | F55: =N(E55)*(1-Inputs!$C$9)+IF(AND(F$3>=Initiatives!$F$33,F$3<Initiatives!$F$33+Initiatives!$F$47),Initiatives!$F$43/Initiatives!$F$47,0) -> 0 | G55: =N(F55)*(1-Inputs!$C$9)+IF(AND(G$3>=Initiatives!$F$33,G$3<Initiatives!$F$33+Initiatives!$F$47),Initiatives!$F$43/Initiatives!$F$47,0) -> 0 | H55: =N(G55)*(1-Inputs!$C$9)+IF(AND(H$3>=Initiatives!$F$33,H$3<Initiatives!$F$33+Initiatives!$F$47),Initiatives!$F$43/Initiatives!$F$47,0) -> 0 | I55: =N(H55)*(1-Inputs!$C$9)+IF(AND(I$3>=Initiatives!$F$33,I$3<Initiatives!$F$33+Initiatives!$F$47),Initiatives!$F$43/Initiatives!$F$47,0) -> 0 | J55: =N(I55)*(1-Inputs!$C$9)+IF(AND(J$3>=Initiatives!$F$33,J$3<Initiatives!$F$33+Initiatives!$F$47),Initiatives!$F$43/Initiatives!$F$47,0) -> 0 | ... Z55: =N(Y55)*(1-Inputs!$C$9)+IF(AND(Z$3>=Initiatives!$F$33,Z$3<Initiatives!$F$33+Initiatives!$F$47),Initiatives!$F$43/Initiatives!$F$47,0) -> 0
A56: Инкр. выручка когорты | B56: rev | C56: =IF(Initiatives!$F$6="adoption",C54*Initiatives!$F$14+C53*Initiatives!$F$9-C55*Initiatives!$F$9,IF(Initiatives!$F$6="reprice",IF(C$3>=Initiatives!$F$33,(Initiatives!$F$41*Initiatives!$F$44+Initiatives!$F$42*Initiatives!$F$20)*(1-Inputs!$C$9)^(C$3-Initiatives!$F$33),0)-C55*Initiatives!$F$9,C$5*Initiatives!$F$22*C50+C53*Inputs!$C$8)) -> 0 | D56: =IF(Initiatives!$F$6="adoption",D54*Initiatives!$F$14+D53*Initiatives!$F$9-D55*Initiatives!$F$9,IF(Initiatives!$F$6="reprice",IF(D$3>=Initiatives!$F$33,(Initiatives!$F$41*Initiatives!$F$44+Initiatives!$F$42*Initiatives!$F$20)*(1-Inputs!$C$9)^(D$3-Initiatives!$F$33),0)-D55*Initiatives!$F$9,D$5*Initiatives!$F$22*D50+D53*Inputs!$C$8)) -> 117612000 | E56: =IF(Initiatives!$F$6="adoption",E54*Initiatives!$F$14+E53*Initiatives!$F$9-E55*Initiatives!$F$9,IF(Initiatives!$F$6="reprice",IF(E$3>=Initiatives!$F$33,(Initiatives!$F$41*Initiatives!$F$44+Initiatives!$F$42*Initiatives!$F$20)*(1-Inputs!$C$9)^(E$3-Initiatives!$F$33),0)-E55*Initiatives!$F$9,E$5*Initiatives!$F$22*E50+E53*Inputs!$C$8)) -> 2.3387734e+08 | F56: =IF(Initiatives!$F$6="adoption",F54*Initiatives!$F$14+F53*Initiatives!$F$9-F55*Initiatives!$F$9,IF(Initiatives!$F$6="reprice",IF(F$3>=Initiatives!$F$33,(Initiatives!$F$41*Initiatives!$F$44+Initiatives!$F$42*Initiatives!$F$20)*(1-Inputs!$C$9)^(F$3-Initiatives!$F$33),0)-F55*Initiatives!$F$9,F$5*Initiatives!$F$22*F50+F53*Inputs!$C$8)) -> 2.3119828e+08 | G56: =IF(Initiatives!$F$6="adoption",G54*Initiatives!$F$14+G53*Initiatives!$F$9-G55*Initiatives!$F$9,IF(Initiatives!$F$6="reprice",IF(G$3>=Initiatives!$F$33,(Initiatives!$F$41*Initiatives!$F$44+Initiatives!$F$42*Initiatives!$F$20)*(1-Inputs!$C$9)^(G$3-Initiatives!$F$33),0)-G55*Initiatives!$F$9,G$5*Initiatives!$F$22*G50+G53*Inputs!$C$8)) -> 2.2854758e+08 | H56: =IF(Initiatives!$F$6="adoption",H54*Initiatives!$F$14+H53*Initiatives!$F$9-H55*Initiatives!$F$9,IF(Initiatives!$F$6="reprice",IF(H$3>=Initiatives!$F$33,(Initiatives!$F$41*Initiatives!$F$44+Initiatives!$F$42*Initiatives!$F$20)*(1-Inputs!$C$9)^(H$3-Initiatives!$F$33),0)-H55*Initiatives!$F$9,H$5*Initiatives!$F$22*H50+H53*Inputs!$C$8)) -> 2.2592501e+08 | I56: =IF(Initiatives!$F$6="adoption",I54*Initiatives!$F$14+I53*Initiatives!$F$9-I55*Initiatives!$F$9,IF(Initiatives!$F$6="reprice",IF(I$3>=Initiatives!$F$33,(Initiatives!$F$41*Initiatives!$F$44+Initiatives!$F$42*Initiatives!$F$20)*(1-Inputs!$C$9)^(I$3-Initiatives!$F$33),0)-I55*Initiatives!$F$9,I$5*Initiatives!$F$22*I50+I53*Inputs!$C$8)) -> 2.2333028e+08 | J56: =IF(Initiatives!$F$6="adoption",J54*Initiatives!$F$14+J53*Initiatives!$F$9-J55*Initiatives!$F$9,IF(Initiatives!$F$6="reprice",IF(J$3>=Initiatives!$F$33,(Initiatives!$F$41*Initiatives!$F$44+Initiatives!$F$42*Initiatives!$F$20)*(1-Inputs!$C$9)^(J$3-Initiatives!$F$33),0)-J55*Initiatives!$F$9,J$5*Initiatives!$F$22*J50+J53*Inputs!$C$8)) -> 2.2076317e+08 | ... Z56: =IF(Initiatives!$F$6="adoption",Z54*Initiatives!$F$14+Z53*Initiatives!$F$9-Z55*Initiatives!$F$9,IF(Initiatives!$F$6="reprice",IF(Z$3>=Initiatives!$F$33,(Initiatives!$F$41*Initiatives!$F$44+Initiatives!$F$42*Initiatives!$F$20)*(1-Inputs!$C$9)^(Z$3-Initiatives!$F$33),0)-Z55*Initiatives!$F$9,Z$5*Initiatives!$F$22*Z50+Z53*Inputs!$C$8)) -> 1.8324183e+08
A57: Выручка новых линий | B57: rev_ext | C57: =C54*Initiatives!$F$24*Initiatives!$F$25 -> 0 | D57: =D54*Initiatives!$F$24*Initiatives!$F$25 -> 0 | E57: =E54*Initiatives!$F$24*Initiatives!$F$25 -> 0 | F57: =F54*Initiatives!$F$24*Initiatives!$F$25 -> 0 | G57: =G54*Initiatives!$F$24*Initiatives!$F$25 -> 0 | H57: =H54*Initiatives!$F$24*Initiatives!$F$25 -> 0 | I57: =I54*Initiatives!$F$24*Initiatives!$F$25 -> 0 | J57: =J54*Initiatives!$F$24*Initiatives!$F$25 -> 0 | ... Z57: =Z54*Initiatives!$F$24*Initiatives!$F$25 -> 0
A58: Затраты | B58: cost | C58: =IF(C$3<=Initiatives!$F$46,Initiatives!$F$29/Initiatives!$F$46,0)+IF(C$3>=Initiatives!$F$33,Initiatives!$F$30,0)+IF(C$3=Initiatives!$F$33,Initiatives!$F$39*Initiatives!$F$26,0)+C52*Initiatives!$F$27+C54*Initiatives!$F$28+IF(AND(Initiatives!$F$6="reprice",C$3>=Initiatives!$F$33),Initiatives!$F$41*Initiatives!$F$21*(1-Inputs!$C$9)^(C$3-Initiatives!$F$33)-Initiatives!$F$31,0) -> 350000000 | D58: =IF(D$3<=Initiatives!$F$46,Initiatives!$F$29/Initiatives!$F$46,0)+IF(D$3>=Initiatives!$F$33,Initiatives!$F$30,0)+IF(D$3=Initiatives!$F$33,Initiatives!$F$39*Initiatives!$F$26,0)+D52*Initiatives!$F$27+D54*Initiatives!$F$28+IF(AND(Initiatives!$F$6="reprice",D$3>=Initiatives!$F$33),Initiatives!$F$41*Initiatives!$F$21*(1-Inputs!$C$9)^(D$3-Initiatives!$F$33)-Initiatives!$F$31,0) -> 41600800 | E58: =IF(E$3<=Initiatives!$F$46,Initiatives!$F$29/Initiatives!$F$46,0)+IF(E$3>=Initiatives!$F$33,Initiatives!$F$30,0)+IF(E$3=Initiatives!$F$33,Initiatives!$F$39*Initiatives!$F$26,0)+E52*Initiatives!$F$27+E54*Initiatives!$F$28+IF(AND(Initiatives!$F$6="reprice",E$3>=Initiatives!$F$33),Initiatives!$F$41*Initiatives!$F$21*(1-Inputs!$C$9)^(E$3-Initiatives!$F$33)-Initiatives!$F$31,0) -> 25569869 | F58: =IF(F$3<=Initiatives!$F$46,Initiatives!$F$29/Initiatives!$F$46,0)+IF(F$3>=Initiatives!$F$33,Initiatives!$F$30,0)+IF(F$3=Initiatives!$F$33,Initiatives!$F$39*Initiatives!$F$26,0)+F52*Initiatives!$F$27+F54*Initiatives!$F$28+IF(AND(Initiatives!$F$6="reprice",F$3>=Initiatives!$F$33),Initiatives!$F$41*Initiatives!$F$21*(1-Inputs!$C$9)^(F$3-Initiatives!$F$33)-Initiatives!$F$31,0) -> 25347998 | G58: =IF(G$3<=Initiatives!$F$46,Initiatives!$F$29/Initiatives!$F$46,0)+IF(G$3>=Initiatives!$F$33,Initiatives!$F$30,0)+IF(G$3=Initiatives!$F$33,Initiatives!$F$39*Initiatives!$F$26,0)+G52*Initiatives!$F$27+G54*Initiatives!$F$28+IF(AND(Initiatives!$F$6="reprice",G$3>=Initiatives!$F$33),Initiatives!$F$41*Initiatives!$F$21*(1-Inputs!$C$9)^(G$3-Initiatives!$F$33)-Initiatives!$F$31,0) -> 25129289 | H58: =IF(H$3<=Initiatives!$F$46,Initiatives!$F$29/Initiatives!$F$46,0)+IF(H$3>=Initiatives!$F$33,Initiatives!$F$30,0)+IF(H$3=Initiatives!$F$33,Initiatives!$F$39*Initiatives!$F$26,0)+H52*Initiatives!$F$27+H54*Initiatives!$F$28+IF(AND(Initiatives!$F$6="reprice",H$3>=Initiatives!$F$33),Initiatives!$F$41*Initiatives!$F$21*(1-Inputs!$C$9)^(H$3-Initiatives!$F$33)-Initiatives!$F$31,0) -> 24913697 | I58: =IF(I$3<=Initiatives!$F$46,Initiatives!$F$29/Initiatives!$F$46,0)+IF(I$3>=Initiatives!$F$33,Initiatives!$F$30,0)+IF(I$3=Initiatives!$F$33,Initiatives!$F$39*Initiatives!$F$26,0)+I52*Initiatives!$F$27+I54*Initiatives!$F$28+IF(AND(Initiatives!$F$6="reprice",I$3>=Initiatives!$F$33),Initiatives!$F$41*Initiatives!$F$21*(1-Inputs!$C$9)^(I$3-Initiatives!$F$33)-Initiatives!$F$31,0) -> 24701176 | J58: =IF(J$3<=Initiatives!$F$46,Initiatives!$F$29/Initiatives!$F$46,0)+IF(J$3>=Initiatives!$F$33,Initiatives!$F$30,0)+IF(J$3=Initiatives!$F$33,Initiatives!$F$39*Initiatives!$F$26,0)+J52*Initiatives!$F$27+J54*Initiatives!$F$28+IF(AND(Initiatives!$F$6="reprice",J$3>=Initiatives!$F$33),Initiatives!$F$41*Initiatives!$F$21*(1-Inputs!$C$9)^(J$3-Initiatives!$F$33)-Initiatives!$F$31,0) -> 24491685 | ... Z58: =IF(Z$3<=Initiatives!$F$46,Initiatives!$F$29/Initiatives!$F$46,0)+IF(Z$3>=Initiatives!$F$33,Initiatives!$F$30,0)+IF(Z$3=Initiatives!$F$33,Initiatives!$F$39*Initiatives!$F$26,0)+Z52*Initiatives!$F$27+Z54*Initiatives!$F$28+IF(AND(Initiatives!$F$6="reprice",Z$3>=Initiatives!$F$33),Initiatives!$F$41*Initiatives!$F$21*(1-Inputs!$C$9)^(Z$3-Initiatives!$F$33)-Initiatives!$F$31,0) -> 21518275
A59: Вклад | B59: contrib | C59: =(C56+C57)*Initiatives!$F$32-C58 -> -350000000 | D59: =(D56+D57)*Initiatives!$F$32-D58 -> 58369400 | E59: =(E56+E57)*Initiatives!$F$32-E58 -> 1.7322587e+08 | F59: =(F56+F57)*Initiatives!$F$32-F58 -> 1.7117054e+08 | G59: =(G56+G57)*Initiatives!$F$32-G58 -> 1.6913616e+08 | H59: =(H56+H57)*Initiatives!$F$32-H58 -> 1.6712256e+08 | I59: =(I56+I57)*Initiatives!$F$32-I58 -> 1.6512957e+08 | J59: =(J56+J57)*Initiatives!$F$32-J58 -> 1.6315701e+08 | ... Z59: =(Z56+Z57)*Initiatives!$F$32-Z58 -> 1.3423728e+08
A60: Δ абонентов когорты | B60: dsubs | C60: =C53-C55 -> 0 | D60: =D53-D55 -> 0 | E60: =E53-E55 -> 11.7612 | F60: =F53-F55 -> 34.939585 | G60: =G53-G55 -> 57.437488 | H60: =H53-H55 -> 79.269859 | I60: =I53-I55 -> 100.45136 | J60: =J53-J55 -> 120.99635 | ... Z60: =Z53-Z55 -> 373.84642
A61: Новые линии | B61: dsubs_ext | C61: =C54*Initiatives!$F$24 -> 0 | D61: =D54*Initiatives!$F$24 -> 0 | E61: =E54*Initiatives!$F$24 -> 0 | F61: =F54*Initiatives!$F$24 -> 0 | G61: =G54*Initiatives!$F$24 -> 0 | H61: =H54*Initiatives!$F$24 -> 0 | I61: =I54*Initiatives!$F$24 -> 0 | J61: =J54*Initiatives!$F$24 -> 0 | ... Z61: =Z54*Initiatives!$F$24 -> 0
A63: A5 — Контент-надстройка (Yandex Plus / OVVA / Ucell TV) для архивных ТП
A64: Доля набора | B64: f | C64: =IF(C$3<Initiatives!$G$33,0,MIN((C$3-Initiatives!$G$33+1)/Initiatives!$G$34,1)) -> 0 | D64: =IF(D$3<Initiatives!$G$33,0,MIN((D$3-Initiatives!$G$33+1)/Initiatives!$G$34,1)) -> 0 | E64: =IF(E$3<Initiatives!$G$33,0,MIN((E$3-Initiatives!$G$33+1)/Initiatives!$G$34,1)) -> 0.25 | F64: =IF(F$3<Initiatives!$G$33,0,MIN((F$3-Initiatives!$G$33+1)/Initiatives!$G$34,1)) -> 0.5 | G64: =IF(G$3<Initiatives!$G$33,0,MIN((G$3-Initiatives!$G$33+1)/Initiatives!$G$34,1)) -> 0.75 | H64: =IF(H$3<Initiatives!$G$33,0,MIN((H$3-Initiatives!$G$33+1)/Initiatives!$G$34,1)) -> 1 | I64: =IF(I$3<Initiatives!$G$33,0,MIN((I$3-Initiatives!$G$33+1)/Initiatives!$G$34,1)) -> 1 | J64: =IF(J$3<Initiatives!$G$33,0,MIN((J$3-Initiatives!$G$33+1)/Initiatives!$G$34,1)) -> 1 | ... Z64: =IF(Z$3<Initiatives!$G$33,0,MIN((Z$3-Initiatives!$G$33+1)/Initiatives!$G$34,1)) -> 1
A65: Адоптеры (цель) | B65: target | C65: =Initiatives!$G$40*C64 -> 0 | D65: =Initiatives!$G$40*D64 -> 0 | E65: =Initiatives!$G$40*E64 -> 4928 | F65: =Initiatives!$G$40*F64 -> 9856 | G65: =Initiatives!$G$40*G64 -> 14784 | H65: =Initiatives!$G$40*H64 -> 19712 | I65: =Initiatives!$G$40*I64 -> 19712 | J65: =Initiatives!$G$40*J64 -> 19712 | ... Z65: =Initiatives!$G$40*Z64 -> 19712
A66: Новые адоптеры | B66: new | C66: =MAX(C65-N(B65),0) -> 0 | D66: =MAX(D65-N(C65),0) -> 0 | E66: =MAX(E65-N(D65),0) -> 4928 | F66: =MAX(F65-N(E65),0) -> 4928 | G66: =MAX(G65-N(F65),0) -> 4928 | H66: =MAX(H65-N(G65),0) -> 4928 | I66: =MAX(I65-N(H65),0) -> 0 | J66: =MAX(J65-N(I65),0) -> 0 | ... Z66: =MAX(Z65-N(Y65),0) -> 0
A67: Удержанные (эффект оттока) | B67: R | C67: =IF(Initiatives!$G$6="adoption",N(B67)*(1-Inputs!$C$9)+N(B68)*Inputs!$C$9*Initiatives!$G$16,IF(Initiatives!$G$6="relative",N(B67)*(1-Inputs!$C$9)+C$4*Inputs!$C$9*Initiatives!$G$23*C64,0)) -> 0 | D67: =IF(Initiatives!$G$6="adoption",N(C67)*(1-Inputs!$C$9)+N(C68)*Inputs!$C$9*Initiatives!$G$16,IF(Initiatives!$G$6="relative",N(C67)*(1-Inputs!$C$9)+D$4*Inputs!$C$9*Initiatives!$G$23*D64,0)) -> 0 | E67: =IF(Initiatives!$G$6="adoption",N(D67)*(1-Inputs!$C$9)+N(D68)*Inputs!$C$9*Initiatives!$G$16,IF(Initiatives!$G$6="relative",N(D67)*(1-Inputs!$C$9)+E$4*Inputs!$C$9*Initiatives!$G$23*E64,0)) -> 0 | F67: =IF(Initiatives!$G$6="adoption",N(E67)*(1-Inputs!$C$9)+N(E68)*Inputs!$C$9*Initiatives!$G$16,IF(Initiatives!$G$6="relative",N(E67)*(1-Inputs!$C$9)+F$4*Inputs!$C$9*Initiatives!$G$23*F64,0)) -> 18.48 | G67: =IF(Initiatives!$G$6="adoption",N(F67)*(1-Inputs!$C$9)+N(F68)*Inputs!$C$9*Initiatives!$G$16,IF(Initiatives!$G$6="relative",N(F67)*(1-Inputs!$C$9)+G$4*Inputs!$C$9*Initiatives!$G$23*G64,0)) -> 54.9549 | H67: =IF(Initiatives!$G$6="adoption",N(G67)*(1-Inputs!$C$9)+N(G68)*Inputs!$C$9*Initiatives!$G$16,IF(Initiatives!$G$6="relative",N(G67)*(1-Inputs!$C$9)+H$4*Inputs!$C$9*Initiatives!$G$23*H64,0)) -> 108.94922 | I67: =IF(Initiatives!$G$6="adoption",N(H67)*(1-Inputs!$C$9)+N(H68)*Inputs!$C$9*Initiatives!$G$16,IF(Initiatives!$G$6="relative",N(H67)*(1-Inputs!$C$9)+I$4*Inputs!$C$9*Initiatives!$G$23*I64,0)) -> 179.99691 | J67: =IF(Initiatives!$G$6="adoption",N(I67)*(1-Inputs!$C$9)+N(I68)*Inputs!$C$9*Initiatives!$G$16,IF(Initiatives!$G$6="relative",N(I67)*(1-Inputs!$C$9)+J$4*Inputs!$C$9*Initiatives!$G$23*J64,0)) -> 249.16121 | ... Z67: =IF(Initiatives!$G$6="adoption",N(Y67)*(1-Inputs!$C$9)+N(Y68)*Inputs!$C$9*Initiatives!$G$16,IF(Initiatives!$G$6="relative",N(Y67)*(1-Inputs!$C$9)+Z$4*Inputs!$C$9*Initiatives!$G$23*Z64,0)) -> 1128.2649
A68: Пул адоптеров | B68: pool | C68: =N(B68)*(1-Initiatives!$G$45)*(1-Inputs!$C$9*(1-Initiatives!$G$16))+C66 -> 0 | D68: =N(C68)*(1-Initiatives!$G$45)*(1-Inputs!$C$9*(1-Initiatives!$G$16))+D66 -> 0 | E68: =N(D68)*(1-Initiatives!$G$45)*(1-Inputs!$C$9*(1-Initiatives!$G$16))+E66 -> 4928 | F68: =N(E68)*(1-Initiatives!$G$45)*(1-Inputs!$C$9*(1-Initiatives!$G$16))+F66 -> 9800.56 | G68: =N(F68)*(1-Initiatives!$G$45)*(1-Inputs!$C$9*(1-Initiatives!$G$16))+G66 -> 14618.304 | H68: =N(G68)*(1-Initiatives!$G$45)*(1-Inputs!$C$9*(1-Initiatives!$G$16))+H66 -> 19381.848 | I68: =N(H68)*(1-Initiatives!$G$45)*(1-Inputs!$C$9*(1-Initiatives!$G$16))+I66 -> 19163.802 | J68: =N(I68)*(1-Initiatives!$G$45)*(1-Inputs!$C$9*(1-Initiatives!$G$16))+J66 -> 18948.209 | ... Z68: =N(Y68)*(1-Initiatives!$G$45)*(1-Inputs!$C$9*(1-Initiatives!$G$16))+Z66 -> 15810.737
A69: Потерянные из-за инициативы | B69: L | C69: =N(B69)*(1-Inputs!$C$9)+IF(AND(C$3>=Initiatives!$G$33,C$3<Initiatives!$G$33+Initiatives!$G$47),Initiatives!$G$43/Initiatives!$G$47,0) -> 0 | D69: =N(C69)*(1-Inputs!$C$9)+IF(AND(D$3>=Initiatives!$G$33,D$3<Initiatives!$G$33+Initiatives!$G$47),Initiatives!$G$43/Initiatives!$G$47,0) -> 0 | E69: =N(D69)*(1-Inputs!$C$9)+IF(AND(E$3>=Initiatives!$G$33,E$3<Initiatives!$G$33+Initiatives!$G$47),Initiatives!$G$43/Initiatives!$G$47,0) -> 0 | F69: =N(E69)*(1-Inputs!$C$9)+IF(AND(F$3>=Initiatives!$G$33,F$3<Initiatives!$G$33+Initiatives!$G$47),Initiatives!$G$43/Initiatives!$G$47,0) -> 0 | G69: =N(F69)*(1-Inputs!$C$9)+IF(AND(G$3>=Initiatives!$G$33,G$3<Initiatives!$G$33+Initiatives!$G$47),Initiatives!$G$43/Initiatives!$G$47,0) -> 0 | H69: =N(G69)*(1-Inputs!$C$9)+IF(AND(H$3>=Initiatives!$G$33,H$3<Initiatives!$G$33+Initiatives!$G$47),Initiatives!$G$43/Initiatives!$G$47,0) -> 0 | I69: =N(H69)*(1-Inputs!$C$9)+IF(AND(I$3>=Initiatives!$G$33,I$3<Initiatives!$G$33+Initiatives!$G$47),Initiatives!$G$43/Initiatives!$G$47,0) -> 0 | J69: =N(I69)*(1-Inputs!$C$9)+IF(AND(J$3>=Initiatives!$G$33,J$3<Initiatives!$G$33+Initiatives!$G$47),Initiatives!$G$43/Initiatives!$G$47,0) -> 0 | ... Z69: =N(Y69)*(1-Inputs!$C$9)+IF(AND(Z$3>=Initiatives!$G$33,Z$3<Initiatives!$G$33+Initiatives!$G$47),Initiatives!$G$43/Initiatives!$G$47,0) -> 0
A70: Инкр. выручка когорты | B70: rev | C70: =IF(Initiatives!$G$6="adoption",C68*Initiatives!$G$14+C67*Initiatives!$G$9-C69*Initiatives!$G$9,IF(Initiatives!$G$6="reprice",IF(C$3>=Initiatives!$G$33,(Initiatives!$G$41*Initiatives!$G$44+Initiatives!$G$42*Initiatives!$G$20)*(1-Inputs!$C$9)^(C$3-Initiatives!$G$33),0)-C69*Initiatives!$G$9,C$5*Initiatives!$G$22*C64+C67*Inputs!$C$8)) -> 0 | D70: =IF(Initiatives!$G$6="adoption",D68*Initiatives!$G$14+D67*Initiatives!$G$9-D69*Initiatives!$G$9,IF(Initiatives!$G$6="reprice",IF(D$3>=Initiatives!$G$33,(Initiatives!$G$41*Initiatives!$G$44+Initiatives!$G$42*Initiatives!$G$20)*(1-Inputs!$C$9)^(D$3-Initiatives!$G$33),0)-D69*Initiatives!$G$9,D$5*Initiatives!$G$22*D64+D67*Inputs!$C$8)) -> 0 | E70: =IF(Initiatives!$G$6="adoption",E68*Initiatives!$G$14+E67*Initiatives!$G$9-E69*Initiatives!$G$9,IF(Initiatives!$G$6="reprice",IF(E$3>=Initiatives!$G$33,(Initiatives!$G$41*Initiatives!$G$44+Initiatives!$G$42*Initiatives!$G$20)*(1-Inputs!$C$9)^(E$3-Initiatives!$G$33),0)-E69*Initiatives!$G$9,E$5*Initiatives!$G$22*E64+E67*Inputs!$C$8)) -> 59136000 | F70: =IF(Initiatives!$G$6="adoption",F68*Initiatives!$G$14+F67*Initiatives!$G$9-F69*Initiatives!$G$9,IF(Initiatives!$G$6="reprice",IF(F$3>=Initiatives!$G$33,(Initiatives!$G$41*Initiatives!$G$44+Initiatives!$G$42*Initiatives!$G$20)*(1-Inputs!$C$9)^(F$3-Initiatives!$G$33),0)-F69*Initiatives!$G$9,F$5*Initiatives!$G$22*F64+F67*Inputs!$C$8)) -> 118124160 | G70: =IF(Initiatives!$G$6="adoption",G68*Initiatives!$G$14+G67*Initiatives!$G$9-G69*Initiatives!$G$9,IF(Initiatives!$G$6="reprice",IF(G$3>=Initiatives!$G$33,(Initiatives!$G$41*Initiatives!$G$44+Initiatives!$G$42*Initiatives!$G$20)*(1-Inputs!$C$9)^(G$3-Initiatives!$G$33),0)-G69*Initiatives!$G$9,G$5*Initiatives!$G$22*G64+G67*Inputs!$C$8)) -> 1.7695838e+08 | H70: =IF(Initiatives!$G$6="adoption",H68*Initiatives!$G$14+H67*Initiatives!$G$9-H69*Initiatives!$G$9,IF(Initiatives!$G$6="reprice",IF(H$3>=Initiatives!$G$33,(Initiatives!$G$41*Initiatives!$G$44+Initiatives!$G$42*Initiatives!$G$20)*(1-Inputs!$C$9)^(H$3-Initiatives!$G$33),0)-H69*Initiatives!$G$9,H$5*Initiatives!$G$22*H64+H67*Inputs!$C$8)) -> 2.3563275e+08 | I70: =IF(Initiatives!$G$6="adoption",I68*Initiatives!$G$14+I67*Initiatives!$G$9-I69*Initiatives!$G$9,IF(Initiatives!$G$6="reprice",IF(I$3>=Initiatives!$G$33,(Initiatives!$G$41*Initiatives!$G$44+Initiatives!$G$42*Initiatives!$G$20)*(1-Inputs!$C$9)^(I$3-Initiatives!$G$33),0)-I69*Initiatives!$G$9,I$5*Initiatives!$G$22*I64+I67*Inputs!$C$8)) -> 2.3500554e+08 | J70: =IF(Initiatives!$G$6="adoption",J68*Initiatives!$G$14+J67*Initiatives!$G$9-J69*Initiatives!$G$9,IF(Initiatives!$G$6="reprice",IF(J$3>=Initiatives!$G$33,(Initiatives!$G$41*Initiatives!$G$44+Initiatives!$G$42*Initiatives!$G$20)*(1-Inputs!$C$9)^(J$3-Initiatives!$G$33),0)-J69*Initiatives!$G$9,J$5*Initiatives!$G$22*J64+J67*Inputs!$C$8)) -> 2.3435502e+08 | ... Z70: =IF(Initiatives!$G$6="adoption",Z68*Initiatives!$G$14+Z67*Initiatives!$G$9-Z69*Initiatives!$G$9,IF(Initiatives!$G$6="reprice",IF(Z$3>=Initiatives!$G$33,(Initiatives!$G$41*Initiatives!$G$44+Initiatives!$G$42*Initiatives!$G$20)*(1-Inputs!$C$9)^(Z$3-Initiatives!$G$33),0)-Z69*Initiatives!$G$9,Z$5*Initiatives!$G$22*Z64+Z67*Inputs!$C$8)) -> 2.2132026e+08
A71: Выручка новых линий | B71: rev_ext | C71: =C68*Initiatives!$G$24*Initiatives!$G$25 -> 0 | D71: =D68*Initiatives!$G$24*Initiatives!$G$25 -> 0 | E71: =E68*Initiatives!$G$24*Initiatives!$G$25 -> 0 | F71: =F68*Initiatives!$G$24*Initiatives!$G$25 -> 0 | G71: =G68*Initiatives!$G$24*Initiatives!$G$25 -> 0 | H71: =H68*Initiatives!$G$24*Initiatives!$G$25 -> 0 | I71: =I68*Initiatives!$G$24*Initiatives!$G$25 -> 0 | J71: =J68*Initiatives!$G$24*Initiatives!$G$25 -> 0 | ... Z71: =Z68*Initiatives!$G$24*Initiatives!$G$25 -> 0
A72: Затраты | B72: cost | C72: =IF(C$3<=Initiatives!$G$46,Initiatives!$G$29/Initiatives!$G$46,0)+IF(C$3>=Initiatives!$G$33,Initiatives!$G$30,0)+IF(C$3=Initiatives!$G$33,Initiatives!$G$39*Initiatives!$G$26,0)+C66*Initiatives!$G$27+C68*Initiatives!$G$28+IF(AND(Initiatives!$G$6="reprice",C$3>=Initiatives!$G$33),Initiatives!$G$41*Initiatives!$G$21*(1-Inputs!$C$9)^(C$3-Initiatives!$G$33)-Initiatives!$G$31,0) -> 100000000 | D72: =IF(D$3<=Initiatives!$G$46,Initiatives!$G$29/Initiatives!$G$46,0)+IF(D$3>=Initiatives!$G$33,Initiatives!$G$30,0)+IF(D$3=Initiatives!$G$33,Initiatives!$G$39*Initiatives!$G$26,0)+D66*Initiatives!$G$27+D68*Initiatives!$G$28+IF(AND(Initiatives!$G$6="reprice",D$3>=Initiatives!$G$33),Initiatives!$G$41*Initiatives!$G$21*(1-Inputs!$C$9)^(D$3-Initiatives!$G$33)-Initiatives!$G$31,0) -> 100000000 | E72: =IF(E$3<=Initiatives!$G$46,Initiatives!$G$29/Initiatives!$G$46,0)+IF(E$3>=Initiatives!$G$33,Initiatives!$G$30,0)+IF(E$3=Initiatives!$G$33,Initiatives!$G$39*Initiatives!$G$26,0)+E66*Initiatives!$G$27+E68*Initiatives!$G$28+IF(AND(Initiatives!$G$6="reprice",E$3>=Initiatives!$G$33),Initiatives!$G$41*Initiatives!$G$21*(1-Inputs!$C$9)^(E$3-Initiatives!$G$33)-Initiatives!$G$31,0) -> 157840000 | F72: =IF(F$3<=Initiatives!$G$46,Initiatives!$G$29/Initiatives!$G$46,0)+IF(F$3>=Initiatives!$G$33,Initiatives!$G$30,0)+IF(F$3=Initiatives!$G$33,Initiatives!$G$39*Initiatives!$G$26,0)+F66*Initiatives!$G$27+F68*Initiatives!$G$28+IF(AND(Initiatives!$G$6="reprice",F$3>=Initiatives!$G$33),Initiatives!$G$41*Initiatives!$G$21*(1-Inputs!$C$9)^(F$3-Initiatives!$G$33)-Initiatives!$G$31,0) -> 10000000 | G72: =IF(G$3<=Initiatives!$G$46,Initiatives!$G$29/Initiatives!$G$46,0)+IF(G$3>=Initiatives!$G$33,Initiatives!$G$30,0)+IF(G$3=Initiatives!$G$33,Initiatives!$G$39*Initiatives!$G$26,0)+G66*Initiatives!$G$27+G68*Initiatives!$G$28+IF(AND(Initiatives!$G$6="reprice",G$3>=Initiatives!$G$33),Initiatives!$G$41*Initiatives!$G$21*(1-Inputs!$C$9)^(G$3-Initiatives!$G$33)-Initiatives!$G$31,0) -> 10000000 | H72: =IF(H$3<=Initiatives!$G$46,Initiatives!$G$29/Initiatives!$G$46,0)+IF(H$3>=Initiatives!$G$33,Initiatives!$G$30,0)+IF(H$3=Initiatives!$G$33,Initiatives!$G$39*Initiatives!$G$26,0)+H66*Initiatives!$G$27+H68*Initiatives!$G$28+IF(AND(Initiatives!$G$6="reprice",H$3>=Initiatives!$G$33),Initiatives!$G$41*Initiatives!$G$21*(1-Inputs!$C$9)^(H$3-Initiatives!$G$33)-Initiatives!$G$31,0) -> 10000000 | I72: =IF(I$3<=Initiatives!$G$46,Initiatives!$G$29/Initiatives!$G$46,0)+IF(I$3>=Initiatives!$G$33,Initiatives!$G$30,0)+IF(I$3=Initiatives!$G$33,Initiatives!$G$39*Initiatives!$G$26,0)+I66*Initiatives!$G$27+I68*Initiatives!$G$28+IF(AND(Initiatives!$G$6="reprice",I$3>=Initiatives!$G$33),Initiatives!$G$41*Initiatives!$G$21*(1-Inputs!$C$9)^(I$3-Initiatives!$G$33)-Initiatives!$G$31,0) -> 10000000 | J72: =IF(J$3<=Initiatives!$G$46,Initiatives!$G$29/Initiatives!$G$46,0)+IF(J$3>=Initiatives!$G$33,Initiatives!$G$30,0)+IF(J$3=Initiatives!$G$33,Initiatives!$G$39*Initiatives!$G$26,0)+J66*Initiatives!$G$27+J68*Initiatives!$G$28+IF(AND(Initiatives!$G$6="reprice",J$3>=Initiatives!$G$33),Initiatives!$G$41*Initiatives!$G$21*(1-Inputs!$C$9)^(J$3-Initiatives!$G$33)-Initiatives!$G$31,0) -> 10000000 | ... Z72: =IF(Z$3<=Initiatives!$G$46,Initiatives!$G$29/Initiatives!$G$46,0)+IF(Z$3>=Initiatives!$G$33,Initiatives!$G$30,0)+IF(Z$3=Initiatives!$G$33,Initiatives!$G$39*Initiatives!$G$26,0)+Z66*Initiatives!$G$27+Z68*Initiatives!$G$28+IF(AND(Initiatives!$G$6="reprice",Z$3>=Initiatives!$G$33),Initiatives!$G$41*Initiatives!$G$21*(1-Inputs!$C$9)^(Z$3-Initiatives!$G$33)-Initiatives!$G$31,0) -> 10000000
A73: Вклад | B73: contrib | C73: =(C70+C71)*Initiatives!$G$32-C72 -> -100000000 | D73: =(D70+D71)*Initiatives!$G$32-D72 -> -100000000 | E73: =(E70+E71)*Initiatives!$G$32-E72 -> -140099200 | F73: =(F70+F71)*Initiatives!$G$32-F72 -> 25437248 | G73: =(G70+G71)*Initiatives!$G$32-G72 -> 43087514 | H73: =(H70+H71)*Initiatives!$G$32-H72 -> 60689825 | I73: =(I70+I71)*Initiatives!$G$32-I72 -> 60501661 | J73: =(J70+J71)*Initiatives!$G$32-J72 -> 60306507 | ... Z73: =(Z70+Z71)*Initiatives!$G$32-Z72 -> 56396079
A74: Δ абонентов когорты | B74: dsubs | C74: =C67-C69 -> 0 | D74: =D67-D69 -> 0 | E74: =E67-E69 -> 0 | F74: =F67-F69 -> 18.48 | G74: =G67-G69 -> 54.9549 | H74: =H67-H69 -> 108.94922 | I74: =I67-I69 -> 179.99691 | J74: =J67-J69 -> 249.16121 | ... Z74: =Z67-Z69 -> 1128.2649
A75: Новые линии | B75: dsubs_ext | C75: =C68*Initiatives!$G$24 -> 0 | D75: =D68*Initiatives!$G$24 -> 0 | E75: =E68*Initiatives!$G$24 -> 0 | F75: =F68*Initiatives!$G$24 -> 0 | G75: =G68*Initiatives!$G$24 -> 0 | H75: =H68*Initiatives!$G$24 -> 0 | I75: =I68*Initiatives!$G$24 -> 0 | J75: =J68*Initiatives!$G$24 -> 0 | ... Z75: =Z68*Initiatives!$G$24 -> 0
A77: A6 — Реактивация спящих архивных SIM (win-back оффер)
A78: Доля набора | B78: f | C78: =IF(C$3<Initiatives!$H$33,0,MIN((C$3-Initiatives!$H$33+1)/Initiatives!$H$34,1)) -> 0 | D78: =IF(D$3<Initiatives!$H$33,0,MIN((D$3-Initiatives!$H$33+1)/Initiatives!$H$34,1)) -> 0.33333333 | E78: =IF(E$3<Initiatives!$H$33,0,MIN((E$3-Initiatives!$H$33+1)/Initiatives!$H$34,1)) -> 0.66666667 | F78: =IF(F$3<Initiatives!$H$33,0,MIN((F$3-Initiatives!$H$33+1)/Initiatives!$H$34,1)) -> 1 | G78: =IF(G$3<Initiatives!$H$33,0,MIN((G$3-Initiatives!$H$33+1)/Initiatives!$H$34,1)) -> 1 | H78: =IF(H$3<Initiatives!$H$33,0,MIN((H$3-Initiatives!$H$33+1)/Initiatives!$H$34,1)) -> 1 | I78: =IF(I$3<Initiatives!$H$33,0,MIN((I$3-Initiatives!$H$33+1)/Initiatives!$H$34,1)) -> 1 | J78: =IF(J$3<Initiatives!$H$33,0,MIN((J$3-Initiatives!$H$33+1)/Initiatives!$H$34,1)) -> 1 | ... Z78: =IF(Z$3<Initiatives!$H$33,0,MIN((Z$3-Initiatives!$H$33+1)/Initiatives!$H$34,1)) -> 1
A79: Адоптеры (цель) | B79: target | C79: =Initiatives!$H$40*C78 -> 0 | D79: =Initiatives!$H$40*D78 -> 7884.8 | E79: =Initiatives!$H$40*E78 -> 15769.6 | F79: =Initiatives!$H$40*F78 -> 23654.4 | G79: =Initiatives!$H$40*G78 -> 23654.4 | H79: =Initiatives!$H$40*H78 -> 23654.4 | I79: =Initiatives!$H$40*I78 -> 23654.4 | J79: =Initiatives!$H$40*J78 -> 23654.4 | ... Z79: =Initiatives!$H$40*Z78 -> 23654.4
A80: Новые адоптеры | B80: new | C80: =MAX(C79-N(B79),0) -> 0 | D80: =MAX(D79-N(C79),0) -> 7884.8 | E80: =MAX(E79-N(D79),0) -> 7884.8 | F80: =MAX(F79-N(E79),0) -> 7884.8 | G80: =MAX(G79-N(F79),0) -> 0 | H80: =MAX(H79-N(G79),0) -> 0 | I80: =MAX(I79-N(H79),0) -> 0 | J80: =MAX(J79-N(I79),0) -> 0 | ... Z80: =MAX(Z79-N(Y79),0) -> 0
A81: Удержанные (эффект оттока) | B81: R | C81: =IF(Initiatives!$H$6="adoption",N(B81)*(1-Inputs!$C$9)+N(B82)*Inputs!$C$9*Initiatives!$H$16,IF(Initiatives!$H$6="relative",N(B81)*(1-Inputs!$C$9)+C$4*Inputs!$C$9*Initiatives!$H$23*C78,0)) -> 0 | D81: =IF(Initiatives!$H$6="adoption",N(C81)*(1-Inputs!$C$9)+N(C82)*Inputs!$C$9*Initiatives!$H$16,IF(Initiatives!$H$6="relative",N(C81)*(1-Inputs!$C$9)+D$4*Inputs!$C$9*Initiatives!$H$23*D78,0)) -> 0 | E81: =IF(Initiatives!$H$6="adoption",N(D81)*(1-Inputs!$C$9)+N(D82)*Inputs!$C$9*Initiatives!$H$16,IF(Initiatives!$H$6="relative",N(D81)*(1-Inputs!$C$9)+E$4*Inputs!$C$9*Initiatives!$H$23*E78,0)) -> 0 | F81: =IF(Initiatives!$H$6="adoption",N(E81)*(1-Inputs!$C$9)+N(E82)*Inputs!$C$9*Initiatives!$H$16,IF(Initiatives!$H$6="relative",N(E81)*(1-Inputs!$C$9)+F$4*Inputs!$C$9*Initiatives!$H$23*F78,0)) -> 0 | G81: =IF(Initiatives!$H$6="adoption",N(F81)*(1-Inputs!$C$9)+N(F82)*Inputs!$C$9*Initiatives!$H$16,IF(Initiatives!$H$6="relative",N(F81)*(1-Inputs!$C$9)+G$4*Inputs!$C$9*Initiatives!$H$23*G78,0)) -> 0 | H81: =IF(Initiatives!$H$6="adoption",N(G81)*(1-Inputs!$C$9)+N(G82)*Inputs!$C$9*Initiatives!$H$16,IF(Initiatives!$H$6="relative",N(G81)*(1-Inputs!$C$9)+H$4*Inputs!$C$9*Initiatives!$H$23*H78,0)) -> 0 | I81: =IF(Initiatives!$H$6="adoption",N(H81)*(1-Inputs!$C$9)+N(H82)*Inputs!$C$9*Initiatives!$H$16,IF(Initiatives!$H$6="relative",N(H81)*(1-Inputs!$C$9)+I$4*Inputs!$C$9*Initiatives!$H$23*I78,0)) -> 0 | J81: =IF(Initiatives!$H$6="adoption",N(I81)*(1-Inputs!$C$9)+N(I82)*Inputs!$C$9*Initiatives!$H$16,IF(Initiatives!$H$6="relative",N(I81)*(1-Inputs!$C$9)+J$4*Inputs!$C$9*Initiatives!$H$23*J78,0)) -> 0 | ... Z81: =IF(Initiatives!$H$6="adoption",N(Y81)*(1-Inputs!$C$9)+N(Y82)*Inputs!$C$9*Initiatives!$H$16,IF(Initiatives!$H$6="relative",N(Y81)*(1-Inputs!$C$9)+Z$4*Inputs!$C$9*Initiatives!$H$23*Z78,0)) -> 0
A82: Пул адоптеров | B82: pool | C82: =N(B82)*(1-Initiatives!$H$45)*(1-Inputs!$C$9*(1-Initiatives!$H$16))+C80 -> 0 | D82: =N(C82)*(1-Initiatives!$H$45)*(1-Inputs!$C$9*(1-Initiatives!$H$16))+D80 -> 7884.8 | E82: =N(D82)*(1-Initiatives!$H$45)*(1-Inputs!$C$9*(1-Initiatives!$H$16))+E80 -> 15113.26 | F82: =N(E82)*(1-Initiatives!$H$45)*(1-Inputs!$C$9*(1-Initiatives!$H$16))+F80 -> 21740.016 | G82: =N(F82)*(1-Initiatives!$H$45)*(1-Inputs!$C$9*(1-Initiatives!$H$16))+G80 -> 19930.352 | H82: =N(G82)*(1-Initiatives!$H$45)*(1-Inputs!$C$9*(1-Initiatives!$H$16))+H80 -> 18271.327 | I82: =N(H82)*(1-Initiatives!$H$45)*(1-Inputs!$C$9*(1-Initiatives!$H$16))+I80 -> 16750.401 | J82: =N(I82)*(1-Initiatives!$H$45)*(1-Inputs!$C$9*(1-Initiatives!$H$16))+J80 -> 15356.079 | ... Z82: =N(Y82)*(1-Initiatives!$H$45)*(1-Inputs!$C$9*(1-Initiatives!$H$16))+Z80 -> 3822.6305
A83: Потерянные из-за инициативы | B83: L | C83: =N(B83)*(1-Inputs!$C$9)+IF(AND(C$3>=Initiatives!$H$33,C$3<Initiatives!$H$33+Initiatives!$H$47),Initiatives!$H$43/Initiatives!$H$47,0) -> 0 | D83: =N(C83)*(1-Inputs!$C$9)+IF(AND(D$3>=Initiatives!$H$33,D$3<Initiatives!$H$33+Initiatives!$H$47),Initiatives!$H$43/Initiatives!$H$47,0) -> 0 | E83: =N(D83)*(1-Inputs!$C$9)+IF(AND(E$3>=Initiatives!$H$33,E$3<Initiatives!$H$33+Initiatives!$H$47),Initiatives!$H$43/Initiatives!$H$47,0) -> 0 | F83: =N(E83)*(1-Inputs!$C$9)+IF(AND(F$3>=Initiatives!$H$33,F$3<Initiatives!$H$33+Initiatives!$H$47),Initiatives!$H$43/Initiatives!$H$47,0) -> 0 | G83: =N(F83)*(1-Inputs!$C$9)+IF(AND(G$3>=Initiatives!$H$33,G$3<Initiatives!$H$33+Initiatives!$H$47),Initiatives!$H$43/Initiatives!$H$47,0) -> 0 | H83: =N(G83)*(1-Inputs!$C$9)+IF(AND(H$3>=Initiatives!$H$33,H$3<Initiatives!$H$33+Initiatives!$H$47),Initiatives!$H$43/Initiatives!$H$47,0) -> 0 | I83: =N(H83)*(1-Inputs!$C$9)+IF(AND(I$3>=Initiatives!$H$33,I$3<Initiatives!$H$33+Initiatives!$H$47),Initiatives!$H$43/Initiatives!$H$47,0) -> 0 | J83: =N(I83)*(1-Inputs!$C$9)+IF(AND(J$3>=Initiatives!$H$33,J$3<Initiatives!$H$33+Initiatives!$H$47),Initiatives!$H$43/Initiatives!$H$47,0) -> 0 | ... Z83: =N(Y83)*(1-Inputs!$C$9)+IF(AND(Z$3>=Initiatives!$H$33,Z$3<Initiatives!$H$33+Initiatives!$H$47),Initiatives!$H$43/Initiatives!$H$47,0) -> 0
A84: Инкр. выручка когорты | B84: rev | C84: =IF(Initiatives!$H$6="adoption",C82*Initiatives!$H$14+C81*Initiatives!$H$9-C83*Initiatives!$H$9,IF(Initiatives!$H$6="reprice",IF(C$3>=Initiatives!$H$33,(Initiatives!$H$41*Initiatives!$H$44+Initiatives!$H$42*Initiatives!$H$20)*(1-Inputs!$C$9)^(C$3-Initiatives!$H$33),0)-C83*Initiatives!$H$9,C$5*Initiatives!$H$22*C78+C81*Inputs!$C$8)) -> 0 | D84: =IF(Initiatives!$H$6="adoption",D82*Initiatives!$H$14+D81*Initiatives!$H$9-D83*Initiatives!$H$9,IF(Initiatives!$H$6="reprice",IF(D$3>=Initiatives!$H$33,(Initiatives!$H$41*Initiatives!$H$44+Initiatives!$H$42*Initiatives!$H$20)*(1-Inputs!$C$9)^(D$3-Initiatives!$H$33),0)-D83*Initiatives!$H$9,D$5*Initiatives!$H$22*D78+D81*Inputs!$C$8)) -> 55193600 | E84: =IF(Initiatives!$H$6="adoption",E82*Initiatives!$H$14+E81*Initiatives!$H$9-E83*Initiatives!$H$9,IF(Initiatives!$H$6="reprice",IF(E$3>=Initiatives!$H$33,(Initiatives!$H$41*Initiatives!$H$44+Initiatives!$H$42*Initiatives!$H$20)*(1-Inputs!$C$9)^(E$3-Initiatives!$H$33),0)-E83*Initiatives!$H$9,E$5*Initiatives!$H$22*E78+E81*Inputs!$C$8)) -> 1.0579282e+08 | F84: =IF(Initiatives!$H$6="adoption",F82*Initiatives!$H$14+F81*Initiatives!$H$9-F83*Initiatives!$H$9,IF(Initiatives!$H$6="reprice",IF(F$3>=Initiatives!$H$33,(Initiatives!$H$41*Initiatives!$H$44+Initiatives!$H$42*Initiatives!$H$20)*(1-Inputs!$C$9)^(F$3-Initiatives!$H$33),0)-F83*Initiatives!$H$9,F$5*Initiatives!$H$22*F78+F81*Inputs!$C$8)) -> 1.5218011e+08 | G84: =IF(Initiatives!$H$6="adoption",G82*Initiatives!$H$14+G81*Initiatives!$H$9-G83*Initiatives!$H$9,IF(Initiatives!$H$6="reprice",IF(G$3>=Initiatives!$H$33,(Initiatives!$H$41*Initiatives!$H$44+Initiatives!$H$42*Initiatives!$H$20)*(1-Inputs!$C$9)^(G$3-Initiatives!$H$33),0)-G83*Initiatives!$H$9,G$5*Initiatives!$H$22*G78+G81*Inputs!$C$8)) -> 1.3951247e+08 | H84: =IF(Initiatives!$H$6="adoption",H82*Initiatives!$H$14+H81*Initiatives!$H$9-H83*Initiatives!$H$9,IF(Initiatives!$H$6="reprice",IF(H$3>=Initiatives!$H$33,(Initiatives!$H$41*Initiatives!$H$44+Initiatives!$H$42*Initiatives!$H$20)*(1-Inputs!$C$9)^(H$3-Initiatives!$H$33),0)-H83*Initiatives!$H$9,H$5*Initiatives!$H$22*H78+H81*Inputs!$C$8)) -> 1.2789929e+08 | I84: =IF(Initiatives!$H$6="adoption",I82*Initiatives!$H$14+I81*Initiatives!$H$9-I83*Initiatives!$H$9,IF(Initiatives!$H$6="reprice",IF(I$3>=Initiatives!$H$33,(Initiatives!$H$41*Initiatives!$H$44+Initiatives!$H$42*Initiatives!$H$20)*(1-Inputs!$C$9)^(I$3-Initiatives!$H$33),0)-I83*Initiatives!$H$9,I$5*Initiatives!$H$22*I78+I81*Inputs!$C$8)) -> 1.1725281e+08 | J84: =IF(Initiatives!$H$6="adoption",J82*Initiatives!$H$14+J81*Initiatives!$H$9-J83*Initiatives!$H$9,IF(Initiatives!$H$6="reprice",IF(J$3>=Initiatives!$H$33,(Initiatives!$H$41*Initiatives!$H$44+Initiatives!$H$42*Initiatives!$H$20)*(1-Inputs!$C$9)^(J$3-Initiatives!$H$33),0)-J83*Initiatives!$H$9,J$5*Initiatives!$H$22*J78+J81*Inputs!$C$8)) -> 1.0749255e+08 | ... Z84: =IF(Initiatives!$H$6="adoption",Z82*Initiatives!$H$14+Z81*Initiatives!$H$9-Z83*Initiatives!$H$9,IF(Initiatives!$H$6="reprice",IF(Z$3>=Initiatives!$H$33,(Initiatives!$H$41*Initiatives!$H$44+Initiatives!$H$42*Initiatives!$H$20)*(1-Inputs!$C$9)^(Z$3-Initiatives!$H$33),0)-Z83*Initiatives!$H$9,Z$5*Initiatives!$H$22*Z78+Z81*Inputs!$C$8)) -> 26758413
A85: Выручка новых линий | B85: rev_ext | C85: =C82*Initiatives!$H$24*Initiatives!$H$25 -> 0 | D85: =D82*Initiatives!$H$24*Initiatives!$H$25 -> 0 | E85: =E82*Initiatives!$H$24*Initiatives!$H$25 -> 0 | F85: =F82*Initiatives!$H$24*Initiatives!$H$25 -> 0 | G85: =G82*Initiatives!$H$24*Initiatives!$H$25 -> 0 | H85: =H82*Initiatives!$H$24*Initiatives!$H$25 -> 0 | I85: =I82*Initiatives!$H$24*Initiatives!$H$25 -> 0 | J85: =J82*Initiatives!$H$24*Initiatives!$H$25 -> 0 | ... Z85: =Z82*Initiatives!$H$24*Initiatives!$H$25 -> 0
A86: Затраты | B86: cost | C86: =IF(C$3<=Initiatives!$H$46,Initiatives!$H$29/Initiatives!$H$46,0)+IF(C$3>=Initiatives!$H$33,Initiatives!$H$30,0)+IF(C$3=Initiatives!$H$33,Initiatives!$H$39*Initiatives!$H$26,0)+C80*Initiatives!$H$27+C82*Initiatives!$H$28+IF(AND(Initiatives!$H$6="reprice",C$3>=Initiatives!$H$33),Initiatives!$H$41*Initiatives!$H$21*(1-Inputs!$C$9)^(C$3-Initiatives!$H$33)-Initiatives!$H$31,0) -> 150000000 | D86: =IF(D$3<=Initiatives!$H$46,Initiatives!$H$29/Initiatives!$H$46,0)+IF(D$3>=Initiatives!$H$33,Initiatives!$H$30,0)+IF(D$3=Initiatives!$H$33,Initiatives!$H$39*Initiatives!$H$26,0)+D80*Initiatives!$H$27+D82*Initiatives!$H$28+IF(AND(Initiatives!$H$6="reprice",D$3>=Initiatives!$H$33),Initiatives!$H$41*Initiatives!$H$21*(1-Inputs!$C$9)^(D$3-Initiatives!$H$33)-Initiatives!$H$31,0) -> 107574400 | E86: =IF(E$3<=Initiatives!$H$46,Initiatives!$H$29/Initiatives!$H$46,0)+IF(E$3>=Initiatives!$H$33,Initiatives!$H$30,0)+IF(E$3=Initiatives!$H$33,Initiatives!$H$39*Initiatives!$H$26,0)+E80*Initiatives!$H$27+E82*Initiatives!$H$28+IF(AND(Initiatives!$H$6="reprice",E$3>=Initiatives!$H$33),Initiatives!$H$41*Initiatives!$H$21*(1-Inputs!$C$9)^(E$3-Initiatives!$H$33)-Initiatives!$H$31,0) -> 33654400 | F86: =IF(F$3<=Initiatives!$H$46,Initiatives!$H$29/Initiatives!$H$46,0)+IF(F$3>=Initiatives!$H$33,Initiatives!$H$30,0)+IF(F$3=Initiatives!$H$33,Initiatives!$H$39*Initiatives!$H$26,0)+F80*Initiatives!$H$27+F82*Initiatives!$H$28+IF(AND(Initiatives!$H$6="reprice",F$3>=Initiatives!$H$33),Initiatives!$H$41*Initiatives!$H$21*(1-Inputs!$C$9)^(F$3-Initiatives!$H$33)-Initiatives!$H$31,0) -> 33654400 | G86: =IF(G$3<=Initiatives!$H$46,Initiatives!$H$29/Initiatives!$H$46,0)+IF(G$3>=Initiatives!$H$33,Initiatives!$H$30,0)+IF(G$3=Initiatives!$H$33,Initiatives!$H$39*Initiatives!$H$26,0)+G80*Initiatives!$H$27+G82*Initiatives!$H$28+IF(AND(Initiatives!$H$6="reprice",G$3>=Initiatives!$H$33),Initiatives!$H$41*Initiatives!$H$21*(1-Inputs!$C$9)^(G$3-Initiatives!$H$33)-Initiatives!$H$31,0) -> 10000000 | H86: =IF(H$3<=Initiatives!$H$46,Initiatives!$H$29/Initiatives!$H$46,0)+IF(H$3>=Initiatives!$H$33,Initiatives!$H$30,0)+IF(H$3=Initiatives!$H$33,Initiatives!$H$39*Initiatives!$H$26,0)+H80*Initiatives!$H$27+H82*Initiatives!$H$28+IF(AND(Initiatives!$H$6="reprice",H$3>=Initiatives!$H$33),Initiatives!$H$41*Initiatives!$H$21*(1-Inputs!$C$9)^(H$3-Initiatives!$H$33)-Initiatives!$H$31,0) -> 10000000 | I86: =IF(I$3<=Initiatives!$H$46,Initiatives!$H$29/Initiatives!$H$46,0)+IF(I$3>=Initiatives!$H$33,Initiatives!$H$30,0)+IF(I$3=Initiatives!$H$33,Initiatives!$H$39*Initiatives!$H$26,0)+I80*Initiatives!$H$27+I82*Initiatives!$H$28+IF(AND(Initiatives!$H$6="reprice",I$3>=Initiatives!$H$33),Initiatives!$H$41*Initiatives!$H$21*(1-Inputs!$C$9)^(I$3-Initiatives!$H$33)-Initiatives!$H$31,0) -> 10000000 | J86: =IF(J$3<=Initiatives!$H$46,Initiatives!$H$29/Initiatives!$H$46,0)+IF(J$3>=Initiatives!$H$33,Initiatives!$H$30,0)+IF(J$3=Initiatives!$H$33,Initiatives!$H$39*Initiatives!$H$26,0)+J80*Initiatives!$H$27+J82*Initiatives!$H$28+IF(AND(Initiatives!$H$6="reprice",J$3>=Initiatives!$H$33),Initiatives!$H$41*Initiatives!$H$21*(1-Inputs!$C$9)^(J$3-Initiatives!$H$33)-Initiatives!$H$31,0) -> 10000000 | ... Z86: =IF(Z$3<=Initiatives!$H$46,Initiatives!$H$29/Initiatives!$H$46,0)+IF(Z$3>=Initiatives!$H$33,Initiatives!$H$30,0)+IF(Z$3=Initiatives!$H$33,Initiatives!$H$39*Initiatives!$H$26,0)+Z80*Initiatives!$H$27+Z82*Initiatives!$H$28+IF(AND(Initiatives!$H$6="reprice",Z$3>=Initiatives!$H$33),Initiatives!$H$41*Initiatives!$H$21*(1-Inputs!$C$9)^(Z$3-Initiatives!$H$33)-Initiatives!$H$31,0) -> 10000000
A87: Вклад | B87: contrib | C87: =(C84+C85)*Initiatives!$H$32-C86 -> -150000000 | D87: =(D84+D85)*Initiatives!$H$32-D86 -> -60659840 | E87: =(E84+E85)*Initiatives!$H$32-E86 -> 56269499 | F87: =(F84+F85)*Initiatives!$H$32-F86 -> 95698693 | G87: =(G84+G85)*Initiatives!$H$32-G86 -> 1.085856e+08 | H87: =(H84+H85)*Initiatives!$H$32-H86 -> 98714398 | I87: =(I84+I85)*Initiatives!$H$32-I86 -> 89664889 | J87: =(J84+J85)*Initiatives!$H$32-J86 -> 81368671 | ... Z87: =(Z84+Z85)*Initiatives!$H$32-Z86 -> 12744651
A88: Δ абонентов когорты | B88: dsubs | C88: =C81-C83 -> 0 | D88: =D81-D83 -> 0 | E88: =E81-E83 -> 0 | F88: =F81-F83 -> 0 | G88: =G81-G83 -> 0 | H88: =H81-H83 -> 0 | I88: =I81-I83 -> 0 | J88: =J81-J83 -> 0 | ... Z88: =Z81-Z83 -> 0
A89: Новые линии | B89: dsubs_ext | C89: =C82*Initiatives!$H$24 -> 0 | D89: =D82*Initiatives!$H$24 -> 0 | E89: =E82*Initiatives!$H$24 -> 0 | F89: =F82*Initiatives!$H$24 -> 0 | G89: =G82*Initiatives!$H$24 -> 0 | H89: =H82*Initiatives!$H$24 -> 0 | I89: =I82*Initiatives!$H$24 -> 0 | J89: =J82*Initiatives!$H$24 -> 0 | ... Z89: =Z82*Initiatives!$H$24 -> 0
A91: A7 — «Musofir»: пакеты роуминга/OTP для трудовых мигрантов на архивных ТП
A92: Доля набора | B92: f | C92: =IF(C$3<Initiatives!$I$33,0,MIN((C$3-Initiatives!$I$33+1)/Initiatives!$I$34,1)) -> 0 | D92: =IF(D$3<Initiatives!$I$33,0,MIN((D$3-Initiatives!$I$33+1)/Initiatives!$I$34,1)) -> 0 | E92: =IF(E$3<Initiatives!$I$33,0,MIN((E$3-Initiatives!$I$33+1)/Initiatives!$I$34,1)) -> 0.33333333 | F92: =IF(F$3<Initiatives!$I$33,0,MIN((F$3-Initiatives!$I$33+1)/Initiatives!$I$34,1)) -> 0.66666667 | G92: =IF(G$3<Initiatives!$I$33,0,MIN((G$3-Initiatives!$I$33+1)/Initiatives!$I$34,1)) -> 1 | H92: =IF(H$3<Initiatives!$I$33,0,MIN((H$3-Initiatives!$I$33+1)/Initiatives!$I$34,1)) -> 1 | I92: =IF(I$3<Initiatives!$I$33,0,MIN((I$3-Initiatives!$I$33+1)/Initiatives!$I$34,1)) -> 1 | J92: =IF(J$3<Initiatives!$I$33,0,MIN((J$3-Initiatives!$I$33+1)/Initiatives!$I$34,1)) -> 1 | ... Z92: =IF(Z$3<Initiatives!$I$33,0,MIN((Z$3-Initiatives!$I$33+1)/Initiatives!$I$34,1)) -> 1
A93: Адоптеры (цель) | B93: target | C93: =Initiatives!$I$40*C92 -> 0 | D93: =Initiatives!$I$40*D92 -> 0 | E93: =Initiatives!$I$40*E92 -> 7603.2 | F93: =Initiatives!$I$40*F92 -> 15206.4 | G93: =Initiatives!$I$40*G92 -> 22809.6 | H93: =Initiatives!$I$40*H92 -> 22809.6 | I93: =Initiatives!$I$40*I92 -> 22809.6 | J93: =Initiatives!$I$40*J92 -> 22809.6 | ... Z93: =Initiatives!$I$40*Z92 -> 22809.6
A94: Новые адоптеры | B94: new | C94: =MAX(C93-N(B93),0) -> 0 | D94: =MAX(D93-N(C93),0) -> 0 | E94: =MAX(E93-N(D93),0) -> 7603.2 | F94: =MAX(F93-N(E93),0) -> 7603.2 | G94: =MAX(G93-N(F93),0) -> 7603.2 | H94: =MAX(H93-N(G93),0) -> 0 | I94: =MAX(I93-N(H93),0) -> 0 | J94: =MAX(J93-N(I93),0) -> 0 | ... Z94: =MAX(Z93-N(Y93),0) -> 0
A95: Удержанные (эффект оттока) | B95: R | C95: =IF(Initiatives!$I$6="adoption",N(B95)*(1-Inputs!$C$9)+N(B96)*Inputs!$C$9*Initiatives!$I$16,IF(Initiatives!$I$6="relative",N(B95)*(1-Inputs!$C$9)+C$4*Inputs!$C$9*Initiatives!$I$23*C92,0)) -> 0 | D95: =IF(Initiatives!$I$6="adoption",N(C95)*(1-Inputs!$C$9)+N(C96)*Inputs!$C$9*Initiatives!$I$16,IF(Initiatives!$I$6="relative",N(C95)*(1-Inputs!$C$9)+D$4*Inputs!$C$9*Initiatives!$I$23*D92,0)) -> 0 | E95: =IF(Initiatives!$I$6="adoption",N(D95)*(1-Inputs!$C$9)+N(D96)*Inputs!$C$9*Initiatives!$I$16,IF(Initiatives!$I$6="relative",N(D95)*(1-Inputs!$C$9)+E$4*Inputs!$C$9*Initiatives!$I$23*E92,0)) -> 0 | F95: =IF(Initiatives!$I$6="adoption",N(E95)*(1-Inputs!$C$9)+N(E96)*Inputs!$C$9*Initiatives!$I$16,IF(Initiatives!$I$6="relative",N(E95)*(1-Inputs!$C$9)+F$4*Inputs!$C$9*Initiatives!$I$23*F92,0)) -> 22.8096 | G95: =IF(Initiatives!$I$6="adoption",N(F95)*(1-Inputs!$C$9)+N(F96)*Inputs!$C$9*Initiatives!$I$16,IF(Initiatives!$I$6="relative",N(F95)*(1-Inputs!$C$9)+G$4*Inputs!$C$9*Initiatives!$I$23*G92,0)) -> 67.812941 | H95: =IF(Initiatives!$I$6="adoption",N(G95)*(1-Inputs!$C$9)+N(G96)*Inputs!$C$9*Initiatives!$I$16,IF(Initiatives!$I$6="relative",N(G95)*(1-Inputs!$C$9)+H$4*Inputs!$C$9*Initiatives!$I$23*H92,0)) -> 134.40669 | I95: =IF(Initiatives!$I$6="adoption",N(H95)*(1-Inputs!$C$9)+N(H96)*Inputs!$C$9*Initiatives!$I$16,IF(Initiatives!$I$6="relative",N(H95)*(1-Inputs!$C$9)+I$4*Inputs!$C$9*Initiatives!$I$23*I92,0)) -> 199.19019 | J95: =IF(Initiatives!$I$6="adoption",N(I95)*(1-Inputs!$C$9)+N(I96)*Inputs!$C$9*Initiatives!$I$16,IF(Initiatives!$I$6="relative",N(I95)*(1-Inputs!$C$9)+J$4*Inputs!$C$9*Initiatives!$I$23*J92,0)) -> 262.20035 | ... Z95: =IF(Initiatives!$I$6="adoption",N(Y95)*(1-Inputs!$C$9)+N(Y96)*Inputs!$C$9*Initiatives!$I$16,IF(Initiatives!$I$6="relative",N(Y95)*(1-Inputs!$C$9)+Z$4*Inputs!$C$9*Initiatives!$I$23*Z92,0)) -> 1056.8201
A96: Пул адоптеров | B96: pool | C96: =N(B96)*(1-Initiatives!$I$45)*(1-Inputs!$C$9*(1-Initiatives!$I$16))+C94 -> 0 | D96: =N(C96)*(1-Initiatives!$I$45)*(1-Inputs!$C$9*(1-Initiatives!$I$16))+D94 -> 0 | E96: =N(D96)*(1-Initiatives!$I$45)*(1-Inputs!$C$9*(1-Initiatives!$I$16))+E94 -> 7603.2 | F96: =N(E96)*(1-Initiatives!$I$45)*(1-Inputs!$C$9*(1-Initiatives!$I$16))+F94 -> 15115.162 | G96: =N(F96)*(1-Initiatives!$I$45)*(1-Inputs!$C$9*(1-Initiatives!$I$16))+G94 -> 22536.98 | H96: =N(G96)*(1-Initiatives!$I$45)*(1-Inputs!$C$9*(1-Initiatives!$I$16))+H94 -> 22266.536 | I96: =N(H96)*(1-Initiatives!$I$45)*(1-Inputs!$C$9*(1-Initiatives!$I$16))+I94 -> 21999.337 | J96: =N(I96)*(1-Initiatives!$I$45)*(1-Inputs!$C$9*(1-Initiatives!$I$16))+J94 -> 21735.345 | ... Z96: =N(Y96)*(1-Initiatives!$I$45)*(1-Inputs!$C$9*(1-Initiatives!$I$16))+Z94 -> 17917.51
A97: Потерянные из-за инициативы | B97: L | C97: =N(B97)*(1-Inputs!$C$9)+IF(AND(C$3>=Initiatives!$I$33,C$3<Initiatives!$I$33+Initiatives!$I$47),Initiatives!$I$43/Initiatives!$I$47,0) -> 0 | D97: =N(C97)*(1-Inputs!$C$9)+IF(AND(D$3>=Initiatives!$I$33,D$3<Initiatives!$I$33+Initiatives!$I$47),Initiatives!$I$43/Initiatives!$I$47,0) -> 0 | E97: =N(D97)*(1-Inputs!$C$9)+IF(AND(E$3>=Initiatives!$I$33,E$3<Initiatives!$I$33+Initiatives!$I$47),Initiatives!$I$43/Initiatives!$I$47,0) -> 0 | F97: =N(E97)*(1-Inputs!$C$9)+IF(AND(F$3>=Initiatives!$I$33,F$3<Initiatives!$I$33+Initiatives!$I$47),Initiatives!$I$43/Initiatives!$I$47,0) -> 0 | G97: =N(F97)*(1-Inputs!$C$9)+IF(AND(G$3>=Initiatives!$I$33,G$3<Initiatives!$I$33+Initiatives!$I$47),Initiatives!$I$43/Initiatives!$I$47,0) -> 0 | H97: =N(G97)*(1-Inputs!$C$9)+IF(AND(H$3>=Initiatives!$I$33,H$3<Initiatives!$I$33+Initiatives!$I$47),Initiatives!$I$43/Initiatives!$I$47,0) -> 0 | I97: =N(H97)*(1-Inputs!$C$9)+IF(AND(I$3>=Initiatives!$I$33,I$3<Initiatives!$I$33+Initiatives!$I$47),Initiatives!$I$43/Initiatives!$I$47,0) -> 0 | J97: =N(I97)*(1-Inputs!$C$9)+IF(AND(J$3>=Initiatives!$I$33,J$3<Initiatives!$I$33+Initiatives!$I$47),Initiatives!$I$43/Initiatives!$I$47,0) -> 0 | ... Z97: =N(Y97)*(1-Inputs!$C$9)+IF(AND(Z$3>=Initiatives!$I$33,Z$3<Initiatives!$I$33+Initiatives!$I$47),Initiatives!$I$43/Initiatives!$I$47,0) -> 0
A98: Инкр. выручка когорты | B98: rev | C98: =IF(Initiatives!$I$6="adoption",C96*Initiatives!$I$14+C95*Initiatives!$I$9-C97*Initiatives!$I$9,IF(Initiatives!$I$6="reprice",IF(C$3>=Initiatives!$I$33,(Initiatives!$I$41*Initiatives!$I$44+Initiatives!$I$42*Initiatives!$I$20)*(1-Inputs!$C$9)^(C$3-Initiatives!$I$33),0)-C97*Initiatives!$I$9,C$5*Initiatives!$I$22*C92+C95*Inputs!$C$8)) -> 0 | D98: =IF(Initiatives!$I$6="adoption",D96*Initiatives!$I$14+D95*Initiatives!$I$9-D97*Initiatives!$I$9,IF(Initiatives!$I$6="reprice",IF(D$3>=Initiatives!$I$33,(Initiatives!$I$41*Initiatives!$I$44+Initiatives!$I$42*Initiatives!$I$20)*(1-Inputs!$C$9)^(D$3-Initiatives!$I$33),0)-D97*Initiatives!$I$9,D$5*Initiatives!$I$22*D92+D95*Inputs!$C$8)) -> 0 | E98: =IF(Initiatives!$I$6="adoption",E96*Initiatives!$I$14+E95*Initiatives!$I$9-E97*Initiatives!$I$9,IF(Initiatives!$I$6="reprice",IF(E$3>=Initiatives!$I$33,(Initiatives!$I$41*Initiatives!$I$44+Initiatives!$I$42*Initiatives!$I$20)*(1-Inputs!$C$9)^(E$3-Initiatives!$I$33),0)-E97*Initiatives!$I$9,E$5*Initiatives!$I$22*E92+E95*Inputs!$C$8)) -> 53222400 | F98: =IF(Initiatives!$I$6="adoption",F96*Initiatives!$I$14+F95*Initiatives!$I$9-F97*Initiatives!$I$9,IF(Initiatives!$I$6="reprice",IF(F$3>=Initiatives!$I$33,(Initiatives!$I$41*Initiatives!$I$44+Initiatives!$I$42*Initiatives!$I$20)*(1-Inputs!$C$9)^(F$3-Initiatives!$I$33),0)-F97*Initiatives!$I$9,F$5*Initiatives!$I$22*F92+F95*Inputs!$C$8)) -> 1.0614828e+08 | G98: =IF(Initiatives!$I$6="adoption",G96*Initiatives!$I$14+G95*Initiatives!$I$9-G97*Initiatives!$I$9,IF(Initiatives!$I$6="reprice",IF(G$3>=Initiatives!$I$33,(Initiatives!$I$41*Initiatives!$I$44+Initiatives!$I$42*Initiatives!$I$20)*(1-Inputs!$C$9)^(G$3-Initiatives!$I$33),0)-G97*Initiatives!$I$9,G$5*Initiatives!$I$22*G92+G95*Inputs!$C$8)) -> 1.5877605e+08 | H98: =IF(Initiatives!$I$6="adoption",H96*Initiatives!$I$14+H95*Initiatives!$I$9-H97*Initiatives!$I$9,IF(Initiatives!$I$6="reprice",IF(H$3>=Initiatives!$I$33,(Initiatives!$I$41*Initiatives!$I$44+Initiatives!$I$42*Initiatives!$I$20)*(1-Inputs!$C$9)^(H$3-Initiatives!$I$33),0)-H97*Initiatives!$I$9,H$5*Initiatives!$I$22*H92+H95*Inputs!$C$8)) -> 1.5788185e+08 | I98: =IF(Initiatives!$I$6="adoption",I96*Initiatives!$I$14+I95*Initiatives!$I$9-I97*Initiatives!$I$9,IF(Initiatives!$I$6="reprice",IF(I$3>=Initiatives!$I$33,(Initiatives!$I$41*Initiatives!$I$44+Initiatives!$I$42*Initiatives!$I$20)*(1-Inputs!$C$9)^(I$3-Initiatives!$I$33),0)-I97*Initiatives!$I$9,I$5*Initiatives!$I$22*I92+I95*Inputs!$C$8)) -> 1.5698322e+08 | J98: =IF(Initiatives!$I$6="adoption",J96*Initiatives!$I$14+J95*Initiatives!$I$9-J97*Initiatives!$I$9,IF(Initiatives!$I$6="reprice",IF(J$3>=Initiatives!$I$33,(Initiatives!$I$41*Initiatives!$I$44+Initiatives!$I$42*Initiatives!$I$20)*(1-Inputs!$C$9)^(J$3-Initiatives!$I$33),0)-J97*Initiatives!$I$9,J$5*Initiatives!$I$22*J92+J95*Inputs!$C$8)) -> 1.5608042e+08 | ... Z98: =IF(Initiatives!$I$6="adoption",Z96*Initiatives!$I$14+Z95*Initiatives!$I$9-Z97*Initiatives!$I$9,IF(Initiatives!$I$6="reprice",IF(Z$3>=Initiatives!$I$33,(Initiatives!$I$41*Initiatives!$I$44+Initiatives!$I$42*Initiatives!$I$20)*(1-Inputs!$C$9)^(Z$3-Initiatives!$I$33),0)-Z97*Initiatives!$I$9,Z$5*Initiatives!$I$22*Z92+Z95*Inputs!$C$8)) -> 1.4127487e+08
A99: Выручка новых линий | B99: rev_ext | C99: =C96*Initiatives!$I$24*Initiatives!$I$25 -> 0 | D99: =D96*Initiatives!$I$24*Initiatives!$I$25 -> 0 | E99: =E96*Initiatives!$I$24*Initiatives!$I$25 -> 0 | F99: =F96*Initiatives!$I$24*Initiatives!$I$25 -> 0 | G99: =G96*Initiatives!$I$24*Initiatives!$I$25 -> 0 | H99: =H96*Initiatives!$I$24*Initiatives!$I$25 -> 0 | I99: =I96*Initiatives!$I$24*Initiatives!$I$25 -> 0 | J99: =J96*Initiatives!$I$24*Initiatives!$I$25 -> 0 | ... Z99: =Z96*Initiatives!$I$24*Initiatives!$I$25 -> 0
A100: Затраты | B100: cost | C100: =IF(C$3<=Initiatives!$I$46,Initiatives!$I$29/Initiatives!$I$46,0)+IF(C$3>=Initiatives!$I$33,Initiatives!$I$30,0)+IF(C$3=Initiatives!$I$33,Initiatives!$I$39*Initiatives!$I$26,0)+C94*Initiatives!$I$27+C96*Initiatives!$I$28+IF(AND(Initiatives!$I$6="reprice",C$3>=Initiatives!$I$33),Initiatives!$I$41*Initiatives!$I$21*(1-Inputs!$C$9)^(C$3-Initiatives!$I$33)-Initiatives!$I$31,0) -> 75000000 | D100: =IF(D$3<=Initiatives!$I$46,Initiatives!$I$29/Initiatives!$I$46,0)+IF(D$3>=Initiatives!$I$33,Initiatives!$I$30,0)+IF(D$3=Initiatives!$I$33,Initiatives!$I$39*Initiatives!$I$26,0)+D94*Initiatives!$I$27+D96*Initiatives!$I$28+IF(AND(Initiatives!$I$6="reprice",D$3>=Initiatives!$I$33),Initiatives!$I$41*Initiatives!$I$21*(1-Inputs!$C$9)^(D$3-Initiatives!$I$33)-Initiatives!$I$31,0) -> 75000000 | E100: =IF(E$3<=Initiatives!$I$46,Initiatives!$I$29/Initiatives!$I$46,0)+IF(E$3>=Initiatives!$I$33,Initiatives!$I$30,0)+IF(E$3=Initiatives!$I$33,Initiatives!$I$39*Initiatives!$I$26,0)+E94*Initiatives!$I$27+E96*Initiatives!$I$28+IF(AND(Initiatives!$I$6="reprice",E$3>=Initiatives!$I$33),Initiatives!$I$41*Initiatives!$I$21*(1-Inputs!$C$9)^(E$3-Initiatives!$I$33)-Initiatives!$I$31,0) -> 35344000 | F100: =IF(F$3<=Initiatives!$I$46,Initiatives!$I$29/Initiatives!$I$46,0)+IF(F$3>=Initiatives!$I$33,Initiatives!$I$30,0)+IF(F$3=Initiatives!$I$33,Initiatives!$I$39*Initiatives!$I$26,0)+F94*Initiatives!$I$27+F96*Initiatives!$I$28+IF(AND(Initiatives!$I$6="reprice",F$3>=Initiatives!$I$33),Initiatives!$I$41*Initiatives!$I$21*(1-Inputs!$C$9)^(F$3-Initiatives!$I$33)-Initiatives!$I$31,0) -> 10000000 | G100: =IF(G$3<=Initiatives!$I$46,Initiatives!$I$29/Initiatives!$I$46,0)+IF(G$3>=Initiatives!$I$33,Initiatives!$I$30,0)+IF(G$3=Initiatives!$I$33,Initiatives!$I$39*Initiatives!$I$26,0)+G94*Initiatives!$I$27+G96*Initiatives!$I$28+IF(AND(Initiatives!$I$6="reprice",G$3>=Initiatives!$I$33),Initiatives!$I$41*Initiatives!$I$21*(1-Inputs!$C$9)^(G$3-Initiatives!$I$33)-Initiatives!$I$31,0) -> 10000000 | H100: =IF(H$3<=Initiatives!$I$46,Initiatives!$I$29/Initiatives!$I$46,0)+IF(H$3>=Initiatives!$I$33,Initiatives!$I$30,0)+IF(H$3=Initiatives!$I$33,Initiatives!$I$39*Initiatives!$I$26,0)+H94*Initiatives!$I$27+H96*Initiatives!$I$28+IF(AND(Initiatives!$I$6="reprice",H$3>=Initiatives!$I$33),Initiatives!$I$41*Initiatives!$I$21*(1-Inputs!$C$9)^(H$3-Initiatives!$I$33)-Initiatives!$I$31,0) -> 10000000 | I100: =IF(I$3<=Initiatives!$I$46,Initiatives!$I$29/Initiatives!$I$46,0)+IF(I$3>=Initiatives!$I$33,Initiatives!$I$30,0)+IF(I$3=Initiatives!$I$33,Initiatives!$I$39*Initiatives!$I$26,0)+I94*Initiatives!$I$27+I96*Initiatives!$I$28+IF(AND(Initiatives!$I$6="reprice",I$3>=Initiatives!$I$33),Initiatives!$I$41*Initiatives!$I$21*(1-Inputs!$C$9)^(I$3-Initiatives!$I$33)-Initiatives!$I$31,0) -> 10000000 | J100: =IF(J$3<=Initiatives!$I$46,Initiatives!$I$29/Initiatives!$I$46,0)+IF(J$3>=Initiatives!$I$33,Initiatives!$I$30,0)+IF(J$3=Initiatives!$I$33,Initiatives!$I$39*Initiatives!$I$26,0)+J94*Initiatives!$I$27+J96*Initiatives!$I$28+IF(AND(Initiatives!$I$6="reprice",J$3>=Initiatives!$I$33),Initiatives!$I$41*Initiatives!$I$21*(1-Inputs!$C$9)^(J$3-Initiatives!$I$33)-Initiatives!$I$31,0) -> 10000000 | ... Z100: =IF(Z$3<=Initiatives!$I$46,Initiatives!$I$29/Initiatives!$I$46,0)+IF(Z$3>=Initiatives!$I$33,Initiatives!$I$30,0)+IF(Z$3=Initiatives!$I$33,Initiatives!$I$39*Initiatives!$I$26,0)+Z94*Initiatives!$I$27+Z96*Initiatives!$I$28+IF(AND(Initiatives!$I$6="reprice",Z$3>=Initiatives!$I$33),Initiatives!$I$41*Initiatives!$I$21*(1-Inputs!$C$9)^(Z$3-Initiatives!$I$33)-Initiatives!$I$31,0) -> 10000000
A101: Вклад | B101: contrib | C101: =(C98+C99)*Initiatives!$I$32-C100 -> -75000000 | D101: =(D98+D99)*Initiatives!$I$32-D100 -> -75000000 | E101: =(E98+E99)*Initiatives!$I$32-E100 -> -3410560 | F101: =(F98+F99)*Initiatives!$I$32-F100 -> 53688965 | G101: =(G98+G99)*Initiatives!$I$32-G100 -> 85265631 | H101: =(H98+H99)*Initiatives!$I$32-H100 -> 84729111 | I101: =(I98+I99)*Initiatives!$I$32-I100 -> 84189929 | J101: =(J98+J99)*Initiatives!$I$32-J100 -> 83648254 | ... Z101: =(Z98+Z99)*Initiatives!$I$32-Z100 -> 74764923
A102: Δ абонентов когорты | B102: dsubs | C102: =C95-C97 -> 0 | D102: =D95-D97 -> 0 | E102: =E95-E97 -> 0 | F102: =F95-F97 -> 22.8096 | G102: =G95-G97 -> 67.812941 | H102: =H95-H97 -> 134.40669 | I102: =I95-I97 -> 199.19019 | J102: =J95-J97 -> 262.20035 | ... Z102: =Z95-Z97 -> 1056.8201
A103: Новые линии | B103: dsubs_ext | C103: =C96*Initiatives!$I$24 -> 0 | D103: =D96*Initiatives!$I$24 -> 0 | E103: =E96*Initiatives!$I$24 -> 0 | F103: =F96*Initiatives!$I$24 -> 0 | G103: =G96*Initiatives!$I$24 -> 0 | H103: =H96*Initiatives!$I$24 -> 0 | I103: =I96*Initiatives!$I$24 -> 0 | J103: =J96*Initiatives!$I$24 -> 0 | ... Z103: =Z96*Initiatives!$I$24 -> 0
A105: A8 — ОПЦИЯ: ежегодная индексация архивных пакетов на инфляцию (волна 2)
A106: Доля набора | B106: f | C106: =IF(C$3<Initiatives!$J$33,0,MIN((C$3-Initiatives!$J$33+1)/Initiatives!$J$34,1)) -> 0 | D106: =IF(D$3<Initiatives!$J$33,0,MIN((D$3-Initiatives!$J$33+1)/Initiatives!$J$34,1)) -> 0 | E106: =IF(E$3<Initiatives!$J$33,0,MIN((E$3-Initiatives!$J$33+1)/Initiatives!$J$34,1)) -> 0 | F106: =IF(F$3<Initiatives!$J$33,0,MIN((F$3-Initiatives!$J$33+1)/Initiatives!$J$34,1)) -> 0 | G106: =IF(G$3<Initiatives!$J$33,0,MIN((G$3-Initiatives!$J$33+1)/Initiatives!$J$34,1)) -> 0 | H106: =IF(H$3<Initiatives!$J$33,0,MIN((H$3-Initiatives!$J$33+1)/Initiatives!$J$34,1)) -> 0 | I106: =IF(I$3<Initiatives!$J$33,0,MIN((I$3-Initiatives!$J$33+1)/Initiatives!$J$34,1)) -> 0 | J106: =IF(J$3<Initiatives!$J$33,0,MIN((J$3-Initiatives!$J$33+1)/Initiatives!$J$34,1)) -> 0 | ... Z106: =IF(Z$3<Initiatives!$J$33,0,MIN((Z$3-Initiatives!$J$33+1)/Initiatives!$J$34,1)) -> 1
A107: Адоптеры (цель) | B107: target | C107: =Initiatives!$J$40*C106 -> 0 | D107: =Initiatives!$J$40*D106 -> 0 | E107: =Initiatives!$J$40*E106 -> 0 | F107: =Initiatives!$J$40*F106 -> 0 | G107: =Initiatives!$J$40*G106 -> 0 | H107: =Initiatives!$J$40*H106 -> 0 | I107: =Initiatives!$J$40*I106 -> 0 | J107: =Initiatives!$J$40*J106 -> 0 | ... Z107: =Initiatives!$J$40*Z106 -> 0
A108: Новые адоптеры | B108: new | C108: =MAX(C107-N(B107),0) -> 0 | D108: =MAX(D107-N(C107),0) -> 0 | E108: =MAX(E107-N(D107),0) -> 0 | F108: =MAX(F107-N(E107),0) -> 0 | G108: =MAX(G107-N(F107),0) -> 0 | H108: =MAX(H107-N(G107),0) -> 0 | I108: =MAX(I107-N(H107),0) -> 0 | J108: =MAX(J107-N(I107),0) -> 0 | ... Z108: =MAX(Z107-N(Y107),0) -> 0
A109: Удержанные (эффект оттока) | B109: R | C109: =IF(Initiatives!$J$6="adoption",N(B109)*(1-Inputs!$C$9)+N(B110)*Inputs!$C$9*Initiatives!$J$16,IF(Initiatives!$J$6="relative",N(B109)*(1-Inputs!$C$9)+C$4*Inputs!$C$9*Initiatives!$J$23*C106,0)) -> 0 | D109: =IF(Initiatives!$J$6="adoption",N(C109)*(1-Inputs!$C$9)+N(C110)*Inputs!$C$9*Initiatives!$J$16,IF(Initiatives!$J$6="relative",N(C109)*(1-Inputs!$C$9)+D$4*Inputs!$C$9*Initiatives!$J$23*D106,0)) -> 0 | E109: =IF(Initiatives!$J$6="adoption",N(D109)*(1-Inputs!$C$9)+N(D110)*Inputs!$C$9*Initiatives!$J$16,IF(Initiatives!$J$6="relative",N(D109)*(1-Inputs!$C$9)+E$4*Inputs!$C$9*Initiatives!$J$23*E106,0)) -> 0 | F109: =IF(Initiatives!$J$6="adoption",N(E109)*(1-Inputs!$C$9)+N(E110)*Inputs!$C$9*Initiatives!$J$16,IF(Initiatives!$J$6="relative",N(E109)*(1-Inputs!$C$9)+F$4*Inputs!$C$9*Initiatives!$J$23*F106,0)) -> 0 | G109: =IF(Initiatives!$J$6="adoption",N(F109)*(1-Inputs!$C$9)+N(F110)*Inputs!$C$9*Initiatives!$J$16,IF(Initiatives!$J$6="relative",N(F109)*(1-Inputs!$C$9)+G$4*Inputs!$C$9*Initiatives!$J$23*G106,0)) -> 0 | H109: =IF(Initiatives!$J$6="adoption",N(G109)*(1-Inputs!$C$9)+N(G110)*Inputs!$C$9*Initiatives!$J$16,IF(Initiatives!$J$6="relative",N(G109)*(1-Inputs!$C$9)+H$4*Inputs!$C$9*Initiatives!$J$23*H106,0)) -> 0 | I109: =IF(Initiatives!$J$6="adoption",N(H109)*(1-Inputs!$C$9)+N(H110)*Inputs!$C$9*Initiatives!$J$16,IF(Initiatives!$J$6="relative",N(H109)*(1-Inputs!$C$9)+I$4*Inputs!$C$9*Initiatives!$J$23*I106,0)) -> 0 | J109: =IF(Initiatives!$J$6="adoption",N(I109)*(1-Inputs!$C$9)+N(I110)*Inputs!$C$9*Initiatives!$J$16,IF(Initiatives!$J$6="relative",N(I109)*(1-Inputs!$C$9)+J$4*Inputs!$C$9*Initiatives!$J$23*J106,0)) -> 0 | ... Z109: =IF(Initiatives!$J$6="adoption",N(Y109)*(1-Inputs!$C$9)+N(Y110)*Inputs!$C$9*Initiatives!$J$16,IF(Initiatives!$J$6="relative",N(Y109)*(1-Inputs!$C$9)+Z$4*Inputs!$C$9*Initiatives!$J$23*Z106,0)) -> 0
...

Sheet Portfolio
A1: Портфель: базовый кейс (детерминированный) — вероятностный прогноз см. MC_Results
A3: Перекрытие эффектов (haircut) | C3: 0.2 | D3: Доля эффекта, «съедаемая» пересечением целевых групп (одни и те же абоненты в нескольких инициативах)
A5: # | B5: Инициатива | C5: Группа | D5: Опция | E5: Выручка Y1 | F5: Выручка Y2 | G5: Run-rate/год | H5: Вклад 24 мес | I5: ROI | J5: ΔARPU (мес. оценки) | K5: Δ доли, п.п. | L5: P(запуска) | M5: Ожид. вклад
A6: A1 | B6: =Initiatives!C4 -> «Ucell 30 — Upgrade»: мягкая миграция с подарком | C6: =Initiatives!C5 -> EASY | D6: =Initiatives!C8 -> 0 | E6: =Initiatives!C51 -> 7.3179048e+09 | F6: =Initiatives!C52 -> 8.4716185e+09 | G6: =Initiatives!C53 -> 8.0688544e+09 | H6: =Initiatives!C56 -> 1.1860393e+10 | I6: =Initiatives!C57 -> 7.5993993 | J6: =Initiatives!C58 -> 0.014079405 | K6: =Initiatives!C61 -> 0.0029168858 | L6: =Initiatives!C35 -> 0.92 | M6: =Initiatives!C62 -> 1.0911562e+10
A7: A2 | B7: =Initiatives!D4 -> Точечная индексация недооценённых архивных ТП (more-for-more) | C7: =Initiatives!D5 -> EASY | D7: =Initiatives!D8 -> 0 | E7: =Initiatives!D51 -> 2.5719985e+10 | F7: =Initiatives!D52 -> 2.3397644e+10 | G7: =Initiatives!D53 -> 2.150208e+10 | H7: =Initiatives!D56 -> 4.2853249e+10 | I7: =Initiatives!D57 -> 6.8407809 | J7: =Initiatives!D58 -> 0.045519115 | K7: =Initiatives!D61 -> -0.038326913 | L7: =Initiatives!D35 -> 0.8 | M7: =Initiatives!D62 -> 3.4282599e+10
A8: A3 | B8: =Initiatives!E4 -> PAYG → суточные/недельные микропакеты | C8: =Initiatives!E5 -> EASY | D8: =Initiatives!E8 -> 0 | E8: =Initiatives!E51 -> 1.6057907e+09 | F8: =Initiatives!E52 -> 1.7005611e+09 | G8: =Initiatives!E53 -> 1.5951189e+09 | H8: =Initiatives!E56 -> 1.7119524e+09 | I8: =Initiatives!E57 -> 1.5585212 | J8: =Initiatives!E58 -> 0.0026650034 | K8: =Initiatives!E61 -> 0.002171174 | L8: =Initiatives!E35 -> 0.9 | M8: =Initiatives!E62 -> 1.5407572e+09
A9: A4 | B9: =Initiatives!F4 -> Smart add-on: пакет-«бустер» в момент исчерпания (opt-in автопродление) | C9: =Initiatives!F5 -> EASY | D9: =Initiatives!F8 -> 0 | E9: =Initiatives!F51 -> 2.3391784e+09 | F9: =Initiatives!F52 -> 2.3467208e+09 | G9: =Initiatives!F53 -> 2.1989019e+09 | H9: =Initiatives!F56 -> 3.0755729e+09 | I9: =Initiatives!F57 -> 3.3892798 | J9: =Initiatives!F58 -> 0.0038192832 | K9: =Initiatives!F61 -> 0.0010242368 | L9: =Initiatives!F35 -> 0.9 | M9: =Initiatives!F62 -> 2.7680156e+09
A10: A5 | B10: =Initiatives!G4 -> Контент-надстройка (Yandex Plus / OVVA / Ucell TV) для архивных ТП | C10: =Initiatives!G5 -> EASY | D10: =Initiatives!G8 -> 0 | E10: =Initiatives!G51 -> 1.9896857e+09 | F10: =Initiatives!G52 -> 2.7143398e+09 | G10: =Initiatives!G53 -> 2.6558431e+09 | H10: =Initiatives!G56 -> 8.4336762e+08 | I10: =Initiatives!G57 -> 1.4852205 | J10: =Initiatives!G58 -> 0.0041433641 | K10: =Initiatives!G61 -> 0.0030911368 | L10: =Initiatives!G35 -> 0.85 | M10: =Initiatives!G62 -> 7.1686248e+08
A11: A6 | B11: =Initiatives!H4 -> Реактивация спящих архивных SIM (win-back оффер) | C11: =Initiatives!H5 -> EASY | D11: =Initiatives!H8 -> 0 | E11: =Initiatives!H51 -> 1.1529593e+09 | F11: =Initiatives!H52 -> 5.4151312e+08 | G11: =Initiatives!H53 -> 3.2110096e+08 | H11: =Initiatives!H56 -> 9.1541833e+08 | I11: =Initiatives!H57 -> 1.744042 | J11: =Initiatives!H58 -> 0.001300974 | K11: =Initiatives!H61 -> 0 | L11: =Initiatives!H35 -> 0.92 | M11: =Initiatives!H62 -> 8.4218487e+08
A12: A7 | B12: =Initiatives!I4 -> «Musofir»: пакеты роуминга/OTP для трудовых мигрантов на архивных ТП | C12: =Initiatives!I5 -> EASY | D12: =Initiatives!I8 -> 0 | E12: =Initiatives!I51 -> 1.4043123e+09 | F12: =Initiatives!I52 -> 1.756884e+09 | G12: =Initiatives!I53 -> 1.6952985e+09 | H12: =Initiatives!I56 -> 1.5013738e+09 | I12: =Initiatives!I57 -> 3.797639 | J12: =Initiatives!I58 -> 0.0026445083 | K12: =Initiatives!I61 -> 0.0028953975 | L12: =Initiatives!I35 -> 0.9 | M12: =Initiatives!I62 -> 1.3512364e+09
A13: A8 | B13: =Initiatives!J4 -> ОПЦИЯ: ежегодная индексация архивных пакетов на инфляцию (волна 2) | C13: =Initiatives!J5 -> EASY | D13: =Initiatives!J8 -> 1 | E13: =Initiatives!J51 -> 0 | F13: =Initiatives!J52 -> 1.8414311e+10 | G13: =Initiatives!J53 -> 1.84129e+10 | H13: =Initiatives!J56 -> 1.6723015e+10 | I13: =Initiatives!J57 -> 9.8876894 | J13: =Initiatives!J58 -> 0.038780132 | K13: =Initiatives!J61 -> -0.031746071 | L13: =Initiatives!J35 -> 0.65 | M13: =Initiatives!J62 -> 1.086996e+10
A14: B1 | B14: =Initiatives!K4 -> AI Next-Best-Offer: персональные офферы в реальном времени (RTD/CVM) | C14: =Initiatives!K5 -> HARD | D14: =Initiatives!K8 -> 0 | E14: =Initiatives!K51 -> 6.1807245e+09 | F14: =Initiatives!K52 -> 2.210659e+10 | G14: =Initiatives!K53 -> 2.2631817e+10 | H14: =Initiatives!K56 -> 1.2494218e+10 | I14: =Initiatives!K57 -> 1.0817505 | J14: =Initiatives!K58 -> 0.029765596 | K14: =Initiatives!K61 -> 0.078003177 | L14: =Initiatives!K35 -> 0.65 | M14: =Initiatives!K62 -> 8.1212415e+09
A15: B2 | B15: =Initiatives!L4 -> «Ucell Oila»: семейный/групповой аккаунт с общим пакетом | C15: =Initiatives!L5 -> HARD | D15: =Initiatives!L8 -> 0 | E15: =Initiatives!L51 -> 1.3505551e+09 | F15: =Initiatives!L52 -> 6.2165895e+09 | G15: =Initiatives!L53 -> 6.0070844e+09 | H15: =Initiatives!L56 -> -66043748 | I15: =Initiatives!L57 -> -0.010163521 | J15: =Initiatives!L58 -> 0.0085341902 | K15: =Initiatives!L61 -> 0.022141453 | L15: =Initiatives!L35 -> 0.65 | M15: =Initiatives!L62 -> -42928436
A16: B3 | B16: =Initiatives!M4 -> Sunset-программа: вывод устаревших семейств ТП с ценовой защитой | C16: =Initiatives!M5 -> HARD | D16: =Initiatives!M8 -> 0 | E16: =Initiatives!M51 -> 3.9521429e+09 | F16: =Initiatives!M52 -> 4.0127466e+10 | G16: =Initiatives!M53 -> 3.6876533e+10 | H16: =Initiatives!M56 -> 3.4053675e+10 | I16: =Initiatives!M57 -> 3.3965592 | J16: =Initiatives!M58 -> 0.080881056 | K16: =Initiatives!M61 -> -0.081054821 | L16: =Initiatives!M35 -> 0.6 | M16: =Initiatives!M62 -> 2.0432205e+10
A17: B4 | B17: =Initiatives!N4 -> Апгрейд 2G/3G → 4G-смартфон в рассрочку (BNPL-партнёр) | C17: =Initiatives!N5 -> HARD | D17: =Initiatives!N8 -> 0 | E17: =Initiatives!N51 -> 2.2088416e+08 | F17: =Initiatives!N52 -> 7.0858929e+08 | G17: =Initiatives!N53 -> 6.7321956e+08 | H17: =Initiatives!N56 -> -2.862504e+09 | I17: =Initiatives!N57 -> -0.78369877 | J17: =Initiatives!N58 -> 0.0011404358 | K17: =Initiatives!N61 -> 0.00063398463 | L17: =Initiatives!N35 -> 0.6 | M17: =Initiatives!N62 -> -1.7175024e+09
A18: B5 | B18: =Initiatives!O4 -> Персональные лимиты «Mobil avans» на ML-скоринге | C18: =Initiatives!O5 -> HARD | D18: =Initiatives!O8 -> 0 | E18: =Initiatives!O51 -> 1.5139852e+09 | F18: =Initiatives!O52 -> 2.8469061e+09 | G18: =Initiatives!O53 -> 2.7352683e+09 | H18: =Initiatives!O56 -> -2.5489609e+08 | I18: =Initiatives!O57 -> -0.077065623 | J18: =Initiatives!O58 -> 0.0043452665 | K18: =Initiatives!O61 -> 0.0047474486 | L18: =Initiatives!O35 -> 0.7 | M18: =Initiatives!O62 -> -1.7842726e+08
A20: Итоги портфеля
A21: Базовый: выручка Y1 после перекрытия, сум | C21: =SUMIFS(E6:E18,$D$6:$D$18,0)*(1-$C$3) -> 4.3798486e+10
A22: Базовый: выручка Y2 после перекрытия, сум | C22: =SUMIFS(F6:F18,$D$6:$D$18,0)*(1-$C$3) -> 9.0348338e+10
A23: Базовый: run-rate/год на мес. 24 после перекрытия, сум | C23: =SUMIFS(G6:G18,$D$6:$D$18,0)*(1-$C$3) -> 8.5568896e+10
A24: Базовый: run-rate/год, USD | C24: =C23/Inputs!$C$11 -> 7071809.6
A25: Базовый: вклад 24 мес. (перекрытие снижает положительный вклад) | C25: =SUMIFS(H6:H18,$D$6:$D$18,0)-$C$3*MAX(SUMIFS(H6:H18,$D$6:$D$18,0),0) -> 8.4900621e+10
A26: Базовый: ARPU когорты до, сум | C26: =Inputs!$C$8 -> 18500
A27: Базовый: ARPU когорты на мес. 12, сум | C27: =Monthly!N196 -> 21424.91
A28: Базовый: ARPU когорты на мес. 24, сум | C28: =Monthly!Z196 -> 21437.711
A29: Базовый: ΔARPU когорты на мес. 12 | C29: =Monthly!N197 -> 0.15810326
A30: Базовый: ΔARPU когорты на мес. 24 | C30: =Monthly!Z197 -> 0.1587952
A31: Stretch (+опции): ΔARPU когорты на мес. 24 | C31: =Monthly!Z199 -> 0.19047287
A32: Базовый: прирост выручки когорты (run-rate), % к базе | C32: =IF(Inputs!C13>0,C23/(Inputs!C13*12),0) -> 0.10950156
A33: Базовый: Δ доли рынка к мес. 24, п.п. | C33: =SUMIFS(K6:K18,$D$6:$D$18,0)*(1-$C$3) -> -0.0014054718
A36: Динамика ΔARPU когорты по месяцам
A37: Месяц | C37: 1 | D37: 2 | E37: 3 | F37: 4 | G37: 5 | H37: 6 | I37: 7 | J37: 8 | K37: 9 | L37: 10 | M37: 11 | N37: 12 | O37: 13 | P37: 14 | Q37: 15 | R37: 16 | S37: 17 | T37: 18 | U37: 19 | V37: 20 | W37: 21 | X37: 22 | Y37: 23 | Z37: 24
A38: Базовый портфель | C38: =Monthly!C197 -> 0 | D38: =Monthly!D197 -> 0.042213931 | E38: =Monthly!E197 -> 0.049121709 | F38: =Monthly!F197 -> 0.054779337 | G38: =Monthly!G197 -> 0.059023932 | H38: =Monthly!H197 -> 0.060889228 | I38: =Monthly!I197 -> 0.062131557 | J38: =Monthly!J197 -> 0.06941872 | ... Z38: =Monthly!Z197 -> 0.1587952
A39: Stretch (+A8) | C39: =Monthly!C199 -> 0 | D39: =Monthly!D199 -> 0.042213931 | E39: =Monthly!E199 -> 0.049121709 | F39: =Monthly!F199 -> 0.054779337 | G39: =Monthly!G199 -> 0.059023932 | H39: =Monthly!H199 -> 0.060889228 | I39: =Monthly!I199 -> 0.062131557 | J39: =Monthly!J199 -> 0.06941872 | ... Z39: =Monthly!Z199 -> 0.19047287

Sheet AB_Calculator
A1: Калькулятор размера выборки A/B (двусторонний тест)
A3: Уровень значимости alpha | B3: 0.05
A4: Мощность (power) | B4: 0.8
A5: Коэф. вариации ARPU σ/μ (из данных, запрос D6) | B5: 1.2
A6: Минимальный детектируемый эффект (MDE), отн. | B6: 0.03
A8: N на группу — ARPU (t-тест) | B8: =ROUNDUP(2*(NORMSINV(1-B3/2)+NORMSINV(B4))^2*B5^2/B6^2,0) -> 25117
A10: Конверсия/отток в контроле p1 | B10: 0.1
A11: Конверсия/отток в тесте p2 | B11: 0.11
A12: N на группу — пропорции | B12: =ROUNDUP((NORMSINV(1-B3/2)*SQRT(2*((B10+B11)/2)*(1-(B10+B11)/2))+NORMSINV(B4)*SQRT(B10*(1-B10)+B11*(1-B11)))^2/(B11-B10)^2,0) -> 14751
A14: Рекомендация: holdout 5–10% целевой группы на весь срок программы; стратификация по сегменту, региону, тенуре, типу устройства; фиксировать гипотезу и MDE до старта (pre-registration).

Sheet MC_Results
A1: Результаты Монте-Карло (20 000 прогонов) — значения из model/output/results.json
A2: Выход внешней модели (python model/arpu_model.py), не формулы. Млрд сум без НДС. Шанс успеха = P(вклад 24м > 0 и ΔARPU > 0) × P(запуска). Бизнес-кейс = ≥70% плана по вкладу и ΔARPU.
A4: # | B4: Инициатива | C4: Группа | D4: Выручка Y1 P10 | E4: Выручка Y1 P50 | F4: Выручка Y1 P90 | G4: Вклад 24м P10 | H4: Вклад 24м P50 | I4: Вклад 24м P90 | J4: ΔARPU P50 | K4: P(вклад>0) | L4: P(запуска) | M4: Шанс успеха | N4: Шанс ≥70% бизнес-кейса
A5: A1 | B5: «Ucell 30 — Upgrade»: мягкая миграция с подарком | C5: EASY | D5: 4.22 | E5: 7.32 | F5: 11.65 | G5: 6.26 | H5: 11.79 | I5: 19.52 | J5: 0.014370196 | K5: 1 | L5: 0.92 | M5: 0.92 | N5: 0.708446
A6: A2 | B6: Точечная индексация недооценённых архивных ТП (more-for-more) | C6: EASY | D6: 19.52 | E6: 24.41 | F6: 29.6 | G6: 30.2 | H6: 39.56 | I6: 49.25 | J6: 0.044199877 | K6: 1 | L6: 0.8 | M6: 0.8 | N6: 0.72408
A7: A3 | B7: PAYG → суточные/недельные микропакеты | C7: EASY | D7: 0.1 | E7: 1.42 | F7: 2.81 | G7: -0.89 | H7: 1.39 | I7: 3.71 | J7: 0.0024164193 | K7: 0.77915 | L7: 0.9 | M7: 0.701235 | N7: 0.48906
A8: A4 | B8: Smart add-on: пакет-«бустер» в момент исчерпания (opt-in автопродление) | C8: EASY | D8: 1.65 | E8: 2.49 | F8: 3.7 | G8: 1.93 | H8: 3.29 | I8: 5.23 | J8: 0.0041554891 | K8: 1 | L8: 0.9 | M8: 0.9 | N8: 0.765495
A9: A5 | B9: Контент-надстройка (Yandex Plus / OVVA / Ucell TV) для архивных ТП | C9: EASY | D9: 1.38 | E9: 2.23 | F9: 3.33 | G9: 0.4 | H9: 1 | I9: 1.79 | J9: 0.0046416956 | K9: 0.99655 | L9: 0.85 | M9: 0.8470675 | N9: 0.6771525
A10: A6 | B10: Реактивация спящих архивных SIM (win-back оффер) | C10: EASY | D10: 0.79 | E10: 1.23 | F10: 1.84 | G10: 0.43 | H10: 0.99 | I10: 1.78 | J10: 0.001377259 | K10: 0.9989 | L10: 0.92 | M10: 0.918988 | N10: 0.710056
A11: A7 | B11: «Musofir»: пакеты роуминга/OTP для трудовых мигрантов на архивных ТП | C11: EASY | D11: 0.87 | E11: 1.44 | F11: 2.26 | G11: 0.79 | H11: 1.54 | I11: 2.64 | J11: 0.0027116665 | K11: 1 | L11: 0.9 | M11: 0.9 | N11: 0.702405
A12: A8 | B12: ОПЦИЯ: ежегодная индексация архивных пакетов на инфляцию (волна 2) | C12: EASY | D12: 0 | E12: 0 | F12: 0 | G12: 11.34 | H12: 15.24 | I12: 19.39 | J12: 0.037503527 | K12: 1 | L12: 0.65 | M12: 0.65 | N12: 0.56953
A13: B1 | B13: AI Next-Best-Offer: персональные офферы в реальном времени (RTD/CVM) | C13: HARD | D13: 4.28 | E13: 6.74 | F13: 9.65 | G13: 5.23 | H13: 14.17 | I13: 24.48 | J13: 0.032382245 | K13: 0.9901 | L13: 0.65 | M13: 0.643565 | N13: 0.5026775
A14: B2 | B14: «Ucell Oila»: семейный/групповой аккаунт с общим пакетом | C14: HARD | D14: 0.92 | E14: 1.44 | F14: 2.15 | G14: -2.6 | H14: 0.05 | I14: 3.38 | J14: 0.0090273165 | K14: 0.5079 | L14: 0.65 | M14: 0.330135 | N14: 0.330135
A15: B3 | B15: Sunset-программа: вывод устаревших семейств ТП с ценовой защитой | C15: HARD | D15: 2.51 | E15: 3.82 | F15: 5.46 | G15: 16.57 | H15: 31.55 | I15: 50.3 | J15: 0.079092681 | K15: 1 | L15: 0.6 | M15: 0.6 | N15: 0.43839
A16: B4 | B16: Апгрейд 2G/3G → 4G-смартфон в рассрочку (BNPL-партнёр) | C16: HARD | D16: 0.14 | E16: 0.24 | F16: 0.38 | G16: -3.78 | H16: -2.97 | I16: -2.24 | J16: 0.0012349158 | K16: 0 | L16: 0.6 | M16: 0 | N16: 0
A17: B5 | B17: Персональные лимиты «Mobil avans» на ML-скоринге | C17: HARD | D17: 1.05 | E17: 1.69 | F17: 2.58 | G17: -1.47 | H17: -0.02 | I17: 1.85 | J17: 0.0048251434 | K17: 0.4928 | L17: 0.7 | M17: 0.34496 | N17: 0.34496
A19: Портфель (с учётом P(запуска) каждой инициативы и перекрытия)
A20: Сценарий | C20: ΔARPU мес.12 P50 | D20: ΔARPU мес.24 P10 | E20: ΔARPU мес.24 P50 | F20: ΔARPU мес.24 P90 | G20: Выручка Y1 P50 | H20: Выручка Y2 P50 | I20: Вклад 24м P50 | J20: P(ΔARPU≥10%) | K20: P(ΔARPU≥15%) | L20: P(ΔARPU≥20%)
A21: Базовый | C21: 0.11470935 | D21: 0.061579131 | E21: 0.11539655 | F21: 0.16995992 | G21: 36.9 | H21: 65 | I21: 58.6 | J21: 0.61145 | K21: 0.2285 | L21: 0.01405
A22: Только EASY | C22: 0.055203947 | D22: 0.022223008 | E22: 0.055036926 | F22: 0.067354323 | G22: 30.2 | H22: 29.7 | I22: 44.3 | J22: 0 | K22: 0 | L22: 0
A23: Только HARD | C23: 0.065569319 | D23: 0.011333602 | E23: 0.066905904 | F23: 0.11297206 | G23: 7.4 | H23: 36.2 | I23: 16.8 | J23: 0.1982 | K23: 0.00435 | L23: 0
A24: Stretch (+A8) | C24: 0.1144742 | D24: 0.07631689 | E24: 0.13468298 | F24: 0.19421288 | G24: 36.9 | H24: 74.1 | I24: 66.4 | J24: 0.75755 | K24: 0.38625 | L24: 0.0764
