Workbook

Sheet README
A1: Ucell v2 — 4 инициативы роста ARPU архивной базы + Loyalty program
A3: I1 Sunset / Migration → ТП дороже на 10–15% · I2 More-for-More · I3 Бустер при исчерпании + роуминг-промо · I4 Loyalty (кэшбэк, Daily Drops, Weekly Wins, Monthly Grand)
A5: Как пользоваться
A6: 1. Жёлтые ячейки — гипотезы: заменить фактом из запроса данных (v2/docs/12_data_request_for_analysts.md).
A7: 2. Синие — параметры (меняйте по итогам пилотов и MVP). Чёрные — формулы. Зелёные — ссылки на другие листы.
A8: 3. Monthly_I и Loyalty_Monthly — помесячные движки на 36 мес. (M1 = ноябрь 2026).
A9: 4. Prizes и Daily_Drops — каталог призов в сумах, фонды Weekly/Monthly, таблица вероятностей сундука.
A10: 5. Thresholds — сравнение вариантов порога участия (O1–O5). MVP_Budget — бюджет пилота программы.
A11: 6. MC_Results — вероятности из Монте-Карло (python v2/model/model_v2.py), это значения, не формулы.
A13: Единицы: сумы без НДС 12% (цены призов и абонплаты — с НДС, где указано). ARPU — по когорте архивных абонентов T0.
A14: Excel повторяет детерминированный прогон Python на модальных значениях.

Sheet Inputs
A1: Базовые допущения (архивная когорта)
A3: Параметр | C3: Значение | D3: Ед. | E3: Источник / комментарий
A4: Абонентская база Ucell | C4: 11000000 | D4: абон. | E4: Ucell: >10,9 млн на начало 2026
A5: Доля абонентов на архивных ТП | C5: 0.4 | D5: % | E5: HYPOTHESIS — запрос D1
A6: Доля активных среди архивных | C6: 0.8 | D6: % | E6: HYPOTHESIS — запрос D1
A7: Активная архивная когорта (N) | C7: =C4*C5*C6 -> 3520000 | D7: абон. | E7: Формула
A8: ARPU архивной когорты (net) | C8: 18500 | D8: сум/мес | E8: HYPOTHESIS — запрос D2
A9: Месячный отток архивной когорты | C9: 0.015 | D9: % | E9: HYPOTHESIS — запрос D4
A10: НДС | C10: 0.12 | D10: % | E10: НК РУз: 12%
A11: Курс, сум за 1 USD | C11: 12100 | D11: сум | E11: ЦБ РУз, 2026
A12: Рынок мобильной связи, абонентов | C12: 36500000 | D12: абон. | E12: HYPOTHESIS
A13: Выручка когорты в месяц | C13: =C7*C8 -> 65120000000 | D13: сум/мес | E13: Формула
A14: Перекрытие эффектов I1–I3 | C14: 0.1 | D14: % | E14: Одни и те же абоненты в нескольких инициативах

Sheet Initiatives
A1: Инициативы I1–I3: параметры (синие) → производные → итоги (из Monthly_I)
A3: Параметр | B3: Ключ | C3: I1 | D3: I2 | E3: I3a | F3: I3b
A4: Название | B4: name | C4: Sunset / Migration старых неэффективных линеек → ТП дороже на 10–15% | D4: More-for-More: + абонплата и + трафик для когорты недооценённых линеек | E4: Пакет-бустер для исчерпывающих трафик (opt-in автопродление) | F4: Роуминг-пакет по акции (−50% первый месяц) для выезжающих
A5: Коротко | B5: short | C5: Sunset / Migration | D5: More-for-More | E5: Бустер при исчерпании | F5: Роуминг-промо
A6: Тип механики | B6: type | C6: reprice | D6: reprice | E6: adoption | F6: adoption
A7: Сложность биллинг/интеграции (1–5) | B7: complexity | C7: 4 | D7: 1 | E7: 2 | F7: 2
A8: ARPU целевого сегмента, сум | B8: segment_arpu | C8: 16000 | D8: 21000 | E8: 28000 | F8: 15000
A9: Доля целевой группы от когорты | B9: eligible_share | C9: 0.3 | D9: 0.22 | E9: 0.15 | F9: 0.06
A10: Новый ТП дороже на, % (I1) | B10: price_up_pct | C10: 0.125 | D10: 0 | E10: 0 | F10: 0
A11: Текущая абонплата мигрируемых линеек, с НДС (I1) | B11: base_fee_gross | C11: 20000 | D11: 0 | E11: 0 | F11: 0
A12: Повышение абонплаты, сум с НДС (I2) | B12: price_up_gross | C12: 0 | D12: 5000 | E12: 0 | F12: 0
A13: Доля выбравших ТП крупнее | B13: upsell_share | C13: 0.12 | D13: 0 | E13: 0 | F13: 0
A14: Доп. ARPU у выбравших крупнее, сум | B14: upsell_delta | C14: 10000 | D14: 0 | E14: 0 | F14: 0
A15: Доля даунгрейда | B15: downgrade | C15: 0.08 | D15: 0.08 | E15: 0 | F15: 0
A16: Δ выручки при даунгрейде, сум | B16: downgrade_delta | C16: -2000 | D16: -3000 | E16: 0 | F16: 0
A17: Доп. отток | B17: churn_incr | C17: 0.03 | D17: 0.025 | E17: 0 | F17: 0
A18: Себестоимость доп. трафика, сум/мес | B18: data_cost_m | C18: 300 | D18: 400 | E18: 0 | F18: 0
... A35: Вероятность запуска | B35: exec_prob | C35: 0.65 | D35: 0.8 | E35: 0.9 | F35: 0.9
A37: ПРОИЗВОДНЫЕ
A38: Целевая группа, абон. | B38: elig | C38: =Inputs!$C$7*C9 -> 1056000 | D38: =Inputs!$C$7*D9 -> 774400 | E38: =Inputs!$C$7*E9 -> 528000 | F38: =Inputs!$C$7*F9 -> 211200
A39: Охвачено, абон. | B39: contacted | C39: =IF(C6="adoption",C38*C20,C38) -> 1056000 | D39: =IF(D6="adoption",D38*D20,D38) -> 774400 | E39: =IF(E6="adoption",E38*E20,E38) -> 475200 | F39: =IF(F6="adoption",F38*F20,F38) -> 168960
A40: Адоптеры при полном наборе | B40: a_final | C40: =IF(C6="adoption",C39*C21*(1-C22),0) -> 0 | D40: =IF(D6="adoption",D39*D21*(1-D22),0) -> 0 | E40: =IF(E6="adoption",E39*E21*(1-E22),0) -> 31363.2 | F40: =IF(F6="adoption",F39*F21*(1-F22),0) -> 25344
A41: Повышение абонплаты net, сум | B41: up_net | C41: =IF(C10>0,C11*C10,C12)/(1+Inputs!$C$10) -> 2232.1429 | D41: =IF(D10>0,D11*D10,D12)/(1+Inputs!$C$10) -> 4464.2857 | E41: =IF(E10>0,E11*E10,E12)/(1+Inputs!$C$10) -> 0 | F41: =IF(F10>0,F11*F10,F12)/(1+Inputs!$C$10) -> 0
A42: Остаются и платят больше | B42: stay | C42: =IF(C6="reprice",C38*(1-C15-C17),0) -> 939840 | D42: =IF(D6="reprice",D38*(1-D15-D17),0) -> 693088 | E42: =IF(E6="reprice",E38*(1-E15-E17),0) -> 0 | F42: =IF(F6="reprice",F38*(1-F15-F17),0) -> 0
A43: Даунгрейд, абон. | B43: down | C43: =IF(C6="reprice",C38*C15,0) -> 84480 | D43: =IF(D6="reprice",D38*D15,0) -> 61952 | E43: =IF(E6="reprice",E38*E15,0) -> 0 | F43: =IF(F6="reprice",F38*F15,0) -> 0
A44: Доп. отток всего, абон. | B44: lost_total | C44: =C39*C17 -> 31680 | D44: =D39*D17 -> 19360 | E44: =E39*E17 -> 0 | F44: =F39*F17 -> 0
A45: Месяцев подготовки | B45: build | C45: =MAX(C31-1,1) -> 5 | D45: =MAX(D31-1,1) -> 1 | E45: =MAX(E31-1,1) -> 1 | F45: =MAX(F31-1,1) -> 1
A46: Месяц оценки (12-й после старта) | B46: eval_m | C46: =MIN(C31+11,36) -> 17 | D46: =MIN(D31+11,36) -> 13 | E46: =MIN(E31+11,36) -> 13 | F46: =MIN(F31+11,36) -> 13
A48: ИТОГИ
A49: Выручка Y1 | B49: rev1 | C49: =SUM(Monthly_I!C16:N16) -> 1.4494602e+10 | D49: =SUM(Monthly_I!C30:N30) -> 2.1823874e+10 | E49: =SUM(Monthly_I!C44:N44) -> 2.3391784e+09 | F49: =SUM(Monthly_I!C58:N58) -> 1.7286954e+09
A50: Выручка Y2 | B50: rev2 | C50: =SUM(Monthly_I!O16:Z16) -> 2.7332819e+10 | D50: =SUM(Monthly_I!O30:Z30) -> 2.4043884e+10 | E50: =SUM(Monthly_I!O44:Z44) -> 2.3467208e+09 | F50: =SUM(Monthly_I!O58:Z58) -> 1.9396764e+09
A51: Выручка Y3 | B51: rev3 | C51: =SUM(Monthly_I!AA16:AL16) -> 2.2799178e+10 | D51: =SUM(Monthly_I!AA30:AL30) -> 2.0055772e+10 | E51: =SUM(Monthly_I!AA44:AL44) -> 2.0388521e+09 | F51: =SUM(Monthly_I!AA58:AL58) -> 1.7901325e+09
A52: Run-rate/год на M24 | B52: runrate | C52: =Monthly_I!Z16*12 -> 2.5118447e+10 | D52: =Monthly_I!Z30*12 -> 2.2095965e+10 | E52: =Monthly_I!Z44*12 -> 2.1989019e+09 | F52: =Monthly_I!Z58*12 -> 1.8711774e+09
A53: Затраты 24 мес. | B53: cost24 | C53: =SUM(Monthly_I!C17:Z17) -> 9.0958994e+09 | D53: =SUM(Monthly_I!C31:Z31) -> 5.9037909e+09 | E53: =SUM(Monthly_I!C45:Z45) -> 9.0744142e+08 | F53: =SUM(Monthly_I!C59:Z59) -> 557408000
A54: Вклад 24 мес. | B54: contrib24 | C54: =SUM(Monthly_I!C18:Z18) -> 3.2731522e+10 | D54: =SUM(Monthly_I!C32:Z32) -> 3.9963968e+10 | E54: =SUM(Monthly_I!C46:Z46) -> 3.0755729e+09 | F54: =SUM(Monthly_I!C60:Z60) -> 1.6436151e+09
A55: Вклад 36 мес. | B55: contrib36 | C55: =SUM(Monthly_I!C18:AL18) -> 5.3496876e+10 | D55: =SUM(Monthly_I!C32:AL32) -> 5.7554455e+10 | E55: =SUM(Monthly_I!C46:AL46) -> 4.5625348e+09 | F55: =SUM(Monthly_I!C60:AL60) -> 2.5976946e+09
A56: ROI 24 мес. | B56: roi24 | C56: =IF(C53>0,C54/C53,0) -> 3.5984921 | D56: =IF(D53>0,D54/D53,0) -> 6.7692044 | E56: =IF(E53>0,E54/E53,0) -> 3.3892798 | F56: =IF(F53>0,F54/F53,0) -> 2.9486751
A57: ΔARPU когорты на месяц оценки | B57: upl_eval | C57: =(INDEX(Monthly_I!$C$5:$AL$5,1,C46)+INDEX(Monthly_I!$C$16:$AL$16,1,C46))/(INDEX(Monthly_I!$C$4:$AL$4,1,C46)+INDEX(Monthly_I!$C$19:$AL$19,1,C46))/Inputs!$C$8-1 -> 0.056936525 | D57: =(INDEX(Monthly_I!$C$5:$AL$5,1,D46)+INDEX(Monthly_I!$C$30:$AL$30,1,D46))/(INDEX(Monthly_I!$C$4:$AL$4,1,D46)+INDEX(Monthly_I!$C$33:$AL$33,1,D46))/Inputs!$C$8-1 -> 0.046783771 | E57: =(INDEX(Monthly_I!$C$5:$AL$5,1,E46)+INDEX(Monthly_I!$C$44:$AL$44,1,E46))/(INDEX(Monthly_I!$C$4:$AL$4,1,E46)+INDEX(Monthly_I!$C$47:$AL$47,1,E46))/Inputs!$C$8-1 -> 0.0038192832 | F57: =(INDEX(Monthly_I!$C$5:$AL$5,1,F46)+INDEX(Monthly_I!$C$58:$AL$58,1,F46))/(INDEX(Monthly_I!$C$4:$AL$4,1,F46)+INDEX(Monthly_I!$C$61:$AL$61,1,F46))/Inputs!$C$8-1 -> 0.0028942094
A58: ΔARPU когорты на M24 | B58: upl24 | C58: =(Monthly_I!Z$5+Monthly_I!Z16)/(Monthly_I!Z$4+Monthly_I!Z19)/Inputs!$C$8-1 -> 0.056936525 | D58: =(Monthly_I!Z$5+Monthly_I!Z30)/(Monthly_I!Z$4+Monthly_I!Z33)/Inputs!$C$8-1 -> 0.046783771 | E58: =(Monthly_I!Z$5+Monthly_I!Z44)/(Monthly_I!Z$4+Monthly_I!Z47)/Inputs!$C$8-1 -> 0.0038910367 | F58: =(Monthly_I!Z$5+Monthly_I!Z58)/(Monthly_I!Z$4+Monthly_I!Z61)/Inputs!$C$8-1 -> 0.0029434064
A59: Δ абонентов на M24 | B59: dsubs24 | C59: =Monthly_I!Z19 -> -24882.204 | D59: =Monthly_I!Z33 -> -14375.707 | E59: =Monthly_I!Z47 -> 373.84642 | F59: =Monthly_I!Z61 -> 1216.3559
A60: Ожидаемый вклад 24м × P(запуска) | B60: exp24 | C60: =C54*C35 -> 2.1275489e+10 | D60: =D54*D35 -> 3.1971174e+10 | E60: =E54*E35 -> 2.7680156e+09 | F60: =F54*F35 -> 1.4792536e+09

Sheet Monthly_I
A1: Помесячный движок I1–I3 (36 мес., сум без НДС)
A3: Месяц | C3: 1 | D3: 2 | E3: 3 | F3: 4 | G3: 5 | H3: 6 | I3: 7 | J3: 8 | K3: 9 | L3: 10 | M3: 11 | N3: 12 | O3: 13 | P3: 14 | Q3: 15 | R3: 16 | S3: 17 | T3: 18 | U3: 19 | V3: 20 | W3: 21 | X3: 22 | Y3: 23 | Z3: 24 | AA3: 25 | AB3: 26 | AC3: 27 | AD3: 28 | AE3: 29 | AF3: 30 | AG3: 31 | AH3: 32 | AI3: 33 | AJ3: 34 | AK3: 35 | AL3: 36
A4: S0: абоненты когорты без инициатив | C4: =Inputs!$C$7*(1-Inputs!$C$9)^C$3 -> 3467200 | D4: =Inputs!$C$7*(1-Inputs!$C$9)^D$3 -> 3415192 | E4: =Inputs!$C$7*(1-Inputs!$C$9)^E$3 -> 3363964.1 | F4: =Inputs!$C$7*(1-Inputs!$C$9)^F$3 -> 3313504.7 | G4: =Inputs!$C$7*(1-Inputs!$C$9)^G$3 -> 3263802.1 | H4: =Inputs!$C$7*(1-Inputs!$C$9)^H$3 -> 3214845.1 | I4: =Inputs!$C$7*(1-Inputs!$C$9)^I$3 -> 3166622.4 | J4: =Inputs!$C$7*(1-Inputs!$C$9)^J$3 -> 3119123 | ... AL4: =Inputs!$C$7*(1-Inputs!$C$9)^AL$3 -> 2042899.3
A5: R0: выручка когорты без инициатив | C5: =C4*Inputs!$C$8 -> 64143200000 | D5: =D4*Inputs!$C$8 -> 63181052000 | E5: =E4*Inputs!$C$8 -> 62233336220 | F5: =F4*Inputs!$C$8 -> 6.1299836e+10 | G5: =G4*Inputs!$C$8 -> 6.0380339e+10 | H5: =H4*Inputs!$C$8 -> 5.9474634e+10 | I5: =I4*Inputs!$C$8 -> 5.8582514e+10 | J5: =J4*Inputs!$C$8 -> 5.7703776e+10 | ... AL5: =AL4*Inputs!$C$8 -> 3.7793637e+10
A7: I1 — Sunset / Migration старых неэффективных линеек → ТП дороже на 10–15%
A8: Доля набора | B8: f | C8: =IF(Initiatives!$C$6="adoption",IF(C$3<Initiatives!$C$31,0,MIN((C$3-Initiatives!$C$31+1)/Initiatives!$C$34,1)),0) -> 0 | D8: =IF(Initiatives!$C$6="adoption",IF(D$3<Initiatives!$C$31,0,MIN((D$3-Initiatives!$C$31+1)/Initiatives!$C$34,1)),0) -> 0 | E8: =IF(Initiatives!$C$6="adoption",IF(E$3<Initiatives!$C$31,0,MIN((E$3-Initiatives!$C$31+1)/Initiatives!$C$34,1)),0) -> 0 | F8: =IF(Initiatives!$C$6="adoption",IF(F$3<Initiatives!$C$31,0,MIN((F$3-Initiatives!$C$31+1)/Initiatives!$C$34,1)),0) -> 0 | G8: =IF(Initiatives!$C$6="adoption",IF(G$3<Initiatives!$C$31,0,MIN((G$3-Initiatives!$C$31+1)/Initiatives!$C$34,1)),0) -> 0 | H8: =IF(Initiatives!$C$6="adoption",IF(H$3<Initiatives!$C$31,0,MIN((H$3-Initiatives!$C$31+1)/Initiatives!$C$34,1)),0) -> 0 | I8: =IF(Initiatives!$C$6="adoption",IF(I$3<Initiatives!$C$31,0,MIN((I$3-Initiatives!$C$31+1)/Initiatives!$C$34,1)),0) -> 0 | J8: =IF(Initiatives!$C$6="adoption",IF(J$3<Initiatives!$C$31,0,MIN((J$3-Initiatives!$C$31+1)/Initiatives!$C$34,1)),0) -> 0 | ... AL8: =IF(Initiatives!$C$6="adoption",IF(AL$3<Initiatives!$C$31,0,MIN((AL$3-Initiatives!$C$31+1)/Initiatives!$C$34,1)),0) -> 0
A9: Адоптеры (цель) | B9: target | C9: =Initiatives!$C$40*C8 -> 0 | D9: =Initiatives!$C$40*D8 -> 0 | E9: =Initiatives!$C$40*E8 -> 0 | F9: =Initiatives!$C$40*F8 -> 0 | G9: =Initiatives!$C$40*G8 -> 0 | H9: =Initiatives!$C$40*H8 -> 0 | I9: =Initiatives!$C$40*I8 -> 0 | J9: =Initiatives!$C$40*J8 -> 0 | ... AL9: =Initiatives!$C$40*AL8 -> 0
A10: Новые адоптеры | B10: new | C10: =MAX(C9-N(B9),0) -> 0 | D10: =MAX(D9-N(C9),0) -> 0 | E10: =MAX(E9-N(D9),0) -> 0 | F10: =MAX(F9-N(E9),0) -> 0 | G10: =MAX(G9-N(F9),0) -> 0 | H10: =MAX(H9-N(G9),0) -> 0 | I10: =MAX(I9-N(H9),0) -> 0 | J10: =MAX(J9-N(I9),0) -> 0 | ... AL10: =MAX(AL9-N(AK9),0) -> 0
A11: Удержанные | B11: R | C11: =IF(Initiatives!$C$6="adoption",N(B11)*(1-Inputs!$C$9)+N(B12)*Inputs!$C$9*Initiatives!$C$24,0) -> 0 | D11: =IF(Initiatives!$C$6="adoption",N(C11)*(1-Inputs!$C$9)+N(C12)*Inputs!$C$9*Initiatives!$C$24,0) -> 0 | E11: =IF(Initiatives!$C$6="adoption",N(D11)*(1-Inputs!$C$9)+N(D12)*Inputs!$C$9*Initiatives!$C$24,0) -> 0 | F11: =IF(Initiatives!$C$6="adoption",N(E11)*(1-Inputs!$C$9)+N(E12)*Inputs!$C$9*Initiatives!$C$24,0) -> 0 | G11: =IF(Initiatives!$C$6="adoption",N(F11)*(1-Inputs!$C$9)+N(F12)*Inputs!$C$9*Initiatives!$C$24,0) -> 0 | H11: =IF(Initiatives!$C$6="adoption",N(G11)*(1-Inputs!$C$9)+N(G12)*Inputs!$C$9*Initiatives!$C$24,0) -> 0 | I11: =IF(Initiatives!$C$6="adoption",N(H11)*(1-Inputs!$C$9)+N(H12)*Inputs!$C$9*Initiatives!$C$24,0) -> 0 | J11: =IF(Initiatives!$C$6="adoption",N(I11)*(1-Inputs!$C$9)+N(I12)*Inputs!$C$9*Initiatives!$C$24,0) -> 0 | ... AL11: =IF(Initiatives!$C$6="adoption",N(AK11)*(1-Inputs!$C$9)+N(AK12)*Inputs!$C$9*Initiatives!$C$24,0) -> 0
A12: Пул адоптеров | B12: pool | C12: =N(B12)*(1-Inputs!$C$9*(1-Initiatives!$C$24))+C10 -> 0 | D12: =N(C12)*(1-Inputs!$C$9*(1-Initiatives!$C$24))+D10 -> 0 | E12: =N(D12)*(1-Inputs!$C$9*(1-Initiatives!$C$24))+E10 -> 0 | F12: =N(E12)*(1-Inputs!$C$9*(1-Initiatives!$C$24))+F10 -> 0 | G12: =N(F12)*(1-Inputs!$C$9*(1-Initiatives!$C$24))+G10 -> 0 | H12: =N(G12)*(1-Inputs!$C$9*(1-Initiatives!$C$24))+H10 -> 0 | I12: =N(H12)*(1-Inputs!$C$9*(1-Initiatives!$C$24))+I10 -> 0 | J12: =N(I12)*(1-Inputs!$C$9*(1-Initiatives!$C$24))+J10 -> 0 | ... AL12: =N(AK12)*(1-Inputs!$C$9*(1-Initiatives!$C$24))+AL10 -> 0
A13: Вес волн × затухание | B13: w | C13: =IF(Initiatives!$C$6="adoption",0,IF(C$3>=Initiatives!$C$31,Initiatives!$C$32*(1-Inputs!$C$9)^(C$3-Initiatives!$C$31),0)+IF(C$3>=Initiatives!$C$33,(1-Initiatives!$C$32)*(1-Inputs!$C$9)^(C$3-Initiatives!$C$33),0)) -> 0 | D13: =IF(Initiatives!$C$6="adoption",0,IF(D$3>=Initiatives!$C$31,Initiatives!$C$32*(1-Inputs!$C$9)^(D$3-Initiatives!$C$31),0)+IF(D$3>=Initiatives!$C$33,(1-Initiatives!$C$32)*(1-Inputs!$C$9)^(D$3-Initiatives!$C$33),0)) -> 0 | E13: =IF(Initiatives!$C$6="adoption",0,IF(E$3>=Initiatives!$C$31,Initiatives!$C$32*(1-Inputs!$C$9)^(E$3-Initiatives!$C$31),0)+IF(E$3>=Initiatives!$C$33,(1-Initiatives!$C$32)*(1-Inputs!$C$9)^(E$3-Initiatives!$C$33),0)) -> 0 | F13: =IF(Initiatives!$C$6="adoption",0,IF(F$3>=Initiatives!$C$31,Initiatives!$C$32*(1-Inputs!$C$9)^(F$3-Initiatives!$C$31),0)+IF(F$3>=Initiatives!$C$33,(1-Initiatives!$C$32)*(1-Inputs!$C$9)^(F$3-Initiatives!$C$33),0)) -> 0 | G13: =IF(Initiatives!$C$6="adoption",0,IF(G$3>=Initiatives!$C$31,Initiatives!$C$32*(1-Inputs!$C$9)^(G$3-Initiatives!$C$31),0)+IF(G$3>=Initiatives!$C$33,(1-Initiatives!$C$32)*(1-Inputs!$C$9)^(G$3-Initiatives!$C$33),0)) -> 0 | H13: =IF(Initiatives!$C$6="adoption",0,IF(H$3>=Initiatives!$C$31,Initiatives!$C$32*(1-Inputs!$C$9)^(H$3-Initiatives!$C$31),0)+IF(H$3>=Initiatives!$C$33,(1-Initiatives!$C$32)*(1-Inputs!$C$9)^(H$3-Initiatives!$C$33),0)) -> 0.5 | I13: =IF(Initiatives!$C$6="adoption",0,IF(I$3>=Initiatives!$C$31,Initiatives!$C$32*(1-Inputs!$C$9)^(I$3-Initiatives!$C$31),0)+IF(I$3>=Initiatives!$C$33,(1-Initiatives!$C$32)*(1-Inputs!$C$9)^(I$3-Initiatives!$C$33),0)) -> 0.4925 | J13: =IF(Initiatives!$C$6="adoption",0,IF(J$3>=Initiatives!$C$31,Initiatives!$C$32*(1-Inputs!$C$9)^(J$3-Initiatives!$C$31),0)+IF(J$3>=Initiatives!$C$33,(1-Initiatives!$C$32)*(1-Inputs!$C$9)^(J$3-Initiatives!$C$33),0)) -> 0.4851125 | ... AL13: =IF(Initiatives!$C$6="adoption",0,IF(AL$3>=Initiatives!$C$31,Initiatives!$C$32*(1-Inputs!$C$9)^(AL$3-Initiatives!$C$31),0)+IF(AL$3>=Initiatives!$C$33,(1-Initiatives!$C$32)*(1-Inputs!$C$9)^(AL$3-Initiatives!$C$33),0)) -> 0.6501958
A14: Новый доп. отток | B14: newlost | C14: =IF(Initiatives!$C$6="adoption",IF(AND(C$3>=Initiatives!$C$31,C$3<Initiatives!$C$31+3),Initiatives!$C$44/3,0),IF(AND(C$3>=Initiatives!$C$31,C$3<Initiatives!$C$31+2),Initiatives!$C$32*Initiatives!$C$44/2,0)+IF(AND(C$3>=Initiatives!$C$33,C$3<Initiatives!$C$33+2),(1-Initiatives!$C$32)*Initiatives!$C$44/2,0)) -> 0 | D14: =IF(Initiatives!$C$6="adoption",IF(AND(D$3>=Initiatives!$C$31,D$3<Initiatives!$C$31+3),Initiatives!$C$44/3,0),IF(AND(D$3>=Initiatives!$C$31,D$3<Initiatives!$C$31+2),Initiatives!$C$32*Initiatives!$C$44/2,0)+IF(AND(D$3>=Initiatives!$C$33,D$3<Initiatives!$C$33+2),(1-Initiatives!$C$32)*Initiatives!$C$44/2,0)) -> 0 | E14: =IF(Initiatives!$C$6="adoption",IF(AND(E$3>=Initiatives!$C$31,E$3<Initiatives!$C$31+3),Initiatives!$C$44/3,0),IF(AND(E$3>=Initiatives!$C$31,E$3<Initiatives!$C$31+2),Initiatives!$C$32*Initiatives!$C$44/2,0)+IF(AND(E$3>=Initiatives!$C$33,E$3<Initiatives!$C$33+2),(1-Initiatives!$C$32)*Initiatives!$C$44/2,0)) -> 0 | F14: =IF(Initiatives!$C$6="adoption",IF(AND(F$3>=Initiatives!$C$31,F$3<Initiatives!$C$31+3),Initiatives!$C$44/3,0),IF(AND(F$3>=Initiatives!$C$31,F$3<Initiatives!$C$31+2),Initiatives!$C$32*Initiatives!$C$44/2,0)+IF(AND(F$3>=Initiatives!$C$33,F$3<Initiatives!$C$33+2),(1-Initiatives!$C$32)*Initiatives!$C$44/2,0)) -> 0 | G14: =IF(Initiatives!$C$6="adoption",IF(AND(G$3>=Initiatives!$C$31,G$3<Initiatives!$C$31+3),Initiatives!$C$44/3,0),IF(AND(G$3>=Initiatives!$C$31,G$3<Initiatives!$C$31+2),Initiatives!$C$32*Initiatives!$C$44/2,0)+IF(AND(G$3>=Initiatives!$C$33,G$3<Initiatives!$C$33+2),(1-Initiatives!$C$32)*Initiatives!$C$44/2,0)) -> 0 | H14: =IF(Initiatives!$C$6="adoption",IF(AND(H$3>=Initiatives!$C$31,H$3<Initiatives!$C$31+3),Initiatives!$C$44/3,0),IF(AND(H$3>=Initiatives!$C$31,H$3<Initiatives!$C$31+2),Initiatives!$C$32*Initiatives!$C$44/2,0)+IF(AND(H$3>=Initiatives!$C$33,H$3<Initiatives!$C$33+2),(1-Initiatives!$C$32)*Initiatives!$C$44/2,0)) -> 7920 | I14: =IF(Initiatives!$C$6="adoption",IF(AND(I$3>=Initiatives!$C$31,I$3<Initiatives!$C$31+3),Initiatives!$C$44/3,0),IF(AND(I$3>=Initiatives!$C$31,I$3<Initiatives!$C$31+2),Initiatives!$C$32*Initiatives!$C$44/2,0)+IF(AND(I$3>=Initiatives!$C$33,I$3<Initiatives!$C$33+2),(1-Initiatives!$C$32)*Initiatives!$C$44/2,0)) -> 7920 | J14: =IF(Initiatives!$C$6="adoption",IF(AND(J$3>=Initiatives!$C$31,J$3<Initiatives!$C$31+3),Initiatives!$C$44/3,0),IF(AND(J$3>=Initiatives!$C$31,J$3<Initiatives!$C$31+2),Initiatives!$C$32*Initiatives!$C$44/2,0)+IF(AND(J$3>=Initiatives!$C$33,J$3<Initiatives!$C$33+2),(1-Initiatives!$C$32)*Initiatives!$C$44/2,0)) -> 0 | ... AL14: =IF(Initiatives!$C$6="adoption",IF(AND(AL$3>=Initiatives!$C$31,AL$3<Initiatives!$C$31+3),Initiatives!$C$44/3,0),IF(AND(AL$3>=Initiatives!$C$31,AL$3<Initiatives!$C$31+2),Initiatives!$C$32*Initiatives!$C$44/2,0)+IF(AND(AL$3>=Initiatives!$C$33,AL$3<Initiatives!$C$33+2),(1-Initiatives!$C$32)*Initiatives!$C$44/2,0)) -> 0
A15: Потерянные | B15: L | C15: =N(B15)*(1-Inputs!$C$9)+C14 -> 0 | D15: =N(C15)*(1-Inputs!$C$9)+D14 -> 0 | E15: =N(D15)*(1-Inputs!$C$9)+E14 -> 0 | F15: =N(E15)*(1-Inputs!$C$9)+F14 -> 0 | G15: =N(F15)*(1-Inputs!$C$9)+G14 -> 0 | H15: =N(G15)*(1-Inputs!$C$9)+H14 -> 7920 | I15: =N(H15)*(1-Inputs!$C$9)+I14 -> 15721.2 | J15: =N(I15)*(1-Inputs!$C$9)+J14 -> 15485.382 | ... AL15: =N(AK15)*(1-Inputs!$C$9)+AL14 -> 20755.042
A16: Инкр. выручка | B16: rev | C16: =IF(Initiatives!$C$6="adoption",C12*Initiatives!$C$23+C11*Initiatives!$C$8-C15*Initiatives!$C$8,(Initiatives!$C$42*Initiatives!$C$41+Initiatives!$C$38*Initiatives!$C$13*Initiatives!$C$14+Initiatives!$C$43*Initiatives!$C$16)*C13-C15*Initiatives!$C$8) -> 0 | D16: =IF(Initiatives!$C$6="adoption",D12*Initiatives!$C$23+D11*Initiatives!$C$8-D15*Initiatives!$C$8,(Initiatives!$C$42*Initiatives!$C$41+Initiatives!$C$38*Initiatives!$C$13*Initiatives!$C$14+Initiatives!$C$43*Initiatives!$C$16)*D13-D15*Initiatives!$C$8) -> 0 | E16: =IF(Initiatives!$C$6="adoption",E12*Initiatives!$C$23+E11*Initiatives!$C$8-E15*Initiatives!$C$8,(Initiatives!$C$42*Initiatives!$C$41+Initiatives!$C$38*Initiatives!$C$13*Initiatives!$C$14+Initiatives!$C$43*Initiatives!$C$16)*E13-E15*Initiatives!$C$8) -> 0 | F16: =IF(Initiatives!$C$6="adoption",F12*Initiatives!$C$23+F11*Initiatives!$C$8-F15*Initiatives!$C$8,(Initiatives!$C$42*Initiatives!$C$41+Initiatives!$C$38*Initiatives!$C$13*Initiatives!$C$14+Initiatives!$C$43*Initiatives!$C$16)*F13-F15*Initiatives!$C$8) -> 0 | G16: =IF(Initiatives!$C$6="adoption",G12*Initiatives!$C$23+G11*Initiatives!$C$8-G15*Initiatives!$C$8,(Initiatives!$C$42*Initiatives!$C$41+Initiatives!$C$38*Initiatives!$C$13*Initiatives!$C$14+Initiatives!$C$43*Initiatives!$C$16)*G13-G15*Initiatives!$C$8) -> 0 | H16: =IF(Initiatives!$C$6="adoption",H12*Initiatives!$C$23+H11*Initiatives!$C$8-H15*Initiatives!$C$8,(Initiatives!$C$42*Initiatives!$C$41+Initiatives!$C$38*Initiatives!$C$13*Initiatives!$C$14+Initiatives!$C$43*Initiatives!$C$16)*H13-H15*Initiatives!$C$8) -> 1.4713286e+09 | I16: =IF(Initiatives!$C$6="adoption",I12*Initiatives!$C$23+I11*Initiatives!$C$8-I15*Initiatives!$C$8,(Initiatives!$C$42*Initiatives!$C$41+Initiatives!$C$38*Initiatives!$C$13*Initiatives!$C$14+Initiatives!$C$43*Initiatives!$C$16)*I13-I15*Initiatives!$C$8) -> 1.3225386e+09 | J16: =IF(Initiatives!$C$6="adoption",J12*Initiatives!$C$23+J11*Initiatives!$C$8-J15*Initiatives!$C$8,(Initiatives!$C$42*Initiatives!$C$41+Initiatives!$C$38*Initiatives!$C$13*Initiatives!$C$14+Initiatives!$C$43*Initiatives!$C$16)*J13-J15*Initiatives!$C$8) -> 1.3027006e+09 | ... AL16: =IF(Initiatives!$C$6="adoption",AL12*Initiatives!$C$23+AL11*Initiatives!$C$8-AL15*Initiatives!$C$8,(Initiatives!$C$42*Initiatives!$C$41+Initiatives!$C$38*Initiatives!$C$13*Initiatives!$C$14+Initiatives!$C$43*Initiatives!$C$16)*AL13-AL15*Initiatives!$C$8) -> 1.7460083e+09
A17: Затраты | B17: cost | C17: =IF(C$3<=Initiatives!$C$45,Initiatives!$C$28/Initiatives!$C$45,0)+IF(Initiatives!$C$6="adoption",C10*Initiatives!$C$26+C12*Initiatives!$C$27+IF(C$3=Initiatives!$C$31,Initiatives!$C$39*Initiatives!$C$25,0)+IF(C$3>=Initiatives!$C$31,Initiatives!$C$29,0),Initiatives!$C$42*Initiatives!$C$18*C13+IF(C$3=Initiatives!$C$31,Initiatives!$C$32*Initiatives!$C$38*Initiatives!$C$25,0)+IF(C$3=Initiatives!$C$33,(1-Initiatives!$C$32)*Initiatives!$C$38*Initiatives!$C$25,0)+IF(C$3>=Initiatives!$C$31,Initiatives!$C$29-Initiatives!$C$19*(Initiatives!$C$32+IF(C$3>=Initiatives!$C$33,1-Initiatives!$C$32,0)),0)) -> 1000000000 | D17: =IF(D$3<=Initiatives!$C$45,Initiatives!$C$28/Initiatives!$C$45,0)+IF(Initiatives!$C$6="adoption",D10*Initiatives!$C$26+D12*Initiatives!$C$27+IF(D$3=Initiatives!$C$31,Initiatives!$C$39*Initiatives!$C$25,0)+IF(D$3>=Initiatives!$C$31,Initiatives!$C$29,0),Initiatives!$C$42*Initiatives!$C$18*D13+IF(D$3=Initiatives!$C$31,Initiatives!$C$32*Initiatives!$C$38*Initiatives!$C$25,0)+IF(D$3=Initiatives!$C$33,(1-Initiatives!$C$32)*Initiatives!$C$38*Initiatives!$C$25,0)+IF(D$3>=Initiatives!$C$31,Initiatives!$C$29-Initiatives!$C$19*(Initiatives!$C$32+IF(D$3>=Initiatives!$C$33,1-Initiatives!$C$32,0)),0)) -> 1000000000 | E17: =IF(E$3<=Initiatives!$C$45,Initiatives!$C$28/Initiatives!$C$45,0)+IF(Initiatives!$C$6="adoption",E10*Initiatives!$C$26+E12*Initiatives!$C$27+IF(E$3=Initiatives!$C$31,Initiatives!$C$39*Initiatives!$C$25,0)+IF(E$3>=Initiatives!$C$31,Initiatives!$C$29,0),Initiatives!$C$42*Initiatives!$C$18*E13+IF(E$3=Initiatives!$C$31,Initiatives!$C$32*Initiatives!$C$38*Initiatives!$C$25,0)+IF(E$3=Initiatives!$C$33,(1-Initiatives!$C$32)*Initiatives!$C$38*Initiatives!$C$25,0)+IF(E$3>=Initiatives!$C$31,Initiatives!$C$29-Initiatives!$C$19*(Initiatives!$C$32+IF(E$3>=Initiatives!$C$33,1-Initiatives!$C$32,0)),0)) -> 1000000000 | F17: =IF(F$3<=Initiatives!$C$45,Initiatives!$C$28/Initiatives!$C$45,0)+IF(Initiatives!$C$6="adoption",F10*Initiatives!$C$26+F12*Initiatives!$C$27+IF(F$3=Initiatives!$C$31,Initiatives!$C$39*Initiatives!$C$25,0)+IF(F$3>=Initiatives!$C$31,Initiatives!$C$29,0),Initiatives!$C$42*Initiatives!$C$18*F13+IF(F$3=Initiatives!$C$31,Initiatives!$C$32*Initiatives!$C$38*Initiatives!$C$25,0)+IF(F$3=Initiatives!$C$33,(1-Initiatives!$C$32)*Initiatives!$C$38*Initiatives!$C$25,0)+IF(F$3>=Initiatives!$C$31,Initiatives!$C$29-Initiatives!$C$19*(Initiatives!$C$32+IF(F$3>=Initiatives!$C$33,1-Initiatives!$C$32,0)),0)) -> 1000000000 | G17: =IF(G$3<=Initiatives!$C$45,Initiatives!$C$28/Initiatives!$C$45,0)+IF(Initiatives!$C$6="adoption",G10*Initiatives!$C$26+G12*Initiatives!$C$27+IF(G$3=Initiatives!$C$31,Initiatives!$C$39*Initiatives!$C$25,0)+IF(G$3>=Initiatives!$C$31,Initiatives!$C$29,0),Initiatives!$C$42*Initiatives!$C$18*G13+IF(G$3=Initiatives!$C$31,Initiatives!$C$32*Initiatives!$C$38*Initiatives!$C$25,0)+IF(G$3=Initiatives!$C$33,(1-Initiatives!$C$32)*Initiatives!$C$38*Initiatives!$C$25,0)+IF(G$3>=Initiatives!$C$31,Initiatives!$C$29-Initiatives!$C$19*(Initiatives!$C$32+IF(G$3>=Initiatives!$C$33,1-Initiatives!$C$32,0)),0)) -> 1000000000 | H17: =IF(H$3<=Initiatives!$C$45,Initiatives!$C$28/Initiatives!$C$45,0)+IF(Initiatives!$C$6="adoption",H10*Initiatives!$C$26+H12*Initiatives!$C$27+IF(H$3=Initiatives!$C$31,Initiatives!$C$39*Initiatives!$C$25,0)+IF(H$3>=Initiatives!$C$31,Initiatives!$C$29,0),Initiatives!$C$42*Initiatives!$C$18*H13+IF(H$3=Initiatives!$C$31,Initiatives!$C$32*Initiatives!$C$38*Initiatives!$C$25,0)+IF(H$3=Initiatives!$C$33,(1-Initiatives!$C$32)*Initiatives!$C$38*Initiatives!$C$25,0)+IF(H$3>=Initiatives!$C$31,Initiatives!$C$29-Initiatives!$C$19*(Initiatives!$C$32+IF(H$3>=Initiatives!$C$33,1-Initiatives!$C$32,0)),0)) -> 246576000 | I17: =IF(I$3<=Initiatives!$C$45,Initiatives!$C$28/Initiatives!$C$45,0)+IF(Initiatives!$C$6="adoption",I10*Initiatives!$C$26+I12*Initiatives!$C$27+IF(I$3=Initiatives!$C$31,Initiatives!$C$39*Initiatives!$C$25,0)+IF(I$3>=Initiatives!$C$31,Initiatives!$C$29,0),Initiatives!$C$42*Initiatives!$C$18*I13+IF(I$3=Initiatives!$C$31,Initiatives!$C$32*Initiatives!$C$38*Initiatives!$C$25,0)+IF(I$3=Initiatives!$C$33,(1-Initiatives!$C$32)*Initiatives!$C$38*Initiatives!$C$25,0)+IF(I$3>=Initiatives!$C$31,Initiatives!$C$29-Initiatives!$C$19*(Initiatives!$C$32+IF(I$3>=Initiatives!$C$33,1-Initiatives!$C$32,0)),0)) -> 138861360 | J17: =IF(J$3<=Initiatives!$C$45,Initiatives!$C$28/Initiatives!$C$45,0)+IF(Initiatives!$C$6="adoption",J10*Initiatives!$C$26+J12*Initiatives!$C$27+IF(J$3=Initiatives!$C$31,Initiatives!$C$39*Initiatives!$C$25,0)+IF(J$3>=Initiatives!$C$31,Initiatives!$C$29,0),Initiatives!$C$42*Initiatives!$C$18*J13+IF(J$3=Initiatives!$C$31,Initiatives!$C$32*Initiatives!$C$38*Initiatives!$C$25,0)+IF(J$3=Initiatives!$C$33,(1-Initiatives!$C$32)*Initiatives!$C$38*Initiatives!$C$25,0)+IF(J$3>=Initiatives!$C$31,Initiatives!$C$29-Initiatives!$C$19*(Initiatives!$C$32+IF(J$3>=Initiatives!$C$33,1-Initiatives!$C$32,0)),0)) -> 1.3677844e+08 | ... AL17: =IF(AL$3<=Initiatives!$C$45,Initiatives!$C$28/Initiatives!$C$45,0)+IF(Initiatives!$C$6="adoption",AL10*Initiatives!$C$26+AL12*Initiatives!$C$27+IF(AL$3=Initiatives!$C$31,Initiatives!$C$39*Initiatives!$C$25,0)+IF(AL$3>=Initiatives!$C$31,Initiatives!$C$29,0),Initiatives!$C$42*Initiatives!$C$18*AL13+IF(AL$3=Initiatives!$C$31,Initiatives!$C$32*Initiatives!$C$38*Initiatives!$C$25,0)+IF(AL$3=Initiatives!$C$33,(1-Initiatives!$C$32)*Initiatives!$C$38*Initiatives!$C$25,0)+IF(AL$3>=Initiatives!$C$31,Initiatives!$C$29-Initiatives!$C$19*(Initiatives!$C$32+IF(AL$3>=Initiatives!$C$33,1-Initiatives!$C$32,0)),0)) -> 1.5332401e+08
A18: Вклад | B18: contrib | C18: =C16*Initiatives!$C$30-C17 -> -1000000000 | D18: =D16*Initiatives!$C$30-D17 -> -1000000000 | E18: =E16*Initiatives!$C$30-E17 -> -1000000000 | F18: =F16*Initiatives!$C$30-F17 -> -1000000000 | G18: =G16*Initiatives!$C$30-G17 -> -1000000000 | H18: =H16*Initiatives!$C$30-H17 -> 1.2247526e+09 | I18: =I16*Initiatives!$C$30-I17 -> 1.1836773e+09 | J18: =J16*Initiatives!$C$30-J17 -> 1.1659221e+09 | ... AL18: =AL16*Initiatives!$C$30-AL17 -> 1.5926843e+09
A19: Δ абонентов | B19: dsubs | C19: =C11-C15 -> 0 | D19: =D11-D15 -> 0 | E19: =E11-E15 -> 0 | F19: =F11-F15 -> 0 | G19: =G11-G15 -> 0 | H19: =H11-H15 -> -7920 | I19: =I11-I15 -> -15721.2 | J19: =J11-J15 -> -15485.382 | ... AL19: =AL11-AL15 -> -20755.042
A21: I2 — More-for-More: + абонплата и + трафик для когорты недооценённых линеек
A22: Доля набора | B22: f | C22: =IF(Initiatives!$D$6="adoption",IF(C$3<Initiatives!$D$31,0,MIN((C$3-Initiatives!$D$31+1)/Initiatives!$D$34,1)),0) -> 0 | D22: =IF(Initiatives!$D$6="adoption",IF(D$3<Initiatives!$D$31,0,MIN((D$3-Initiatives!$D$31+1)/Initiatives!$D$34,1)),0) -> 0 | E22: =IF(Initiatives!$D$6="adoption",IF(E$3<Initiatives!$D$31,0,MIN((E$3-Initiatives!$D$31+1)/Initiatives!$D$34,1)),0) -> 0 | F22: =IF(Initiatives!$D$6="adoption",IF(F$3<Initiatives!$D$31,0,MIN((F$3-Initiatives!$D$31+1)/Initiatives!$D$34,1)),0) -> 0 | G22: =IF(Initiatives!$D$6="adoption",IF(G$3<Initiatives!$D$31,0,MIN((G$3-Initiatives!$D$31+1)/Initiatives!$D$34,1)),0) -> 0 | H22: =IF(Initiatives!$D$6="adoption",IF(H$3<Initiatives!$D$31,0,MIN((H$3-Initiatives!$D$31+1)/Initiatives!$D$34,1)),0) -> 0 | I22: =IF(Initiatives!$D$6="adoption",IF(I$3<Initiatives!$D$31,0,MIN((I$3-Initiatives!$D$31+1)/Initiatives!$D$34,1)),0) -> 0 | J22: =IF(Initiatives!$D$6="adoption",IF(J$3<Initiatives!$D$31,0,MIN((J$3-Initiatives!$D$31+1)/Initiatives!$D$34,1)),0) -> 0 | ... AL22: =IF(Initiatives!$D$6="adoption",IF(AL$3<Initiatives!$D$31,0,MIN((AL$3-Initiatives!$D$31+1)/Initiatives!$D$34,1)),0) -> 0
A23: Адоптеры (цель) | B23: target | C23: =Initiatives!$D$40*C22 -> 0 | D23: =Initiatives!$D$40*D22 -> 0 | E23: =Initiatives!$D$40*E22 -> 0 | F23: =Initiatives!$D$40*F22 -> 0 | G23: =Initiatives!$D$40*G22 -> 0 | H23: =Initiatives!$D$40*H22 -> 0 | I23: =Initiatives!$D$40*I22 -> 0 | J23: =Initiatives!$D$40*J22 -> 0 | ... AL23: =Initiatives!$D$40*AL22 -> 0
A24: Новые адоптеры | B24: new | C24: =MAX(C23-N(B23),0) -> 0 | D24: =MAX(D23-N(C23),0) -> 0 | E24: =MAX(E23-N(D23),0) -> 0 | F24: =MAX(F23-N(E23),0) -> 0 | G24: =MAX(G23-N(F23),0) -> 0 | H24: =MAX(H23-N(G23),0) -> 0 | I24: =MAX(I23-N(H23),0) -> 0 | J24: =MAX(J23-N(I23),0) -> 0 | ... AL24: =MAX(AL23-N(AK23),0) -> 0
A25: Удержанные | B25: R | C25: =IF(Initiatives!$D$6="adoption",N(B25)*(1-Inputs!$C$9)+N(B26)*Inputs!$C$9*Initiatives!$D$24,0) -> 0 | D25: =IF(Initiatives!$D$6="adoption",N(C25)*(1-Inputs!$C$9)+N(C26)*Inputs!$C$9*Initiatives!$D$24,0) -> 0 | E25: =IF(Initiatives!$D$6="adoption",N(D25)*(1-Inputs!$C$9)+N(D26)*Inputs!$C$9*Initiatives!$D$24,0) -> 0 | F25: =IF(Initiatives!$D$6="adoption",N(E25)*(1-Inputs!$C$9)+N(E26)*Inputs!$C$9*Initiatives!$D$24,0) -> 0 | G25: =IF(Initiatives!$D$6="adoption",N(F25)*(1-Inputs!$C$9)+N(F26)*Inputs!$C$9*Initiatives!$D$24,0) -> 0 | H25: =IF(Initiatives!$D$6="adoption",N(G25)*(1-Inputs!$C$9)+N(G26)*Inputs!$C$9*Initiatives!$D$24,0) -> 0 | I25: =IF(Initiatives!$D$6="adoption",N(H25)*(1-Inputs!$C$9)+N(H26)*Inputs!$C$9*Initiatives!$D$24,0) -> 0 | J25: =IF(Initiatives!$D$6="adoption",N(I25)*(1-Inputs!$C$9)+N(I26)*Inputs!$C$9*Initiatives!$D$24,0) -> 0 | ... AL25: =IF(Initiatives!$D$6="adoption",N(AK25)*(1-Inputs!$C$9)+N(AK26)*Inputs!$C$9*Initiatives!$D$24,0) -> 0
A26: Пул адоптеров | B26: pool | C26: =N(B26)*(1-Inputs!$C$9*(1-Initiatives!$D$24))+C24 -> 0 | D26: =N(C26)*(1-Inputs!$C$9*(1-Initiatives!$D$24))+D24 -> 0 | E26: =N(D26)*(1-Inputs!$C$9*(1-Initiatives!$D$24))+E24 -> 0 | F26: =N(E26)*(1-Inputs!$C$9*(1-Initiatives!$D$24))+F24 -> 0 | G26: =N(F26)*(1-Inputs!$C$9*(1-Initiatives!$D$24))+G24 -> 0 | H26: =N(G26)*(1-Inputs!$C$9*(1-Initiatives!$D$24))+H24 -> 0 | I26: =N(H26)*(1-Inputs!$C$9*(1-Initiatives!$D$24))+I24 -> 0 | J26: =N(I26)*(1-Inputs!$C$9*(1-Initiatives!$D$24))+J24 -> 0 | ... AL26: =N(AK26)*(1-Inputs!$C$9*(1-Initiatives!$D$24))+AL24 -> 0
A27: Вес волн × затухание | B27: w | C27: =IF(Initiatives!$D$6="adoption",0,IF(C$3>=Initiatives!$D$31,Initiatives!$D$32*(1-Inputs!$C$9)^(C$3-Initiatives!$D$31),0)+IF(C$3>=Initiatives!$D$33,(1-Initiatives!$D$32)*(1-Inputs!$C$9)^(C$3-Initiatives!$D$33),0)) -> 0 | D27: =IF(Initiatives!$D$6="adoption",0,IF(D$3>=Initiatives!$D$31,Initiatives!$D$32*(1-Inputs!$C$9)^(D$3-Initiatives!$D$31),0)+IF(D$3>=Initiatives!$D$33,(1-Initiatives!$D$32)*(1-Inputs!$C$9)^(D$3-Initiatives!$D$33),0)) -> 0.1 | E27: =IF(Initiatives!$D$6="adoption",0,IF(E$3>=Initiatives!$D$31,Initiatives!$D$32*(1-Inputs!$C$9)^(E$3-Initiatives!$D$31),0)+IF(E$3>=Initiatives!$D$33,(1-Initiatives!$D$32)*(1-Inputs!$C$9)^(E$3-Initiatives!$D$33),0)) -> 0.0985 | F27: =IF(Initiatives!$D$6="adoption",0,IF(F$3>=Initiatives!$D$31,Initiatives!$D$32*(1-Inputs!$C$9)^(F$3-Initiatives!$D$31),0)+IF(F$3>=Initiatives!$D$33,(1-Initiatives!$D$32)*(1-Inputs!$C$9)^(F$3-Initiatives!$D$33),0)) -> 0.9970225 | G27: =IF(Initiatives!$D$6="adoption",0,IF(G$3>=Initiatives!$D$31,Initiatives!$D$32*(1-Inputs!$C$9)^(G$3-Initiatives!$D$31),0)+IF(G$3>=Initiatives!$D$33,(1-Initiatives!$D$32)*(1-Inputs!$C$9)^(G$3-Initiatives!$D$33),0)) -> 0.98206716 | H27: =IF(Initiatives!$D$6="adoption",0,IF(H$3>=Initiatives!$D$31,Initiatives!$D$32*(1-Inputs!$C$9)^(H$3-Initiatives!$D$31),0)+IF(H$3>=Initiatives!$D$33,(1-Initiatives!$D$32)*(1-Inputs!$C$9)^(H$3-Initiatives!$D$33),0)) -> 0.96733616 | I27: =IF(Initiatives!$D$6="adoption",0,IF(I$3>=Initiatives!$D$31,Initiatives!$D$32*(1-Inputs!$C$9)^(I$3-Initiatives!$D$31),0)+IF(I$3>=Initiatives!$D$33,(1-Initiatives!$D$32)*(1-Inputs!$C$9)^(I$3-Initiatives!$D$33),0)) -> 0.95282611 | J27: =IF(Initiatives!$D$6="adoption",0,IF(J$3>=Initiatives!$D$31,Initiatives!$D$32*(1-Inputs!$C$9)^(J$3-Initiatives!$D$31),0)+IF(J$3>=Initiatives!$D$33,(1-Initiatives!$D$32)*(1-Inputs!$C$9)^(J$3-Initiatives!$D$33),0)) -> 0.93853372 | ... AL27: =IF(Initiatives!$D$6="adoption",0,IF(AL$3>=Initiatives!$D$31,Initiatives!$D$32*(1-Inputs!$C$9)^(AL$3-Initiatives!$D$31),0)+IF(AL$3>=Initiatives!$D$33,(1-Initiatives!$D$32)*(1-Inputs!$C$9)^(AL$3-Initiatives!$D$33),0)) -> 0.61470159
A28: Новый доп. отток | B28: newlost | C28: =IF(Initiatives!$D$6="adoption",IF(AND(C$3>=Initiatives!$D$31,C$3<Initiatives!$D$31+3),Initiatives!$D$44/3,0),IF(AND(C$3>=Initiatives!$D$31,C$3<Initiatives!$D$31+2),Initiatives!$D$32*Initiatives!$D$44/2,0)+IF(AND(C$3>=Initiatives!$D$33,C$3<Initiatives!$D$33+2),(1-Initiatives!$D$32)*Initiatives!$D$44/2,0)) -> 0 | D28: =IF(Initiatives!$D$6="adoption",IF(AND(D$3>=Initiatives!$D$31,D$3<Initiatives!$D$31+3),Initiatives!$D$44/3,0),IF(AND(D$3>=Initiatives!$D$31,D$3<Initiatives!$D$31+2),Initiatives!$D$32*Initiatives!$D$44/2,0)+IF(AND(D$3>=Initiatives!$D$33,D$3<Initiatives!$D$33+2),(1-Initiatives!$D$32)*Initiatives!$D$44/2,0)) -> 968 | E28: =IF(Initiatives!$D$6="adoption",IF(AND(E$3>=Initiatives!$D$31,E$3<Initiatives!$D$31+3),Initiatives!$D$44/3,0),IF(AND(E$3>=Initiatives!$D$31,E$3<Initiatives!$D$31+2),Initiatives!$D$32*Initiatives!$D$44/2,0)+IF(AND(E$3>=Initiatives!$D$33,E$3<Initiatives!$D$33+2),(1-Initiatives!$D$32)*Initiatives!$D$44/2,0)) -> 968 | F28: =IF(Initiatives!$D$6="adoption",IF(AND(F$3>=Initiatives!$D$31,F$3<Initiatives!$D$31+3),Initiatives!$D$44/3,0),IF(AND(F$3>=Initiatives!$D$31,F$3<Initiatives!$D$31+2),Initiatives!$D$32*Initiatives!$D$44/2,0)+IF(AND(F$3>=Initiatives!$D$33,F$3<Initiatives!$D$33+2),(1-Initiatives!$D$32)*Initiatives!$D$44/2,0)) -> 8712 | G28: =IF(Initiatives!$D$6="adoption",IF(AND(G$3>=Initiatives!$D$31,G$3<Initiatives!$D$31+3),Initiatives!$D$44/3,0),IF(AND(G$3>=Initiatives!$D$31,G$3<Initiatives!$D$31+2),Initiatives!$D$32*Initiatives!$D$44/2,0)+IF(AND(G$3>=Initiatives!$D$33,G$3<Initiatives!$D$33+2),(1-Initiatives!$D$32)*Initiatives!$D$44/2,0)) -> 8712 | H28: =IF(Initiatives!$D$6="adoption",IF(AND(H$3>=Initiatives!$D$31,H$3<Initiatives!$D$31+3),Initiatives!$D$44/3,0),IF(AND(H$3>=Initiatives!$D$31,H$3<Initiatives!$D$31+2),Initiatives!$D$32*Initiatives!$D$44/2,0)+IF(AND(H$3>=Initiatives!$D$33,H$3<Initiatives!$D$33+2),(1-Initiatives!$D$32)*Initiatives!$D$44/2,0)) -> 0 | I28: =IF(Initiatives!$D$6="adoption",IF(AND(I$3>=Initiatives!$D$31,I$3<Initiatives!$D$31+3),Initiatives!$D$44/3,0),IF(AND(I$3>=Initiatives!$D$31,I$3<Initiatives!$D$31+2),Initiatives!$D$32*Initiatives!$D$44/2,0)+IF(AND(I$3>=Initiatives!$D$33,I$3<Initiatives!$D$33+2),(1-Initiatives!$D$32)*Initiatives!$D$44/2,0)) -> 0 | J28: =IF(Initiatives!$D$6="adoption",IF(AND(J$3>=Initiatives!$D$31,J$3<Initiatives!$D$31+3),Initiatives!$D$44/3,0),IF(AND(J$3>=Initiatives!$D$31,J$3<Initiatives!$D$31+2),Initiatives!$D$32*Initiatives!$D$44/2,0)+IF(AND(J$3>=Initiatives!$D$33,J$3<Initiatives!$D$33+2),(1-Initiatives!$D$32)*Initiatives!$D$44/2,0)) -> 0 | ... AL28: =IF(Initiatives!$D$6="adoption",IF(AND(AL$3>=Initiatives!$D$31,AL$3<Initiatives!$D$31+3),Initiatives!$D$44/3,0),IF(AND(AL$3>=Initiatives!$D$31,AL$3<Initiatives!$D$31+2),Initiatives!$D$32*Initiatives!$D$44/2,0)+IF(AND(AL$3>=Initiatives!$D$33,AL$3<Initiatives!$D$33+2),(1-Initiatives!$D$32)*Initiatives!$D$44/2,0)) -> 0
A29: Потерянные | B29: L | C29: =N(B29)*(1-Inputs!$C$9)+C28 -> 0 | D29: =N(C29)*(1-Inputs!$C$9)+D28 -> 968 | E29: =N(D29)*(1-Inputs!$C$9)+E28 -> 1921.48 | F29: =N(E29)*(1-Inputs!$C$9)+F28 -> 10604.658 | G29: =N(F29)*(1-Inputs!$C$9)+G28 -> 19157.588 | H29: =N(G29)*(1-Inputs!$C$9)+H28 -> 18870.224 | I29: =N(H29)*(1-Inputs!$C$9)+I28 -> 18587.171 | J29: =N(I29)*(1-Inputs!$C$9)+J28 -> 18308.363 | ... AL29: =N(AK29)*(1-Inputs!$C$9)+AL28 -> 11991.237
A30: Инкр. выручка | B30: rev | C30: =IF(Initiatives!$D$6="adoption",C26*Initiatives!$D$23+C25*Initiatives!$D$8-C29*Initiatives!$D$8,(Initiatives!$D$42*Initiatives!$D$41+Initiatives!$D$38*Initiatives!$D$13*Initiatives!$D$14+Initiatives!$D$43*Initiatives!$D$16)*C27-C29*Initiatives!$D$8) -> 0 | D30: =IF(Initiatives!$D$6="adoption",D26*Initiatives!$D$23+D25*Initiatives!$D$8-D29*Initiatives!$D$8,(Initiatives!$D$42*Initiatives!$D$41+Initiatives!$D$38*Initiatives!$D$13*Initiatives!$D$14+Initiatives!$D$43*Initiatives!$D$16)*D27-D29*Initiatives!$D$8) -> 2.7050069e+08 | E30: =IF(Initiatives!$D$6="adoption",E26*Initiatives!$D$23+E25*Initiatives!$D$8-E29*Initiatives!$D$8,(Initiatives!$D$42*Initiatives!$D$41+Initiatives!$D$38*Initiatives!$D$13*Initiatives!$D$14+Initiatives!$D$43*Initiatives!$D$16)*E27-E29*Initiatives!$D$8) -> 2.4611518e+08 | F30: =IF(Initiatives!$D$6="adoption",F26*Initiatives!$D$23+F25*Initiatives!$D$8-F29*Initiatives!$D$8,(Initiatives!$D$42*Initiatives!$D$41+Initiatives!$D$38*Initiatives!$D$13*Initiatives!$D$14+Initiatives!$D$43*Initiatives!$D$16)*F27-F29*Initiatives!$D$8) -> 2.6769296e+09 | G30: =IF(Initiatives!$D$6="adoption",G26*Initiatives!$D$23+G25*Initiatives!$D$8-G29*Initiatives!$D$8,(Initiatives!$D$42*Initiatives!$D$41+Initiatives!$D$38*Initiatives!$D$13*Initiatives!$D$14+Initiatives!$D$43*Initiatives!$D$16)*G27-G29*Initiatives!$D$8) -> 2.4538237e+09 | H30: =IF(Initiatives!$D$6="adoption",H26*Initiatives!$D$23+H25*Initiatives!$D$8-H29*Initiatives!$D$8,(Initiatives!$D$42*Initiatives!$D$41+Initiatives!$D$38*Initiatives!$D$13*Initiatives!$D$14+Initiatives!$D$43*Initiatives!$D$16)*H27-H29*Initiatives!$D$8) -> 2.4170163e+09 | I30: =IF(Initiatives!$D$6="adoption",I26*Initiatives!$D$23+I25*Initiatives!$D$8-I29*Initiatives!$D$8,(Initiatives!$D$42*Initiatives!$D$41+Initiatives!$D$38*Initiatives!$D$13*Initiatives!$D$14+Initiatives!$D$43*Initiatives!$D$16)*I27-I29*Initiatives!$D$8) -> 2.3807611e+09 | J30: =IF(Initiatives!$D$6="adoption",J26*Initiatives!$D$23+J25*Initiatives!$D$8-J29*Initiatives!$D$8,(Initiatives!$D$42*Initiatives!$D$41+Initiatives!$D$38*Initiatives!$D$13*Initiatives!$D$14+Initiatives!$D$43*Initiatives!$D$16)*J27-J29*Initiatives!$D$8) -> 2.3450497e+09 | ... AL30: =IF(Initiatives!$D$6="adoption",AL26*Initiatives!$D$23+AL25*Initiatives!$D$8-AL29*Initiatives!$D$8,(Initiatives!$D$42*Initiatives!$D$41+Initiatives!$D$38*Initiatives!$D$13*Initiatives!$D$14+Initiatives!$D$43*Initiatives!$D$16)*AL27-AL29*Initiatives!$D$8) -> 1.5359126e+09
A31: Затраты | B31: cost | C31: =IF(C$3<=Initiatives!$D$45,Initiatives!$D$28/Initiatives!$D$45,0)+IF(Initiatives!$D$6="adoption",C24*Initiatives!$D$26+C26*Initiatives!$D$27+IF(C$3=Initiatives!$D$31,Initiatives!$D$39*Initiatives!$D$25,0)+IF(C$3>=Initiatives!$D$31,Initiatives!$D$29,0),Initiatives!$D$42*Initiatives!$D$18*C27+IF(C$3=Initiatives!$D$31,Initiatives!$D$32*Initiatives!$D$38*Initiatives!$D$25,0)+IF(C$3=Initiatives!$D$33,(1-Initiatives!$D$32)*Initiatives!$D$38*Initiatives!$D$25,0)+IF(C$3>=Initiatives!$D$31,Initiatives!$D$29-Initiatives!$D$19*(Initiatives!$D$32+IF(C$3>=Initiatives!$D$33,1-Initiatives!$D$32,0)),0)) -> 300000000 | D31: =IF(D$3<=Initiatives!$D$45,Initiatives!$D$28/Initiatives!$D$45,0)+IF(Initiatives!$D$6="adoption",D24*Initiatives!$D$26+D26*Initiatives!$D$27+IF(D$3=Initiatives!$D$31,Initiatives!$D$39*Initiatives!$D$25,0)+IF(D$3>=Initiatives!$D$31,Initiatives!$D$29,0),Initiatives!$D$42*Initiatives!$D$18*D27+IF(D$3=Initiatives!$D$31,Initiatives!$D$32*Initiatives!$D$38*Initiatives!$D$25,0)+IF(D$3=Initiatives!$D$33,(1-Initiatives!$D$32)*Initiatives!$D$38*Initiatives!$D$25,0)+IF(D$3>=Initiatives!$D$31,Initiatives!$D$29-Initiatives!$D$19*(Initiatives!$D$32+IF(D$3>=Initiatives!$D$33,1-Initiatives!$D$32,0)),0)) -> 55467520 | E31: =IF(E$3<=Initiatives!$D$45,Initiatives!$D$28/Initiatives!$D$45,0)+IF(Initiatives!$D$6="adoption",E24*Initiatives!$D$26+E26*Initiatives!$D$27+IF(E$3=Initiatives!$D$31,Initiatives!$D$39*Initiatives!$D$25,0)+IF(E$3>=Initiatives!$D$31,Initiatives!$D$29,0),Initiatives!$D$42*Initiatives!$D$18*E27+IF(E$3=Initiatives!$D$31,Initiatives!$D$32*Initiatives!$D$38*Initiatives!$D$25,0)+IF(E$3=Initiatives!$D$33,(1-Initiatives!$D$32)*Initiatives!$D$38*Initiatives!$D$25,0)+IF(E$3>=Initiatives!$D$31,Initiatives!$D$29-Initiatives!$D$19*(Initiatives!$D$32+IF(E$3>=Initiatives!$D$33,1-Initiatives!$D$32,0)),0)) -> 47307667 | F31: =IF(F$3<=Initiatives!$D$45,Initiatives!$D$28/Initiatives!$D$45,0)+IF(Initiatives!$D$6="adoption",F24*Initiatives!$D$26+F26*Initiatives!$D$27+IF(F$3=Initiatives!$D$31,Initiatives!$D$39*Initiatives!$D$25,0)+IF(F$3>=Initiatives!$D$31,Initiatives!$D$29,0),Initiatives!$D$42*Initiatives!$D$18*F27+IF(F$3=Initiatives!$D$31,Initiatives!$D$32*Initiatives!$D$38*Initiatives!$D$25,0)+IF(F$3=Initiatives!$D$33,(1-Initiatives!$D$32)*Initiatives!$D$38*Initiatives!$D$25,0)+IF(F$3>=Initiatives!$D$31,Initiatives!$D$29-Initiatives!$D$19*(Initiatives!$D$32+IF(F$3>=Initiatives!$D$33,1-Initiatives!$D$32,0)),0)) -> 3.6610573e+08 | G31: =IF(G$3<=Initiatives!$D$45,Initiatives!$D$28/Initiatives!$D$45,0)+IF(Initiatives!$D$6="adoption",G24*Initiatives!$D$26+G26*Initiatives!$D$27+IF(G$3=Initiatives!$D$31,Initiatives!$D$39*Initiatives!$D$25,0)+IF(G$3>=Initiatives!$D$31,Initiatives!$D$29,0),Initiatives!$D$42*Initiatives!$D$18*G27+IF(G$3=Initiatives!$D$31,Initiatives!$D$32*Initiatives!$D$38*Initiatives!$D$25,0)+IF(G$3=Initiatives!$D$33,(1-Initiatives!$D$32)*Initiatives!$D$38*Initiatives!$D$25,0)+IF(G$3>=Initiatives!$D$31,Initiatives!$D$29-Initiatives!$D$19*(Initiatives!$D$32+IF(G$3>=Initiatives!$D$33,1-Initiatives!$D$32,0)),0)) -> 2.9226359e+08 | H31: =IF(H$3<=Initiatives!$D$45,Initiatives!$D$28/Initiatives!$D$45,0)+IF(Initiatives!$D$6="adoption",H24*Initiatives!$D$26+H26*Initiatives!$D$27+IF(H$3=Initiatives!$D$31,Initiatives!$D$39*Initiatives!$D$25,0)+IF(H$3>=Initiatives!$D$31,Initiatives!$D$29,0),Initiatives!$D$42*Initiatives!$D$18*H27+IF(H$3=Initiatives!$D$31,Initiatives!$D$32*Initiatives!$D$38*Initiatives!$D$25,0)+IF(H$3=Initiatives!$D$33,(1-Initiatives!$D$32)*Initiatives!$D$38*Initiatives!$D$25,0)+IF(H$3>=Initiatives!$D$31,Initiatives!$D$29-Initiatives!$D$19*(Initiatives!$D$32+IF(H$3>=Initiatives!$D$33,1-Initiatives!$D$32,0)),0)) -> 2.8817963e+08 | I31: =IF(I$3<=Initiatives!$D$45,Initiatives!$D$28/Initiatives!$D$45,0)+IF(Initiatives!$D$6="adoption",I24*Initiatives!$D$26+I26*Initiatives!$D$27+IF(I$3=Initiatives!$D$31,Initiatives!$D$39*Initiatives!$D$25,0)+IF(I$3>=Initiatives!$D$31,Initiatives!$D$29,0),Initiatives!$D$42*Initiatives!$D$18*I27+IF(I$3=Initiatives!$D$31,Initiatives!$D$32*Initiatives!$D$38*Initiatives!$D$25,0)+IF(I$3=Initiatives!$D$33,(1-Initiatives!$D$32)*Initiatives!$D$38*Initiatives!$D$25,0)+IF(I$3>=Initiatives!$D$31,Initiatives!$D$29-Initiatives!$D$19*(Initiatives!$D$32+IF(I$3>=Initiatives!$D$33,1-Initiatives!$D$32,0)),0)) -> 2.8415694e+08 | J31: =IF(J$3<=Initiatives!$D$45,Initiatives!$D$28/Initiatives!$D$45,0)+IF(Initiatives!$D$6="adoption",J24*Initiatives!$D$26+J26*Initiatives!$D$27+IF(J$3=Initiatives!$D$31,Initiatives!$D$39*Initiatives!$D$25,0)+IF(J$3>=Initiatives!$D$31,Initiatives!$D$29,0),Initiatives!$D$42*Initiatives!$D$18*J27+IF(J$3=Initiatives!$D$31,Initiatives!$D$32*Initiatives!$D$38*Initiatives!$D$25,0)+IF(J$3=Initiatives!$D$33,(1-Initiatives!$D$32)*Initiatives!$D$38*Initiatives!$D$25,0)+IF(J$3>=Initiatives!$D$31,Initiatives!$D$29-Initiatives!$D$19*(Initiatives!$D$32+IF(J$3>=Initiatives!$D$33,1-Initiatives!$D$32,0)),0)) -> 2.8019458e+08 | ... AL31: =IF(AL$3<=Initiatives!$D$45,Initiatives!$D$28/Initiatives!$D$45,0)+IF(Initiatives!$D$6="adoption",AL24*Initiatives!$D$26+AL26*Initiatives!$D$27+IF(AL$3=Initiatives!$D$31,Initiatives!$D$39*Initiatives!$D$25,0)+IF(AL$3>=Initiatives!$D$31,Initiatives!$D$29,0),Initiatives!$D$42*Initiatives!$D$18*AL27+IF(AL$3=Initiatives!$D$31,Initiatives!$D$32*Initiatives!$D$38*Initiatives!$D$25,0)+IF(AL$3=Initiatives!$D$33,(1-Initiatives!$D$32)*Initiatives!$D$38*Initiatives!$D$25,0)+IF(AL$3>=Initiatives!$D$31,Initiatives!$D$29-Initiatives!$D$19*(Initiatives!$D$32+IF(AL$3>=Initiatives!$D$33,1-Initiatives!$D$32,0)),0)) -> 1.9041692e+08
A32: Вклад | B32: contrib | C32: =C30*Initiatives!$D$30-C31 -> -300000000 | D32: =D30*Initiatives!$D$30-D31 -> 2.1503317e+08 | E32: =E30*Initiatives!$D$30-E31 -> 1.9880751e+08 | F32: =F30*Initiatives!$D$30-F31 -> 2.3108239e+09 | G32: =G30*Initiatives!$D$30-G31 -> 2.1615601e+09 | H32: =H30*Initiatives!$D$30-H31 -> 2.1288367e+09 | I32: =I30*Initiatives!$D$30-I31 -> 2.0966041e+09 | J32: =J30*Initiatives!$D$30-J31 -> 2.0648551e+09 | ... AL32: =AL30*Initiatives!$D$30-AL31 -> 1.3454957e+09
A33: Δ абонентов | B33: dsubs | C33: =C25-C29 -> 0 | D33: =D25-D29 -> -968 | E33: =E25-E29 -> -1921.48 | F33: =F25-F29 -> -10604.658 | G33: =G25-G29 -> -19157.588 | H33: =H25-H29 -> -18870.224 | I33: =I25-I29 -> -18587.171 | J33: =J25-J29 -> -18308.363 | ... AL33: =AL25-AL29 -> -11991.237
A35: I3a — Пакет-бустер для исчерпывающих трафик (opt-in автопродление)
A36: Доля набора | B36: f | C36: =IF(Initiatives!$E$6="adoption",IF(C$3<Initiatives!$E$31,0,MIN((C$3-Initiatives!$E$31+1)/Initiatives!$E$34,1)),0) -> 0 | D36: =IF(Initiatives!$E$6="adoption",IF(D$3<Initiatives!$E$31,0,MIN((D$3-Initiatives!$E$31+1)/Initiatives!$E$34,1)),0) -> 0.5 | E36: =IF(Initiatives!$E$6="adoption",IF(E$3<Initiatives!$E$31,0,MIN((E$3-Initiatives!$E$31+1)/Initiatives!$E$34,1)),0) -> 1 | F36: =IF(Initiatives!$E$6="adoption",IF(F$3<Initiatives!$E$31,0,MIN((F$3-Initiatives!$E$31+1)/Initiatives!$E$34,1)),0) -> 1 | G36: =IF(Initiatives!$E$6="adoption",IF(G$3<Initiatives!$E$31,0,MIN((G$3-Initiatives!$E$31+1)/Initiatives!$E$34,1)),0) -> 1 | H36: =IF(Initiatives!$E$6="adoption",IF(H$3<Initiatives!$E$31,0,MIN((H$3-Initiatives!$E$31+1)/Initiatives!$E$34,1)),0) -> 1 | I36: =IF(Initiatives!$E$6="adoption",IF(I$3<Initiatives!$E$31,0,MIN((I$3-Initiatives!$E$31+1)/Initiatives!$E$34,1)),0) -> 1 | J36: =IF(Initiatives!$E$6="adoption",IF(J$3<Initiatives!$E$31,0,MIN((J$3-Initiatives!$E$31+1)/Initiatives!$E$34,1)),0) -> 1 | ... AL36: =IF(Initiatives!$E$6="adoption",IF(AL$3<Initiatives!$E$31,0,MIN((AL$3-Initiatives!$E$31+1)/Initiatives!$E$34,1)),0) -> 1
A37: Адоптеры (цель) | B37: target | C37: =Initiatives!$E$40*C36 -> 0 | D37: =Initiatives!$E$40*D36 -> 15681.6 | E37: =Initiatives!$E$40*E36 -> 31363.2 | F37: =Initiatives!$E$40*F36 -> 31363.2 | G37: =Initiatives!$E$40*G36 -> 31363.2 | H37: =Initiatives!$E$40*H36 -> 31363.2 | I37: =Initiatives!$E$40*I36 -> 31363.2 | J37: =Initiatives!$E$40*J36 -> 31363.2 | ... AL37: =Initiatives!$E$40*AL36 -> 31363.2
A38: Новые адоптеры | B38: new | C38: =MAX(C37-N(B37),0) -> 0 | D38: =MAX(D37-N(C37),0) -> 15681.6 | E38: =MAX(E37-N(D37),0) -> 15681.6 | F38: =MAX(F37-N(E37),0) -> 0 | G38: =MAX(G37-N(F37),0) -> 0 | H38: =MAX(H37-N(G37),0) -> 0 | I38: =MAX(I37-N(H37),0) -> 0 | J38: =MAX(J37-N(I37),0) -> 0 | ... AL38: =MAX(AL37-N(AK37),0) -> 0
A39: Удержанные | B39: R | C39: =IF(Initiatives!$E$6="adoption",N(B39)*(1-Inputs!$C$9)+N(B40)*Inputs!$C$9*Initiatives!$E$24,0) -> 0 | D39: =IF(Initiatives!$E$6="adoption",N(C39)*(1-Inputs!$C$9)+N(C40)*Inputs!$C$9*Initiatives!$E$24,0) -> 0 | E39: =IF(Initiatives!$E$6="adoption",N(D39)*(1-Inputs!$C$9)+N(D40)*Inputs!$C$9*Initiatives!$E$24,0) -> 11.7612 | F39: =IF(Initiatives!$E$6="adoption",N(E39)*(1-Inputs!$C$9)+N(E40)*Inputs!$C$9*Initiatives!$E$24,0) -> 34.939585 | G39: =IF(Initiatives!$E$6="adoption",N(F39)*(1-Inputs!$C$9)+N(F40)*Inputs!$C$9*Initiatives!$E$24,0) -> 57.437488 | H39: =IF(Initiatives!$E$6="adoption",N(G39)*(1-Inputs!$C$9)+N(G40)*Inputs!$C$9*Initiatives!$E$24,0) -> 79.269859 | I39: =IF(Initiatives!$E$6="adoption",N(H39)*(1-Inputs!$C$9)+N(H40)*Inputs!$C$9*Initiatives!$E$24,0) -> 100.45136 | J39: =IF(Initiatives!$E$6="adoption",N(I39)*(1-Inputs!$C$9)+N(I40)*Inputs!$C$9*Initiatives!$E$24,0) -> 120.99635 | ... AL39: =IF(Initiatives!$E$6="adoption",N(AK39)*(1-Inputs!$C$9)+N(AK40)*Inputs!$C$9*Initiatives!$E$24,0) -> 488.1477
A40: Пул адоптеров | B40: pool | C40: =N(B40)*(1-Inputs!$C$9*(1-Initiatives!$E$24))+C38 -> 0 | D40: =N(C40)*(1-Inputs!$C$9*(1-Initiatives!$E$24))+D38 -> 15681.6 | E40: =N(D40)*(1-Inputs!$C$9*(1-Initiatives!$E$24))+E38 -> 31139.737 | F40: =N(E40)*(1-Inputs!$C$9*(1-Initiatives!$E$24))+F38 -> 30695.996 | G40: =N(F40)*(1-Inputs!$C$9*(1-Initiatives!$E$24))+G38 -> 30258.578 | H40: =N(G40)*(1-Inputs!$C$9*(1-Initiatives!$E$24))+H38 -> 29827.393 | I40: =N(H40)*(1-Inputs!$C$9*(1-Initiatives!$E$24))+I38 -> 29402.353 | J40: =N(I40)*(1-Inputs!$C$9*(1-Initiatives!$E$24))+J38 -> 28983.369 | ... AL40: =N(AK40)*(1-Inputs!$C$9*(1-Initiatives!$E$24))+AL38 -> 19391.833
A41: Вес волн × затухание | B41: w | C41: =IF(Initiatives!$E$6="adoption",0,IF(C$3>=Initiatives!$E$31,Initiatives!$E$32*(1-Inputs!$C$9)^(C$3-Initiatives!$E$31),0)+IF(C$3>=Initiatives!$E$33,(1-Initiatives!$E$32)*(1-Inputs!$C$9)^(C$3-Initiatives!$E$33),0)) -> 0 | D41: =IF(Initiatives!$E$6="adoption",0,IF(D$3>=Initiatives!$E$31,Initiatives!$E$32*(1-Inputs!$C$9)^(D$3-Initiatives!$E$31),0)+IF(D$3>=Initiatives!$E$33,(1-Initiatives!$E$32)*(1-Inputs!$C$9)^(D$3-Initiatives!$E$33),0)) -> 0 | E41: =IF(Initiatives!$E$6="adoption",0,IF(E$3>=Initiatives!$E$31,Initiatives!$E$32*(1-Inputs!$C$9)^(E$3-Initiatives!$E$31),0)+IF(E$3>=Initiatives!$E$33,(1-Initiatives!$E$32)*(1-Inputs!$C$9)^(E$3-Initiatives!$E$33),0)) -> 0 | F41: =IF(Initiatives!$E$6="adoption",0,IF(F$3>=Initiatives!$E$31,Initiatives!$E$32*(1-Inputs!$C$9)^(F$3-Initiatives!$E$31),0)+IF(F$3>=Initiatives!$E$33,(1-Initiatives!$E$32)*(1-Inputs!$C$9)^(F$3-Initiatives!$E$33),0)) -> 0 | G41: =IF(Initiatives!$E$6="adoption",0,IF(G$3>=Initiatives!$E$31,Initiatives!$E$32*(1-Inputs!$C$9)^(G$3-Initiatives!$E$31),0)+IF(G$3>=Initiatives!$E$33,(1-Initiatives!$E$32)*(1-Inputs!$C$9)^(G$3-Initiatives!$E$33),0)) -> 0 | H41: =IF(Initiatives!$E$6="adoption",0,IF(H$3>=Initiatives!$E$31,Initiatives!$E$32*(1-Inputs!$C$9)^(H$3-Initiatives!$E$31),0)+IF(H$3>=Initiatives!$E$33,(1-Initiatives!$E$32)*(1-Inputs!$C$9)^(H$3-Initiatives!$E$33),0)) -> 0 | I41: =IF(Initiatives!$E$6="adoption",0,IF(I$3>=Initiatives!$E$31,Initiatives!$E$32*(1-Inputs!$C$9)^(I$3-Initiatives!$E$31),0)+IF(I$3>=Initiatives!$E$33,(1-Initiatives!$E$32)*(1-Inputs!$C$9)^(I$3-Initiatives!$E$33),0)) -> 0 | J41: =IF(Initiatives!$E$6="adoption",0,IF(J$3>=Initiatives!$E$31,Initiatives!$E$32*(1-Inputs!$C$9)^(J$3-Initiatives!$E$31),0)+IF(J$3>=Initiatives!$E$33,(1-Initiatives!$E$32)*(1-Inputs!$C$9)^(J$3-Initiatives!$E$33),0)) -> 0 | ... AL41: =IF(Initiatives!$E$6="adoption",0,IF(AL$3>=Initiatives!$E$31,Initiatives!$E$32*(1-Inputs!$C$9)^(AL$3-Initiatives!$E$31),0)+IF(AL$3>=Initiatives!$E$33,(1-Initiatives!$E$32)*(1-Inputs!$C$9)^(AL$3-Initiatives!$E$33),0)) -> 0
A42: Новый доп. отток | B42: newlost | C42: =IF(Initiatives!$E$6="adoption",IF(AND(C$3>=Initiatives!$E$31,C$3<Initiatives!$E$31+3),Initiatives!$E$44/3,0),IF(AND(C$3>=Initiatives!$E$31,C$3<Initiatives!$E$31+2),Initiatives!$E$32*Initiatives!$E$44/2,0)+IF(AND(C$3>=Initiatives!$E$33,C$3<Initiatives!$E$33+2),(1-Initiatives!$E$32)*Initiatives!$E$44/2,0)) -> 0 | D42: =IF(Initiatives!$E$6="adoption",IF(AND(D$3>=Initiatives!$E$31,D$3<Initiatives!$E$31+3),Initiatives!$E$44/3,0),IF(AND(D$3>=Initiatives!$E$31,D$3<Initiatives!$E$31+2),Initiatives!$E$32*Initiatives!$E$44/2,0)+IF(AND(D$3>=Initiatives!$E$33,D$3<Initiatives!$E$33+2),(1-Initiatives!$E$32)*Initiatives!$E$44/2,0)) -> 0 | E42: =IF(Initiatives!$E$6="adoption",IF(AND(E$3>=Initiatives!$E$31,E$3<Initiatives!$E$31+3),Initiatives!$E$44/3,0),IF(AND(E$3>=Initiatives!$E$31,E$3<Initiatives!$E$31+2),Initiatives!$E$32*Initiatives!$E$44/2,0)+IF(AND(E$3>=Initiatives!$E$33,E$3<Initiatives!$E$33+2),(1-Initiatives!$E$32)*Initiatives!$E$44/2,0)) -> 0 | F42: =IF(Initiatives!$E$6="adoption",IF(AND(F$3>=Initiatives!$E$31,F$3<Initiatives!$E$31+3),Initiatives!$E$44/3,0),IF(AND(F$3>=Initiatives!$E$31,F$3<Initiatives!$E$31+2),Initiatives!$E$32*Initiatives!$E$44/2,0)+IF(AND(F$3>=Initiatives!$E$33,F$3<Initiatives!$E$33+2),(1-Initiatives!$E$32)*Initiatives!$E$44/2,0)) -> 0 | G42: =IF(Initiatives!$E$6="adoption",IF(AND(G$3>=Initiatives!$E$31,G$3<Initiatives!$E$31+3),Initiatives!$E$44/3,0),IF(AND(G$3>=Initiatives!$E$31,G$3<Initiatives!$E$31+2),Initiatives!$E$32*Initiatives!$E$44/2,0)+IF(AND(G$3>=Initiatives!$E$33,G$3<Initiatives!$E$33+2),(1-Initiatives!$E$32)*Initiatives!$E$44/2,0)) -> 0 | H42: =IF(Initiatives!$E$6="adoption",IF(AND(H$3>=Initiatives!$E$31,H$3<Initiatives!$E$31+3),Initiatives!$E$44/3,0),IF(AND(H$3>=Initiatives!$E$31,H$3<Initiatives!$E$31+2),Initiatives!$E$32*Initiatives!$E$44/2,0)+IF(AND(H$3>=Initiatives!$E$33,H$3<Initiatives!$E$33+2),(1-Initiatives!$E$32)*Initiatives!$E$44/2,0)) -> 0 | I42: =IF(Initiatives!$E$6="adoption",IF(AND(I$3>=Initiatives!$E$31,I$3<Initiatives!$E$31+3),Initiatives!$E$44/3,0),IF(AND(I$3>=Initiatives!$E$31,I$3<Initiatives!$E$31+2),Initiatives!$E$32*Initiatives!$E$44/2,0)+IF(AND(I$3>=Initiatives!$E$33,I$3<Initiatives!$E$33+2),(1-Initiatives!$E$32)*Initiatives!$E$44/2,0)) -> 0 | J42: =IF(Initiatives!$E$6="adoption",IF(AND(J$3>=Initiatives!$E$31,J$3<Initiatives!$E$31+3),Initiatives!$E$44/3,0),IF(AND(J$3>=Initiatives!$E$31,J$3<Initiatives!$E$31+2),Initiatives!$E$32*Initiatives!$E$44/2,0)+IF(AND(J$3>=Initiatives!$E$33,J$3<Initiatives!$E$33+2),(1-Initiatives!$E$32)*Initiatives!$E$44/2,0)) -> 0 | ... AL42: =IF(Initiatives!$E$6="adoption",IF(AND(AL$3>=Initiatives!$E$31,AL$3<Initiatives!$E$31+3),Initiatives!$E$44/3,0),IF(AND(AL$3>=Initiatives!$E$31,AL$3<Initiatives!$E$31+2),Initiatives!$E$32*Initiatives!$E$44/2,0)+IF(AND(AL$3>=Initiatives!$E$33,AL$3<Initiatives!$E$33+2),(1-Initiatives!$E$32)*Initiatives!$E$44/2,0)) -> 0
A43: Потерянные | B43: L | C43: =N(B43)*(1-Inputs!$C$9)+C42 -> 0 | D43: =N(C43)*(1-Inputs!$C$9)+D42 -> 0 | E43: =N(D43)*(1-Inputs!$C$9)+E42 -> 0 | F43: =N(E43)*(1-Inputs!$C$9)+F42 -> 0 | G43: =N(F43)*(1-Inputs!$C$9)+G42 -> 0 | H43: =N(G43)*(1-Inputs!$C$9)+H42 -> 0 | I43: =N(H43)*(1-Inputs!$C$9)+I42 -> 0 | J43: =N(I43)*(1-Inputs!$C$9)+J42 -> 0 | ... AL43: =N(AK43)*(1-Inputs!$C$9)+AL42 -> 0
A44: Инкр. выручка | B44: rev | C44: =IF(Initiatives!$E$6="adoption",C40*Initiatives!$E$23+C39*Initiatives!$E$8-C43*Initiatives!$E$8,(Initiatives!$E$42*Initiatives!$E$41+Initiatives!$E$38*Initiatives!$E$13*Initiatives!$E$14+Initiatives!$E$43*Initiatives!$E$16)*C41-C43*Initiatives!$E$8) -> 0 | D44: =IF(Initiatives!$E$6="adoption",D40*Initiatives!$E$23+D39*Initiatives!$E$8-D43*Initiatives!$E$8,(Initiatives!$E$42*Initiatives!$E$41+Initiatives!$E$38*Initiatives!$E$13*Initiatives!$E$14+Initiatives!$E$43*Initiatives!$E$16)*D41-D43*Initiatives!$E$8) -> 117612000 | E44: =IF(Initiatives!$E$6="adoption",E40*Initiatives!$E$23+E39*Initiatives!$E$8-E43*Initiatives!$E$8,(Initiatives!$E$42*Initiatives!$E$41+Initiatives!$E$38*Initiatives!$E$13*Initiatives!$E$14+Initiatives!$E$43*Initiatives!$E$16)*E41-E43*Initiatives!$E$8) -> 2.3387734e+08 | F44: =IF(Initiatives!$E$6="adoption",F40*Initiatives!$E$23+F39*Initiatives!$E$8-F43*Initiatives!$E$8,(Initiatives!$E$42*Initiatives!$E$41+Initiatives!$E$38*Initiatives!$E$13*Initiatives!$E$14+Initiatives!$E$43*Initiatives!$E$16)*F41-F43*Initiatives!$E$8) -> 2.3119828e+08 | G44: =IF(Initiatives!$E$6="adoption",G40*Initiatives!$E$23+G39*Initiatives!$E$8-G43*Initiatives!$E$8,(Initiatives!$E$42*Initiatives!$E$41+Initiatives!$E$38*Initiatives!$E$13*Initiatives!$E$14+Initiatives!$E$43*Initiatives!$E$16)*G41-G43*Initiatives!$E$8) -> 2.2854758e+08 | H44: =IF(Initiatives!$E$6="adoption",H40*Initiatives!$E$23+H39*Initiatives!$E$8-H43*Initiatives!$E$8,(Initiatives!$E$42*Initiatives!$E$41+Initiatives!$E$38*Initiatives!$E$13*Initiatives!$E$14+Initiatives!$E$43*Initiatives!$E$16)*H41-H43*Initiatives!$E$8) -> 2.2592501e+08 | I44: =IF(Initiatives!$E$6="adoption",I40*Initiatives!$E$23+I39*Initiatives!$E$8-I43*Initiatives!$E$8,(Initiatives!$E$42*Initiatives!$E$41+Initiatives!$E$38*Initiatives!$E$13*Initiatives!$E$14+Initiatives!$E$43*Initiatives!$E$16)*I41-I43*Initiatives!$E$8) -> 2.2333028e+08 | J44: =IF(Initiatives!$E$6="adoption",J40*Initiatives!$E$23+J39*Initiatives!$E$8-J43*Initiatives!$E$8,(Initiatives!$E$42*Initiatives!$E$41+Initiatives!$E$38*Initiatives!$E$13*Initiatives!$E$14+Initiatives!$E$43*Initiatives!$E$16)*J41-J43*Initiatives!$E$8) -> 2.2076317e+08 | ... AL44: =IF(Initiatives!$E$6="adoption",AL40*Initiatives!$E$23+AL39*Initiatives!$E$8-AL43*Initiatives!$E$8,(Initiatives!$E$42*Initiatives!$E$41+Initiatives!$E$38*Initiatives!$E$13*Initiatives!$E$14+Initiatives!$E$43*Initiatives!$E$16)*AL41-AL43*Initiatives!$E$8) -> 1.5910689e+08
A45: Затраты | B45: cost | C45: =IF(C$3<=Initiatives!$E$45,Initiatives!$E$28/Initiatives!$E$45,0)+IF(Initiatives!$E$6="adoption",C38*Initiatives!$E$26+C40*Initiatives!$E$27+IF(C$3=Initiatives!$E$31,Initiatives!$E$39*Initiatives!$E$25,0)+IF(C$3>=Initiatives!$E$31,Initiatives!$E$29,0),Initiatives!$E$42*Initiatives!$E$18*C41+IF(C$3=Initiatives!$E$31,Initiatives!$E$32*Initiatives!$E$38*Initiatives!$E$25,0)+IF(C$3=Initiatives!$E$33,(1-Initiatives!$E$32)*Initiatives!$E$38*Initiatives!$E$25,0)+IF(C$3>=Initiatives!$E$31,Initiatives!$E$29-Initiatives!$E$19*(Initiatives!$E$32+IF(C$3>=Initiatives!$E$33,1-Initiatives!$E$32,0)),0)) -> 350000000 | D45: =IF(D$3<=Initiatives!$E$45,Initiatives!$E$28/Initiatives!$E$45,0)+IF(Initiatives!$E$6="adoption",D38*Initiatives!$E$26+D40*Initiatives!$E$27+IF(D$3=Initiatives!$E$31,Initiatives!$E$39*Initiatives!$E$25,0)+IF(D$3>=Initiatives!$E$31,Initiatives!$E$29,0),Initiatives!$E$42*Initiatives!$E$18*D41+IF(D$3=Initiatives!$E$31,Initiatives!$E$32*Initiatives!$E$38*Initiatives!$E$25,0)+IF(D$3=Initiatives!$E$33,(1-Initiatives!$E$32)*Initiatives!$E$38*Initiatives!$E$25,0)+IF(D$3>=Initiatives!$E$31,Initiatives!$E$29-Initiatives!$E$19*(Initiatives!$E$32+IF(D$3>=Initiatives!$E$33,1-Initiatives!$E$32,0)),0)) -> 41600800 | E45: =IF(E$3<=Initiatives!$E$45,Initiatives!$E$28/Initiatives!$E$45,0)+IF(Initiatives!$E$6="adoption",E38*Initiatives!$E$26+E40*Initiatives!$E$27+IF(E$3=Initiatives!$E$31,Initiatives!$E$39*Initiatives!$E$25,0)+IF(E$3>=Initiatives!$E$31,Initiatives!$E$29,0),Initiatives!$E$42*Initiatives!$E$18*E41+IF(E$3=Initiatives!$E$31,Initiatives!$E$32*Initiatives!$E$38*Initiatives!$E$25,0)+IF(E$3=Initiatives!$E$33,(1-Initiatives!$E$32)*Initiatives!$E$38*Initiatives!$E$25,0)+IF(E$3>=Initiatives!$E$31,Initiatives!$E$29-Initiatives!$E$19*(Initiatives!$E$32+IF(E$3>=Initiatives!$E$33,1-Initiatives!$E$32,0)),0)) -> 25569869 | F45: =IF(F$3<=Initiatives!$E$45,Initiatives!$E$28/Initiatives!$E$45,0)+IF(Initiatives!$E$6="adoption",F38*Initiatives!$E$26+F40*Initiatives!$E$27+IF(F$3=Initiatives!$E$31,Initiatives!$E$39*Initiatives!$E$25,0)+IF(F$3>=Initiatives!$E$31,Initiatives!$E$29,0),Initiatives!$E$42*Initiatives!$E$18*F41+IF(F$3=Initiatives!$E$31,Initiatives!$E$32*Initiatives!$E$38*Initiatives!$E$25,0)+IF(F$3=Initiatives!$E$33,(1-Initiatives!$E$32)*Initiatives!$E$38*Initiatives!$E$25,0)+IF(F$3>=Initiatives!$E$31,Initiatives!$E$29-Initiatives!$E$19*(Initiatives!$E$32+IF(F$3>=Initiatives!$E$33,1-Initiatives!$E$32,0)),0)) -> 25347998 | G45: =IF(G$3<=Initiatives!$E$45,Initiatives!$E$28/Initiatives!$E$45,0)+IF(Initiatives!$E$6="adoption",G38*Initiatives!$E$26+G40*Initiatives!$E$27+IF(G$3=Initiatives!$E$31,Initiatives!$E$39*Initiatives!$E$25,0)+IF(G$3>=Initiatives!$E$31,Initiatives!$E$29,0),Initiatives!$E$42*Initiatives!$E$18*G41+IF(G$3=Initiatives!$E$31,Initiatives!$E$32*Initiatives!$E$38*Initiatives!$E$25,0)+IF(G$3=Initiatives!$E$33,(1-Initiatives!$E$32)*Initiatives!$E$38*Initiatives!$E$25,0)+IF(G$3>=Initiatives!$E$31,Initiatives!$E$29-Initiatives!$E$19*(Initiatives!$E$32+IF(G$3>=Initiatives!$E$33,1-Initiatives!$E$32,0)),0)) -> 25129289 | H45: =IF(H$3<=Initiatives!$E$45,Initiatives!$E$28/Initiatives!$E$45,0)+IF(Initiatives!$E$6="adoption",H38*Initiatives!$E$26+H40*Initiatives!$E$27+IF(H$3=Initiatives!$E$31,Initiatives!$E$39*Initiatives!$E$25,0)+IF(H$3>=Initiatives!$E$31,Initiatives!$E$29,0),Initiatives!$E$42*Initiatives!$E$18*H41+IF(H$3=Initiatives!$E$31,Initiatives!$E$32*Initiatives!$E$38*Initiatives!$E$25,0)+IF(H$3=Initiatives!$E$33,(1-Initiatives!$E$32)*Initiatives!$E$38*Initiatives!$E$25,0)+IF(H$3>=Initiatives!$E$31,Initiatives!$E$29-Initiatives!$E$19*(Initiatives!$E$32+IF(H$3>=Initiatives!$E$33,1-Initiatives!$E$32,0)),0)) -> 24913697 | I45: =IF(I$3<=Initiatives!$E$45,Initiatives!$E$28/Initiatives!$E$45,0)+IF(Initiatives!$E$6="adoption",I38*Initiatives!$E$26+I40*Initiatives!$E$27+IF(I$3=Initiatives!$E$31,Initiatives!$E$39*Initiatives!$E$25,0)+IF(I$3>=Initiatives!$E$31,Initiatives!$E$29,0),Initiatives!$E$42*Initiatives!$E$18*I41+IF(I$3=Initiatives!$E$31,Initiatives!$E$32*Initiatives!$E$38*Initiatives!$E$25,0)+IF(I$3=Initiatives!$E$33,(1-Initiatives!$E$32)*Initiatives!$E$38*Initiatives!$E$25,0)+IF(I$3>=Initiatives!$E$31,Initiatives!$E$29-Initiatives!$E$19*(Initiatives!$E$32+IF(I$3>=Initiatives!$E$33,1-Initiatives!$E$32,0)),0)) -> 24701176 | J45: =IF(J$3<=Initiatives!$E$45,Initiatives!$E$28/Initiatives!$E$45,0)+IF(Initiatives!$E$6="adoption",J38*Initiatives!$E$26+J40*Initiatives!$E$27+IF(J$3=Initiatives!$E$31,Initiatives!$E$39*Initiatives!$E$25,0)+IF(J$3>=Initiatives!$E$31,Initiatives!$E$29,0),Initiatives!$E$42*Initiatives!$E$18*J41+IF(J$3=Initiatives!$E$31,Initiatives!$E$32*Initiatives!$E$38*Initiatives!$E$25,0)+IF(J$3=Initiatives!$E$33,(1-Initiatives!$E$32)*Initiatives!$E$38*Initiatives!$E$25,0)+IF(J$3>=Initiatives!$E$31,Initiatives!$E$29-Initiatives!$E$19*(Initiatives!$E$32+IF(J$3>=Initiatives!$E$33,1-Initiatives!$E$32,0)),0)) -> 24491685 | ... AL45: =IF(AL$3<=Initiatives!$E$45,Initiatives!$E$28/Initiatives!$E$45,0)+IF(Initiatives!$E$6="adoption",AL38*Initiatives!$E$26+AL40*Initiatives!$E$27+IF(AL$3=Initiatives!$E$31,Initiatives!$E$39*Initiatives!$E$25,0)+IF(AL$3>=Initiatives!$E$31,Initiatives!$E$29,0),Initiatives!$E$42*Initiatives!$E$18*AL41+IF(AL$3=Initiatives!$E$31,Initiatives!$E$32*Initiatives!$E$38*Initiatives!$E$25,0)+IF(AL$3=Initiatives!$E$33,(1-Initiatives!$E$32)*Initiatives!$E$38*Initiatives!$E$25,0)+IF(AL$3>=Initiatives!$E$31,Initiatives!$E$29-Initiatives!$E$19*(Initiatives!$E$32+IF(AL$3>=Initiatives!$E$33,1-Initiatives!$E$32,0)),0)) -> 19695917
A46: Вклад | B46: contrib | C46: =C44*Initiatives!$E$30-C45 -> -350000000 | D46: =D44*Initiatives!$E$30-D45 -> 58369400 | E46: =E44*Initiatives!$E$30-E45 -> 1.7322587e+08 | F46: =F44*Initiatives!$E$30-F45 -> 1.7117054e+08 | G46: =G44*Initiatives!$E$30-G45 -> 1.6913616e+08 | H46: =H44*Initiatives!$E$30-H45 -> 1.6712256e+08 | I46: =I44*Initiatives!$E$30-I45 -> 1.6512957e+08 | J46: =J44*Initiatives!$E$30-J45 -> 1.6315701e+08 | ... AL46: =AL44*Initiatives!$E$30-AL45 -> 1.1554494e+08
A47: Δ абонентов | B47: dsubs | C47: =C39-C43 -> 0 | D47: =D39-D43 -> 0 | E47: =E39-E43 -> 11.7612 | F47: =F39-F43 -> 34.939585 | G47: =G39-G43 -> 57.437488 | H47: =H39-H43 -> 79.269859 | I47: =I39-I43 -> 100.45136 | J47: =J39-J43 -> 120.99635 | ... AL47: =AL39-AL43 -> 488.1477
A49: I3b — Роуминг-пакет по акции (−50% первый месяц) для выезжающих
A50: Доля набора | B50: f | C50: =IF(Initiatives!$F$6="adoption",IF(C$3<Initiatives!$F$31,0,MIN((C$3-Initiatives!$F$31+1)/Initiatives!$F$34,1)),0) -> 0 | D50: =IF(Initiatives!$F$6="adoption",IF(D$3<Initiatives!$F$31,0,MIN((D$3-Initiatives!$F$31+1)/Initiatives!$F$34,1)),0) -> 0.33333333 | E50: =IF(Initiatives!$F$6="adoption",IF(E$3<Initiatives!$F$31,0,MIN((E$3-Initiatives!$F$31+1)/Initiatives!$F$34,1)),0) -> 0.66666667 | F50: =IF(Initiatives!$F$6="adoption",IF(F$3<Initiatives!$F$31,0,MIN((F$3-Initiatives!$F$31+1)/Initiatives!$F$34,1)),0) -> 1 | G50: =IF(Initiatives!$F$6="adoption",IF(G$3<Initiatives!$F$31,0,MIN((G$3-Initiatives!$F$31+1)/Initiatives!$F$34,1)),0) -> 1 | H50: =IF(Initiatives!$F$6="adoption",IF(H$3<Initiatives!$F$31,0,MIN((H$3-Initiatives!$F$31+1)/Initiatives!$F$34,1)),0) -> 1 | I50: =IF(Initiatives!$F$6="adoption",IF(I$3<Initiatives!$F$31,0,MIN((I$3-Initiatives!$F$31+1)/Initiatives!$F$34,1)),0) -> 1 | J50: =IF(Initiatives!$F$6="adoption",IF(J$3<Initiatives!$F$31,0,MIN((J$3-Initiatives!$F$31+1)/Initiatives!$F$34,1)),0) -> 1 | ... AL50: =IF(Initiatives!$F$6="adoption",IF(AL$3<Initiatives!$F$31,0,MIN((AL$3-Initiatives!$F$31+1)/Initiatives!$F$34,1)),0) -> 1
A51: Адоптеры (цель) | B51: target | C51: =Initiatives!$F$40*C50 -> 0 | D51: =Initiatives!$F$40*D50 -> 8448 | E51: =Initiatives!$F$40*E50 -> 16896 | F51: =Initiatives!$F$40*F50 -> 25344 | G51: =Initiatives!$F$40*G50 -> 25344 | H51: =Initiatives!$F$40*H50 -> 25344 | I51: =Initiatives!$F$40*I50 -> 25344 | J51: =Initiatives!$F$40*J50 -> 25344 | ... AL51: =Initiatives!$F$40*AL50 -> 25344
A52: Новые адоптеры | B52: new | C52: =MAX(C51-N(B51),0) -> 0 | D52: =MAX(D51-N(C51),0) -> 8448 | E52: =MAX(E51-N(D51),0) -> 8448 | F52: =MAX(F51-N(E51),0) -> 8448 | G52: =MAX(G51-N(F51),0) -> 0 | H52: =MAX(H51-N(G51),0) -> 0 | I52: =MAX(I51-N(H51),0) -> 0 | J52: =MAX(J51-N(I51),0) -> 0 | ... AL52: =MAX(AL51-N(AK51),0) -> 0
A53: Удержанные | B53: R | C53: =IF(Initiatives!$F$6="adoption",N(B53)*(1-Inputs!$C$9)+N(B54)*Inputs!$C$9*Initiatives!$F$24,0) -> 0 | D53: =IF(Initiatives!$F$6="adoption",N(C53)*(1-Inputs!$C$9)+N(C54)*Inputs!$C$9*Initiatives!$F$24,0) -> 0 | E53: =IF(Initiatives!$F$6="adoption",N(D53)*(1-Inputs!$C$9)+N(D54)*Inputs!$C$9*Initiatives!$F$24,0) -> 25.344 | F53: =IF(Initiatives!$F$6="adoption",N(E53)*(1-Inputs!$C$9)+N(E54)*Inputs!$C$9*Initiatives!$F$24,0) -> 75.347712 | G53: =IF(Initiatives!$F$6="adoption",N(F53)*(1-Inputs!$C$9)+N(F54)*Inputs!$C$9*Initiatives!$F$24,0) -> 149.34076 | H53: =IF(Initiatives!$F$6="adoption",N(G53)*(1-Inputs!$C$9)+N(G54)*Inputs!$C$9*Initiatives!$F$24,0) -> 221.32244 | I53: =IF(Initiatives!$F$6="adoption",N(H53)*(1-Inputs!$C$9)+N(H54)*Inputs!$C$9*Initiatives!$F$24,0) -> 291.33373 | J53: =IF(Initiatives!$F$6="adoption",N(I53)*(1-Inputs!$C$9)+N(I54)*Inputs!$C$9*Initiatives!$F$24,0) -> 359.41487 | ... AL53: =IF(Initiatives!$F$6="adoption",N(AK53)*(1-Inputs!$C$9)+N(AK54)*Inputs!$C$9*Initiatives!$F$24,0) -> 1624.3923
A54: Пул адоптеров | B54: pool | C54: =N(B54)*(1-Inputs!$C$9*(1-Initiatives!$F$24))+C52 -> 0 | D54: =N(C54)*(1-Inputs!$C$9*(1-Initiatives!$F$24))+D52 -> 8448 | E54: =N(D54)*(1-Inputs!$C$9*(1-Initiatives!$F$24))+E52 -> 16794.624 | F54: =N(E54)*(1-Inputs!$C$9*(1-Initiatives!$F$24))+F52 -> 25041.089 | G54: =N(F54)*(1-Inputs!$C$9*(1-Initiatives!$F$24))+G52 -> 24740.595 | H54: =N(G54)*(1-Inputs!$C$9*(1-Initiatives!$F$24))+H52 -> 24443.708 | I54: =N(H54)*(1-Inputs!$C$9*(1-Initiatives!$F$24))+I52 -> 24150.384 | J54: =N(I54)*(1-Inputs!$C$9*(1-Initiatives!$F$24))+J52 -> 23860.579 | ... AL54: =N(AK54)*(1-Inputs!$C$9*(1-Initiatives!$F$24))+AL52 -> 17016.703
A55: Вес волн × затухание | B55: w | C55: =IF(Initiatives!$F$6="adoption",0,IF(C$3>=Initiatives!$F$31,Initiatives!$F$32*(1-Inputs!$C$9)^(C$3-Initiatives!$F$31),0)+IF(C$3>=Initiatives!$F$33,(1-Initiatives!$F$32)*(1-Inputs!$C$9)^(C$3-Initiatives!$F$33),0)) -> 0 | D55: =IF(Initiatives!$F$6="adoption",0,IF(D$3>=Initiatives!$F$31,Initiatives!$F$32*(1-Inputs!$C$9)^(D$3-Initiatives!$F$31),0)+IF(D$3>=Initiatives!$F$33,(1-Initiatives!$F$32)*(1-Inputs!$C$9)^(D$3-Initiatives!$F$33),0)) -> 0 | E55: =IF(Initiatives!$F$6="adoption",0,IF(E$3>=Initiatives!$F$31,Initiatives!$F$32*(1-Inputs!$C$9)^(E$3-Initiatives!$F$31),0)+IF(E$3>=Initiatives!$F$33,(1-Initiatives!$F$32)*(1-Inputs!$C$9)^(E$3-Initiatives!$F$33),0)) -> 0 | F55: =IF(Initiatives!$F$6="adoption",0,IF(F$3>=Initiatives!$F$31,Initiatives!$F$32*(1-Inputs!$C$9)^(F$3-Initiatives!$F$31),0)+IF(F$3>=Initiatives!$F$33,(1-Initiatives!$F$32)*(1-Inputs!$C$9)^(F$3-Initiatives!$F$33),0)) -> 0 | G55: =IF(Initiatives!$F$6="adoption",0,IF(G$3>=Initiatives!$F$31,Initiatives!$F$32*(1-Inputs!$C$9)^(G$3-Initiatives!$F$31),0)+IF(G$3>=Initiatives!$F$33,(1-Initiatives!$F$32)*(1-Inputs!$C$9)^(G$3-Initiatives!$F$33),0)) -> 0 | H55: =IF(Initiatives!$F$6="adoption",0,IF(H$3>=Initiatives!$F$31,Initiatives!$F$32*(1-Inputs!$C$9)^(H$3-Initiatives!$F$31),0)+IF(H$3>=Initiatives!$F$33,(1-Initiatives!$F$32)*(1-Inputs!$C$9)^(H$3-Initiatives!$F$33),0)) -> 0 | I55: =IF(Initiatives!$F$6="adoption",0,IF(I$3>=Initiatives!$F$31,Initiatives!$F$32*(1-Inputs!$C$9)^(I$3-Initiatives!$F$31),0)+IF(I$3>=Initiatives!$F$33,(1-Initiatives!$F$32)*(1-Inputs!$C$9)^(I$3-Initiatives!$F$33),0)) -> 0 | J55: =IF(Initiatives!$F$6="adoption",0,IF(J$3>=Initiatives!$F$31,Initiatives!$F$32*(1-Inputs!$C$9)^(J$3-Initiatives!$F$31),0)+IF(J$3>=Initiatives!$F$33,(1-Initiatives!$F$32)*(1-Inputs!$C$9)^(J$3-Initiatives!$F$33),0)) -> 0 | ... AL55: =IF(Initiatives!$F$6="adoption",0,IF(AL$3>=Initiatives!$F$31,Initiatives!$F$32*(1-Inputs!$C$9)^(AL$3-Initiatives!$F$31),0)+IF(AL$3>=Initiatives!$F$33,(1-Initiatives!$F$32)*(1-Inputs!$C$9)^(AL$3-Initiatives!$F$33),0)) -> 0
A56: Новый доп. отток | B56: newlost | C56: =IF(Initiatives!$F$6="adoption",IF(AND(C$3>=Initiatives!$F$31,C$3<Initiatives!$F$31+3),Initiatives!$F$44/3,0),IF(AND(C$3>=Initiatives!$F$31,C$3<Initiatives!$F$31+2),Initiatives!$F$32*Initiatives!$F$44/2,0)+IF(AND(C$3>=Initiatives!$F$33,C$3<Initiatives!$F$33+2),(1-Initiatives!$F$32)*Initiatives!$F$44/2,0)) -> 0 | D56: =IF(Initiatives!$F$6="adoption",IF(AND(D$3>=Initiatives!$F$31,D$3<Initiatives!$F$31+3),Initiatives!$F$44/3,0),IF(AND(D$3>=Initiatives!$F$31,D$3<Initiatives!$F$31+2),Initiatives!$F$32*Initiatives!$F$44/2,0)+IF(AND(D$3>=Initiatives!$F$33,D$3<Initiatives!$F$33+2),(1-Initiatives!$F$32)*Initiatives!$F$44/2,0)) -> 0 | E56: =IF(Initiatives!$F$6="adoption",IF(AND(E$3>=Initiatives!$F$31,E$3<Initiatives!$F$31+3),Initiatives!$F$44/3,0),IF(AND(E$3>=Initiatives!$F$31,E$3<Initiatives!$F$31+2),Initiatives!$F$32*Initiatives!$F$44/2,0)+IF(AND(E$3>=Initiatives!$F$33,E$3<Initiatives!$F$33+2),(1-Initiatives!$F$32)*Initiatives!$F$44/2,0)) -> 0 | F56: =IF(Initiatives!$F$6="adoption",IF(AND(F$3>=Initiatives!$F$31,F$3<Initiatives!$F$31+3),Initiatives!$F$44/3,0),IF(AND(F$3>=Initiatives!$F$31,F$3<Initiatives!$F$31+2),Initiatives!$F$32*Initiatives!$F$44/2,0)+IF(AND(F$3>=Initiatives!$F$33,F$3<Initiatives!$F$33+2),(1-Initiatives!$F$32)*Initiatives!$F$44/2,0)) -> 0 | G56: =IF(Initiatives!$F$6="adoption",IF(AND(G$3>=Initiatives!$F$31,G$3<Initiatives!$F$31+3),Initiatives!$F$44/3,0),IF(AND(G$3>=Initiatives!$F$31,G$3<Initiatives!$F$31+2),Initiatives!$F$32*Initiatives!$F$44/2,0)+IF(AND(G$3>=Initiatives!$F$33,G$3<Initiatives!$F$33+2),(1-Initiatives!$F$32)*Initiatives!$F$44/2,0)) -> 0 | H56: =IF(Initiatives!$F$6="adoption",IF(AND(H$3>=Initiatives!$F$31,H$3<Initiatives!$F$31+3),Initiatives!$F$44/3,0),IF(AND(H$3>=Initiatives!$F$31,H$3<Initiatives!$F$31+2),Initiatives!$F$32*Initiatives!$F$44/2,0)+IF(AND(H$3>=Initiatives!$F$33,H$3<Initiatives!$F$33+2),(1-Initiatives!$F$32)*Initiatives!$F$44/2,0)) -> 0 | I56: =IF(Initiatives!$F$6="adoption",IF(AND(I$3>=Initiatives!$F$31,I$3<Initiatives!$F$31+3),Initiatives!$F$44/3,0),IF(AND(I$3>=Initiatives!$F$31,I$3<Initiatives!$F$31+2),Initiatives!$F$32*Initiatives!$F$44/2,0)+IF(AND(I$3>=Initiatives!$F$33,I$3<Initiatives!$F$33+2),(1-Initiatives!$F$32)*Initiatives!$F$44/2,0)) -> 0 | J56: =IF(Initiatives!$F$6="adoption",IF(AND(J$3>=Initiatives!$F$31,J$3<Initiatives!$F$31+3),Initiatives!$F$44/3,0),IF(AND(J$3>=Initiatives!$F$31,J$3<Initiatives!$F$31+2),Initiatives!$F$32*Initiatives!$F$44/2,0)+IF(AND(J$3>=Initiatives!$F$33,J$3<Initiatives!$F$33+2),(1-Initiatives!$F$32)*Initiatives!$F$44/2,0)) -> 0 | ... AL56: =IF(Initiatives!$F$6="adoption",IF(AND(AL$3>=Initiatives!$F$31,AL$3<Initiatives!$F$31+3),Initiatives!$F$44/3,0),IF(AND(AL$3>=Initiatives!$F$31,AL$3<Initiatives!$F$31+2),Initiatives!$F$32*Initiatives!$F$44/2,0)+IF(AND(AL$3>=Initiatives!$F$33,AL$3<Initiatives!$F$33+2),(1-Initiatives!$F$32)*Initiatives!$F$44/2,0)) -> 0
A57: Потерянные | B57: L | C57: =N(B57)*(1-Inputs!$C$9)+C56 -> 0 | D57: =N(C57)*(1-Inputs!$C$9)+D56 -> 0 | E57: =N(D57)*(1-Inputs!$C$9)+E56 -> 0 | F57: =N(E57)*(1-Inputs!$C$9)+F56 -> 0 | G57: =N(F57)*(1-Inputs!$C$9)+G56 -> 0 | H57: =N(G57)*(1-Inputs!$C$9)+H56 -> 0 | I57: =N(H57)*(1-Inputs!$C$9)+I56 -> 0 | J57: =N(I57)*(1-Inputs!$C$9)+J56 -> 0 | ... AL57: =N(AK57)*(1-Inputs!$C$9)+AL56 -> 0
A58: Инкр. выручка | B58: rev | C58: =IF(Initiatives!$F$6="adoption",C54*Initiatives!$F$23+C53*Initiatives!$F$8-C57*Initiatives!$F$8,(Initiatives!$F$42*Initiatives!$F$41+Initiatives!$F$38*Initiatives!$F$13*Initiatives!$F$14+Initiatives!$F$43*Initiatives!$F$16)*C55-C57*Initiatives!$F$8) -> 0 | D58: =IF(Initiatives!$F$6="adoption",D54*Initiatives!$F$23+D53*Initiatives!$F$8-D57*Initiatives!$F$8,(Initiatives!$F$42*Initiatives!$F$41+Initiatives!$F$38*Initiatives!$F$13*Initiatives!$F$14+Initiatives!$F$43*Initiatives!$F$16)*D55-D57*Initiatives!$F$8) -> 59136000 | E58: =IF(Initiatives!$F$6="adoption",E54*Initiatives!$F$23+E53*Initiatives!$F$8-E57*Initiatives!$F$8,(Initiatives!$F$42*Initiatives!$F$41+Initiatives!$F$38*Initiatives!$F$13*Initiatives!$F$14+Initiatives!$F$43*Initiatives!$F$16)*E55-E57*Initiatives!$F$8) -> 117942528 | F58: =IF(Initiatives!$F$6="adoption",F54*Initiatives!$F$23+F53*Initiatives!$F$8-F57*Initiatives!$F$8,(Initiatives!$F$42*Initiatives!$F$41+Initiatives!$F$38*Initiatives!$F$13*Initiatives!$F$14+Initiatives!$F$43*Initiatives!$F$16)*F55-F57*Initiatives!$F$8) -> 1.7641784e+08 | G58: =IF(Initiatives!$F$6="adoption",G54*Initiatives!$F$23+G53*Initiatives!$F$8-G57*Initiatives!$F$8,(Initiatives!$F$42*Initiatives!$F$41+Initiatives!$F$38*Initiatives!$F$13*Initiatives!$F$14+Initiatives!$F$43*Initiatives!$F$16)*G55-G57*Initiatives!$F$8) -> 1.7542428e+08 | H58: =IF(Initiatives!$F$6="adoption",H54*Initiatives!$F$23+H53*Initiatives!$F$8-H57*Initiatives!$F$8,(Initiatives!$F$42*Initiatives!$F$41+Initiatives!$F$38*Initiatives!$F$13*Initiatives!$F$14+Initiatives!$F$43*Initiatives!$F$16)*H55-H57*Initiatives!$F$8) -> 1.7442579e+08 | I58: =IF(Initiatives!$F$6="adoption",I54*Initiatives!$F$23+I53*Initiatives!$F$8-I57*Initiatives!$F$8,(Initiatives!$F$42*Initiatives!$F$41+Initiatives!$F$38*Initiatives!$F$13*Initiatives!$F$14+Initiatives!$F$43*Initiatives!$F$16)*I55-I57*Initiatives!$F$8) -> 1.7342269e+08 | J58: =IF(Initiatives!$F$6="adoption",J54*Initiatives!$F$23+J53*Initiatives!$F$8-J57*Initiatives!$F$8,(Initiatives!$F$42*Initiatives!$F$41+Initiatives!$F$38*Initiatives!$F$13*Initiatives!$F$14+Initiatives!$F$43*Initiatives!$F$16)*J55-J57*Initiatives!$F$8) -> 1.7241528e+08 | ... AL58: =IF(Initiatives!$F$6="adoption",AL54*Initiatives!$F$23+AL53*Initiatives!$F$8-AL57*Initiatives!$F$8,(Initiatives!$F$42*Initiatives!$F$41+Initiatives!$F$38*Initiatives!$F$13*Initiatives!$F$14+Initiatives!$F$43*Initiatives!$F$16)*AL55-AL57*Initiatives!$F$8) -> 1.4348281e+08
A59: Затраты | B59: cost | C59: =IF(C$3<=Initiatives!$F$45,Initiatives!$F$28/Initiatives!$F$45,0)+IF(Initiatives!$F$6="adoption",C52*Initiatives!$F$26+C54*Initiatives!$F$27+IF(C$3=Initiatives!$F$31,Initiatives!$F$39*Initiatives!$F$25,0)+IF(C$3>=Initiatives!$F$31,Initiatives!$F$29,0),Initiatives!$F$42*Initiatives!$F$18*C55+IF(C$3=Initiatives!$F$31,Initiatives!$F$32*Initiatives!$F$38*Initiatives!$F$25,0)+IF(C$3=Initiatives!$F$33,(1-Initiatives!$F$32)*Initiatives!$F$38*Initiatives!$F$25,0)+IF(C$3>=Initiatives!$F$31,Initiatives!$F$29-Initiatives!$F$19*(Initiatives!$F$32+IF(C$3>=Initiatives!$F$33,1-Initiatives!$F$32,0)),0)) -> 150000000 | D59: =IF(D$3<=Initiatives!$F$45,Initiatives!$F$28/Initiatives!$F$45,0)+IF(Initiatives!$F$6="adoption",D52*Initiatives!$F$26+D54*Initiatives!$F$27+IF(D$3=Initiatives!$F$31,Initiatives!$F$39*Initiatives!$F$25,0)+IF(D$3>=Initiatives!$F$31,Initiatives!$F$29,0),Initiatives!$F$42*Initiatives!$F$18*D55+IF(D$3=Initiatives!$F$31,Initiatives!$F$32*Initiatives!$F$38*Initiatives!$F$25,0)+IF(D$3=Initiatives!$F$33,(1-Initiatives!$F$32)*Initiatives!$F$38*Initiatives!$F$25,0)+IF(D$3>=Initiatives!$F$31,Initiatives!$F$29-Initiatives!$F$19*(Initiatives!$F$32+IF(D$3>=Initiatives!$F$33,1-Initiatives!$F$32,0)),0)) -> 86032000 | E59: =IF(E$3<=Initiatives!$F$45,Initiatives!$F$28/Initiatives!$F$45,0)+IF(Initiatives!$F$6="adoption",E52*Initiatives!$F$26+E54*Initiatives!$F$27+IF(E$3=Initiatives!$F$31,Initiatives!$F$39*Initiatives!$F$25,0)+IF(E$3>=Initiatives!$F$31,Initiatives!$F$29,0),Initiatives!$F$42*Initiatives!$F$18*E55+IF(E$3=Initiatives!$F$31,Initiatives!$F$32*Initiatives!$F$38*Initiatives!$F$25,0)+IF(E$3=Initiatives!$F$33,(1-Initiatives!$F$32)*Initiatives!$F$38*Initiatives!$F$25,0)+IF(E$3>=Initiatives!$F$31,Initiatives!$F$29-Initiatives!$F$19*(Initiatives!$F$32+IF(E$3>=Initiatives!$F$33,1-Initiatives!$F$32,0)),0)) -> 60688000 | F59: =IF(F$3<=Initiatives!$F$45,Initiatives!$F$28/Initiatives!$F$45,0)+IF(Initiatives!$F$6="adoption",F52*Initiatives!$F$26+F54*Initiatives!$F$27+IF(F$3=Initiatives!$F$31,Initiatives!$F$39*Initiatives!$F$25,0)+IF(F$3>=Initiatives!$F$31,Initiatives!$F$29,0),Initiatives!$F$42*Initiatives!$F$18*F55+IF(F$3=Initiatives!$F$31,Initiatives!$F$32*Initiatives!$F$38*Initiatives!$F$25,0)+IF(F$3=Initiatives!$F$33,(1-Initiatives!$F$32)*Initiatives!$F$38*Initiatives!$F$25,0)+IF(F$3>=Initiatives!$F$31,Initiatives!$F$29-Initiatives!$F$19*(Initiatives!$F$32+IF(F$3>=Initiatives!$F$33,1-Initiatives!$F$32,0)),0)) -> 60688000 | G59: =IF(G$3<=Initiatives!$F$45,Initiatives!$F$28/Initiatives!$F$45,0)+IF(Initiatives!$F$6="adoption",G52*Initiatives!$F$26+G54*Initiatives!$F$27+IF(G$3=Initiatives!$F$31,Initiatives!$F$39*Initiatives!$F$25,0)+IF(G$3>=Initiatives!$F$31,Initiatives!$F$29,0),Initiatives!$F$42*Initiatives!$F$18*G55+IF(G$3=Initiatives!$F$31,Initiatives!$F$32*Initiatives!$F$38*Initiatives!$F$25,0)+IF(G$3=Initiatives!$F$33,(1-Initiatives!$F$32)*Initiatives!$F$38*Initiatives!$F$25,0)+IF(G$3>=Initiatives!$F$31,Initiatives!$F$29-Initiatives!$F$19*(Initiatives!$F$32+IF(G$3>=Initiatives!$F$33,1-Initiatives!$F$32,0)),0)) -> 10000000 | H59: =IF(H$3<=Initiatives!$F$45,Initiatives!$F$28/Initiatives!$F$45,0)+IF(Initiatives!$F$6="adoption",H52*Initiatives!$F$26+H54*Initiatives!$F$27+IF(H$3=Initiatives!$F$31,Initiatives!$F$39*Initiatives!$F$25,0)+IF(H$3>=Initiatives!$F$31,Initiatives!$F$29,0),Initiatives!$F$42*Initiatives!$F$18*H55+IF(H$3=Initiatives!$F$31,Initiatives!$F$32*Initiatives!$F$38*Initiatives!$F$25,0)+IF(H$3=Initiatives!$F$33,(1-Initiatives!$F$32)*Initiatives!$F$38*Initiatives!$F$25,0)+IF(H$3>=Initiatives!$F$31,Initiatives!$F$29-Initiatives!$F$19*(Initiatives!$F$32+IF(H$3>=Initiatives!$F$33,1-Initiatives!$F$32,0)),0)) -> 10000000 | I59: =IF(I$3<=Initiatives!$F$45,Initiatives!$F$28/Initiatives!$F$45,0)+IF(Initiatives!$F$6="adoption",I52*Initiatives!$F$26+I54*Initiatives!$F$27+IF(I$3=Initiatives!$F$31,Initiatives!$F$39*Initiatives!$F$25,0)+IF(I$3>=Initiatives!$F$31,Initiatives!$F$29,0),Initiatives!$F$42*Initiatives!$F$18*I55+IF(I$3=Initiatives!$F$31,Initiatives!$F$32*Initiatives!$F$38*Initiatives!$F$25,0)+IF(I$3=Initiatives!$F$33,(1-Initiatives!$F$32)*Initiatives!$F$38*Initiatives!$F$25,0)+IF(I$3>=Initiatives!$F$31,Initiatives!$F$29-Initiatives!$F$19*(Initiatives!$F$32+IF(I$3>=Initiatives!$F$33,1-Initiatives!$F$32,0)),0)) -> 10000000 | J59: =IF(J$3<=Initiatives!$F$45,Initiatives!$F$28/Initiatives!$F$45,0)+IF(Initiatives!$F$6="adoption",J52*Initiatives!$F$26+J54*Initiatives!$F$27+IF(J$3=Initiatives!$F$31,Initiatives!$F$39*Initiatives!$F$25,0)+IF(J$3>=Initiatives!$F$31,Initiatives!$F$29,0),Initiatives!$F$42*Initiatives!$F$18*J55+IF(J$3=Initiatives!$F$31,Initiatives!$F$32*Initiatives!$F$38*Initiatives!$F$25,0)+IF(J$3=Initiatives!$F$33,(1-Initiatives!$F$32)*Initiatives!$F$38*Initiatives!$F$25,0)+IF(J$3>=Initiatives!$F$31,Initiatives!$F$29-Initiatives!$F$19*(Initiatives!$F$32+IF(J$3>=Initiatives!$F$33,1-Initiatives!$F$32,0)),0)) -> 10000000 | ... AL59: =IF(AL$3<=Initiatives!$F$45,Initiatives!$F$28/Initiatives!$F$45,0)+IF(Initiatives!$F$6="adoption",AL52*Initiatives!$F$26+AL54*Initiatives!$F$27+IF(AL$3=Initiatives!$F$31,Initiatives!$F$39*Initiatives!$F$25,0)+IF(AL$3>=Initiatives!$F$31,Initiatives!$F$29,0),Initiatives!$F$42*Initiatives!$F$18*AL55+IF(AL$3=Initiatives!$F$31,Initiatives!$F$32*Initiatives!$F$38*Initiatives!$F$25,0)+IF(AL$3=Initiatives!$F$33,(1-Initiatives!$F$32)*Initiatives!$F$38*Initiatives!$F$25,0)+IF(AL$3>=Initiatives!$F$31,Initiatives!$F$29-Initiatives!$F$19*(Initiatives!$F$32+IF(AL$3>=Initiatives!$F$33,1-Initiatives!$F$32,0)),0)) -> 10000000
A60: Вклад | B60: contrib | C60: =C58*Initiatives!$F$30-C59 -> -150000000 | D60: =D58*Initiatives!$F$30-D59 -> -50550400 | E60: =E58*Initiatives!$F$30-E59 -> 10077517 | F60: =F58*Initiatives!$F$30-F59 -> 45162701 | G60: =G58*Initiatives!$F$30-G59 -> 95254568 | H60: =H58*Initiatives!$F$30-H59 -> 94655477 | I60: =I58*Initiatives!$F$30-I59 -> 94053616 | J60: =J58*Initiatives!$F$30-J59 -> 93449166 | ... AL60: =AL58*Initiatives!$F$30-AL59 -> 76089685
A61: Δ абонентов | B61: dsubs | C61: =C53-C57 -> 0 | D61: =D53-D57 -> 0 | E61: =E53-E57 -> 25.344 | F61: =F53-F57 -> 75.347712 | G61: =G53-G57 -> 149.34076 | H61: =H53-H57 -> 221.32244 | I61: =I53-I57 -> 291.33373 | J61: =J53-J57 -> 359.41487 | ... AL61: =AL53-AL57 -> 1624.3923

Sheet Loyalty_Inputs
A1: Loyalty program: параметры
A3: Параметр | B3: Ключ | C3: Значение | D3: Комментарий
A4: MAU приложения / база | B4: app_mau_share | C4: 0.27 | D4: HYPOTHESIS — запрос L1
A5: Вступили в программу из MAU | B5: enroll_of_mau | C5: 0.5 | D5: HYPOTHESIS; проверяется MVP
A6: Доля архивных среди участников | B6: archive_share_members | C6: 0.2 | D6: HYPOTHESIS — запрос L1
A7: Участников MVP | B7: mvp_participants | C7: 150000 | D7: Стратифицированная выборка
A8: Месяц старта MVP (M5 = март 2027) | B8: mvp_start | C8: 5
A9: Длительность MVP, мес. | B9: mvp_months | C9: 3
A10: Месяц старта масштаба (M11 = сентябрь 2027) | B10: scale_start | C10: 11
A11: Набор участников при масштабе, мес. | B11: scale_ramp | C11: 6
A12: Доля оплат вовремя (кэшбэк только им) | B12: ontime_share | C12: 0.85 | D12: запрос L3
A13: Breakage: монеты не потрачены (12 мес.) | B13: breakage | C13: 0.3 | D13: Бенчмарки 25–40%
A14: Себестоимость погашения монет | B14: redeem_cost_ratio | C14: 0.515 | D14: 50% услуги×0,15 + 30% счёт×1 + 20% мерч×0,7
A15: Ежедневно открывают сундук (доля участников) | B15: drops_dau_share | C15: 0.3 | D15: проверяется MVP
A16: Призовые фонды MVP, доля от масштаба | B16: mvp_prize_share | C16: 0.3
A17: Разработка MVP, сум | B17: mvp_build | C17: 1800000000 | D17: web-view в приложении
A18: Разработка масштаба, сум | B18: scale_build | C18: 3000000000
A19: OPEX MVP, сум/мес | B19: mvp_opex_m | C19: 120000000
A20: OPEX программы, сум/мес | B20: opex_m | C20: 250000000 | D20: команда, лицензии, фулфилмент, КЦ
A21: Маркетинг, сум/мес | B21: marketing_m | C21: 150000000
A22: Маркетинг запуска масштаба, сум | B22: launch_marketing | C22: 1500000000
A23: Маркетинг MVP, сум | B23: mvp_marketing | C23: 250000000
A24: Месячный отток участников (база) | B24: member_churn_base | C24: 0.012 | D24: запрос L4
A25: Снижение оттока участников (отн.) | B25: churn_reduction | C25: 0.15 | D25: T-Mobile Tuesdays −27% (с самоотбором)
A26: Рост выручки от оплат вовремя | B26: ontime_rev_uplift | C26: 0.015 | D26: H2 MVP
A27: Доп. переходы на ТП ≥ 60 тыс., в мес. | B27: upgrade_rate_m | C27: 0.004 | D27: H1 MVP — главный драйвер
A28: ΔARPU при переходе, сум | B28: upgrade_delta | C28: 20000
A29: Club+ Pass: доля участников < 60 тыс. | B29: pass_adoption | C29: 0.03 | D29: H3 MVP
A30: Club+ Pass: цена с НДС, сум/мес | B30: pass_price_gross | C30: 9999
A31: Себестоимость ценности Pass | B31: pass_value_cost | C31: 0.25 | D31: ГБ, ×1,5 кэшбэк
A32: Допродажи в приложении (при DAU 30%) | B32: engagement_upsell | C32: 0.008
A33: Платные размещения партнёров, сум/мес (с M+6 масштаба) | B33: partner_cash_m | C33: 50000000
A34: Маржинальность доп. выручки | B34: margin | C34: 0.85
A35: ARPU архивного участника, сум | B35: archive_member_arpu | C35: 22000 | D35: запрос L1
A36: Отток архивных участников | B36: archive_churn_base | C36: 0.015
A37: Архивные: переход на актуальный ТП, в мес. | B37: archive_upgrade_rate_m | C37: 0.004
A38: Архивные: ΔARPU при переходе, сум | B38: archive_upgrade_delta | C38: 12000
A40: Распределение участников по абонплате (HYPOTHESIS — запрос L2)
A41: Полоса | B41: Ключ | C41: Доля участников | D41: Доля архивных участников | E41: Средняя АП с НДС | F41: Кэшбэк | G41: Шансы/нед. (O5)
A42: АП < 30 тыс. | B42: lt30 | C42: 0.3 | D42: 0.8 | E42: 22000 | F42: 0.03 | G42: 1
A43: АП 30–59 тыс. | B43: 30_59 | C43: 0.4 | D43: 0.17 | E43: 45000 | F43: 0.03 | G43: 2
A44: АП 60–79 тыс. | B44: 60_79 | C44: 0.18 | D44: 0.02 | E44: 70000 | F44: 0.04 | G44: 3
A45: АП ≥ 80 тыс. | B45: ge80 | C45: 0.12 | D45: 0.01 | E45: 100000 | F45: 0.05 | G45: 5
A47: ARPU участника net | B47: arpu_net | C47: =SUMPRODUCT(C42:C45,E42:E45)/(1+Inputs!$C$10) -> 43928.571
A48: Начисляется монет на участника/мес | B48: earn | C48: =SUMPRODUCT(C42:C45,E42:E45,F42:F45) -> 1842
A49: Средняя ставка кэшбэка | B49: cb_avg | C49: =C48/SUMPRODUCT(C42:C45,E42:E45) -> 0.037439024
A50: Доля участников с АП < 60 тыс. | B50: below60 | C50: =C42+C43 -> 0.7
A51: Монет на архивного участника/мес | B51: a_earn | C51: =SUMPRODUCT(D42:D45,E42:E45,F42:F45) -> 863.5
A52: Доля архивных участников < 60 тыс. | B52: a_below60 | C52: =D42+D43 -> 0.97
A53: Участников при полном масштабе | B53: full | C53: =Inputs!$C$4*Loyalty_Inputs!$C$4*Loyalty_Inputs!$C$5 -> 1485000
A54: Club+ Pass net, сум | B54: pass_net | C54: =Loyalty_Inputs!$C$30/(1+Inputs!$C$10) -> 8927.6786
A55: Проверка долей | B55: check | C55: =IF(AND(ABS(SUM(C42:C45)-1)<0.0001,ABS(SUM(D42:D45)-1)<0.0001),"OK","ОШИБКА") -> OK

Sheet Prizes
A1: Каталог призов (цены — ориентиры 10/2026, уточнить у закупок) и призовые фонды
A3: Ключ | B3: Приз | C3: Цена, сум с НДС | D3: Источник
A4: car_onix | B4: Chevrolet Onix 1LS MT | C4: 176900000 | D4: kursiv.media, 04/2026
A5: car_cobalt | B5: Chevrolet Cobalt | C5: 146455000 | D5: kursiv.media, 04/2026
A6: trip_turkey2 | B6: Путешествие в Турцию на двоих (7 ночей) | C6: 32000000 | D6: оценка ~$2 600
A7: umrah2 | B7: Умра на двоих | C7: 50000000 | D7: оценка ~$2 000/чел.
A8: domestic_trip2 | B8: Самарканд–Бухара–Хива на двоих (Afrosiyob + отель) | C8: 7000000 | D8: оценка
A9: iphone17 | B9: iPhone 17 256 ГБ | C9: 12500000 | D9: оценка, OLX/ритейл 11,3–13 млн
A10: galaxy_a | B10: Samsung Galaxy A (A36/A56) | C10: 4500000 | D10: оценка
A11: tablet | B11: Планшет Samsung Galaxy Tab A9+ | C11: 3000000 | D11: оценка
A12: airpods | B12: AirPods 4 | C12: 2000000 | D12: оценка (MSRP $129 + импорт)
A13: jbl | B13: Наушники JBL Tune | C13: 700000 | D13: оценка
A14: concert_pair | B14: 2 билета на концерт | C14: 1200000 | D14: оценка
A15: cinema_pair | B15: 2 билета в кино | C15: 160000 | D15: Premier Cinema 80–100 тыс./билет
... A21: partner_voucher | B21: Ваучер партнёра (номинал 100 тыс.) | C21: 100000 | D21: 100% финансирует партнёр
A23: Weekly Wins — еженедельный фонд (масштаб)
A24: Ключ | B24: Приз | C24: Кол-во в неделю | D24: Софинансирует партнёр | E24: Затраты/нед., сум
A25: iphone17 | B25: =INDEX($B$4:$B$21,MATCH(A25,$A$4:$A$21,0)) -> iPhone 17 256 ГБ | C25: 1 | D25: 0 | E25: =INDEX($C$4:$C$21,MATCH(A25,$A$4:$A$21,0))*C25*(1-D25) -> 12500000
A26: tablet | B26: =INDEX($B$4:$B$21,MATCH(A26,$A$4:$A$21,0)) -> Планшет Samsung Galaxy Tab A9+ | C26: 2 | D26: 0 | E26: =INDEX($C$4:$C$21,MATCH(A26,$A$4:$A$21,0))*C26*(1-D26) -> 6000000
A27: airpods | B27: =INDEX($B$4:$B$21,MATCH(A27,$A$4:$A$21,0)) -> AirPods 4 | C27: 5 | D27: 0 | E27: =INDEX($C$4:$C$21,MATCH(A27,$A$4:$A$21,0))*C27*(1-D27) -> 10000000
A28: concert_pair | B28: =INDEX($B$4:$B$21,MATCH(A28,$A$4:$A$21,0)) -> 2 билета на концерт | C28: 10 | D28: 0.5 | E28: =INDEX($C$4:$C$21,MATCH(A28,$A$4:$A$21,0))*C28*(1-D28) -> 6000000
A29: cinema_pair | B29: =INDEX($B$4:$B$21,MATCH(A29,$A$4:$A$21,0)) -> 2 билета в кино | C29: 30 | D29: 0.5 | E29: =INDEX($C$4:$C$21,MATCH(A29,$A$4:$A$21,0))*C29*(1-D29) -> 2400000
A30: galaxy_a | B30: =INDEX($B$4:$B$21,MATCH(A30,$A$4:$A$21,0)) -> Samsung Galaxy A (A36/A56) | C30: 1 | D30: 0 | E30: =INDEX($C$4:$C$21,MATCH(A30,$A$4:$A$21,0))*C30*(1-D30) -> 4500000
A31: jbl | B31: =INDEX($B$4:$B$21,MATCH(A31,$A$4:$A$21,0)) -> Наушники JBL Tune | C31: 5 | D31: 0 | E31: =INDEX($C$4:$C$21,MATCH(A31,$A$4:$A$21,0))*C31*(1-D31) -> 3500000
A32: data_5gb | B32: =INDEX($B$4:$B$21,MATCH(A32,$A$4:$A$21,0)) -> 5 ГБ интернета (себестоимость) | C32: 1000 | D32: 0 | E32: =INDEX($C$4:$C$21,MATCH(A32,$A$4:$A$21,0))*C32*(1-D32) -> 1250000
A33: partner_voucher | B33: =INDEX($B$4:$B$21,MATCH(A33,$A$4:$A$21,0)) -> Ваучер партнёра (номинал 100 тыс.) | C33: 300 | D33: 1 | E33: =INDEX($C$4:$C$21,MATCH(A33,$A$4:$A$21,0))*C33*(1-D33) -> 0
B34: Итого в неделю | C34: =SUM(C25:C33) -> 1354 | E34: =SUM(E25:E33) -> 46150000
B35: Итого в месяц (×52/12) | E35: =E34*52/12 -> 1.9998333e+08
A37: Daily Drops — еженедельный инвентарь (масштаб)
A38: Ключ | B38: Приз | C38: Кол-во в неделю | D38: Софинансирует партнёр | E38: Затраты/нед., сум
A39: cinema_pair | B39: =INDEX($B$4:$B$21,MATCH(A39,$A$4:$A$21,0)) -> 2 билета в кино | C39: 500 | D39: 0.5 | E39: =INDEX($C$4:$C$21,MATCH(A39,$A$4:$A$21,0))*C39*(1-D39) -> 40000000
A40: hoodie | B40: =INDEX($B$4:$B$21,MATCH(A40,$A$4:$A$21,0)) -> Худи с принтом (мерч) | C40: 100 | D40: 0 | E40: =INDEX($C$4:$C$21,MATCH(A40,$A$4:$A$21,0))*C40*(1-D40) -> 16000000
A41: cap | B41: =INDEX($B$4:$B$21,MATCH(A41,$A$4:$A$21,0)) -> Кепка / шоппер | C41: 60 | D41: 0 | E41: =INDEX($C$4:$C$21,MATCH(A41,$A$4:$A$21,0))*C41*(1-D41) -> 3600000
A42: powerbank | B42: =INDEX($B$4:$B$21,MATCH(A42,$A$4:$A$21,0)) -> Power bank 10 000 мА·ч | C42: 40 | D42: 0 | E42: =INDEX($C$4:$C$21,MATCH(A42,$A$4:$A$21,0))*C42*(1-D42) -> 7200000
A43: jbl | B43: =INDEX($B$4:$B$21,MATCH(A43,$A$4:$A$21,0)) -> Наушники JBL Tune | C43: 20 | D43: 0 | E43: =INDEX($C$4:$C$21,MATCH(A43,$A$4:$A$21,0))*C43*(1-D43) -> 14000000
A44: galaxy_a | B44: =INDEX($B$4:$B$21,MATCH(A44,$A$4:$A$21,0)) -> Samsung Galaxy A (A36/A56) | C44: 2 | D44: 0 | E44: =INDEX($C$4:$C$21,MATCH(A44,$A$4:$A$21,0))*C44*(1-D44) -> 9000000
B45: Итого в неделю | C45: =SUM(C39:C44) -> 722 | E45: =SUM(E39:E44) -> 89800000
B46: Итого в месяц (×52/12) | E46: =E45*52/12 -> 3.8913333e+08
A48: Monthly Grand — календарь на 12 месяцев
A49: Месяц | B49: Приз | C49: Стоимость, сум
A50: Сен | B50: Chevrolet Onix 1LS MT | C50: =INDEX($C$4:$C$21,MATCH("car_onix",$A$4:$A$21,0)) -> 176900000
A51: Окт | B51: Путешествие в Турцию на двоих (7 ночей) | C51: =INDEX($C$4:$C$21,MATCH("trip_turkey2",$A$4:$A$21,0)) -> 32000000
A52: Ноя | B52: Умра на двоих | C52: =INDEX($C$4:$C$21,MATCH("umrah2",$A$4:$A$21,0)) -> 50000000
A53: Дек | B53: Chevrolet Onix 1LS MT | C53: =INDEX($C$4:$C$21,MATCH("car_onix",$A$4:$A$21,0)) -> 176900000
A54: Янв | B54: Путешествие в Турцию на двоих (7 ночей) | C54: =INDEX($C$4:$C$21,MATCH("trip_turkey2",$A$4:$A$21,0)) -> 32000000
A55: Фев | B55: 5 × iPhone 17 | C55: =5*INDEX($C$4:$C$21,MATCH("iphone17",$A$4:$A$21,0)) -> 62500000
A56: Мар | B56: Chevrolet Onix 1LS MT | C56: =INDEX($C$4:$C$21,MATCH("car_onix",$A$4:$A$21,0)) -> 176900000
A57: Апр | B57: Путешествие в Турцию на двоих (7 ночей) | C57: =INDEX($C$4:$C$21,MATCH("trip_turkey2",$A$4:$A$21,0)) -> 32000000
A58: Май | B58: 10 × год связи бесплатно | C58: =10*INDEX($C$4:$C$21,MATCH("free_year",$A$4:$A$21,0)) -> 12000000
A59: Июн | B59: Chevrolet Onix 1LS MT | C59: =INDEX($C$4:$C$21,MATCH("car_onix",$A$4:$A$21,0)) -> 176900000
A60: Июл | B60: Путешествие в Турцию на двоих (7 ночей) | C60: =INDEX($C$4:$C$21,MATCH("trip_turkey2",$A$4:$A$21,0)) -> 32000000
A61: Авг | B61: Умра на двоих | C61: =INDEX($C$4:$C$21,MATCH("umrah2",$A$4:$A$21,0)) -> 50000000
B62: Итого за год | C62: =SUM(C50:C61) -> 1010100000
B63: Накладные (логистика, нотариус/комиссия, резерв налогов) | C63: 0.1
B64: В среднем в месяц с накладными | C64: =C62/12*(1+C63) -> 92592500

Sheet Daily_Drops
A1: Daily Drops: что выпадает из сундука (цифровые призы) и недельный бюджет
A3: Приз | B3: Вероятность | C3: Себестоимость, сум | D3: Ожидаемо на открытие, сум | E3: Комментарий
A4: 30–100 Ucell Coins | B4: 0.5 | C4: 23 | D4: =B4*C4 -> 11.5 | E4: 65 монет × 70% погашения × 0,515 себестоимости
A5: 300 МБ – 1 ГБ интернета | B5: 0.25 | C5: 150 | D5: =B5*C5 -> 37.5 | E5: 0,6 ГБ × ~250 сум/ГБ маржинальной себестоимости
A6: 30 мин внутри сети / безлимит мессенджеров на сутки | B6: 0.07 | C6: 40 | D6: =B6*C6 -> 2.8
A7: Купон партнёра (−10…30%) | B7: 0.14 | C7: 5 | D7: =B7*C7 -> 0.7 | E7: финансирует партнёр, наша стоимость — платформа
A8: Жетон серии: +1 шанс в Weekly Wins | B8: 0.02 | C8: 0 | D8: =B8*C8 -> 0 | E8: только шанс
A9: Слот инвентаря (кино, мерч, наушники, смартфон) | B9: 0.02 | C9: 0 | D9: =B9*C9 -> 0 | E9: лимит в неделю, бюджет — отдельной строкой
A10: Итого | B10: =SUM(B4:B9) -> 1 | D10: =SUM(D4:D9) -> 52.5
A11: Проверка: вероятности = 100% | B11: =IF(ABS(B10-1)<0.0001,"OK","ОШИБКА") -> OK
A13: Недельный бюджет Daily Drops при масштабе
A14: Участников | C14: =Loyalty_Inputs!$C$53 -> 1485000
A15: Открытий в неделю | C15: =C14*Loyalty_Inputs!$C$15*7 -> 3118500
A16: Цифровые призы, сум/нед. | C16: =C15*Daily_Drops!$D$10 -> 163721250
A17: Инвентарь, сум/нед. (лист Prizes) | C17: =Prizes!$E$45 -> 89800000
A18: Итого Daily Drops, сум/нед. | C18: =C16+C17 -> 253521250
A19: Стоимость на одно открытие, сум | C19: =C18/C15 -> 81.295895
A20: Правило безубыточности: ≤ доп. маржа от допродаж на одно открытие, сум | C20: =Loyalty_Inputs!$C$47*Loyalty_Inputs!$C$32*Loyalty_Inputs!$C$34/(Loyalty_Inputs!$C$15*30)*(Loyalty_Inputs!$C$15/0.3) -> 33.190476

Sheet Loyalty_Monthly
A1: Loyalty program: помесячный движок (36 мес.; MVP M5–M7, масштаб с M11)
A3: Месяц | C3: 1 | D3: 2 | E3: 3 | F3: 4 | G3: 5 | H3: 6 | I3: 7 | J3: 8 | K3: 9 | L3: 10 | M3: 11 | N3: 12 | O3: 13 | P3: 14 | Q3: 15 | R3: 16 | S3: 17 | T3: 18 | U3: 19 | V3: 20 | W3: 21 | X3: 22 | Y3: 23 | Z3: 24 | AA3: 25 | AB3: 26 | AC3: 27 | AD3: 28 | AE3: 29 | AF3: 30 | AG3: 31 | AH3: 32 | AI3: 33 | AJ3: 34 | AK3: 35 | AL3: 36
A4: Участники | B4: mem | C4: =IF(C$3<Loyalty_Inputs!$C$8,0,IF(C$3<Loyalty_Inputs!$C$10,Loyalty_Inputs!$C$7,MAX(Loyalty_Inputs!$C$7,Loyalty_Inputs!$C$53*MIN((C$3-Loyalty_Inputs!$C$10+1)/Loyalty_Inputs!$C$11,1)))) -> 0 | D4: =IF(D$3<Loyalty_Inputs!$C$8,0,IF(D$3<Loyalty_Inputs!$C$10,Loyalty_Inputs!$C$7,MAX(Loyalty_Inputs!$C$7,Loyalty_Inputs!$C$53*MIN((D$3-Loyalty_Inputs!$C$10+1)/Loyalty_Inputs!$C$11,1)))) -> 0 | E4: =IF(E$3<Loyalty_Inputs!$C$8,0,IF(E$3<Loyalty_Inputs!$C$10,Loyalty_Inputs!$C$7,MAX(Loyalty_Inputs!$C$7,Loyalty_Inputs!$C$53*MIN((E$3-Loyalty_Inputs!$C$10+1)/Loyalty_Inputs!$C$11,1)))) -> 0 | F4: =IF(F$3<Loyalty_Inputs!$C$8,0,IF(F$3<Loyalty_Inputs!$C$10,Loyalty_Inputs!$C$7,MAX(Loyalty_Inputs!$C$7,Loyalty_Inputs!$C$53*MIN((F$3-Loyalty_Inputs!$C$10+1)/Loyalty_Inputs!$C$11,1)))) -> 0 | G4: =IF(G$3<Loyalty_Inputs!$C$8,0,IF(G$3<Loyalty_Inputs!$C$10,Loyalty_Inputs!$C$7,MAX(Loyalty_Inputs!$C$7,Loyalty_Inputs!$C$53*MIN((G$3-Loyalty_Inputs!$C$10+1)/Loyalty_Inputs!$C$11,1)))) -> 150000 | H4: =IF(H$3<Loyalty_Inputs!$C$8,0,IF(H$3<Loyalty_Inputs!$C$10,Loyalty_Inputs!$C$7,MAX(Loyalty_Inputs!$C$7,Loyalty_Inputs!$C$53*MIN((H$3-Loyalty_Inputs!$C$10+1)/Loyalty_Inputs!$C$11,1)))) -> 150000 | I4: =IF(I$3<Loyalty_Inputs!$C$8,0,IF(I$3<Loyalty_Inputs!$C$10,Loyalty_Inputs!$C$7,MAX(Loyalty_Inputs!$C$7,Loyalty_Inputs!$C$53*MIN((I$3-Loyalty_Inputs!$C$10+1)/Loyalty_Inputs!$C$11,1)))) -> 150000 | J4: =IF(J$3<Loyalty_Inputs!$C$8,0,IF(J$3<Loyalty_Inputs!$C$10,Loyalty_Inputs!$C$7,MAX(Loyalty_Inputs!$C$7,Loyalty_Inputs!$C$53*MIN((J$3-Loyalty_Inputs!$C$10+1)/Loyalty_Inputs!$C$11,1)))) -> 150000 | ... AL4: =IF(AL$3<Loyalty_Inputs!$C$8,0,IF(AL$3<Loyalty_Inputs!$C$10,Loyalty_Inputs!$C$7,MAX(Loyalty_Inputs!$C$7,Loyalty_Inputs!$C$53*MIN((AL$3-Loyalty_Inputs!$C$10+1)/Loyalty_Inputs!$C$11,1)))) -> 1485000
A5: Коэф. призовых фондов | B5: pf | C5: =IF(C4>0,MAX(Loyalty_Inputs!$C$16,C4/Loyalty_Inputs!$C$53),0) -> 0 | D5: =IF(D4>0,MAX(Loyalty_Inputs!$C$16,D4/Loyalty_Inputs!$C$53),0) -> 0 | E5: =IF(E4>0,MAX(Loyalty_Inputs!$C$16,E4/Loyalty_Inputs!$C$53),0) -> 0 | F5: =IF(F4>0,MAX(Loyalty_Inputs!$C$16,F4/Loyalty_Inputs!$C$53),0) -> 0 | G5: =IF(G4>0,MAX(Loyalty_Inputs!$C$16,G4/Loyalty_Inputs!$C$53),0) -> 0.3 | H5: =IF(H4>0,MAX(Loyalty_Inputs!$C$16,H4/Loyalty_Inputs!$C$53),0) -> 0.3 | I5: =IF(I4>0,MAX(Loyalty_Inputs!$C$16,I4/Loyalty_Inputs!$C$53),0) -> 0.3 | J5: =IF(J4>0,MAX(Loyalty_Inputs!$C$16,J4/Loyalty_Inputs!$C$53),0) -> 0.3 | ... AL5: =IF(AL4>0,MAX(Loyalty_Inputs!$C$16,AL4/Loyalty_Inputs!$C$53),0) -> 1
A6: Разработка | B6: c_build | C6: =IF(AND(C$3>=2,C$3<Loyalty_Inputs!$C$8),Loyalty_Inputs!$C$17/(Loyalty_Inputs!$C$8-2),0)+IF(AND(C$3>=Loyalty_Inputs!$C$8+Loyalty_Inputs!$C$9,C$3<Loyalty_Inputs!$C$10),Loyalty_Inputs!$C$18/(Loyalty_Inputs!$C$10-Loyalty_Inputs!$C$8-Loyalty_Inputs!$C$9),0) -> 0 | D6: =IF(AND(D$3>=2,D$3<Loyalty_Inputs!$C$8),Loyalty_Inputs!$C$17/(Loyalty_Inputs!$C$8-2),0)+IF(AND(D$3>=Loyalty_Inputs!$C$8+Loyalty_Inputs!$C$9,D$3<Loyalty_Inputs!$C$10),Loyalty_Inputs!$C$18/(Loyalty_Inputs!$C$10-Loyalty_Inputs!$C$8-Loyalty_Inputs!$C$9),0) -> 600000000 | E6: =IF(AND(E$3>=2,E$3<Loyalty_Inputs!$C$8),Loyalty_Inputs!$C$17/(Loyalty_Inputs!$C$8-2),0)+IF(AND(E$3>=Loyalty_Inputs!$C$8+Loyalty_Inputs!$C$9,E$3<Loyalty_Inputs!$C$10),Loyalty_Inputs!$C$18/(Loyalty_Inputs!$C$10-Loyalty_Inputs!$C$8-Loyalty_Inputs!$C$9),0) -> 600000000 | F6: =IF(AND(F$3>=2,F$3<Loyalty_Inputs!$C$8),Loyalty_Inputs!$C$17/(Loyalty_Inputs!$C$8-2),0)+IF(AND(F$3>=Loyalty_Inputs!$C$8+Loyalty_Inputs!$C$9,F$3<Loyalty_Inputs!$C$10),Loyalty_Inputs!$C$18/(Loyalty_Inputs!$C$10-Loyalty_Inputs!$C$8-Loyalty_Inputs!$C$9),0) -> 600000000 | G6: =IF(AND(G$3>=2,G$3<Loyalty_Inputs!$C$8),Loyalty_Inputs!$C$17/(Loyalty_Inputs!$C$8-2),0)+IF(AND(G$3>=Loyalty_Inputs!$C$8+Loyalty_Inputs!$C$9,G$3<Loyalty_Inputs!$C$10),Loyalty_Inputs!$C$18/(Loyalty_Inputs!$C$10-Loyalty_Inputs!$C$8-Loyalty_Inputs!$C$9),0) -> 0 | H6: =IF(AND(H$3>=2,H$3<Loyalty_Inputs!$C$8),Loyalty_Inputs!$C$17/(Loyalty_Inputs!$C$8-2),0)+IF(AND(H$3>=Loyalty_Inputs!$C$8+Loyalty_Inputs!$C$9,H$3<Loyalty_Inputs!$C$10),Loyalty_Inputs!$C$18/(Loyalty_Inputs!$C$10-Loyalty_Inputs!$C$8-Loyalty_Inputs!$C$9),0) -> 0 | I6: =IF(AND(I$3>=2,I$3<Loyalty_Inputs!$C$8),Loyalty_Inputs!$C$17/(Loyalty_Inputs!$C$8-2),0)+IF(AND(I$3>=Loyalty_Inputs!$C$8+Loyalty_Inputs!$C$9,I$3<Loyalty_Inputs!$C$10),Loyalty_Inputs!$C$18/(Loyalty_Inputs!$C$10-Loyalty_Inputs!$C$8-Loyalty_Inputs!$C$9),0) -> 0 | J6: =IF(AND(J$3>=2,J$3<Loyalty_Inputs!$C$8),Loyalty_Inputs!$C$17/(Loyalty_Inputs!$C$8-2),0)+IF(AND(J$3>=Loyalty_Inputs!$C$8+Loyalty_Inputs!$C$9,J$3<Loyalty_Inputs!$C$10),Loyalty_Inputs!$C$18/(Loyalty_Inputs!$C$10-Loyalty_Inputs!$C$8-Loyalty_Inputs!$C$9),0) -> 1000000000 | ... AL6: =IF(AND(AL$3>=2,AL$3<Loyalty_Inputs!$C$8),Loyalty_Inputs!$C$17/(Loyalty_Inputs!$C$8-2),0)+IF(AND(AL$3>=Loyalty_Inputs!$C$8+Loyalty_Inputs!$C$9,AL$3<Loyalty_Inputs!$C$10),Loyalty_Inputs!$C$18/(Loyalty_Inputs!$C$10-Loyalty_Inputs!$C$8-Loyalty_Inputs!$C$9),0) -> 0
A7: OPEX | B7: c_opex | C7: =IF(AND(C$3>=Loyalty_Inputs!$C$8,C$3<Loyalty_Inputs!$C$10),Loyalty_Inputs!$C$19,0)+IF(C$3>=Loyalty_Inputs!$C$10,Loyalty_Inputs!$C$20,0) -> 0 | D7: =IF(AND(D$3>=Loyalty_Inputs!$C$8,D$3<Loyalty_Inputs!$C$10),Loyalty_Inputs!$C$19,0)+IF(D$3>=Loyalty_Inputs!$C$10,Loyalty_Inputs!$C$20,0) -> 0 | E7: =IF(AND(E$3>=Loyalty_Inputs!$C$8,E$3<Loyalty_Inputs!$C$10),Loyalty_Inputs!$C$19,0)+IF(E$3>=Loyalty_Inputs!$C$10,Loyalty_Inputs!$C$20,0) -> 0 | F7: =IF(AND(F$3>=Loyalty_Inputs!$C$8,F$3<Loyalty_Inputs!$C$10),Loyalty_Inputs!$C$19,0)+IF(F$3>=Loyalty_Inputs!$C$10,Loyalty_Inputs!$C$20,0) -> 0 | G7: =IF(AND(G$3>=Loyalty_Inputs!$C$8,G$3<Loyalty_Inputs!$C$10),Loyalty_Inputs!$C$19,0)+IF(G$3>=Loyalty_Inputs!$C$10,Loyalty_Inputs!$C$20,0) -> 120000000 | H7: =IF(AND(H$3>=Loyalty_Inputs!$C$8,H$3<Loyalty_Inputs!$C$10),Loyalty_Inputs!$C$19,0)+IF(H$3>=Loyalty_Inputs!$C$10,Loyalty_Inputs!$C$20,0) -> 120000000 | I7: =IF(AND(I$3>=Loyalty_Inputs!$C$8,I$3<Loyalty_Inputs!$C$10),Loyalty_Inputs!$C$19,0)+IF(I$3>=Loyalty_Inputs!$C$10,Loyalty_Inputs!$C$20,0) -> 120000000 | J7: =IF(AND(J$3>=Loyalty_Inputs!$C$8,J$3<Loyalty_Inputs!$C$10),Loyalty_Inputs!$C$19,0)+IF(J$3>=Loyalty_Inputs!$C$10,Loyalty_Inputs!$C$20,0) -> 120000000 | ... AL7: =IF(AND(AL$3>=Loyalty_Inputs!$C$8,AL$3<Loyalty_Inputs!$C$10),Loyalty_Inputs!$C$19,0)+IF(AL$3>=Loyalty_Inputs!$C$10,Loyalty_Inputs!$C$20,0) -> 250000000
A8: Маркетинг | B8: c_mkt | C8: =IF(C$3>=Loyalty_Inputs!$C$10,Loyalty_Inputs!$C$21,0)+IF(OR(C$3=Loyalty_Inputs!$C$10,C$3=Loyalty_Inputs!$C$10+1),Loyalty_Inputs!$C$22/2,0)+IF(C$3=Loyalty_Inputs!$C$8,Loyalty_Inputs!$C$23,0) -> 0 | D8: =IF(D$3>=Loyalty_Inputs!$C$10,Loyalty_Inputs!$C$21,0)+IF(OR(D$3=Loyalty_Inputs!$C$10,D$3=Loyalty_Inputs!$C$10+1),Loyalty_Inputs!$C$22/2,0)+IF(D$3=Loyalty_Inputs!$C$8,Loyalty_Inputs!$C$23,0) -> 0 | E8: =IF(E$3>=Loyalty_Inputs!$C$10,Loyalty_Inputs!$C$21,0)+IF(OR(E$3=Loyalty_Inputs!$C$10,E$3=Loyalty_Inputs!$C$10+1),Loyalty_Inputs!$C$22/2,0)+IF(E$3=Loyalty_Inputs!$C$8,Loyalty_Inputs!$C$23,0) -> 0 | F8: =IF(F$3>=Loyalty_Inputs!$C$10,Loyalty_Inputs!$C$21,0)+IF(OR(F$3=Loyalty_Inputs!$C$10,F$3=Loyalty_Inputs!$C$10+1),Loyalty_Inputs!$C$22/2,0)+IF(F$3=Loyalty_Inputs!$C$8,Loyalty_Inputs!$C$23,0) -> 0 | G8: =IF(G$3>=Loyalty_Inputs!$C$10,Loyalty_Inputs!$C$21,0)+IF(OR(G$3=Loyalty_Inputs!$C$10,G$3=Loyalty_Inputs!$C$10+1),Loyalty_Inputs!$C$22/2,0)+IF(G$3=Loyalty_Inputs!$C$8,Loyalty_Inputs!$C$23,0) -> 250000000 | H8: =IF(H$3>=Loyalty_Inputs!$C$10,Loyalty_Inputs!$C$21,0)+IF(OR(H$3=Loyalty_Inputs!$C$10,H$3=Loyalty_Inputs!$C$10+1),Loyalty_Inputs!$C$22/2,0)+IF(H$3=Loyalty_Inputs!$C$8,Loyalty_Inputs!$C$23,0) -> 0 | I8: =IF(I$3>=Loyalty_Inputs!$C$10,Loyalty_Inputs!$C$21,0)+IF(OR(I$3=Loyalty_Inputs!$C$10,I$3=Loyalty_Inputs!$C$10+1),Loyalty_Inputs!$C$22/2,0)+IF(I$3=Loyalty_Inputs!$C$8,Loyalty_Inputs!$C$23,0) -> 0 | J8: =IF(J$3>=Loyalty_Inputs!$C$10,Loyalty_Inputs!$C$21,0)+IF(OR(J$3=Loyalty_Inputs!$C$10,J$3=Loyalty_Inputs!$C$10+1),Loyalty_Inputs!$C$22/2,0)+IF(J$3=Loyalty_Inputs!$C$8,Loyalty_Inputs!$C$23,0) -> 0 | ... AL8: =IF(AL$3>=Loyalty_Inputs!$C$10,Loyalty_Inputs!$C$21,0)+IF(OR(AL$3=Loyalty_Inputs!$C$10,AL$3=Loyalty_Inputs!$C$10+1),Loyalty_Inputs!$C$22/2,0)+IF(AL$3=Loyalty_Inputs!$C$8,Loyalty_Inputs!$C$23,0) -> 150000000
A9: Кэшбэк (себестоимость погашений) | B9: c_cb | C9: =C4*Loyalty_Inputs!$C$12*Loyalty_Inputs!$C$48*(1-Loyalty_Inputs!$C$13)*Loyalty_Inputs!$C$14 -> 0 | D9: =D4*Loyalty_Inputs!$C$12*Loyalty_Inputs!$C$48*(1-Loyalty_Inputs!$C$13)*Loyalty_Inputs!$C$14 -> 0 | E9: =E4*Loyalty_Inputs!$C$12*Loyalty_Inputs!$C$48*(1-Loyalty_Inputs!$C$13)*Loyalty_Inputs!$C$14 -> 0 | F9: =F4*Loyalty_Inputs!$C$12*Loyalty_Inputs!$C$48*(1-Loyalty_Inputs!$C$13)*Loyalty_Inputs!$C$14 -> 0 | G9: =G4*Loyalty_Inputs!$C$12*Loyalty_Inputs!$C$48*(1-Loyalty_Inputs!$C$13)*Loyalty_Inputs!$C$14 -> 84665228 | H9: =H4*Loyalty_Inputs!$C$12*Loyalty_Inputs!$C$48*(1-Loyalty_Inputs!$C$13)*Loyalty_Inputs!$C$14 -> 84665228 | I9: =I4*Loyalty_Inputs!$C$12*Loyalty_Inputs!$C$48*(1-Loyalty_Inputs!$C$13)*Loyalty_Inputs!$C$14 -> 84665228 | J9: =J4*Loyalty_Inputs!$C$12*Loyalty_Inputs!$C$48*(1-Loyalty_Inputs!$C$13)*Loyalty_Inputs!$C$14 -> 84665228 | ... AL9: =AL4*Loyalty_Inputs!$C$12*Loyalty_Inputs!$C$48*(1-Loyalty_Inputs!$C$13)*Loyalty_Inputs!$C$14 -> 8.3818575e+08
A10: Daily Drops — цифровые | B10: c_dd | C10: =C4*Loyalty_Inputs!$C$15*30*Daily_Drops!$D$10 -> 0 | D10: =D4*Loyalty_Inputs!$C$15*30*Daily_Drops!$D$10 -> 0 | E10: =E4*Loyalty_Inputs!$C$15*30*Daily_Drops!$D$10 -> 0 | F10: =F4*Loyalty_Inputs!$C$15*30*Daily_Drops!$D$10 -> 0 | G10: =G4*Loyalty_Inputs!$C$15*30*Daily_Drops!$D$10 -> 70875000 | H10: =H4*Loyalty_Inputs!$C$15*30*Daily_Drops!$D$10 -> 70875000 | I10: =I4*Loyalty_Inputs!$C$15*30*Daily_Drops!$D$10 -> 70875000 | J10: =J4*Loyalty_Inputs!$C$15*30*Daily_Drops!$D$10 -> 70875000 | ... AL10: =AL4*Loyalty_Inputs!$C$15*30*Daily_Drops!$D$10 -> 701662500
A11: Daily Drops — инвентарь | B11: c_inv | C11: =Prizes!$E$45*52/12*C5 -> 0 | D11: =Prizes!$E$45*52/12*D5 -> 0 | E11: =Prizes!$E$45*52/12*E5 -> 0 | F11: =Prizes!$E$45*52/12*F5 -> 0 | G11: =Prizes!$E$45*52/12*G5 -> 116740000 | H11: =Prizes!$E$45*52/12*H5 -> 116740000 | I11: =Prizes!$E$45*52/12*I5 -> 116740000 | J11: =Prizes!$E$45*52/12*J5 -> 116740000 | ... AL11: =Prizes!$E$45*52/12*AL5 -> 3.8913333e+08
A12: Weekly Wins | B12: c_ww | C12: =Prizes!$E$34*52/12*C5 -> 0 | D12: =Prizes!$E$34*52/12*D5 -> 0 | E12: =Prizes!$E$34*52/12*E5 -> 0 | F12: =Prizes!$E$34*52/12*F5 -> 0 | G12: =Prizes!$E$34*52/12*G5 -> 59995000 | H12: =Prizes!$E$34*52/12*H5 -> 59995000 | I12: =Prizes!$E$34*52/12*I5 -> 59995000 | J12: =Prizes!$E$34*52/12*J5 -> 59995000 | ... AL12: =Prizes!$E$34*52/12*AL5 -> 1.9998333e+08
A13: Monthly Grand | B13: c_gr | C13: =Prizes!$C$64*C5 -> 0 | D13: =Prizes!$C$64*D5 -> 0 | E13: =Prizes!$C$64*E5 -> 0 | F13: =Prizes!$C$64*F5 -> 0 | G13: =Prizes!$C$64*G5 -> 27777750 | H13: =Prizes!$C$64*H5 -> 27777750 | I13: =Prizes!$C$64*I5 -> 27777750 | J13: =Prizes!$C$64*J5 -> 27777750 | ... AL13: =Prizes!$C$64*AL5 -> 92592500
A14: ЗАТРАТЫ ВСЕГО | B14: cost | C14: =SUM(C6:C13) -> 0 | D14: =SUM(D6:D13) -> 600000000 | E14: =SUM(E6:E13) -> 600000000 | F14: =SUM(F6:F13) -> 600000000 | G14: =SUM(G6:G13) -> 7.3005298e+08 | H14: =SUM(H6:H13) -> 4.8005298e+08 | I14: =SUM(I6:I13) -> 4.8005298e+08 | J14: =SUM(J6:J13) -> 1.480053e+09 | ... AL14: =SUM(AL6:AL13) -> 2.6215574e+09
A15: Удержанные участники | B15: R | C15: =N(B15)*(1-Loyalty_Inputs!$C$24)+N(B4)*Loyalty_Inputs!$C$24*Loyalty_Inputs!$C$25 -> 0 | D15: =N(C15)*(1-Loyalty_Inputs!$C$24)+N(C4)*Loyalty_Inputs!$C$24*Loyalty_Inputs!$C$25 -> 0 | E15: =N(D15)*(1-Loyalty_Inputs!$C$24)+N(D4)*Loyalty_Inputs!$C$24*Loyalty_Inputs!$C$25 -> 0 | F15: =N(E15)*(1-Loyalty_Inputs!$C$24)+N(E4)*Loyalty_Inputs!$C$24*Loyalty_Inputs!$C$25 -> 0 | G15: =N(F15)*(1-Loyalty_Inputs!$C$24)+N(F4)*Loyalty_Inputs!$C$24*Loyalty_Inputs!$C$25 -> 0 | H15: =N(G15)*(1-Loyalty_Inputs!$C$24)+N(G4)*Loyalty_Inputs!$C$24*Loyalty_Inputs!$C$25 -> 270 | I15: =N(H15)*(1-Loyalty_Inputs!$C$24)+N(H4)*Loyalty_Inputs!$C$24*Loyalty_Inputs!$C$25 -> 536.76 | J15: =N(I15)*(1-Loyalty_Inputs!$C$24)+N(I4)*Loyalty_Inputs!$C$24*Loyalty_Inputs!$C$25 -> 800.31888 | ... AL15: =N(AK15)*(1-Loyalty_Inputs!$C$24)+N(AK4)*Loyalty_Inputs!$C$24*Loyalty_Inputs!$C$25 -> 54111.18
A16: Выручка: удержание | B16: b_ret | C16: =C15*Loyalty_Inputs!$C$47 -> 0 | D16: =D15*Loyalty_Inputs!$C$47 -> 0 | E16: =E15*Loyalty_Inputs!$C$47 -> 0 | F16: =F15*Loyalty_Inputs!$C$47 -> 0 | G16: =G15*Loyalty_Inputs!$C$47 -> 0 | H16: =H15*Loyalty_Inputs!$C$47 -> 11860714 | I16: =I15*Loyalty_Inputs!$C$47 -> 23579100 | J16: =J15*Loyalty_Inputs!$C$47 -> 35156865 | ... AL16: =AL15*Loyalty_Inputs!$C$47 -> 2.3770268e+09
A17: Выручка: оплаты вовремя | B17: b_ont | C17: =C4*Loyalty_Inputs!$C$47*Loyalty_Inputs!$C$26 -> 0 | D17: =D4*Loyalty_Inputs!$C$47*Loyalty_Inputs!$C$26 -> 0 | E17: =E4*Loyalty_Inputs!$C$47*Loyalty_Inputs!$C$26 -> 0 | F17: =F4*Loyalty_Inputs!$C$47*Loyalty_Inputs!$C$26 -> 0 | G17: =G4*Loyalty_Inputs!$C$47*Loyalty_Inputs!$C$26 -> 98839286 | H17: =H4*Loyalty_Inputs!$C$47*Loyalty_Inputs!$C$26 -> 98839286 | I17: =I4*Loyalty_Inputs!$C$47*Loyalty_Inputs!$C$26 -> 98839286 | J17: =J4*Loyalty_Inputs!$C$47*Loyalty_Inputs!$C$26 -> 98839286 | ... AL17: =AL4*Loyalty_Inputs!$C$47*Loyalty_Inputs!$C$26 -> 9.7850893e+08
A18: Накопленные переходы на ТП ≥ 60 тыс. | B18: U | C18: =N(B18)*(1-Loyalty_Inputs!$C$24)+C4*Loyalty_Inputs!$C$50*Loyalty_Inputs!$C$27 -> 0 | D18: =N(C18)*(1-Loyalty_Inputs!$C$24)+D4*Loyalty_Inputs!$C$50*Loyalty_Inputs!$C$27 -> 0 | E18: =N(D18)*(1-Loyalty_Inputs!$C$24)+E4*Loyalty_Inputs!$C$50*Loyalty_Inputs!$C$27 -> 0 | F18: =N(E18)*(1-Loyalty_Inputs!$C$24)+F4*Loyalty_Inputs!$C$50*Loyalty_Inputs!$C$27 -> 0 | G18: =N(F18)*(1-Loyalty_Inputs!$C$24)+G4*Loyalty_Inputs!$C$50*Loyalty_Inputs!$C$27 -> 420 | H18: =N(G18)*(1-Loyalty_Inputs!$C$24)+H4*Loyalty_Inputs!$C$50*Loyalty_Inputs!$C$27 -> 834.96 | I18: =N(H18)*(1-Loyalty_Inputs!$C$24)+I4*Loyalty_Inputs!$C$50*Loyalty_Inputs!$C$27 -> 1244.9405 | J18: =N(I18)*(1-Loyalty_Inputs!$C$24)+J4*Loyalty_Inputs!$C$50*Loyalty_Inputs!$C$27 -> 1650.0012 | ... AL18: =N(AK18)*(1-Loyalty_Inputs!$C$24)+AL4*Loyalty_Inputs!$C$50*Loyalty_Inputs!$C$27 -> 87320.871
A19: Выручка: переходы | B19: b_upg | C19: =C18*Loyalty_Inputs!$C$28 -> 0 | D19: =D18*Loyalty_Inputs!$C$28 -> 0 | E19: =E18*Loyalty_Inputs!$C$28 -> 0 | F19: =F18*Loyalty_Inputs!$C$28 -> 0 | G19: =G18*Loyalty_Inputs!$C$28 -> 8400000 | H19: =H18*Loyalty_Inputs!$C$28 -> 16699200 | I19: =I18*Loyalty_Inputs!$C$28 -> 24898810 | J19: =J18*Loyalty_Inputs!$C$28 -> 33000024 | ... AL19: =AL18*Loyalty_Inputs!$C$28 -> 1.7464174e+09
A20: Club+ Pass (net) | B20: b_pass | C20: =C4*Loyalty_Inputs!$C$50*Loyalty_Inputs!$C$29*Loyalty_Inputs!$C$54 -> 0 | D20: =D4*Loyalty_Inputs!$C$50*Loyalty_Inputs!$C$29*Loyalty_Inputs!$C$54 -> 0 | E20: =E4*Loyalty_Inputs!$C$50*Loyalty_Inputs!$C$29*Loyalty_Inputs!$C$54 -> 0 | F20: =F4*Loyalty_Inputs!$C$50*Loyalty_Inputs!$C$29*Loyalty_Inputs!$C$54 -> 0 | G20: =G4*Loyalty_Inputs!$C$50*Loyalty_Inputs!$C$29*Loyalty_Inputs!$C$54 -> 28122188 | H20: =H4*Loyalty_Inputs!$C$50*Loyalty_Inputs!$C$29*Loyalty_Inputs!$C$54 -> 28122188 | I20: =I4*Loyalty_Inputs!$C$50*Loyalty_Inputs!$C$29*Loyalty_Inputs!$C$54 -> 28122188 | J20: =J4*Loyalty_Inputs!$C$50*Loyalty_Inputs!$C$29*Loyalty_Inputs!$C$54 -> 28122188 | ... AL20: =AL4*Loyalty_Inputs!$C$50*Loyalty_Inputs!$C$29*Loyalty_Inputs!$C$54 -> 2.7840966e+08
A21: Выручка: допродажи | B21: b_eng | C21: =C4*Loyalty_Inputs!$C$47*Loyalty_Inputs!$C$32*Loyalty_Inputs!$C$15/0.3 -> 0 | D21: =D4*Loyalty_Inputs!$C$47*Loyalty_Inputs!$C$32*Loyalty_Inputs!$C$15/0.3 -> 0 | E21: =E4*Loyalty_Inputs!$C$47*Loyalty_Inputs!$C$32*Loyalty_Inputs!$C$15/0.3 -> 0 | F21: =F4*Loyalty_Inputs!$C$47*Loyalty_Inputs!$C$32*Loyalty_Inputs!$C$15/0.3 -> 0 | G21: =G4*Loyalty_Inputs!$C$47*Loyalty_Inputs!$C$32*Loyalty_Inputs!$C$15/0.3 -> 52714286 | H21: =H4*Loyalty_Inputs!$C$47*Loyalty_Inputs!$C$32*Loyalty_Inputs!$C$15/0.3 -> 52714286 | I21: =I4*Loyalty_Inputs!$C$47*Loyalty_Inputs!$C$32*Loyalty_Inputs!$C$15/0.3 -> 52714286 | J21: =J4*Loyalty_Inputs!$C$47*Loyalty_Inputs!$C$32*Loyalty_Inputs!$C$15/0.3 -> 52714286 | ... AL21: =AL4*Loyalty_Inputs!$C$47*Loyalty_Inputs!$C$32*Loyalty_Inputs!$C$15/0.3 -> 5.2187143e+08
A22: Партнёры (платные размещения) | B22: b_par | C22: =IF(C$3>=Loyalty_Inputs!$C$10+6,Loyalty_Inputs!$C$33,0) -> 0 | D22: =IF(D$3>=Loyalty_Inputs!$C$10+6,Loyalty_Inputs!$C$33,0) -> 0 | E22: =IF(E$3>=Loyalty_Inputs!$C$10+6,Loyalty_Inputs!$C$33,0) -> 0 | F22: =IF(F$3>=Loyalty_Inputs!$C$10+6,Loyalty_Inputs!$C$33,0) -> 0 | G22: =IF(G$3>=Loyalty_Inputs!$C$10+6,Loyalty_Inputs!$C$33,0) -> 0 | H22: =IF(H$3>=Loyalty_Inputs!$C$10+6,Loyalty_Inputs!$C$33,0) -> 0 | I22: =IF(I$3>=Loyalty_Inputs!$C$10+6,Loyalty_Inputs!$C$33,0) -> 0 | J22: =IF(J$3>=Loyalty_Inputs!$C$10+6,Loyalty_Inputs!$C$33,0) -> 0 | ... AL22: =IF(AL$3>=Loyalty_Inputs!$C$10+6,Loyalty_Inputs!$C$33,0) -> 50000000
A23: ВКЛАД | B23: contrib | C23: =(C16+C17+C19+C21)*Loyalty_Inputs!$C$34+C20*(1-Loyalty_Inputs!$C$31)+C22-C14 -> 0 | D23: =(D16+D17+D19+D21)*Loyalty_Inputs!$C$34+D20*(1-Loyalty_Inputs!$C$31)+D22-D14 -> -600000000 | E23: =(E16+E17+E19+E21)*Loyalty_Inputs!$C$34+E20*(1-Loyalty_Inputs!$C$31)+E22-E14 -> -600000000 | F23: =(F16+F17+F19+F21)*Loyalty_Inputs!$C$34+F20*(1-Loyalty_Inputs!$C$31)+F22-F14 -> -600000000 | G23: =(G16+G17+G19+G21)*Loyalty_Inputs!$C$34+G20*(1-Loyalty_Inputs!$C$31)+G22-G14 -> -5.730008e+08 | H23: =(H16+H17+H19+H21)*Loyalty_Inputs!$C$34+H20*(1-Loyalty_Inputs!$C$31)+H22-H14 -> -3.0586487e+08 | I23: =(I16+I17+I19+I21)*Loyalty_Inputs!$C$34+I20*(1-Loyalty_Inputs!$C$31)+I22-I14 -> -2.8893458e+08 | J23: =(J16+J17+J19+J21)*Loyalty_Inputs!$C$34+J20*(1-Loyalty_Inputs!$C$31)+J22-J14 -> -1.2722074e+09 | ... AL23: =(AL16+AL17+AL19+AL21)*Loyalty_Inputs!$C$34+AL20*(1-Loyalty_Inputs!$C$31)+AL22-AL14 -> 2.4175007e+09
A24: Вклад накопленный | B24: cum | C24: =N(B24)+C23 -> 0 | D24: =N(C24)+D23 -> -600000000 | E24: =N(D24)+E23 -> -1200000000 | F24: =N(E24)+F23 -> -1800000000 | G24: =N(F24)+G23 -> -2.3730008e+09 | H24: =N(G24)+H23 -> -2.6788657e+09 | I24: =N(H24)+I23 -> -2.9678003e+09 | J24: =N(I24)+J23 -> -4.2400077e+09 | ... AL24: =N(AK24)+AL23 -> 1.0253742e+10
A25: Архивные участники | B25: am | C25: =C4*Loyalty_Inputs!$C$6 -> 0 | D25: =D4*Loyalty_Inputs!$C$6 -> 0 | E25: =E4*Loyalty_Inputs!$C$6 -> 0 | F25: =F4*Loyalty_Inputs!$C$6 -> 0 | G25: =G4*Loyalty_Inputs!$C$6 -> 30000 | H25: =H4*Loyalty_Inputs!$C$6 -> 30000 | I25: =I4*Loyalty_Inputs!$C$6 -> 30000 | J25: =J4*Loyalty_Inputs!$C$6 -> 30000 | ... AL25: =AL4*Loyalty_Inputs!$C$6 -> 297000
A26: Архивные: удержанные | B26: Ra | C26: =N(B26)*(1-Loyalty_Inputs!$C$36)+N(B25)*Loyalty_Inputs!$C$36*Loyalty_Inputs!$C$25 -> 0 | D26: =N(C26)*(1-Loyalty_Inputs!$C$36)+N(C25)*Loyalty_Inputs!$C$36*Loyalty_Inputs!$C$25 -> 0 | E26: =N(D26)*(1-Loyalty_Inputs!$C$36)+N(D25)*Loyalty_Inputs!$C$36*Loyalty_Inputs!$C$25 -> 0 | F26: =N(E26)*(1-Loyalty_Inputs!$C$36)+N(E25)*Loyalty_Inputs!$C$36*Loyalty_Inputs!$C$25 -> 0 | G26: =N(F26)*(1-Loyalty_Inputs!$C$36)+N(F25)*Loyalty_Inputs!$C$36*Loyalty_Inputs!$C$25 -> 0 | H26: =N(G26)*(1-Loyalty_Inputs!$C$36)+N(G25)*Loyalty_Inputs!$C$36*Loyalty_Inputs!$C$25 -> 67.5 | I26: =N(H26)*(1-Loyalty_Inputs!$C$36)+N(H25)*Loyalty_Inputs!$C$36*Loyalty_Inputs!$C$25 -> 133.9875 | J26: =N(I26)*(1-Loyalty_Inputs!$C$36)+N(I25)*Loyalty_Inputs!$C$36*Loyalty_Inputs!$C$25 -> 199.47769 | ... AL26: =N(AK26)*(1-Loyalty_Inputs!$C$36)+N(AK25)*Loyalty_Inputs!$C$36*Loyalty_Inputs!$C$25 -> 13099.231
A27: Архивные: перешли на актуальный ТП | B27: Ua | C27: =N(B27)*(1-Loyalty_Inputs!$C$36)+C25*Loyalty_Inputs!$C$37 -> 0 | D27: =N(C27)*(1-Loyalty_Inputs!$C$36)+D25*Loyalty_Inputs!$C$37 -> 0 | E27: =N(D27)*(1-Loyalty_Inputs!$C$36)+E25*Loyalty_Inputs!$C$37 -> 0 | F27: =N(E27)*(1-Loyalty_Inputs!$C$36)+F25*Loyalty_Inputs!$C$37 -> 0 | G27: =N(F27)*(1-Loyalty_Inputs!$C$36)+G25*Loyalty_Inputs!$C$37 -> 120 | H27: =N(G27)*(1-Loyalty_Inputs!$C$36)+H25*Loyalty_Inputs!$C$37 -> 238.2 | I27: =N(H27)*(1-Loyalty_Inputs!$C$36)+I25*Loyalty_Inputs!$C$37 -> 354.627 | J27: =N(I27)*(1-Loyalty_Inputs!$C$36)+J25*Loyalty_Inputs!$C$37 -> 469.30759 | ... AL27: =N(AK27)*(1-Loyalty_Inputs!$C$36)+AL25*Loyalty_Inputs!$C$37 -> 24126.209
A28: Архивные: погашение счёта монетами | B28: contra | C28: =C25*Loyalty_Inputs!$C$12*Loyalty_Inputs!$C$51*(1-Loyalty_Inputs!$C$13)*0.3 -> 0 | D28: =D25*Loyalty_Inputs!$C$12*Loyalty_Inputs!$C$51*(1-Loyalty_Inputs!$C$13)*0.3 -> 0 | E28: =E25*Loyalty_Inputs!$C$12*Loyalty_Inputs!$C$51*(1-Loyalty_Inputs!$C$13)*0.3 -> 0 | F28: =F25*Loyalty_Inputs!$C$12*Loyalty_Inputs!$C$51*(1-Loyalty_Inputs!$C$13)*0.3 -> 0 | G28: =G25*Loyalty_Inputs!$C$12*Loyalty_Inputs!$C$51*(1-Loyalty_Inputs!$C$13)*0.3 -> 4624042.5 | H28: =H25*Loyalty_Inputs!$C$12*Loyalty_Inputs!$C$51*(1-Loyalty_Inputs!$C$13)*0.3 -> 4624042.5 | I28: =I25*Loyalty_Inputs!$C$12*Loyalty_Inputs!$C$51*(1-Loyalty_Inputs!$C$13)*0.3 -> 4624042.5 | J28: =J25*Loyalty_Inputs!$C$12*Loyalty_Inputs!$C$51*(1-Loyalty_Inputs!$C$13)*0.3 -> 4624042.5 | ... AL28: =AL25*Loyalty_Inputs!$C$12*Loyalty_Inputs!$C$51*(1-Loyalty_Inputs!$C$13)*0.3 -> 45778021
A29: Архивные: доп. выручка | B29: a_rev | C29: =C26*Loyalty_Inputs!$C$35+C27*Loyalty_Inputs!$C$38+C25*Loyalty_Inputs!$C$35*Loyalty_Inputs!$C$26+C25*Loyalty_Inputs!$C$52*Loyalty_Inputs!$C$29*Loyalty_Inputs!$C$54+C25*Loyalty_Inputs!$C$35*Loyalty_Inputs!$C$32*Loyalty_Inputs!$C$15/0.3-C28 -> 0 | D29: =D26*Loyalty_Inputs!$C$35+D27*Loyalty_Inputs!$C$38+D25*Loyalty_Inputs!$C$35*Loyalty_Inputs!$C$26+D25*Loyalty_Inputs!$C$52*Loyalty_Inputs!$C$29*Loyalty_Inputs!$C$54+D25*Loyalty_Inputs!$C$35*Loyalty_Inputs!$C$32*Loyalty_Inputs!$C$15/0.3-D28 -> 0 | E29: =E26*Loyalty_Inputs!$C$35+E27*Loyalty_Inputs!$C$38+E25*Loyalty_Inputs!$C$35*Loyalty_Inputs!$C$26+E25*Loyalty_Inputs!$C$52*Loyalty_Inputs!$C$29*Loyalty_Inputs!$C$54+E25*Loyalty_Inputs!$C$35*Loyalty_Inputs!$C$32*Loyalty_Inputs!$C$15/0.3-E28 -> 0 | F29: =F26*Loyalty_Inputs!$C$35+F27*Loyalty_Inputs!$C$38+F25*Loyalty_Inputs!$C$35*Loyalty_Inputs!$C$26+F25*Loyalty_Inputs!$C$52*Loyalty_Inputs!$C$29*Loyalty_Inputs!$C$54+F25*Loyalty_Inputs!$C$35*Loyalty_Inputs!$C$32*Loyalty_Inputs!$C$15/0.3-F28 -> 0 | G29: =G26*Loyalty_Inputs!$C$35+G27*Loyalty_Inputs!$C$38+G25*Loyalty_Inputs!$C$35*Loyalty_Inputs!$C$26+G25*Loyalty_Inputs!$C$52*Loyalty_Inputs!$C$29*Loyalty_Inputs!$C$54+G25*Loyalty_Inputs!$C$35*Loyalty_Inputs!$C$32*Loyalty_Inputs!$C$15/0.3-G28 -> 19789821 | H29: =H26*Loyalty_Inputs!$C$35+H27*Loyalty_Inputs!$C$38+H25*Loyalty_Inputs!$C$35*Loyalty_Inputs!$C$26+H25*Loyalty_Inputs!$C$52*Loyalty_Inputs!$C$29*Loyalty_Inputs!$C$54+H25*Loyalty_Inputs!$C$35*Loyalty_Inputs!$C$32*Loyalty_Inputs!$C$15/0.3-H28 -> 22693221 | I29: =I26*Loyalty_Inputs!$C$35+I27*Loyalty_Inputs!$C$38+I25*Loyalty_Inputs!$C$35*Loyalty_Inputs!$C$26+I25*Loyalty_Inputs!$C$52*Loyalty_Inputs!$C$29*Loyalty_Inputs!$C$54+I25*Loyalty_Inputs!$C$35*Loyalty_Inputs!$C$32*Loyalty_Inputs!$C$15/0.3-I28 -> 25553070 | J29: =J26*Loyalty_Inputs!$C$35+J27*Loyalty_Inputs!$C$38+J25*Loyalty_Inputs!$C$35*Loyalty_Inputs!$C$26+J25*Loyalty_Inputs!$C$52*Loyalty_Inputs!$C$29*Loyalty_Inputs!$C$54+J25*Loyalty_Inputs!$C$35*Loyalty_Inputs!$C$32*Loyalty_Inputs!$C$15/0.3-J28 -> 28370021 | ... AL29: =AL26*Loyalty_Inputs!$C$35+AL27*Loyalty_Inputs!$C$38+AL25*Loyalty_Inputs!$C$35*Loyalty_Inputs!$C$26+AL25*Loyalty_Inputs!$C$52*Loyalty_Inputs!$C$29*Loyalty_Inputs!$C$54+AL25*Loyalty_Inputs!$C$35*Loyalty_Inputs!$C$32*Loyalty_Inputs!$C$15/0.3-AL28 -> 7.5936083e+08
A30: Архивные: Δ абонентов | B30: a_ds | C30: =C26 -> 0 | D30: =D26 -> 0 | E30: =E26 -> 0 | F30: =F26 -> 0 | G30: =G26 -> 0 | H30: =H26 -> 67.5 | I30: =I26 -> 133.9875 | J30: =J26 -> 199.47769 | ... AL30: =AL26 -> 13099.231

Sheet MVP_Budget
A1: Бюджет MVP Loyalty (разработка дек–фев + 3 мес. пилота мар–май 2027)
A3: Статья | B3: Сум | C3: USD | D3: Доля
A4: Разработка MVP (web-view в приложении, CRM, антифрод) | B4: =SUM(Loyalty_Monthly!C6:I6) -> 1800000000 | C4: =B4/Inputs!$C$11 -> 148760.33 | D4: =B4/B12 -> 0.51573583
A5: Операционные (команда, фулфилмент, КЦ) | B5: =SUM(Loyalty_Monthly!C7:I7) -> 360000000 | C5: =B5/Inputs!$C$11 -> 29752.066 | D5: =B5/B12 -> 0.10314717
A6: Маркетинг MVP | B6: =SUM(Loyalty_Monthly!C8:I8) -> 250000000 | C6: =B6/Inputs!$C$11 -> 20661.157 | D6: =B6/B12 -> 0.071629976
A7: Кэшбэк | B7: =SUM(Loyalty_Monthly!C9:I9) -> 2.5399568e+08 | C7: =B7/Inputs!$C$11 -> 20991.379 | D7: =B7/B12 -> 0.072774818
A8: Daily Drops — цифровые призы | B8: =SUM(Loyalty_Monthly!C10:I10) -> 212625000 | C8: =B8/Inputs!$C$11 -> 17572.314 | D8: =B8/B12 -> 0.060921294
A9: Daily Drops — инвентарь | B9: =SUM(Loyalty_Monthly!C11:I11) -> 350220000 | C9: =B9/Inputs!$C$11 -> 28943.802 | D9: =B9/B12 -> 0.100345
A10: Weekly Wins | B10: =SUM(Loyalty_Monthly!C12:I12) -> 179985000 | C10: =B10/Inputs!$C$11 -> 14874.793 | D10: =B10/B12 -> 0.051569285
A11: Monthly Grand (1 розыгрыш) | B11: =SUM(Loyalty_Monthly!C13:I13) -> 83333250 | C11: =B11/Inputs!$C$11 -> 6887.0455 | D11: =B11/B12 -> 0.023876635
A12: ИТОГО MVP | B12: =SUM(B4:B11) -> 3.4901589e+09 | C12: =B12/Inputs!$C$11 -> 288442.89
A13: На одного участника MVP, сум | B13: =B12/Loyalty_Inputs!$C$7 -> 23267.726
A14: Без разработки (стоимость самого теста), сум | B14: =B12-B4 -> 1.6901589e+09

Sheet Thresholds
A1: Порог участия в Weekly/Monthly: сравнение вариантов (стационарный режим масштаба, сум/мес)
A2: Кэшбэк, Daily Drops и OPEX одинаковы во всех вариантах и сюда не входят. Поведенческие параметры — гипотезы; O2 и O5 тестируются двумя ветками MVP.
A4: Вариант | B4: Описание | C4: Доля < 60 тыс., которые играют | D4: Вовлечённость < 60 тыс. | E4: Переходы на ≥ 60 тыс./мес | F4: Club+ Pass: доля | G4: Цена Pass, с НДС | H4: Платный вход: доля | I4: Цена входа (средн.), с НДС | J4: P(запрет/предписание) | K4: Коэф. переходов архивных | L4: Удержание | M4: Переходы | N4: Pass | O4: Платный вход | P4: Призы W+M | Q4: ЧИСТЫЙ ЭФФЕКТ | R4: С учётом риска | S4: Играют всего | T4: Архивных играют | U4: Шанс выиграть за неделю | V4: Юр. риск | W4: PR-риск
A5: O1 | B5: Открыто всем (без порога) | C5: 1 | D5: 1 | E5: 0.002 | F5: 0 | G5: 0 | H5: 0 | I5: 0 | J5: 0.02 | K5: 0.5 | L5: =Loyalty_Inputs!$C$53*Loyalty_Inputs!$C$24*Loyalty_Inputs!$C$25*((1-Loyalty_Inputs!$C$50)+Loyalty_Inputs!$C$50*D5)*(1-(1-Loyalty_Inputs!$C$24)^12)/Loyalty_Inputs!$C$24*Loyalty_Inputs!$C$47*Loyalty_Inputs!$C$34 -> 1.1217252e+09 | M5: =Loyalty_Inputs!$C$53*Loyalty_Inputs!$C$50*E5*(1-(1-Loyalty_Inputs!$C$24)^12)/Loyalty_Inputs!$C$24*Loyalty_Inputs!$C$28*Loyalty_Inputs!$C$34 -> 3.9721435e+08 | N5: =Loyalty_Inputs!$C$53*Loyalty_Inputs!$C$50*F5*G5/(1+Inputs!$C$10)*(1-Loyalty_Inputs!$C$31) -> 0 | O5: =Loyalty_Inputs!$C$53*Loyalty_Inputs!$C$50*H5*I5/(1+Inputs!$C$10) -> 0 | P5: =-(Prizes!$E$34*52/12+Prizes!$C$64) -> -2.9257583e+08 | Q5: =SUM(L5:P5) -> 1.2263637e+09 | R5: =Q5*(1-J5) -> 1.2018365e+09 | S5: =Loyalty_Inputs!$C$53*((1-Loyalty_Inputs!$C$50)+Loyalty_Inputs!$C$50*C5) -> 1485000 | T5: =0.03+0.97*C5 -> 1 | U5: =IF(S5>0,Prizes!$C$34/S5,0) -> 0.00091178451 | V5: низкий | W5: низкий
A6: O2 | B6: Weekly/Monthly только АП ≥ 60 тыс. и оплата вовремя | C6: 0 | D6: 0.7 | E6: 0.0036 | F6: 0 | G6: 0 | H6: 0 | I6: 0 | J6: 0.03 | K6: 0.8 | L6: =Loyalty_Inputs!$C$53*Loyalty_Inputs!$C$24*Loyalty_Inputs!$C$25*((1-Loyalty_Inputs!$C$50)+Loyalty_Inputs!$C$50*D6)*(1-(1-Loyalty_Inputs!$C$24)^12)/Loyalty_Inputs!$C$24*Loyalty_Inputs!$C$47*Loyalty_Inputs!$C$34 -> 8.8616293e+08 | M6: =Loyalty_Inputs!$C$53*Loyalty_Inputs!$C$50*E6*(1-(1-Loyalty_Inputs!$C$24)^12)/Loyalty_Inputs!$C$24*Loyalty_Inputs!$C$28*Loyalty_Inputs!$C$34 -> 7.1498583e+08 | N6: =Loyalty_Inputs!$C$53*Loyalty_Inputs!$C$50*F6*G6/(1+Inputs!$C$10)*(1-Loyalty_Inputs!$C$31) -> 0 | O6: =Loyalty_Inputs!$C$53*Loyalty_Inputs!$C$50*H6*I6/(1+Inputs!$C$10) -> 0 | P6: =-(Prizes!$E$34*52/12+Prizes!$C$64) -> -2.9257583e+08 | Q6: =SUM(L6:P6) -> 1.3085729e+09 | R6: =Q6*(1-J6) -> 1.2693157e+09 | S6: =Loyalty_Inputs!$C$53*((1-Loyalty_Inputs!$C$50)+Loyalty_Inputs!$C$50*C6) -> 445500 | T6: =0.03+0.97*C6 -> 0.03 | U6: =IF(S6>0,Prizes!$C$34/S6,0) -> 0.0030392817 | V6: низкий | W6: средний
A7: O3 | B7: Weekly/Monthly только АП ≥ 80 тыс. | C7: 0 | D7: 0.6 | E7: 0.0024 | F7: 0 | G7: 0 | H7: 0 | I7: 0 | J7: 0.05 | K7: 0.6 | L7: =Loyalty_Inputs!$C$53*Loyalty_Inputs!$C$24*Loyalty_Inputs!$C$25*((1-Loyalty_Inputs!$C$50)+Loyalty_Inputs!$C$50*D7)*(1-(1-Loyalty_Inputs!$C$24)^12)/Loyalty_Inputs!$C$24*Loyalty_Inputs!$C$47*Loyalty_Inputs!$C$34 -> 8.0764216e+08 | M7: =Loyalty_Inputs!$C$53*Loyalty_Inputs!$C$50*E7*(1-(1-Loyalty_Inputs!$C$24)^12)/Loyalty_Inputs!$C$24*Loyalty_Inputs!$C$28*Loyalty_Inputs!$C$34 -> 4.7665722e+08 | N7: =Loyalty_Inputs!$C$53*Loyalty_Inputs!$C$50*F7*G7/(1+Inputs!$C$10)*(1-Loyalty_Inputs!$C$31) -> 0 | O7: =Loyalty_Inputs!$C$53*Loyalty_Inputs!$C$50*H7*I7/(1+Inputs!$C$10) -> 0 | P7: =-(Prizes!$E$34*52/12+Prizes!$C$64) -> -2.9257583e+08 | Q7: =SUM(L7:P7) -> 9.9172355e+08 | R7: =Q7*(1-J7) -> 9.4213737e+08 | S7: =Loyalty_Inputs!$C$53*((1-Loyalty_Inputs!$C$50)+Loyalty_Inputs!$C$50*C7) -> 445500 | T7: =0.03+0.97*C7 -> 0.03 | U7: =IF(S7>0,Prizes!$C$34/S7,0) -> 0.0030392817 | V7: низкий | W7: высокий
A8: O4 | B8: Порог 60 тыс. + платный вход 4 999 / 9 999 сум для остальных | C8: 0.04 | D8: 0.8 | E8: 0.0028 | F8: 0 | G8: 0 | H8: 0.04 | I8: 7500 | J8: 0.4 | K8: 0.7 | L8: =Loyalty_Inputs!$C$53*Loyalty_Inputs!$C$24*Loyalty_Inputs!$C$25*((1-Loyalty_Inputs!$C$50)+Loyalty_Inputs!$C$50*D8)*(1-(1-Loyalty_Inputs!$C$24)^12)/Loyalty_Inputs!$C$24*Loyalty_Inputs!$C$47*Loyalty_Inputs!$C$34 -> 9.6468369e+08 | M8: =Loyalty_Inputs!$C$53*Loyalty_Inputs!$C$50*E8*(1-(1-Loyalty_Inputs!$C$24)^12)/Loyalty_Inputs!$C$24*Loyalty_Inputs!$C$28*Loyalty_Inputs!$C$34 -> 5.5610009e+08 | N8: =Loyalty_Inputs!$C$53*Loyalty_Inputs!$C$50*F8*G8/(1+Inputs!$C$10)*(1-Loyalty_Inputs!$C$31) -> 0 | O8: =Loyalty_Inputs!$C$53*Loyalty_Inputs!$C$50*H8*I8/(1+Inputs!$C$10) -> 278437500 | P8: =-(Prizes!$E$34*52/12+Prizes!$C$64) -> -2.9257583e+08 | Q8: =SUM(L8:P8) -> 1.5066455e+09 | R8: =Q8*(1-J8) -> 9.0398727e+08 | S8: =Loyalty_Inputs!$C$53*((1-Loyalty_Inputs!$C$50)+Loyalty_Inputs!$C$50*C8) -> 487080 | T8: =0.03+0.97*C8 -> 0.0688 | U8: =IF(S8>0,Prizes!$C$34/S8,0) -> 0.0027798308 | V8: ВЫСОКИЙ (платный шанс = лотерея, лицензия НАПП) | W8: высокий
A9: O5 | B9: РЕКОМЕНДУЕМ: играют все, шансы растут с АП + Club+ Pass с реальной ценностью | C9: 1 | D9: 1 | E9: 0.005 | F9: 0.03 | G9: 9999 | H9: 0 | I9: 0 | J9: 0.05 | K9: 1 | L9: =Loyalty_Inputs!$C$53*Loyalty_Inputs!$C$24*Loyalty_Inputs!$C$25*((1-Loyalty_Inputs!$C$50)+Loyalty_Inputs!$C$50*D9)*(1-(1-Loyalty_Inputs!$C$24)^12)/Loyalty_Inputs!$C$24*Loyalty_Inputs!$C$47*Loyalty_Inputs!$C$34 -> 1.1217252e+09 | M9: =Loyalty_Inputs!$C$53*Loyalty_Inputs!$C$50*E9*(1-(1-Loyalty_Inputs!$C$24)^12)/Loyalty_Inputs!$C$24*Loyalty_Inputs!$C$28*Loyalty_Inputs!$C$34 -> 9.9303588e+08 | N9: =Loyalty_Inputs!$C$53*Loyalty_Inputs!$C$50*F9*G9/(1+Inputs!$C$10)*(1-Loyalty_Inputs!$C$31) -> 2.0880724e+08 | O9: =Loyalty_Inputs!$C$53*Loyalty_Inputs!$C$50*H9*I9/(1+Inputs!$C$10) -> 0 | P9: =-(Prizes!$E$34*52/12+Prizes!$C$64) -> -2.9257583e+08 | Q9: =SUM(L9:P9) -> 2.0309925e+09 | R9: =Q9*(1-J9) -> 1.9294429e+09 | S9: =Loyalty_Inputs!$C$53*((1-Loyalty_Inputs!$C$50)+Loyalty_Inputs!$C$50*C9) -> 1485000 | T9: =0.03+0.97*C9 -> 1 | U9: =IF(S9>0,Prizes!$C$34/S9,0) -> 0.00091178451 | V9: низкий–средний (Pass ≥ своей цены по ценности) | W9: низкий

Sheet Portfolio
A1: Портфель: ARPU архивной когорты (план: всё запущено) и вклад
A3: Месяц | C3: 1 | D3: 2 | E3: 3 | F3: 4 | G3: 5 | H3: 6 | I3: 7 | J3: 8 | K3: 9 | L3: 10 | M3: 11 | N3: 12 | O3: 13 | P3: 14 | Q3: 15 | R3: 16 | S3: 17 | T3: 18 | U3: 19 | V3: 20 | W3: 21 | X3: 22 | Y3: 23 | Z3: 24 | AA3: 25 | AB3: 26 | AC3: 27 | AD3: 28 | AE3: 29 | AF3: 30 | AG3: 31 | AH3: 32 | AI3: 33 | AJ3: 34 | AK3: 35 | AL3: 36
A4: I1–I3: выручка (после перекрытия) | C4: =(Monthly_I!C16+Monthly_I!C30+Monthly_I!C44+Monthly_I!C58)*(1-Inputs!$C$14) -> 0 | D4: =(Monthly_I!D16+Monthly_I!D30+Monthly_I!D44+Monthly_I!D58)*(1-Inputs!$C$14) -> 4.0252382e+08 | E4: =(Monthly_I!E16+Monthly_I!E30+Monthly_I!E44+Monthly_I!E58)*(1-Inputs!$C$14) -> 5.3814154e+08 | F4: =(Monthly_I!F16+Monthly_I!F30+Monthly_I!F44+Monthly_I!F58)*(1-Inputs!$C$14) -> 2.7760912e+09 | G4: =(Monthly_I!G16+Monthly_I!G30+Monthly_I!G44+Monthly_I!G58)*(1-Inputs!$C$14) -> 2.572016e+09 | H4: =(Monthly_I!H16+Monthly_I!H30+Monthly_I!H44+Monthly_I!H58)*(1-Inputs!$C$14) -> 3.8598261e+09 | I4: =(Monthly_I!I16+Monthly_I!I30+Monthly_I!I44+Monthly_I!I58)*(1-Inputs!$C$14) -> 3.6900474e+09 | J4: =(Monthly_I!J16+Monthly_I!J30+Monthly_I!J44+Monthly_I!J58)*(1-Inputs!$C$14) -> 3.6368358e+09 | ... AL4: =(Monthly_I!AL16+Monthly_I!AL30+Monthly_I!AL44+Monthly_I!AL58)*(1-Inputs!$C$14) -> 3.2260595e+09
A5: I1–I3: Δ абонентов (после перекрытия) | C5: =(Monthly_I!C19+Monthly_I!C33+Monthly_I!C47+Monthly_I!C61)*(1-Inputs!$C$14) -> 0 | D5: =(Monthly_I!D19+Monthly_I!D33+Monthly_I!D47+Monthly_I!D61)*(1-Inputs!$C$14) -> -871.2 | E5: =(Monthly_I!E19+Monthly_I!E33+Monthly_I!E47+Monthly_I!E61)*(1-Inputs!$C$14) -> -1695.9373 | F5: =(Monthly_I!F19+Monthly_I!F33+Monthly_I!F47+Monthly_I!F61)*(1-Inputs!$C$14) -> -9444.9335 | G5: =(Monthly_I!G19+Monthly_I!G33+Monthly_I!G47+Monthly_I!G61)*(1-Inputs!$C$14) -> -17055.729 | H5: =(Monthly_I!H19+Monthly_I!H33+Monthly_I!H47+Monthly_I!H61)*(1-Inputs!$C$14) -> -23840.669 | I5: =(Monthly_I!I19+Monthly_I!I33+Monthly_I!I47+Monthly_I!I61)*(1-Inputs!$C$14) -> -30524.927 | J5: =(Monthly_I!J19+Monthly_I!J33+Monthly_I!J47+Monthly_I!J61)*(1-Inputs!$C$14) -> -29982.001 | ... AL5: =(Monthly_I!AL19+Monthly_I!AL33+Monthly_I!AL47+Monthly_I!AL61)*(1-Inputs!$C$14) -> -27570.365
A6: Loyalty: доп. выручка архивных | C6: =Loyalty_Monthly!C29 -> 0 | D6: =Loyalty_Monthly!D29 -> 0 | E6: =Loyalty_Monthly!E29 -> 0 | F6: =Loyalty_Monthly!F29 -> 0 | G6: =Loyalty_Monthly!G29 -> 19789821 | H6: =Loyalty_Monthly!H29 -> 22693221 | I6: =Loyalty_Monthly!I29 -> 25553070 | J6: =Loyalty_Monthly!J29 -> 28370021 | ... AL6: =Loyalty_Monthly!AL29 -> 7.5936083e+08
A7: Loyalty: Δ архивных абонентов | C7: =Loyalty_Monthly!C30 -> 0 | D7: =Loyalty_Monthly!D30 -> 0 | E7: =Loyalty_Monthly!E30 -> 0 | F7: =Loyalty_Monthly!F30 -> 0 | G7: =Loyalty_Monthly!G30 -> 0 | H7: =Loyalty_Monthly!H30 -> 67.5 | I7: =Loyalty_Monthly!I30 -> 133.9875 | J7: =Loyalty_Monthly!J30 -> 199.47769 | ... AL7: =Loyalty_Monthly!AL30 -> 13099.231
A8: ARPU когорты, сум | C8: =(Monthly_I!C$5+C4+C6)/(Monthly_I!C$4+C5+C7) -> 18500 | D8: =(Monthly_I!D$5+D4+D6)/(Monthly_I!D$4+D5+D7) -> 18622.613 | E8: =(Monthly_I!E$5+E4+E6)/(Monthly_I!E$4+E5+E7) -> 18669.385 | F8: =(Monthly_I!F$5+F4+F6)/(Monthly_I!F$4+F5+F7) -> 19393.09 | G8: =(Monthly_I!G$5+G4+G6)/(Monthly_I!G$4+G5+G7) -> 19395.462 | H8: =(Monthly_I!H$5+H4+H6)/(Monthly_I!H$4+H5+H7) -> 19854.505 | I8: =(Monthly_I!I$5+I4+I6)/(Monthly_I!I$4+I5+I7) -> 19864.004 | J8: =(Monthly_I!J$5+J4+J6)/(Monthly_I!J$4+J5+J7) -> 19864.752 | ... AL8: =(Monthly_I!AL$5+AL4+AL6)/(Monthly_I!AL$4+AL5+AL7) -> 20596.765
A9: ΔARPU когорты | C9: =C8/Inputs!$C$8-1 -> 0 | D9: =D8/Inputs!$C$8-1 -> 0.006627744 | E9: =E8/Inputs!$C$8-1 -> 0.0091559232 | F9: =F8/Inputs!$C$8-1 -> 0.048275131 | G9: =G8/Inputs!$C$8-1 -> 0.048403331 | H9: =H8/Inputs!$C$8-1 -> 0.073216489 | I9: =I8/Inputs!$C$8-1 -> 0.073729957 | J9: =J8/Inputs!$C$8-1 -> 0.073770358 | ... AL9: =AL8/Inputs!$C$8-1 -> 0.11333862
A10: ΔARPU только I1–I3 | C10: =(Monthly_I!C$5+C4)/(Monthly_I!C$4+C5)/Inputs!$C$8-1 -> 0 | D10: =(Monthly_I!D$5+D4)/(Monthly_I!D$4+D5)/Inputs!$C$8-1 -> 0.006627744 | E10: =(Monthly_I!E$5+E4)/(Monthly_I!E$4+E5)/Inputs!$C$8-1 -> 0.0091559232 | F10: =(Monthly_I!F$5+F4)/(Monthly_I!F$4+F5)/Inputs!$C$8-1 -> 0.048275131 | G10: =(Monthly_I!G$5+G4)/(Monthly_I!G$4+G5)/Inputs!$C$8-1 -> 0.048073857 | H10: =(Monthly_I!H$5+H4)/(Monthly_I!H$4+H5)/Inputs!$C$8-1 -> 0.072854779 | I10: =(Monthly_I!I$5+I4)/(Monthly_I!I$4+I5)/Inputs!$C$8-1 -> 0.073335396 | J10: =(Monthly_I!J$5+J4)/(Monthly_I!J$4+J5)/Inputs!$C$8-1 -> 0.073343274 | ... AL10: =(Monthly_I!AL$5+AL4)/(Monthly_I!AL$4+AL5)/Inputs!$C$8-1 -> 0.10020794
A11: Вклад I1–I3 | C11: =(Monthly_I!C18+Monthly_I!C17)*(1-Inputs!$C$14)-Monthly_I!C17+(Monthly_I!C32+Monthly_I!C31)*(1-Inputs!$C$14)-Monthly_I!C31+(Monthly_I!C46+Monthly_I!C45)*(1-Inputs!$C$14)-Monthly_I!C45+(Monthly_I!C60+Monthly_I!C59)*(1-Inputs!$C$14)-Monthly_I!C59 -> -1800000000 | D11: =(Monthly_I!D18+Monthly_I!D17)*(1-Inputs!$C$14)-Monthly_I!D17+(Monthly_I!D32+Monthly_I!D31)*(1-Inputs!$C$14)-Monthly_I!D31+(Monthly_I!D46+Monthly_I!D45)*(1-Inputs!$C$14)-Monthly_I!D45+(Monthly_I!D60+Monthly_I!D59)*(1-Inputs!$C$14)-Monthly_I!D59 -> -8.1774308e+08 | E11: =(Monthly_I!E18+Monthly_I!E17)*(1-Inputs!$C$14)-Monthly_I!E17+(Monthly_I!E32+Monthly_I!E31)*(1-Inputs!$C$14)-Monthly_I!E31+(Monthly_I!E46+Monthly_I!E45)*(1-Inputs!$C$14)-Monthly_I!E45+(Monthly_I!E60+Monthly_I!E59)*(1-Inputs!$C$14)-Monthly_I!E59 -> -6.6945675e+08 | F11: =(Monthly_I!F18+Monthly_I!F17)*(1-Inputs!$C$14)-Monthly_I!F17+(Monthly_I!F32+Monthly_I!F31)*(1-Inputs!$C$14)-Monthly_I!F31+(Monthly_I!F46+Monthly_I!F45)*(1-Inputs!$C$14)-Monthly_I!F45+(Monthly_I!F60+Monthly_I!F59)*(1-Inputs!$C$14)-Monthly_I!F59 -> 1.2292272e+09 | G11: =(Monthly_I!G18+Monthly_I!G17)*(1-Inputs!$C$14)-Monthly_I!G17+(Monthly_I!G32+Monthly_I!G31)*(1-Inputs!$C$14)-Monthly_I!G31+(Monthly_I!G46+Monthly_I!G45)*(1-Inputs!$C$14)-Monthly_I!G45+(Monthly_I!G60+Monthly_I!G59)*(1-Inputs!$C$14)-Monthly_I!G59 -> 1.1506164e+09 | H11: =(Monthly_I!H18+Monthly_I!H17)*(1-Inputs!$C$14)-Monthly_I!H17+(Monthly_I!H32+Monthly_I!H31)*(1-Inputs!$C$14)-Monthly_I!H31+(Monthly_I!H46+Monthly_I!H45)*(1-Inputs!$C$14)-Monthly_I!H45+(Monthly_I!H60+Monthly_I!H59)*(1-Inputs!$C$14)-Monthly_I!H59 -> 3.1968636e+09 | I11: =(Monthly_I!I18+Monthly_I!I17)*(1-Inputs!$C$14)-Monthly_I!I17+(Monthly_I!I32+Monthly_I!I31)*(1-Inputs!$C$14)-Monthly_I!I31+(Monthly_I!I46+Monthly_I!I45)*(1-Inputs!$C$14)-Monthly_I!I45+(Monthly_I!I60+Monthly_I!I59)*(1-Inputs!$C$14)-Monthly_I!I59 -> 3.1397462e+09 | J11: =(Monthly_I!J18+Monthly_I!J17)*(1-Inputs!$C$14)-Monthly_I!J17+(Monthly_I!J32+Monthly_I!J31)*(1-Inputs!$C$14)-Monthly_I!J31+(Monthly_I!J46+Monthly_I!J45)*(1-Inputs!$C$14)-Monthly_I!J45+(Monthly_I!J60+Monthly_I!J59)*(1-Inputs!$C$14)-Monthly_I!J59 -> 3.0934986e+09 | ... AL11: =(Monthly_I!AL18+Monthly_I!AL17)*(1-Inputs!$C$14)-Monthly_I!AL17+(Monthly_I!AL32+Monthly_I!AL31)*(1-Inputs!$C$14)-Monthly_I!AL31+(Monthly_I!AL46+Monthly_I!AL45)*(1-Inputs!$C$14)-Monthly_I!AL45+(Monthly_I!AL60+Monthly_I!AL59)*(1-Inputs!$C$14)-Monthly_I!AL59 -> 2.7794894e+09
A12: Вклад Loyalty (вся программа) | C12: =Loyalty_Monthly!C23 -> 0 | D12: =Loyalty_Monthly!D23 -> -600000000 | E12: =Loyalty_Monthly!E23 -> -600000000 | F12: =Loyalty_Monthly!F23 -> -600000000 | G12: =Loyalty_Monthly!G23 -> -5.730008e+08 | H12: =Loyalty_Monthly!H23 -> -3.0586487e+08 | I12: =Loyalty_Monthly!I23 -> -2.8893458e+08 | J12: =Loyalty_Monthly!J23 -> -1.2722074e+09 | ... AL12: =Loyalty_Monthly!AL23 -> 2.4175007e+09
A13: Вклад портфеля накопленный | C13: =C11+C12 -> -1800000000 | D13: =N(C13)+D11+D12 -> -3.2177431e+09 | E13: =N(D13)+E11+E12 -> -4.4871998e+09 | F13: =N(E13)+F11+F12 -> -3.8579726e+09 | G13: =N(F13)+G11+G12 -> -3.2803569e+09 | H13: =N(G13)+H11+H12 -> -3.8935819e+08 | I13: =N(H13)+I11+I12 -> 2.4614534e+09 | J13: =N(I13)+J11+J12 -> 4.2827445e+09 | K13: =N(J13)+K11+K12 -> 7.1826092e+09 | ... AL13: =N(AK13)+AL11+AL12 -> 1.1451118e+11
A15: Итоги
A16: ΔARPU когорты M12 | C16: =N9 -> 0.10146098
A17: ΔARPU когорты M24 | C17: =Z9 -> 0.10795345
A18: ΔARPU когорты M36 | C18: =AL9 -> 0.11333862
A19: из них I1–I3 на M24 | C19: =Z10 -> 0.10011921
A20: ARPU когорты M24, сум | C20: =Z8 -> 20497.139
A21: Доп. выручка архивной когорты Y1 | C21: =SUM(C4:N4)+SUM(C6:N6) -> 3.6645202e+10
A22: Доп. выручка архивной когорты Y2 | C22: =SUM(O4:Z4)+SUM(O6:Z6) -> 5.4118444e+10
A23: Доп. выручка архивной когорты Y3 | C23: =SUM(AA4:AL4)+SUM(AA6:AL6) -> 4.969676e+10
A24: Вклад портфеля 24 мес. | C24: =Z13 -> 5.8207174e+10
A25: Вклад портфеля 36 мес. | C25: =AL13 -> 1.1451118e+11

Sheet AB_Calculator
A1: Калькулятор выборок (двусторонний тест, α и мощность — ниже)
A3: Уровень значимости α | B3: 0.05
A4: Мощность | B4: 0.8
A5: CV ARPU (σ/μ) | B5: 1.2
A6: MDE ARPU, отн. | B6: 0.02
A7: Пропорция в контроле p1 (напр. отток) | B7: 0.012
A8: Пропорция в тесте p2 | B8: 0.01
A10: N на группу — ARPU | B10: =ROUNDUP(2*(NORMSINV(1-B3/2)+NORMSINV(B4))^2*B5^2/B6^2,0) -> 56512
A11: N на группу — пропорции | B11: =ROUNDUP((NORMSINV(1-B3/2)*SQRT(2*((B7+B8)/2)*(1-(B7+B8)/2))+NORMSINV(B4)*SQRT(B7*(1-B7)+B8*(1-B8)))^2/(B8-B7)^2,0) -> 42693

Sheet MC_Results
A1: Монте-Карло (20 000 прогонов) — значения из v2/model/output/results_v2.json
A3: # | B3: Инициатива | C3: Вклад 24м P10 | D3: P50 | E3: P90 | F3: ΔARPU P50 | G3: P(запуска) | H3: Шанс успеха | I3: Шанс ≥70% плана
A4: I1 | B4: Sunset / Migration | C4: 25.589806 | D4: 35.600867 | E4: 47.576258 | F4: 0.062104504 | G4: 0.65 | H4: 0.65 | I4: 0.6220825
A5: I2 | B5: More-for-More | C5: 28.248217 | D5: 36.795761 | E5: 45.872499 | F5: 0.045466717 | G5: 0.8 | H5: 0.8 | I5: 0.72628
A6: I3a | B6: Бустер при исчерпании | C6: 1.947677 | D6: 3.2781708 | E6: 5.2235439 | F6: 0.0041500278 | G6: 0.9 | H6: 0.9 | I6: 0.768195
A7: I3b | B7: Роуминг-промо | C7: 0.86481074 | D7: 1.6827129 | E7: 2.8361842 | F7: 0.0029692476 | G7: 0.9 | H7: 0.9 | I7: 0.704115
A8: I4 | B8: Loyalty (вклад 36м) | C8: -3.2435176 | D8: 12.415668 | E8: 30.696406 | F8: 0.0086583229 | G8: 0.6375 | H8: 0.53543625 | I8: 0.41574563
A10: Портфель
A11: ΔARPU M24 P10 | C11: 0.043058458
A12: ΔARPU M24 P50 | C12: 0.091403675
A13: ΔARPU M24 P90 | C13: 0.12054367
A14: P(ΔARPU ≥ 8%) | C14: 0.5378
A15: P(ΔARPU ≥ 10%) | C15: 0.41935
A16: Вклад 36м P50, млрд | C16: 89.560513
A17: Бюджет MVP P50, млрд | C17: 3.6462377
A18: Затраты Loyalty в мес. при масштабе P50, млрд | C18: 2.5967011
